Workbook

Sheet Table XI-split
A1: Table XI: Conflicted CIOs: Plan Performance in the First versus Second Half of Tenure (updated benchmark)
A2: This table repeats the regressions of Table III, splitting the Conflicted CIO indicator into two indicators: Conflicted CIO x First Half of Tenure, equal to 1 in the fiscal years in which a conflicted CIO's tenure is at most one half of the CIO's tenure at departure, and Conflicted CIO x Second Half of Tenure, equal to 1 in the remaining fiscal years of a conflicted CIO's tenure. The omitted category is all plan-years run by non-conflicted CIOs, so each coefficient is the performance differential of conflicted CIOs in that part of their tenure relative to non-conflicted CIOs. Tenure at departure is the CIO's tenure in the last fiscal year observed in the plan plus any gap to the departure year. 11 conflicted plan-years for which tenure at departure cannot be determined are absorbed by a separate indicator that is not reported. The performance measure in Panel A is Peer-Adjusted Return, which is the difference of a plan's return and the average pension plan return each year. The performance measure in Panel B is Benchmark-Adjusted Return, which is calculated as the plan's return minus the return of its updated policy benchmark (the benchmark return reported in the plan's financial report or, where none is stated, an inferred value graded A or B). The other independent variables are as defined in Table I. The last row reports the p-value of a test that the first-half and second-half coefficients are equal. The standard errors are double clustered by plan and year. Coefficients marked with ***, **, and * are significant at the 1%, 5%, and 10% level, respectively.
A4: Panel A. Peer-Adjusted Returns
B5: (1) | C5: (2) | D5: (3) | E5: (4)
B6: Peer-adj. Ret. (t) | C6: Peer-adj. Ret. (t) | D6: Peer-adj. Ret. (t) | E6: Peer-adj. Ret. (t)
A7: Conflicted CIO x First Half of Tenure (0/1) | B7: =TEXT('Estimates-split'!B4,"0.000")&IF('Estimates-split'!E4="","",IF('Estimates-split'!E4<0.01,"***",IF('Estimates-split'!E4<0.05,"**",IF('Estimates-split'!E4<0.1,"*","")))) -> -0.510*** | C7: =TEXT('Estimates-split'!F4,"0.000")&IF('Estimates-split'!I4="","",IF('Estimates-split'!I4<0.01,"***",IF('Estimates-split'!I4<0.05,"**",IF('Estimates-split'!I4<0.1,"*","")))) -> -0.605** | D7: =TEXT('Estimates-split'!J4,"0.000")&IF('Estimates-split'!M4="","",IF('Estimates-split'!M4<0.01,"***",IF('Estimates-split'!M4<0.05,"**",IF('Estimates-split'!M4<0.1,"*","")))) -> -0.773** | E7: =TEXT('Estimates-split'!N4,"0.000")&IF('Estimates-split'!Q4="","",IF('Estimates-split'!Q4<0.01,"***",IF('Estimates-split'!Q4<0.05,"**",IF('Estimates-split'!Q4<0.1,"*","")))) -> -0.861**
B8: =IF('Estimates-split'!D4="","(n/a)","("&TEXT('Estimates-split'!D4,"0.00")&")") -> (-2.89) | C8: =IF('Estimates-split'!H4="","(n/a)","("&TEXT('Estimates-split'!H4,"0.00")&")") -> (-2.83) | D8: =IF('Estimates-split'!L4="","(n/a)","("&TEXT('Estimates-split'!L4,"0.00")&")") -> (-2.29) | E8: =IF('Estimates-split'!P4="","(n/a)","("&TEXT('Estimates-split'!P4,"0.00")&")") -> (-2.45)
A9: Conflicted CIO x Second Half of Tenure (0/1) | B9: =TEXT('Estimates-split'!B5,"0.000")&IF('Estimates-split'!E5="","",IF('Estimates-split'!E5<0.01,"***",IF('Estimates-split'!E5<0.05,"**",IF('Estimates-split'!E5<0.1,"*","")))) -> -0.615*** | C9: =TEXT('Estimates-split'!F5,"0.000")&IF('Estimates-split'!I5="","",IF('Estimates-split'!I5<0.01,"***",IF('Estimates-split'!I5<0.05,"**",IF('Estimates-split'!I5<0.1,"*","")))) -> -0.581** | D9: =TEXT('Estimates-split'!J5,"0.000")&IF('Estimates-split'!M5="","",IF('Estimates-split'!M5<0.01,"***",IF('Estimates-split'!M5<0.05,"**",IF('Estimates-split'!M5<0.1,"*","")))) -> -0.553* | E9: =TEXT('Estimates-split'!N5,"0.000")&IF('Estimates-split'!Q5="","",IF('Estimates-split'!Q5<0.01,"***",IF('Estimates-split'!Q5<0.05,"**",IF('Estimates-split'!Q5<0.1,"*","")))) -> -0.579*
B10: =IF('Estimates-split'!D5="","(n/a)","("&TEXT('Estimates-split'!D5,"0.00")&")") -> (-2.99) | C10: =IF('Estimates-split'!H5="","(n/a)","("&TEXT('Estimates-split'!H5,"0.00")&")") -> (-2.68) | D10: =IF('Estimates-split'!L5="","(n/a)","("&TEXT('Estimates-split'!L5,"0.00")&")") -> (-1.84) | E10: =IF('Estimates-split'!P5="","(n/a)","("&TEXT('Estimates-split'!P5,"0.00")&")") -> (-1.97)
A11: Investment Return (t - 1) | B11: =TEXT('Estimates-split'!B6,"0.000")&IF('Estimates-split'!E6="","",IF('Estimates-split'!E6<0.01,"***",IF('Estimates-split'!E6<0.05,"**",IF('Estimates-split'!E6<0.1,"*","")))) -> 0.014 | C11: =TEXT('Estimates-split'!F6,"0.000")&IF('Estimates-split'!I6="","",IF('Estimates-split'!I6<0.01,"***",IF('Estimates-split'!I6<0.05,"**",IF('Estimates-split'!I6<0.1,"*","")))) -> 0.004 | D11: =TEXT('Estimates-split'!J6,"0.000")&IF('Estimates-split'!M6="","",IF('Estimates-split'!M6<0.01,"***",IF('Estimates-split'!M6<0.05,"**",IF('Estimates-split'!M6<0.1,"*","")))) -> 0.011 | E11: =TEXT('Estimates-split'!N6,"0.000")&IF('Estimates-split'!Q6="","",IF('Estimates-split'!Q6<0.01,"***",IF('Estimates-split'!Q6<0.05,"**",IF('Estimates-split'!Q6<0.1,"*","")))) -> 0.000
B12: =IF('Estimates-split'!D6="","(n/a)","("&TEXT('Estimates-split'!D6,"0.00")&")") -> (0.65) | C12: =IF('Estimates-split'!H6="","(n/a)","("&TEXT('Estimates-split'!H6,"0.00")&")") -> (0.20) | D12: =IF('Estimates-split'!L6="","(n/a)","("&TEXT('Estimates-split'!L6,"0.00")&")") -> (1.19) | E12: =IF('Estimates-split'!P6="","(n/a)","("&TEXT('Estimates-split'!P6,"0.00")&")") -> (0.01)
A13: Log (Plan Size) (t-1) | B13: =TEXT('Estimates-split'!B7,"0.000")&IF('Estimates-split'!E7="","",IF('Estimates-split'!E7<0.01,"***",IF('Estimates-split'!E7<0.05,"**",IF('Estimates-split'!E7<0.1,"*","")))) -> 0.007 | C13: =TEXT('Estimates-split'!F7,"0.000")&IF('Estimates-split'!I7="","",IF('Estimates-split'!I7<0.01,"***",IF('Estimates-split'!I7<0.05,"**",IF('Estimates-split'!I7<0.1,"*","")))) -> 0.068 | D13: =TEXT('Estimates-split'!J7,"0.000")&IF('Estimates-split'!M7="","",IF('Estimates-split'!M7<0.01,"***",IF('Estimates-split'!M7<0.05,"**",IF('Estimates-split'!M7<0.1,"*","")))) -> -0.945** | E13: =TEXT('Estimates-split'!N7,"0.000")&IF('Estimates-split'!Q7="","",IF('Estimates-split'!Q7<0.01,"***",IF('Estimates-split'!Q7<0.05,"**",IF('Estimates-split'!Q7<0.1,"*","")))) -> -1.418*
B14: =IF('Estimates-split'!D7="","(n/a)","("&TEXT('Estimates-split'!D7,"0.00")&")") -> (0.13) | C14: =IF('Estimates-split'!H7="","(n/a)","("&TEXT('Estimates-split'!H7,"0.00")&")") -> (1.04) | D14: =IF('Estimates-split'!L7="","(n/a)","("&TEXT('Estimates-split'!L7,"0.00")&")") -> (-2.48) | E14: =IF('Estimates-split'!P7="","(n/a)","("&TEXT('Estimates-split'!P7,"0.00")&")") -> (-1.95)
A15: Funding Ratio (t-1) | B15: =TEXT('Estimates-split'!B8,"0.000")&IF('Estimates-split'!E8="","",IF('Estimates-split'!E8<0.01,"***",IF('Estimates-split'!E8<0.05,"**",IF('Estimates-split'!E8<0.1,"*","")))) -> -0.005 | C15: =TEXT('Estimates-split'!F8,"0.000")&IF('Estimates-split'!I8="","",IF('Estimates-split'!I8<0.01,"***",IF('Estimates-split'!I8<0.05,"**",IF('Estimates-split'!I8<0.1,"*","")))) -> -0.006 | D15: =TEXT('Estimates-split'!J8,"0.000")&IF('Estimates-split'!M8="","",IF('Estimates-split'!M8<0.01,"***",IF('Estimates-split'!M8<0.05,"**",IF('Estimates-split'!M8<0.1,"*","")))) -> -0.027*** | E15: =TEXT('Estimates-split'!N8,"0.000")&IF('Estimates-split'!Q8="","",IF('Estimates-split'!Q8<0.01,"***",IF('Estimates-split'!Q8<0.05,"**",IF('Estimates-split'!Q8<0.1,"*","")))) -> -0.030***
B16: =IF('Estimates-split'!D8="","(n/a)","("&TEXT('Estimates-split'!D8,"0.00")&")") -> (-1.17) | C16: =IF('Estimates-split'!H8="","(n/a)","("&TEXT('Estimates-split'!H8,"0.00")&")") -> (-1.20) | D16: =IF('Estimates-split'!L8="","(n/a)","("&TEXT('Estimates-split'!L8,"0.00")&")") -> (-3.18) | E16: =IF('Estimates-split'!P8="","(n/a)","("&TEXT('Estimates-split'!P8,"0.00")&")") -> (-2.95)
A17: Equity Allocation (%) | B17: =TEXT('Estimates-split'!B9,"0.000")&IF('Estimates-split'!E9="","",IF('Estimates-split'!E9<0.01,"***",IF('Estimates-split'!E9<0.05,"**",IF('Estimates-split'!E9<0.1,"*","")))) -> -0.082 | C17: =TEXT('Estimates-split'!F9,"0.000")&IF('Estimates-split'!I9="","",IF('Estimates-split'!I9<0.01,"***",IF('Estimates-split'!I9<0.05,"**",IF('Estimates-split'!I9<0.1,"*","")))) -> 0.005 | D17: =TEXT('Estimates-split'!J9,"0.000")&IF('Estimates-split'!M9="","",IF('Estimates-split'!M9<0.01,"***",IF('Estimates-split'!M9<0.05,"**",IF('Estimates-split'!M9<0.1,"*","")))) -> -0.048 | E17: =TEXT('Estimates-split'!N9,"0.000")&IF('Estimates-split'!Q9="","",IF('Estimates-split'!Q9<0.01,"***",IF('Estimates-split'!Q9<0.05,"**",IF('Estimates-split'!Q9<0.1,"*","")))) -> -0.029
B18: =IF('Estimates-split'!D9="","(n/a)","("&TEXT('Estimates-split'!D9,"0.00")&")") -> (-0.61) | C18: =IF('Estimates-split'!H9="","(n/a)","("&TEXT('Estimates-split'!H9,"0.00")&")") -> (0.07) | D18: =IF('Estimates-split'!L9="","(n/a)","("&TEXT('Estimates-split'!L9,"0.00")&")") -> (-0.58) | E18: =IF('Estimates-split'!P9="","(n/a)","("&TEXT('Estimates-split'!P9,"0.00")&")") -> (-0.34)
A19: Fixed Income Allocation (%) | B19: =TEXT('Estimates-split'!B10,"0.000")&IF('Estimates-split'!E10="","",IF('Estimates-split'!E10<0.01,"***",IF('Estimates-split'!E10<0.05,"**",IF('Estimates-split'!E10<0.1,"*","")))) -> -0.091 | C19: =TEXT('Estimates-split'!F10,"0.000")&IF('Estimates-split'!I10="","",IF('Estimates-split'!I10<0.01,"***",IF('Estimates-split'!I10<0.05,"**",IF('Estimates-split'!I10<0.1,"*","")))) -> 0.000 | D19: =TEXT('Estimates-split'!J10,"0.000")&IF('Estimates-split'!M10="","",IF('Estimates-split'!M10<0.01,"***",IF('Estimates-split'!M10<0.05,"**",IF('Estimates-split'!M10<0.1,"*","")))) -> -0.059 | E19: =TEXT('Estimates-split'!N10,"0.000")&IF('Estimates-split'!Q10="","",IF('Estimates-split'!Q10<0.01,"***",IF('Estimates-split'!Q10<0.05,"**",IF('Estimates-split'!Q10<0.1,"*","")))) -> -0.035
B20: =IF('Estimates-split'!D10="","(n/a)","("&TEXT('Estimates-split'!D10,"0.00")&")") -> (-0.63) | C20: =IF('Estimates-split'!H10="","(n/a)","("&TEXT('Estimates-split'!H10,"0.00")&")") -> (0.00) | D20: =IF('Estimates-split'!L10="","(n/a)","("&TEXT('Estimates-split'!L10,"0.00")&")") -> (-0.61) | E20: =IF('Estimates-split'!P10="","(n/a)","("&TEXT('Estimates-split'!P10,"0.00")&")") -> (-0.36)
A21: Real Estate Allocation (%) | B21: =TEXT('Estimates-split'!B11,"0.000")&IF('Estimates-split'!E11="","",IF('Estimates-split'!E11<0.01,"***",IF('Estimates-split'!E11<0.05,"**",IF('Estimates-split'!E11<0.1,"*","")))) -> -0.062 | C21: =TEXT('Estimates-split'!F11,"0.000")&IF('Estimates-split'!I11="","",IF('Estimates-split'!I11<0.01,"***",IF('Estimates-split'!I11<0.05,"**",IF('Estimates-split'!I11<0.1,"*","")))) -> 0.026 | D21: =TEXT('Estimates-split'!J11,"0.000")&IF('Estimates-split'!M11="","",IF('Estimates-split'!M11<0.01,"***",IF('Estimates-split'!M11<0.05,"**",IF('Estimates-split'!M11<0.1,"*","")))) -> -0.091 | E21: =TEXT('Estimates-split'!N11,"0.000")&IF('Estimates-split'!Q11="","",IF('Estimates-split'!Q11<0.01,"***",IF('Estimates-split'!Q11<0.05,"**",IF('Estimates-split'!Q11<0.1,"*","")))) -> -0.079
B22: =IF('Estimates-split'!D11="","(n/a)","("&TEXT('Estimates-split'!D11,"0.00")&")") -> (-0.46) | C22: =IF('Estimates-split'!H11="","(n/a)","("&TEXT('Estimates-split'!H11,"0.00")&")") -> (0.43) | D22: =IF('Estimates-split'!L11="","(n/a)","("&TEXT('Estimates-split'!L11,"0.00")&")") -> (-1.14) | E22: =IF('Estimates-split'!P11="","(n/a)","("&TEXT('Estimates-split'!P11,"0.00")&")") -> (-0.90)
A23: Private Equity Allocation (%) | B23: =TEXT('Estimates-split'!B12,"0.000")&IF('Estimates-split'!E12="","",IF('Estimates-split'!E12<0.01,"***",IF('Estimates-split'!E12<0.05,"**",IF('Estimates-split'!E12<0.1,"*","")))) -> -0.073 | C23: =TEXT('Estimates-split'!F12,"0.000")&IF('Estimates-split'!I12="","",IF('Estimates-split'!I12<0.01,"***",IF('Estimates-split'!I12<0.05,"**",IF('Estimates-split'!I12<0.1,"*","")))) -> 0.025 | D23: =TEXT('Estimates-split'!J12,"0.000")&IF('Estimates-split'!M12="","",IF('Estimates-split'!M12<0.01,"***",IF('Estimates-split'!M12<0.05,"**",IF('Estimates-split'!M12<0.1,"*","")))) -> -0.042 | E23: =TEXT('Estimates-split'!N12,"0.000")&IF('Estimates-split'!Q12="","",IF('Estimates-split'!Q12<0.01,"***",IF('Estimates-split'!Q12<0.05,"**",IF('Estimates-split'!Q12<0.1,"*","")))) -> 0.011
B24: =IF('Estimates-split'!D12="","(n/a)","("&TEXT('Estimates-split'!D12,"0.00")&")") -> (-0.51) | C24: =IF('Estimates-split'!H12="","(n/a)","("&TEXT('Estimates-split'!H12,"0.00")&")") -> (0.39) | D24: =IF('Estimates-split'!L12="","(n/a)","("&TEXT('Estimates-split'!L12,"0.00")&")") -> (-0.47) | E24: =IF('Estimates-split'!P12="","(n/a)","("&TEXT('Estimates-split'!P12,"0.00")&")") -> (0.12)
A25: Hedge Fund Allocation (%) | B25: =TEXT('Estimates-split'!B13,"0.000")&IF('Estimates-split'!E13="","",IF('Estimates-split'!E13<0.01,"***",IF('Estimates-split'!E13<0.05,"**",IF('Estimates-split'!E13<0.1,"*","")))) -> -0.129 | C25: =TEXT('Estimates-split'!F13,"0.000")&IF('Estimates-split'!I13="","",IF('Estimates-split'!I13<0.01,"***",IF('Estimates-split'!I13<0.05,"**",IF('Estimates-split'!I13<0.1,"*","")))) -> -0.039 | D25: =TEXT('Estimates-split'!J13,"0.000")&IF('Estimates-split'!M13="","",IF('Estimates-split'!M13<0.01,"***",IF('Estimates-split'!M13<0.05,"**",IF('Estimates-split'!M13<0.1,"*","")))) -> -0.097 | E25: =TEXT('Estimates-split'!N13,"0.000")&IF('Estimates-split'!Q13="","",IF('Estimates-split'!Q13<0.01,"***",IF('Estimates-split'!Q13<0.05,"**",IF('Estimates-split'!Q13<0.1,"*","")))) -> -0.083
B26: =IF('Estimates-split'!D13="","(n/a)","("&TEXT('Estimates-split'!D13,"0.00")&")") -> (-0.96) | C26: =IF('Estimates-split'!H13="","(n/a)","("&TEXT('Estimates-split'!H13,"0.00")&")") -> (-0.59) | D26: =IF('Estimates-split'!L13="","(n/a)","("&TEXT('Estimates-split'!L13,"0.00")&")") -> (-1.27) | E26: =IF('Estimates-split'!P13="","(n/a)","("&TEXT('Estimates-split'!P13,"0.00")&")") -> (-1.12)
A27: Misc. Alternatives Allocation (%) | B27: =TEXT('Estimates-split'!B14,"0.000")&IF('Estimates-split'!E14="","",IF('Estimates-split'!E14<0.01,"***",IF('Estimates-split'!E14<0.05,"**",IF('Estimates-split'!E14<0.1,"*","")))) -> -0.096 | C27: =TEXT('Estimates-split'!F14,"0.000")&IF('Estimates-split'!I14="","",IF('Estimates-split'!I14<0.01,"***",IF('Estimates-split'!I14<0.05,"**",IF('Estimates-split'!I14<0.1,"*","")))) -> -0.010 | D27: =TEXT('Estimates-split'!J14,"0.000")&IF('Estimates-split'!M14="","",IF('Estimates-split'!M14<0.01,"***",IF('Estimates-split'!M14<0.05,"**",IF('Estimates-split'!M14<0.1,"*","")))) -> -0.115 | E27: =TEXT('Estimates-split'!N14,"0.000")&IF('Estimates-split'!Q14="","",IF('Estimates-split'!Q14<0.01,"***",IF('Estimates-split'!Q14<0.05,"**",IF('Estimates-split'!Q14<0.1,"*","")))) -> -0.076
B28: =IF('Estimates-split'!D14="","(n/a)","("&TEXT('Estimates-split'!D14,"0.00")&")") -> (-0.69) | C28: =IF('Estimates-split'!H14="","(n/a)","("&TEXT('Estimates-split'!H14,"0.00")&")") -> (-0.16) | D28: =IF('Estimates-split'!L14="","(n/a)","("&TEXT('Estimates-split'!L14,"0.00")&")") -> (-1.34) | E28: =IF('Estimates-split'!P14="","(n/a)","("&TEXT('Estimates-split'!P14,"0.00")&")") -> (-0.88)
A29: Commodities Allocation (%) | B29: =TEXT('Estimates-split'!B15,"0.000")&IF('Estimates-split'!E15="","",IF('Estimates-split'!E15<0.01,"***",IF('Estimates-split'!E15<0.05,"**",IF('Estimates-split'!E15<0.1,"*","")))) -> -0.143 | C29: =TEXT('Estimates-split'!F15,"0.000")&IF('Estimates-split'!I15="","",IF('Estimates-split'!I15<0.01,"***",IF('Estimates-split'!I15<0.05,"**",IF('Estimates-split'!I15<0.1,"*","")))) -> -0.047 | D29: =TEXT('Estimates-split'!J15,"0.000")&IF('Estimates-split'!M15="","",IF('Estimates-split'!M15<0.01,"***",IF('Estimates-split'!M15<0.05,"**",IF('Estimates-split'!M15<0.1,"*","")))) -> -0.139 | E29: =TEXT('Estimates-split'!N15,"0.000")&IF('Estimates-split'!Q15="","",IF('Estimates-split'!Q15<0.01,"***",IF('Estimates-split'!Q15<0.05,"**",IF('Estimates-split'!Q15<0.1,"*","")))) -> -0.123
B30: =IF('Estimates-split'!D15="","(n/a)","("&TEXT('Estimates-split'!D15,"0.00")&")") -> (-1.03) | C30: =IF('Estimates-split'!H15="","(n/a)","("&TEXT('Estimates-split'!H15,"0.00")&")") -> (-0.77) | D30: =IF('Estimates-split'!L15="","(n/a)","("&TEXT('Estimates-split'!L15,"0.00")&")") -> (-1.46) | E30: =IF('Estimates-split'!P15="","(n/a)","("&TEXT('Estimates-split'!P15,"0.00")&")") -> (-1.25)
A31: Cash Allocation (%) | B31: =TEXT('Estimates-split'!B16,"0.000")&IF('Estimates-split'!E16="","",IF('Estimates-split'!E16<0.01,"***",IF('Estimates-split'!E16<0.05,"**",IF('Estimates-split'!E16<0.1,"*","")))) -> -0.102 | C31: =TEXT('Estimates-split'!F16,"0.000")&IF('Estimates-split'!I16="","",IF('Estimates-split'!I16<0.01,"***",IF('Estimates-split'!I16<0.05,"**",IF('Estimates-split'!I16<0.1,"*","")))) -> -0.018 | D31: =TEXT('Estimates-split'!J16,"0.000")&IF('Estimates-split'!M16="","",IF('Estimates-split'!M16<0.01,"***",IF('Estimates-split'!M16<0.05,"**",IF('Estimates-split'!M16<0.1,"*","")))) -> -0.068 | E31: =TEXT('Estimates-split'!N16,"0.000")&IF('Estimates-split'!Q16="","",IF('Estimates-split'!Q16<0.01,"***",IF('Estimates-split'!Q16<0.05,"**",IF('Estimates-split'!Q16<0.1,"*","")))) -> -0.046
B32: =IF('Estimates-split'!D16="","(n/a)","("&TEXT('Estimates-split'!D16,"0.00")&")") -> (-0.69) | C32: =IF('Estimates-split'!H16="","(n/a)","("&TEXT('Estimates-split'!H16,"0.00")&")") -> (-0.23) | D32: =IF('Estimates-split'!L16="","(n/a)","("&TEXT('Estimates-split'!L16,"0.00")&")") -> (-0.61) | E32: =IF('Estimates-split'!P16="","(n/a)","("&TEXT('Estimates-split'!P16,"0.00")&")") -> (-0.41)
A33: Financial Center (0/1) | B33: =TEXT('Estimates-split'!B17,"0.000")&IF('Estimates-split'!E17="","",IF('Estimates-split'!E17<0.01,"***",IF('Estimates-split'!E17<0.05,"**",IF('Estimates-split'!E17<0.1,"*","")))) -> 0.110 | C33: =TEXT('Estimates-split'!F17,"0.000")&IF('Estimates-split'!I17="","",IF('Estimates-split'!I17<0.01,"***",IF('Estimates-split'!I17<0.05,"**",IF('Estimates-split'!I17<0.1,"*","")))) -> 0.144
B34: =IF('Estimates-split'!D17="","(n/a)","("&TEXT('Estimates-split'!D17,"0.00")&")") -> (0.77) | C34: =IF('Estimates-split'!H17="","(n/a)","("&TEXT('Estimates-split'!H17,"0.00")&")") -> (1.02)
A35: Log (CIO Age) (t-1) | C35: =TEXT('Estimates-split'!F18,"0.000")&IF('Estimates-split'!I18="","",IF('Estimates-split'!I18<0.01,"***",IF('Estimates-split'!I18<0.05,"**",IF('Estimates-split'!I18<0.1,"*","")))) -> -0.404 | D35: =TEXT('Estimates-split'!J18,"0.000")&IF('Estimates-split'!M18="","",IF('Estimates-split'!M18<0.01,"***",IF('Estimates-split'!M18<0.05,"**",IF('Estimates-split'!M18<0.1,"*","")))) -> 0.821 | E35: =TEXT('Estimates-split'!N18,"0.000")&IF('Estimates-split'!Q18="","",IF('Estimates-split'!Q18<0.01,"***",IF('Estimates-split'!Q18<0.05,"**",IF('Estimates-split'!Q18<0.1,"*","")))) -> 0.916
C36: =IF('Estimates-split'!H18="","(n/a)","("&TEXT('Estimates-split'!H18,"0.00")&")") -> (-0.77) | D36: =IF('Estimates-split'!L18="","(n/a)","("&TEXT('Estimates-split'!L18,"0.00")&")") -> (1.28) | E36: =IF('Estimates-split'!P18="","(n/a)","("&TEXT('Estimates-split'!P18,"0.00")&")") -> (1.37)
A37: Log (CIO Tenure) (t-1) | C37: =TEXT('Estimates-split'!F19,"0.000")&IF('Estimates-split'!I19="","",IF('Estimates-split'!I19<0.01,"***",IF('Estimates-split'!I19<0.05,"**",IF('Estimates-split'!I19<0.1,"*","")))) -> 0.036 | D37: =TEXT('Estimates-split'!J19,"0.000")&IF('Estimates-split'!M19="","",IF('Estimates-split'!M19<0.01,"***",IF('Estimates-split'!M19<0.05,"**",IF('Estimates-split'!M19<0.1,"*","")))) -> -0.012 | E37: =TEXT('Estimates-split'!N19,"0.000")&IF('Estimates-split'!Q19="","",IF('Estimates-split'!Q19<0.01,"***",IF('Estimates-split'!Q19<0.05,"**",IF('Estimates-split'!Q19<0.1,"*","")))) -> -0.037
C38: =IF('Estimates-split'!H19="","(n/a)","("&TEXT('Estimates-split'!H19,"0.00")&")") -> (0.38) | D38: =IF('Estimates-split'!L19="","(n/a)","("&TEXT('Estimates-split'!L19,"0.00")&")") -> (-0.10) | E38: =IF('Estimates-split'!P19="","(n/a)","("&TEXT('Estimates-split'!P19,"0.00")&")") -> (-0.28)
A39: CIO Prior Private Experience (0/1) | C39: =TEXT('Estimates-split'!F20,"0.000")&IF('Estimates-split'!I20="","",IF('Estimates-split'!I20<0.01,"***",IF('Estimates-split'!I20<0.05,"**",IF('Estimates-split'!I20<0.1,"*","")))) -> 0.031 | D39: =TEXT('Estimates-split'!J20,"0.000")&IF('Estimates-split'!M20="","",IF('Estimates-split'!M20<0.01,"***",IF('Estimates-split'!M20<0.05,"**",IF('Estimates-split'!M20<0.1,"*","")))) -> -0.037 | E39: =TEXT('Estimates-split'!N20,"0.000")&IF('Estimates-split'!Q20="","",IF('Estimates-split'!Q20<0.01,"***",IF('Estimates-split'!Q20<0.05,"**",IF('Estimates-split'!Q20<0.1,"*","")))) -> 0.004
C40: =IF('Estimates-split'!H20="","(n/a)","("&TEXT('Estimates-split'!H20,"0.00")&")") -> (0.29) | D40: =IF('Estimates-split'!L20="","(n/a)","("&TEXT('Estimates-split'!L20,"0.00")&")") -> (-0.22) | E40: =IF('Estimates-split'!P20="","(n/a)","("&TEXT('Estimates-split'!P20,"0.00")&")") -> (0.03)
A41: CIO Attended Elite College (0/1) | C41: =TEXT('Estimates-split'!F21,"0.000")&IF('Estimates-split'!I21="","",IF('Estimates-split'!I21<0.01,"***",IF('Estimates-split'!I21<0.05,"**",IF('Estimates-split'!I21<0.1,"*","")))) -> -0.112 | D41: =TEXT('Estimates-split'!J21,"0.000")&IF('Estimates-split'!M21="","",IF('Estimates-split'!M21<0.01,"***",IF('Estimates-split'!M21<0.05,"**",IF('Estimates-split'!M21<0.1,"*","")))) -> 0.244 | E41: =TEXT('Estimates-split'!N21,"0.000")&IF('Estimates-split'!Q21="","",IF('Estimates-split'!Q21<0.01,"***",IF('Estimates-split'!Q21<0.05,"**",IF('Estimates-split'!Q21<0.1,"*","")))) -> 0.289
C42: =IF('Estimates-split'!H21="","(n/a)","("&TEXT('Estimates-split'!H21,"0.00")&")") -> (-0.80) | D42: =IF('Estimates-split'!L21="","(n/a)","("&TEXT('Estimates-split'!L21,"0.00")&")") -> (1.01) | E42: =IF('Estimates-split'!P21="","(n/a)","("&TEXT('Estimates-split'!P21,"0.00")&")") -> (1.20)
A43: Separate Investment Board (0/1) | C43: =TEXT('Estimates-split'!F22,"0.000")&IF('Estimates-split'!I22="","",IF('Estimates-split'!I22<0.01,"***",IF('Estimates-split'!I22<0.05,"**",IF('Estimates-split'!I22<0.1,"*","")))) -> 0.269* | D43: =TEXT('Estimates-split'!J22,"0.000")&IF('Estimates-split'!M22="","",IF('Estimates-split'!M22<0.01,"***",IF('Estimates-split'!M22<0.05,"**",IF('Estimates-split'!M22<0.1,"*","")))) -> -0.260 | E43: =TEXT('Estimates-split'!N22,"0.000")&IF('Estimates-split'!Q22="","",IF('Estimates-split'!Q22<0.01,"***",IF('Estimates-split'!Q22<0.05,"**",IF('Estimates-split'!Q22<0.1,"*","")))) -> -0.187
C44: =IF('Estimates-split'!H22="","(n/a)","("&TEXT('Estimates-split'!H22,"0.00")&")") -> (2.04) | D44: =IF('Estimates-split'!L22="","(n/a)","("&TEXT('Estimates-split'!L22,"0.00")&")") -> (-0.31) | E44: =IF('Estimates-split'!P22="","(n/a)","("&TEXT('Estimates-split'!P22,"0.00")&")") -> (-0.19)
A45: % Political Appointees on Board | C45: =TEXT('Estimates-split'!F23,"0.000")&IF('Estimates-split'!I23="","",IF('Estimates-split'!I23<0.01,"***",IF('Estimates-split'!I23<0.05,"**",IF('Estimates-split'!I23<0.1,"*","")))) -> -0.373 | D45: =TEXT('Estimates-split'!J23,"0.000")&IF('Estimates-split'!M23="","",IF('Estimates-split'!M23<0.01,"***",IF('Estimates-split'!M23<0.05,"**",IF('Estimates-split'!M23<0.1,"*","")))) -> -0.068 | E45: =TEXT('Estimates-split'!N23,"0.000")&IF('Estimates-split'!Q23="","",IF('Estimates-split'!Q23<0.01,"***",IF('Estimates-split'!Q23<0.05,"**",IF('Estimates-split'!Q23<0.1,"*","")))) -> -0.466
C46: =IF('Estimates-split'!H23="","(n/a)","("&TEXT('Estimates-split'!H23,"0.00")&")") -> (-1.53) | D46: =IF('Estimates-split'!L23="","(n/a)","("&TEXT('Estimates-split'!L23,"0.00")&")") -> (-0.04) | E46: =IF('Estimates-split'!P23="","(n/a)","("&TEXT('Estimates-split'!P23,"0.00")&")") -> (-0.28)
A48: Observations | B48: ='Estimates-split'!B26 -> 1727 | C48: ='Estimates-split'!F26 -> 1483 | D48: ='Estimates-split'!J26 -> 1482 | E48: ='Estimates-split'!N26 -> 1482
A49: Adjusted R-squared | B49: ='Estimates-split'!B29 -> 0.048732205 | C49: ='Estimates-split'!F29 -> 0.058351239 | D49: ='Estimates-split'!J29 -> 0.080509584 | E49: ='Estimates-split'!N29 -> 0.095258826
A50: Plan FE | B50: No | C50: No | D50: Yes | E50: Yes
A51: Year FE | B51: Yes | C51: Yes | D51: No | E51: Yes
A52: p-value: First Half = Second Half | B52: ='Estimates-split'!E24 -> 0.65733503 | C52: ='Estimates-split'!I24 -> 0.91153112 | D52: ='Estimates-split'!M24 -> 0.32069434 | E52: ='Estimates-split'!Q24 -> 0.2419817
A54: Panel B. Benchmark-Adjusted Returns
B55: (1) | C55: (2) | D55: (3) | E55: (4)
B56: Bench-adj. Ret. (t) | C56: Bench-adj. Ret. (t) | D56: Bench-adj. Ret. (t) | E56: Bench-adj. Ret. (t)
A57: Conflicted CIO x First Half of Tenure (0/1) | B57: =TEXT('Estimates-split'!R4,"0.000")&IF('Estimates-split'!U4="","",IF('Estimates-split'!U4<0.01,"***",IF('Estimates-split'!U4<0.05,"**",IF('Estimates-split'!U4<0.1,"*","")))) -> -0.486** | C57: =TEXT('Estimates-split'!V4,"0.000")&IF('Estimates-split'!Y4="","",IF('Estimates-split'!Y4<0.01,"***",IF('Estimates-split'!Y4<0.05,"**",IF('Estimates-split'!Y4<0.1,"*","")))) -> -0.611*** | D57: =TEXT('Estimates-split'!Z4,"0.000")&IF('Estimates-split'!AC4="","",IF('Estimates-split'!AC4<0.01,"***",IF('Estimates-split'!AC4<0.05,"**",IF('Estimates-split'!AC4<0.1,"*","")))) -> -0.584** | E57: =TEXT('Estimates-split'!AD4,"0.000")&IF('Estimates-split'!AG4="","",IF('Estimates-split'!AG4<0.01,"***",IF('Estimates-split'!AG4<0.05,"**",IF('Estimates-split'!AG4<0.1,"*","")))) -> -0.684**
B58: =IF('Estimates-split'!T4="","(n/a)","("&TEXT('Estimates-split'!T4,"0.00")&")") -> (-2.46) | C58: =IF('Estimates-split'!X4="","(n/a)","("&TEXT('Estimates-split'!X4,"0.00")&")") -> (-3.85) | D58: =IF('Estimates-split'!AB4="","(n/a)","("&TEXT('Estimates-split'!AB4,"0.00")&")") -> (-2.51) | E58: =IF('Estimates-split'!AF4="","(n/a)","("&TEXT('Estimates-split'!AF4,"0.00")&")") -> (-2.86)
A59: Conflicted CIO x Second Half of Tenure (0/1) | B59: =TEXT('Estimates-split'!R5,"0.000")&IF('Estimates-split'!U5="","",IF('Estimates-split'!U5<0.01,"***",IF('Estimates-split'!U5<0.05,"**",IF('Estimates-split'!U5<0.1,"*","")))) -> -0.330 | C59: =TEXT('Estimates-split'!V5,"0.000")&IF('Estimates-split'!Y5="","",IF('Estimates-split'!Y5<0.01,"***",IF('Estimates-split'!Y5<0.05,"**",IF('Estimates-split'!Y5<0.1,"*","")))) -> -0.424** | D59: =TEXT('Estimates-split'!Z5,"0.000")&IF('Estimates-split'!AC5="","",IF('Estimates-split'!AC5<0.01,"***",IF('Estimates-split'!AC5<0.05,"**",IF('Estimates-split'!AC5<0.1,"*","")))) -> -0.227 | E59: =TEXT('Estimates-split'!AD5,"0.000")&IF('Estimates-split'!AG5="","",IF('Estimates-split'!AG5<0.01,"***",IF('Estimates-split'!AG5<0.05,"**",IF('Estimates-split'!AG5<0.1,"*","")))) -> -0.248
B60: =IF('Estimates-split'!T5="","(n/a)","("&TEXT('Estimates-split'!T5,"0.00")&")") -> (-1.53) | C60: =IF('Estimates-split'!X5="","(n/a)","("&TEXT('Estimates-split'!X5,"0.00")&")") -> (-2.63) | D60: =IF('Estimates-split'!AB5="","(n/a)","("&TEXT('Estimates-split'!AB5,"0.00")&")") -> (-1.02) | E60: =IF('Estimates-split'!AF5="","(n/a)","("&TEXT('Estimates-split'!AF5,"0.00")&")") -> (-1.08)
A61: Investment Return (t - 1) | B61: =TEXT('Estimates-split'!R6,"0.000")&IF('Estimates-split'!U6="","",IF('Estimates-split'!U6<0.01,"***",IF('Estimates-split'!U6<0.05,"**",IF('Estimates-split'!U6<0.1,"*","")))) -> -0.003 | C61: =TEXT('Estimates-split'!V6,"0.000")&IF('Estimates-split'!Y6="","",IF('Estimates-split'!Y6<0.01,"***",IF('Estimates-split'!Y6<0.05,"**",IF('Estimates-split'!Y6<0.1,"*","")))) -> -0.012 | D61: =TEXT('Estimates-split'!Z6,"0.000")&IF('Estimates-split'!AC6="","",IF('Estimates-split'!AC6<0.01,"***",IF('Estimates-split'!AC6<0.05,"**",IF('Estimates-split'!AC6<0.1,"*","")))) -> 0.006 | E61: =TEXT('Estimates-split'!AD6,"0.000")&IF('Estimates-split'!AG6="","",IF('Estimates-split'!AG6<0.01,"***",IF('Estimates-split'!AG6<0.05,"**",IF('Estimates-split'!AG6<0.1,"*","")))) -> -0.017
B62: =IF('Estimates-split'!T6="","(n/a)","("&TEXT('Estimates-split'!T6,"0.00")&")") -> (-0.19) | C62: =IF('Estimates-split'!X6="","(n/a)","("&TEXT('Estimates-split'!X6,"0.00")&")") -> (-0.60) | D62: =IF('Estimates-split'!AB6="","(n/a)","("&TEXT('Estimates-split'!AB6,"0.00")&")") -> (0.34) | E62: =IF('Estimates-split'!AF6="","(n/a)","("&TEXT('Estimates-split'!AF6,"0.00")&")") -> (-1.04)
A63: Log (Plan Size) (t-1) | B63: =TEXT('Estimates-split'!R7,"0.000")&IF('Estimates-split'!U7="","",IF('Estimates-split'!U7<0.01,"***",IF('Estimates-split'!U7<0.05,"**",IF('Estimates-split'!U7<0.1,"*","")))) -> -0.050 | C63: =TEXT('Estimates-split'!V7,"0.000")&IF('Estimates-split'!Y7="","",IF('Estimates-split'!Y7<0.01,"***",IF('Estimates-split'!Y7<0.05,"**",IF('Estimates-split'!Y7<0.1,"*","")))) -> -0.002 | D63: =TEXT('Estimates-split'!Z7,"0.000")&IF('Estimates-split'!AC7="","",IF('Estimates-split'!AC7<0.01,"***",IF('Estimates-split'!AC7<0.05,"**",IF('Estimates-split'!AC7<0.1,"*","")))) -> -1.142* | E63: =TEXT('Estimates-split'!AD7,"0.000")&IF('Estimates-split'!AG7="","",IF('Estimates-split'!AG7<0.01,"***",IF('Estimates-split'!AG7<0.05,"**",IF('Estimates-split'!AG7<0.1,"*","")))) -> -0.242
B64: =IF('Estimates-split'!T7="","(n/a)","("&TEXT('Estimates-split'!T7,"0.00")&")") -> (-1.28) | C64: =IF('Estimates-split'!X7="","(n/a)","("&TEXT('Estimates-split'!X7,"0.00")&")") -> (-0.05) | D64: =IF('Estimates-split'!AB7="","(n/a)","("&TEXT('Estimates-split'!AB7,"0.00")&")") -> (-1.82) | E64: =IF('Estimates-split'!AF7="","(n/a)","("&TEXT('Estimates-split'!AF7,"0.00")&")") -> (-0.34)
A65: Funding Ratio (t-1) | B65: =TEXT('Estimates-split'!R8,"0.000")&IF('Estimates-split'!U8="","",IF('Estimates-split'!U8<0.01,"***",IF('Estimates-split'!U8<0.05,"**",IF('Estimates-split'!U8<0.1,"*","")))) -> 0.003 | C65: =TEXT('Estimates-split'!V8,"0.000")&IF('Estimates-split'!Y8="","",IF('Estimates-split'!Y8<0.01,"***",IF('Estimates-split'!Y8<0.05,"**",IF('Estimates-split'!Y8<0.1,"*","")))) -> 0.004 | D65: =TEXT('Estimates-split'!Z8,"0.000")&IF('Estimates-split'!AC8="","",IF('Estimates-split'!AC8<0.01,"***",IF('Estimates-split'!AC8<0.05,"**",IF('Estimates-split'!AC8<0.1,"*","")))) -> -0.020 | E65: =TEXT('Estimates-split'!AD8,"0.000")&IF('Estimates-split'!AG8="","",IF('Estimates-split'!AG8<0.01,"***",IF('Estimates-split'!AG8<0.05,"**",IF('Estimates-split'!AG8<0.1,"*","")))) -> -0.017
B66: =IF('Estimates-split'!T8="","(n/a)","("&TEXT('Estimates-split'!T8,"0.00")&")") -> (0.62) | C66: =IF('Estimates-split'!X8="","(n/a)","("&TEXT('Estimates-split'!X8,"0.00")&")") -> (0.72) | D66: =IF('Estimates-split'!AB8="","(n/a)","("&TEXT('Estimates-split'!AB8,"0.00")&")") -> (-1.55) | E66: =IF('Estimates-split'!AF8="","(n/a)","("&TEXT('Estimates-split'!AF8,"0.00")&")") -> (-1.49)
A67: Equity Allocation (%) | B67: =TEXT('Estimates-split'!R9,"0.000")&IF('Estimates-split'!U9="","",IF('Estimates-split'!U9<0.01,"***",IF('Estimates-split'!U9<0.05,"**",IF('Estimates-split'!U9<0.1,"*","")))) -> -0.171 | C67: =TEXT('Estimates-split'!V9,"0.000")&IF('Estimates-split'!Y9="","",IF('Estimates-split'!Y9<0.01,"***",IF('Estimates-split'!Y9<0.05,"**",IF('Estimates-split'!Y9<0.1,"*","")))) -> -0.010 | D67: =TEXT('Estimates-split'!Z9,"0.000")&IF('Estimates-split'!AC9="","",IF('Estimates-split'!AC9<0.01,"***",IF('Estimates-split'!AC9<0.05,"**",IF('Estimates-split'!AC9<0.1,"*","")))) -> -0.002 | E67: =TEXT('Estimates-split'!AD9,"0.000")&IF('Estimates-split'!AG9="","",IF('Estimates-split'!AG9<0.01,"***",IF('Estimates-split'!AG9<0.05,"**",IF('Estimates-split'!AG9<0.1,"*","")))) -> 0.020
B68: =IF('Estimates-split'!T9="","(n/a)","("&TEXT('Estimates-split'!T9,"0.00")&")") -> (-1.29) | C68: =IF('Estimates-split'!X9="","(n/a)","("&TEXT('Estimates-split'!X9,"0.00")&")") -> (-0.09) | D68: =IF('Estimates-split'!AB9="","(n/a)","("&TEXT('Estimates-split'!AB9,"0.00")&")") -> (-0.01) | E68: =IF('Estimates-split'!AF9="","(n/a)","("&TEXT('Estimates-split'!AF9,"0.00")&")") -> (0.12)
A69: Fixed Income Allocation (%) | B69: =TEXT('Estimates-split'!R10,"0.000")&IF('Estimates-split'!U10="","",IF('Estimates-split'!U10<0.01,"***",IF('Estimates-split'!U10<0.05,"**",IF('Estimates-split'!U10<0.1,"*","")))) -> -0.159 | C69: =TEXT('Estimates-split'!V10,"0.000")&IF('Estimates-split'!Y10="","",IF('Estimates-split'!Y10<0.01,"***",IF('Estimates-split'!Y10<0.05,"**",IF('Estimates-split'!Y10<0.1,"*","")))) -> -0.006 | D69: =TEXT('Estimates-split'!Z10,"0.000")&IF('Estimates-split'!AC10="","",IF('Estimates-split'!AC10<0.01,"***",IF('Estimates-split'!AC10<0.05,"**",IF('Estimates-split'!AC10<0.1,"*","")))) -> -0.019 | E69: =TEXT('Estimates-split'!AD10,"0.000")&IF('Estimates-split'!AG10="","",IF('Estimates-split'!AG10<0.01,"***",IF('Estimates-split'!AG10<0.05,"**",IF('Estimates-split'!AG10<0.1,"*","")))) -> 0.018
B70: =IF('Estimates-split'!T10="","(n/a)","("&TEXT('Estimates-split'!T10,"0.00")&")") -> (-1.20) | C70: =IF('Estimates-split'!X10="","(n/a)","("&TEXT('Estimates-split'!X10,"0.00")&")") -> (-0.05) | D70: =IF('Estimates-split'!AB10="","(n/a)","("&TEXT('Estimates-split'!AB10,"0.00")&")") -> (-0.11) | E70: =IF('Estimates-split'!AF10="","(n/a)","("&TEXT('Estimates-split'!AF10,"0.00")&")") -> (0.10)
A71: Real Estate Allocation (%) | B71: =TEXT('Estimates-split'!R11,"0.000")&IF('Estimates-split'!U11="","",IF('Estimates-split'!U11<0.01,"***",IF('Estimates-split'!U11<0.05,"**",IF('Estimates-split'!U11<0.1,"*","")))) -> -0.184 | C71: =TEXT('Estimates-split'!V11,"0.000")&IF('Estimates-split'!Y11="","",IF('Estimates-split'!Y11<0.01,"***",IF('Estimates-split'!Y11<0.05,"**",IF('Estimates-split'!Y11<0.1,"*","")))) -> -0.014 | D71: =TEXT('Estimates-split'!Z11,"0.000")&IF('Estimates-split'!AC11="","",IF('Estimates-split'!AC11<0.01,"***",IF('Estimates-split'!AC11<0.05,"**",IF('Estimates-split'!AC11<0.1,"*","")))) -> -0.049 | E71: =TEXT('Estimates-split'!AD11,"0.000")&IF('Estimates-split'!AG11="","",IF('Estimates-split'!AG11<0.01,"***",IF('Estimates-split'!AG11<0.05,"**",IF('Estimates-split'!AG11<0.1,"*","")))) -> -0.018
B72: =IF('Estimates-split'!T11="","(n/a)","("&TEXT('Estimates-split'!T11,"0.00")&")") -> (-1.50) | C72: =IF('Estimates-split'!X11="","(n/a)","("&TEXT('Estimates-split'!X11,"0.00")&")") -> (-0.13) | D72: =IF('Estimates-split'!AB11="","(n/a)","("&TEXT('Estimates-split'!AB11,"0.00")&")") -> (-0.28) | E72: =IF('Estimates-split'!AF11="","(n/a)","("&TEXT('Estimates-split'!AF11,"0.00")&")") -> (-0.11)
A73: Private Equity Allocation (%) | B73: =TEXT('Estimates-split'!R12,"0.000")&IF('Estimates-split'!U12="","",IF('Estimates-split'!U12<0.01,"***",IF('Estimates-split'!U12<0.05,"**",IF('Estimates-split'!U12<0.1,"*","")))) -> -0.158 | C73: =TEXT('Estimates-split'!V12,"0.000")&IF('Estimates-split'!Y12="","",IF('Estimates-split'!Y12<0.01,"***",IF('Estimates-split'!Y12<0.05,"**",IF('Estimates-split'!Y12<0.1,"*","")))) -> 0.004 | D73: =TEXT('Estimates-split'!Z12,"0.000")&IF('Estimates-split'!AC12="","",IF('Estimates-split'!AC12<0.01,"***",IF('Estimates-split'!AC12<0.05,"**",IF('Estimates-split'!AC12<0.1,"*","")))) -> -0.021 | E73: =TEXT('Estimates-split'!AD12,"0.000")&IF('Estimates-split'!AG12="","",IF('Estimates-split'!AG12<0.01,"***",IF('Estimates-split'!AG12<0.05,"**",IF('Estimates-split'!AG12<0.1,"*","")))) -> 0.030
B74: =IF('Estimates-split'!T12="","(n/a)","("&TEXT('Estimates-split'!T12,"0.00")&")") -> (-1.21) | C74: =IF('Estimates-split'!X12="","(n/a)","("&TEXT('Estimates-split'!X12,"0.00")&")") -> (0.03) | D74: =IF('Estimates-split'!AB12="","(n/a)","("&TEXT('Estimates-split'!AB12,"0.00")&")") -> (-0.13) | E74: =IF('Estimates-split'!AF12="","(n/a)","("&TEXT('Estimates-split'!AF12,"0.00")&")") -> (0.17)
A75: Hedge Fund Allocation (%) | B75: =TEXT('Estimates-split'!R13,"0.000")&IF('Estimates-split'!U13="","",IF('Estimates-split'!U13<0.01,"***",IF('Estimates-split'!U13<0.05,"**",IF('Estimates-split'!U13<0.1,"*","")))) -> -0.161 | C75: =TEXT('Estimates-split'!V13,"0.000")&IF('Estimates-split'!Y13="","",IF('Estimates-split'!Y13<0.01,"***",IF('Estimates-split'!Y13<0.05,"**",IF('Estimates-split'!Y13<0.1,"*","")))) -> -0.003 | D75: =TEXT('Estimates-split'!Z13,"0.000")&IF('Estimates-split'!AC13="","",IF('Estimates-split'!AC13<0.01,"***",IF('Estimates-split'!AC13<0.05,"**",IF('Estimates-split'!AC13<0.1,"*","")))) -> -0.007 | E75: =TEXT('Estimates-split'!AD13,"0.000")&IF('Estimates-split'!AG13="","",IF('Estimates-split'!AG13<0.01,"***",IF('Estimates-split'!AG13<0.05,"**",IF('Estimates-split'!AG13<0.1,"*","")))) -> 0.012
B76: =IF('Estimates-split'!T13="","(n/a)","("&TEXT('Estimates-split'!T13,"0.00")&")") -> (-1.27) | C76: =IF('Estimates-split'!X13="","(n/a)","("&TEXT('Estimates-split'!X13,"0.00")&")") -> (-0.03) | D76: =IF('Estimates-split'!AB13="","(n/a)","("&TEXT('Estimates-split'!AB13,"0.00")&")") -> (-0.04) | E76: =IF('Estimates-split'!AF13="","(n/a)","("&TEXT('Estimates-split'!AF13,"0.00")&")") -> (0.07)
A77: Misc. Alternatives Allocation (%) | B77: =TEXT('Estimates-split'!R14,"0.000")&IF('Estimates-split'!U14="","",IF('Estimates-split'!U14<0.01,"***",IF('Estimates-split'!U14<0.05,"**",IF('Estimates-split'!U14<0.1,"*","")))) -> -0.179 | C77: =TEXT('Estimates-split'!V14,"0.000")&IF('Estimates-split'!Y14="","",IF('Estimates-split'!Y14<0.01,"***",IF('Estimates-split'!Y14<0.05,"**",IF('Estimates-split'!Y14<0.1,"*","")))) -> -0.011 | D77: =TEXT('Estimates-split'!Z14,"0.000")&IF('Estimates-split'!AC14="","",IF('Estimates-split'!AC14<0.01,"***",IF('Estimates-split'!AC14<0.05,"**",IF('Estimates-split'!AC14<0.1,"*","")))) -> -0.024 | E77: =TEXT('Estimates-split'!AD14,"0.000")&IF('Estimates-split'!AG14="","",IF('Estimates-split'!AG14<0.01,"***",IF('Estimates-split'!AG14<0.05,"**",IF('Estimates-split'!AG14<0.1,"*","")))) -> 0.034
B78: =IF('Estimates-split'!T14="","(n/a)","("&TEXT('Estimates-split'!T14,"0.00")&")") -> (-1.43) | C78: =IF('Estimates-split'!X14="","(n/a)","("&TEXT('Estimates-split'!X14,"0.00")&")") -> (-0.10) | D78: =IF('Estimates-split'!AB14="","(n/a)","("&TEXT('Estimates-split'!AB14,"0.00")&")") -> (-0.13) | E78: =IF('Estimates-split'!AF14="","(n/a)","("&TEXT('Estimates-split'!AF14,"0.00")&")") -> (0.19)
A79: Commodities Allocation (%) | B79: =TEXT('Estimates-split'!R15,"0.000")&IF('Estimates-split'!U15="","",IF('Estimates-split'!U15<0.01,"***",IF('Estimates-split'!U15<0.05,"**",IF('Estimates-split'!U15<0.1,"*","")))) -> -0.198 | C79: =TEXT('Estimates-split'!V15,"0.000")&IF('Estimates-split'!Y15="","",IF('Estimates-split'!Y15<0.01,"***",IF('Estimates-split'!Y15<0.05,"**",IF('Estimates-split'!Y15<0.1,"*","")))) -> -0.021 | D79: =TEXT('Estimates-split'!Z15,"0.000")&IF('Estimates-split'!AC15="","",IF('Estimates-split'!AC15<0.01,"***",IF('Estimates-split'!AC15<0.05,"**",IF('Estimates-split'!AC15<0.1,"*","")))) -> -0.032 | E79: =TEXT('Estimates-split'!AD15,"0.000")&IF('Estimates-split'!AG15="","",IF('Estimates-split'!AG15<0.01,"***",IF('Estimates-split'!AG15<0.05,"**",IF('Estimates-split'!AG15<0.1,"*","")))) -> 0.003
B80: =IF('Estimates-split'!T15="","(n/a)","("&TEXT('Estimates-split'!T15,"0.00")&")") -> (-1.46) | C80: =IF('Estimates-split'!X15="","(n/a)","("&TEXT('Estimates-split'!X15,"0.00")&")") -> (-0.18) | D80: =IF('Estimates-split'!AB15="","(n/a)","("&TEXT('Estimates-split'!AB15,"0.00")&")") -> (-0.18) | E80: =IF('Estimates-split'!AF15="","(n/a)","("&TEXT('Estimates-split'!AF15,"0.00")&")") -> (0.02)
A81: Cash Allocation (%) | B81: =TEXT('Estimates-split'!R16,"0.000")&IF('Estimates-split'!U16="","",IF('Estimates-split'!U16<0.01,"***",IF('Estimates-split'!U16<0.05,"**",IF('Estimates-split'!U16<0.1,"*","")))) -> -0.126 | C81: =TEXT('Estimates-split'!V16,"0.000")&IF('Estimates-split'!Y16="","",IF('Estimates-split'!Y16<0.01,"***",IF('Estimates-split'!Y16<0.05,"**",IF('Estimates-split'!Y16<0.1,"*","")))) -> 0.021 | D81: =TEXT('Estimates-split'!Z16,"0.000")&IF('Estimates-split'!AC16="","",IF('Estimates-split'!AC16<0.01,"***",IF('Estimates-split'!AC16<0.05,"**",IF('Estimates-split'!AC16<0.1,"*","")))) -> 0.037 | E81: =TEXT('Estimates-split'!AD16,"0.000")&IF('Estimates-split'!AG16="","",IF('Estimates-split'!AG16<0.01,"***",IF('Estimates-split'!AG16<0.05,"**",IF('Estimates-split'!AG16<0.1,"*","")))) -> 0.063
B82: =IF('Estimates-split'!T16="","(n/a)","("&TEXT('Estimates-split'!T16,"0.00")&")") -> (-0.86) | C82: =IF('Estimates-split'!X16="","(n/a)","("&TEXT('Estimates-split'!X16,"0.00")&")") -> (0.16) | D82: =IF('Estimates-split'!AB16="","(n/a)","("&TEXT('Estimates-split'!AB16,"0.00")&")") -> (0.19) | E82: =IF('Estimates-split'!AF16="","(n/a)","("&TEXT('Estimates-split'!AF16,"0.00")&")") -> (0.34)
A83: Financial Center (0/1) | B83: =TEXT('Estimates-split'!R17,"0.000")&IF('Estimates-split'!U17="","",IF('Estimates-split'!U17<0.01,"***",IF('Estimates-split'!U17<0.05,"**",IF('Estimates-split'!U17<0.1,"*","")))) -> -0.120* | C83: =TEXT('Estimates-split'!V17,"0.000")&IF('Estimates-split'!Y17="","",IF('Estimates-split'!Y17<0.01,"***",IF('Estimates-split'!Y17<0.05,"**",IF('Estimates-split'!Y17<0.1,"*","")))) -> -0.124
B84: =IF('Estimates-split'!T17="","(n/a)","("&TEXT('Estimates-split'!T17,"0.00")&")") -> (-1.80) | C84: =IF('Estimates-split'!X17="","(n/a)","("&TEXT('Estimates-split'!X17,"0.00")&")") -> (-1.56)
A85: Log (CIO Age) (t-1) | C85: =TEXT('Estimates-split'!V18,"0.000")&IF('Estimates-split'!Y18="","",IF('Estimates-split'!Y18<0.01,"***",IF('Estimates-split'!Y18<0.05,"**",IF('Estimates-split'!Y18<0.1,"*","")))) -> -1.210*** | D85: =TEXT('Estimates-split'!Z18,"0.000")&IF('Estimates-split'!AC18="","",IF('Estimates-split'!AC18<0.01,"***",IF('Estimates-split'!AC18<0.05,"**",IF('Estimates-split'!AC18<0.1,"*","")))) -> -0.155 | E85: =TEXT('Estimates-split'!AD18,"0.000")&IF('Estimates-split'!AG18="","",IF('Estimates-split'!AG18<0.01,"***",IF('Estimates-split'!AG18<0.05,"**",IF('Estimates-split'!AG18<0.1,"*","")))) -> 0.211
C86: =IF('Estimates-split'!X18="","(n/a)","("&TEXT('Estimates-split'!X18,"0.00")&")") -> (-3.31) | D86: =IF('Estimates-split'!AB18="","(n/a)","("&TEXT('Estimates-split'!AB18,"0.00")&")") -> (-0.23) | E86: =IF('Estimates-split'!AF18="","(n/a)","("&TEXT('Estimates-split'!AF18,"0.00")&")") -> (0.31)
A87: Log (CIO Tenure) (t-1) | C87: =TEXT('Estimates-split'!V19,"0.000")&IF('Estimates-split'!Y19="","",IF('Estimates-split'!Y19<0.01,"***",IF('Estimates-split'!Y19<0.05,"**",IF('Estimates-split'!Y19<0.1,"*","")))) -> -0.012 | D87: =TEXT('Estimates-split'!Z19,"0.000")&IF('Estimates-split'!AC19="","",IF('Estimates-split'!AC19<0.01,"***",IF('Estimates-split'!AC19<0.05,"**",IF('Estimates-split'!AC19<0.1,"*","")))) -> -0.077 | E87: =TEXT('Estimates-split'!AD19,"0.000")&IF('Estimates-split'!AG19="","",IF('Estimates-split'!AG19<0.01,"***",IF('Estimates-split'!AG19<0.05,"**",IF('Estimates-split'!AG19<0.1,"*","")))) -> -0.193
C88: =IF('Estimates-split'!X19="","(n/a)","("&TEXT('Estimates-split'!X19,"0.00")&")") -> (-0.11) | D88: =IF('Estimates-split'!AB19="","(n/a)","("&TEXT('Estimates-split'!AB19,"0.00")&")") -> (-0.64) | E88: =IF('Estimates-split'!AF19="","(n/a)","("&TEXT('Estimates-split'!AF19,"0.00")&")") -> (-1.47)
A89: CIO Prior Private Experience (0/1) | C89: =TEXT('Estimates-split'!V20,"0.000")&IF('Estimates-split'!Y20="","",IF('Estimates-split'!Y20<0.01,"***",IF('Estimates-split'!Y20<0.05,"**",IF('Estimates-split'!Y20<0.1,"*","")))) -> 0.102 | D89: =TEXT('Estimates-split'!Z20,"0.000")&IF('Estimates-split'!AC20="","",IF('Estimates-split'!AC20<0.01,"***",IF('Estimates-split'!AC20<0.05,"**",IF('Estimates-split'!AC20<0.1,"*","")))) -> 0.134 | E89: =TEXT('Estimates-split'!AD20,"0.000")&IF('Estimates-split'!AG20="","",IF('Estimates-split'!AG20<0.01,"***",IF('Estimates-split'!AG20<0.05,"**",IF('Estimates-split'!AG20<0.1,"*","")))) -> 0.107
C90: =IF('Estimates-split'!X20="","(n/a)","("&TEXT('Estimates-split'!X20,"0.00")&")") -> (0.98) | D90: =IF('Estimates-split'!AB20="","(n/a)","("&TEXT('Estimates-split'!AB20,"0.00")&")") -> (0.66) | E90: =IF('Estimates-split'!AF20="","(n/a)","("&TEXT('Estimates-split'!AF20,"0.00")&")") -> (0.51)
A91: CIO Attended Elite College (0/1) | C91: =TEXT('Estimates-split'!V21,"0.000")&IF('Estimates-split'!Y21="","",IF('Estimates-split'!Y21<0.01,"***",IF('Estimates-split'!Y21<0.05,"**",IF('Estimates-split'!Y21<0.1,"*","")))) -> -0.154 | D91: =TEXT('Estimates-split'!Z21,"0.000")&IF('Estimates-split'!AC21="","",IF('Estimates-split'!AC21<0.01,"***",IF('Estimates-split'!AC21<0.05,"**",IF('Estimates-split'!AC21<0.1,"*","")))) -> 0.103 | E91: =TEXT('Estimates-split'!AD21,"0.000")&IF('Estimates-split'!AG21="","",IF('Estimates-split'!AG21<0.01,"***",IF('Estimates-split'!AG21<0.05,"**",IF('Estimates-split'!AG21<0.1,"*","")))) -> -0.017
C92: =IF('Estimates-split'!X21="","(n/a)","("&TEXT('Estimates-split'!X21,"0.00")&")") -> (-0.98) | D92: =IF('Estimates-split'!AB21="","(n/a)","("&TEXT('Estimates-split'!AB21,"0.00")&")") -> (0.51) | E92: =IF('Estimates-split'!AF21="","(n/a)","("&TEXT('Estimates-split'!AF21,"0.00")&")") -> (-0.08)
A93: Separate Investment Board (0/1) | C93: =TEXT('Estimates-split'!V22,"0.000")&IF('Estimates-split'!Y22="","",IF('Estimates-split'!Y22<0.01,"***",IF('Estimates-split'!Y22<0.05,"**",IF('Estimates-split'!Y22<0.1,"*","")))) -> 0.314* | D93: =TEXT('Estimates-split'!Z22,"0.000")&IF('Estimates-split'!AC22="","",IF('Estimates-split'!AC22<0.01,"***",IF('Estimates-split'!AC22<0.05,"**",IF('Estimates-split'!AC22<0.1,"*","")))) -> -0.048 | E93: =TEXT('Estimates-split'!AD22,"0.000")&IF('Estimates-split'!AG22="","",IF('Estimates-split'!AG22<0.01,"***",IF('Estimates-split'!AG22<0.05,"**",IF('Estimates-split'!AG22<0.1,"*","")))) -> 0.541
C94: =IF('Estimates-split'!X22="","(n/a)","("&TEXT('Estimates-split'!X22,"0.00")&")") -> (1.87) | D94: =IF('Estimates-split'!AB22="","(n/a)","("&TEXT('Estimates-split'!AB22,"0.00")&")") -> (-0.05) | E94: =IF('Estimates-split'!AF22="","(n/a)","("&TEXT('Estimates-split'!AF22,"0.00")&")") -> (0.72)
A95: % Political Appointees on Board | C95: =TEXT('Estimates-split'!V23,"0.000")&IF('Estimates-split'!Y23="","",IF('Estimates-split'!Y23<0.01,"***",IF('Estimates-split'!Y23<0.05,"**",IF('Estimates-split'!Y23<0.1,"*","")))) -> -0.042 | D95: =TEXT('Estimates-split'!Z23,"0.000")&IF('Estimates-split'!AC23="","",IF('Estimates-split'!AC23<0.01,"***",IF('Estimates-split'!AC23<0.05,"**",IF('Estimates-split'!AC23<0.1,"*","")))) -> 0.388 | E95: =TEXT('Estimates-split'!AD23,"0.000")&IF('Estimates-split'!AG23="","",IF('Estimates-split'!AG23<0.01,"***",IF('Estimates-split'!AG23<0.05,"**",IF('Estimates-split'!AG23<0.1,"*","")))) -> -0.322
C96: =IF('Estimates-split'!X23="","(n/a)","("&TEXT('Estimates-split'!X23,"0.00")&")") -> (-0.20) | D96: =IF('Estimates-split'!AB23="","(n/a)","("&TEXT('Estimates-split'!AB23,"0.00")&")") -> (0.24) | E96: =IF('Estimates-split'!AF23="","(n/a)","("&TEXT('Estimates-split'!AF23,"0.00")&")") -> (-0.24)
A98: Observations | B98: ='Estimates-split'!R26 -> 1538 | C98: ='Estimates-split'!V26 -> 1320 | D98: ='Estimates-split'!Z26 -> 1319 | E98: ='Estimates-split'!AD26 -> 1319
A99: Adjusted R-squared | B99: ='Estimates-split'!R29 -> 0.11857809 | C99: ='Estimates-split'!V29 -> 0.12810988 | D99: ='Estimates-split'!Z29 -> 0.020791442 | E99: ='Estimates-split'!AD29 -> 0.1239048
A100: Plan FE | B100: No | C100: No | D100: Yes | E100: Yes
A101: Year FE | B101: Yes | C101: Yes | D101: No | E101: Yes
A102: p-value: First Half = Second Half | B102: ='Estimates-split'!U24 -> 0.57244011 | C102: ='Estimates-split'!Y24 -> 0.38615056 | D102: ='Estimates-split'!AC24 -> 0.19050089 | E102: ='Estimates-split'!AG24 -> 0.095611012

Sheet Table XII-split
A1: Table XII: Conflicted CIOs: Fee Ratio in the First versus Second Half of Tenure
A2: This table repeats the regressions of Table XI with Fee Ratio as the dependent variable. Fee Ratio is the plan's total investment fees as a percentage of plan assets. Conflicted CIO x First Half of Tenure and Conflicted CIO x Second Half of Tenure are defined as in Table XI, and the omitted category is all plan-years run by non-conflicted CIOs. The other independent variables are as defined in Table I. The last row reports the p-value of a test that the first-half and second-half coefficients are equal. The standard errors are double clustered by plan and year. Coefficients marked with ***, **, and * are significant at the 1%, 5%, and 10% level, respectively.
B4: (1) | C4: (2) | D4: (3) | E4: (4)
B5: Fee Ratio (t) | C5: Fee Ratio (t) | D5: Fee Ratio (t) | E5: Fee Ratio (t)
A6: Conflicted CIO x First Half of Tenure (0/1) | B6: =TEXT('Estimates-split'!AH4,"0.000")&IF('Estimates-split'!AK4="","",IF('Estimates-split'!AK4<0.01,"***",IF('Estimates-split'!AK4<0.05,"**",IF('Estimates-split'!AK4<0.1,"*","")))) -> -0.045 | C6: =TEXT('Estimates-split'!AL4,"0.000")&IF('Estimates-split'!AO4="","",IF('Estimates-split'!AO4<0.01,"***",IF('Estimates-split'!AO4<0.05,"**",IF('Estimates-split'!AO4<0.1,"*","")))) -> -0.028 | D6: =TEXT('Estimates-split'!AP4,"0.000")&IF('Estimates-split'!AS4="","",IF('Estimates-split'!AS4<0.01,"***",IF('Estimates-split'!AS4<0.05,"**",IF('Estimates-split'!AS4<0.1,"*","")))) -> 0.039 | E6: =TEXT('Estimates-split'!AT4,"0.000")&IF('Estimates-split'!AW4="","",IF('Estimates-split'!AW4<0.01,"***",IF('Estimates-split'!AW4<0.05,"**",IF('Estimates-split'!AW4<0.1,"*","")))) -> 0.037
B7: =IF('Estimates-split'!AJ4="","(n/a)","("&TEXT('Estimates-split'!AJ4,"0.00")&")") -> (-1.30) | C7: =IF('Estimates-split'!AN4="","(n/a)","("&TEXT('Estimates-split'!AN4,"0.00")&")") -> (-0.62) | D7: =IF('Estimates-split'!AR4="","(n/a)","("&TEXT('Estimates-split'!AR4,"0.00")&")") -> (0.71) | E7: =IF('Estimates-split'!AV4="","(n/a)","("&TEXT('Estimates-split'!AV4,"0.00")&")") -> (0.67)
A8: Conflicted CIO x Second Half of Tenure (0/1) | B8: =TEXT('Estimates-split'!AH5,"0.000")&IF('Estimates-split'!AK5="","",IF('Estimates-split'!AK5<0.01,"***",IF('Estimates-split'!AK5<0.05,"**",IF('Estimates-split'!AK5<0.1,"*","")))) -> -0.047 | C8: =TEXT('Estimates-split'!AL5,"0.000")&IF('Estimates-split'!AO5="","",IF('Estimates-split'!AO5<0.01,"***",IF('Estimates-split'!AO5<0.05,"**",IF('Estimates-split'!AO5<0.1,"*","")))) -> -0.035 | D8: =TEXT('Estimates-split'!AP5,"0.000")&IF('Estimates-split'!AS5="","",IF('Estimates-split'!AS5<0.01,"***",IF('Estimates-split'!AS5<0.05,"**",IF('Estimates-split'!AS5<0.1,"*","")))) -> 0.031 | E8: =TEXT('Estimates-split'!AT5,"0.000")&IF('Estimates-split'!AW5="","",IF('Estimates-split'!AW5<0.01,"***",IF('Estimates-split'!AW5<0.05,"**",IF('Estimates-split'!AW5<0.1,"*","")))) -> 0.028
B9: =IF('Estimates-split'!AJ5="","(n/a)","("&TEXT('Estimates-split'!AJ5,"0.00")&")") -> (-1.17) | C9: =IF('Estimates-split'!AN5="","(n/a)","("&TEXT('Estimates-split'!AN5,"0.00")&")") -> (-0.90) | D9: =IF('Estimates-split'!AR5="","(n/a)","("&TEXT('Estimates-split'!AR5,"0.00")&")") -> (0.53) | E9: =IF('Estimates-split'!AV5="","(n/a)","("&TEXT('Estimates-split'!AV5,"0.00")&")") -> (0.50)
A10: Investment Return (t - 1) | B10: =TEXT('Estimates-split'!AH6,"0.000")&IF('Estimates-split'!AK6="","",IF('Estimates-split'!AK6<0.01,"***",IF('Estimates-split'!AK6<0.05,"**",IF('Estimates-split'!AK6<0.1,"*","")))) -> 0.000 | C10: =TEXT('Estimates-split'!AL6,"0.000")&IF('Estimates-split'!AO6="","",IF('Estimates-split'!AO6<0.01,"***",IF('Estimates-split'!AO6<0.05,"**",IF('Estimates-split'!AO6<0.1,"*","")))) -> 0.000 | D10: =TEXT('Estimates-split'!AP6,"0.000")&IF('Estimates-split'!AS6="","",IF('Estimates-split'!AS6<0.01,"***",IF('Estimates-split'!AS6<0.05,"**",IF('Estimates-split'!AS6<0.1,"*","")))) -> -0.001 | E10: =TEXT('Estimates-split'!AT6,"0.000")&IF('Estimates-split'!AW6="","",IF('Estimates-split'!AW6<0.01,"***",IF('Estimates-split'!AW6<0.05,"**",IF('Estimates-split'!AW6<0.1,"*","")))) -> -0.001**
B11: =IF('Estimates-split'!AJ6="","(n/a)","("&TEXT('Estimates-split'!AJ6,"0.00")&")") -> (-0.40) | C11: =IF('Estimates-split'!AN6="","(n/a)","("&TEXT('Estimates-split'!AN6,"0.00")&")") -> (-0.56) | D11: =IF('Estimates-split'!AR6="","(n/a)","("&TEXT('Estimates-split'!AR6,"0.00")&")") -> (-1.20) | E11: =IF('Estimates-split'!AV6="","(n/a)","("&TEXT('Estimates-split'!AV6,"0.00")&")") -> (-2.39)
A12: Log (Plan Size) (t-1) | B12: =TEXT('Estimates-split'!AH7,"0.000")&IF('Estimates-split'!AK7="","",IF('Estimates-split'!AK7<0.01,"***",IF('Estimates-split'!AK7<0.05,"**",IF('Estimates-split'!AK7<0.1,"*","")))) -> -0.022 | C12: =TEXT('Estimates-split'!AL7,"0.000")&IF('Estimates-split'!AO7="","",IF('Estimates-split'!AO7<0.01,"***",IF('Estimates-split'!AO7<0.05,"**",IF('Estimates-split'!AO7<0.1,"*","")))) -> -0.019 | D12: =TEXT('Estimates-split'!AP7,"0.000")&IF('Estimates-split'!AS7="","",IF('Estimates-split'!AS7<0.01,"***",IF('Estimates-split'!AS7<0.05,"**",IF('Estimates-split'!AS7<0.1,"*","")))) -> 0.008 | E12: =TEXT('Estimates-split'!AT7,"0.000")&IF('Estimates-split'!AW7="","",IF('Estimates-split'!AW7<0.01,"***",IF('Estimates-split'!AW7<0.05,"**",IF('Estimates-split'!AW7<0.1,"*","")))) -> 0.042
B13: =IF('Estimates-split'!AJ7="","(n/a)","("&TEXT('Estimates-split'!AJ7,"0.00")&")") -> (-1.62) | C13: =IF('Estimates-split'!AN7="","(n/a)","("&TEXT('Estimates-split'!AN7,"0.00")&")") -> (-1.32) | D13: =IF('Estimates-split'!AR7="","(n/a)","("&TEXT('Estimates-split'!AR7,"0.00")&")") -> (0.16) | E13: =IF('Estimates-split'!AV7="","(n/a)","("&TEXT('Estimates-split'!AV7,"0.00")&")") -> (0.41)
A14: Funding Ratio (t-1) | B14: =TEXT('Estimates-split'!AH8,"0.000")&IF('Estimates-split'!AK8="","",IF('Estimates-split'!AK8<0.01,"***",IF('Estimates-split'!AK8<0.05,"**",IF('Estimates-split'!AK8<0.1,"*","")))) -> -0.001 | C14: =TEXT('Estimates-split'!AL8,"0.000")&IF('Estimates-split'!AO8="","",IF('Estimates-split'!AO8<0.01,"***",IF('Estimates-split'!AO8<0.05,"**",IF('Estimates-split'!AO8<0.1,"*","")))) -> -0.001 | D14: =TEXT('Estimates-split'!AP8,"0.000")&IF('Estimates-split'!AS8="","",IF('Estimates-split'!AS8<0.01,"***",IF('Estimates-split'!AS8<0.05,"**",IF('Estimates-split'!AS8<0.1,"*","")))) -> -0.001 | E14: =TEXT('Estimates-split'!AT8,"0.000")&IF('Estimates-split'!AW8="","",IF('Estimates-split'!AW8<0.01,"***",IF('Estimates-split'!AW8<0.05,"**",IF('Estimates-split'!AW8<0.1,"*","")))) -> -0.002**
B15: =IF('Estimates-split'!AJ8="","(n/a)","("&TEXT('Estimates-split'!AJ8,"0.00")&")") -> (-0.94) | C15: =IF('Estimates-split'!AN8="","(n/a)","("&TEXT('Estimates-split'!AN8,"0.00")&")") -> (-1.18) | D15: =IF('Estimates-split'!AR8="","(n/a)","("&TEXT('Estimates-split'!AR8,"0.00")&")") -> (-1.14) | E15: =IF('Estimates-split'!AV8="","(n/a)","("&TEXT('Estimates-split'!AV8,"0.00")&")") -> (-2.38)
A16: Equity Allocation (%) | B16: =TEXT('Estimates-split'!AH9,"0.000")&IF('Estimates-split'!AK9="","",IF('Estimates-split'!AK9<0.01,"***",IF('Estimates-split'!AK9<0.05,"**",IF('Estimates-split'!AK9<0.1,"*","")))) -> -0.039 | C16: =TEXT('Estimates-split'!AL9,"0.000")&IF('Estimates-split'!AO9="","",IF('Estimates-split'!AO9<0.01,"***",IF('Estimates-split'!AO9<0.05,"**",IF('Estimates-split'!AO9<0.1,"*","")))) -> -0.082 | D16: =TEXT('Estimates-split'!AP9,"0.000")&IF('Estimates-split'!AS9="","",IF('Estimates-split'!AS9<0.01,"***",IF('Estimates-split'!AS9<0.05,"**",IF('Estimates-split'!AS9<0.1,"*","")))) -> -0.085 | E16: =TEXT('Estimates-split'!AT9,"0.000")&IF('Estimates-split'!AW9="","",IF('Estimates-split'!AW9<0.01,"***",IF('Estimates-split'!AW9<0.05,"**",IF('Estimates-split'!AW9<0.1,"*","")))) -> -0.086
B17: =IF('Estimates-split'!AJ9="","(n/a)","("&TEXT('Estimates-split'!AJ9,"0.00")&")") -> (-1.12) | C17: =IF('Estimates-split'!AN9="","(n/a)","("&TEXT('Estimates-split'!AN9,"0.00")&")") -> (-1.19) | D17: =IF('Estimates-split'!AR9="","(n/a)","("&TEXT('Estimates-split'!AR9,"0.00")&")") -> (-1.44) | E17: =IF('Estimates-split'!AV9="","(n/a)","("&TEXT('Estimates-split'!AV9,"0.00")&")") -> (-1.55)
A18: Fixed Income Allocation (%) | B18: =TEXT('Estimates-split'!AH10,"0.000")&IF('Estimates-split'!AK10="","",IF('Estimates-split'!AK10<0.01,"***",IF('Estimates-split'!AK10<0.05,"**",IF('Estimates-split'!AK10<0.1,"*","")))) -> -0.043 | C18: =TEXT('Estimates-split'!AL10,"0.000")&IF('Estimates-split'!AO10="","",IF('Estimates-split'!AO10<0.01,"***",IF('Estimates-split'!AO10<0.05,"**",IF('Estimates-split'!AO10<0.1,"*","")))) -> -0.087 | D18: =TEXT('Estimates-split'!AP10,"0.000")&IF('Estimates-split'!AS10="","",IF('Estimates-split'!AS10<0.01,"***",IF('Estimates-split'!AS10<0.05,"**",IF('Estimates-split'!AS10<0.1,"*","")))) -> -0.090 | E18: =TEXT('Estimates-split'!AT10,"0.000")&IF('Estimates-split'!AW10="","",IF('Estimates-split'!AW10<0.01,"***",IF('Estimates-split'!AW10<0.05,"**",IF('Estimates-split'!AW10<0.1,"*","")))) -> -0.091
B19: =IF('Estimates-split'!AJ10="","(n/a)","("&TEXT('Estimates-split'!AJ10,"0.00")&")") -> (-1.23) | C19: =IF('Estimates-split'!AN10="","(n/a)","("&TEXT('Estimates-split'!AN10,"0.00")&")") -> (-1.25) | D19: =IF('Estimates-split'!AR10="","(n/a)","("&TEXT('Estimates-split'!AR10,"0.00")&")") -> (-1.52) | E19: =IF('Estimates-split'!AV10="","(n/a)","("&TEXT('Estimates-split'!AV10,"0.00")&")") -> (-1.64)
A20: Real Estate Allocation (%) | B20: =TEXT('Estimates-split'!AH11,"0.000")&IF('Estimates-split'!AK11="","",IF('Estimates-split'!AK11<0.01,"***",IF('Estimates-split'!AK11<0.05,"**",IF('Estimates-split'!AK11<0.1,"*","")))) -> -0.032 | C20: =TEXT('Estimates-split'!AL11,"0.000")&IF('Estimates-split'!AO11="","",IF('Estimates-split'!AO11<0.01,"***",IF('Estimates-split'!AO11<0.05,"**",IF('Estimates-split'!AO11<0.1,"*","")))) -> -0.075 | D20: =TEXT('Estimates-split'!AP11,"0.000")&IF('Estimates-split'!AS11="","",IF('Estimates-split'!AS11<0.01,"***",IF('Estimates-split'!AS11<0.05,"**",IF('Estimates-split'!AS11<0.1,"*","")))) -> -0.085 | E20: =TEXT('Estimates-split'!AT11,"0.000")&IF('Estimates-split'!AW11="","",IF('Estimates-split'!AW11<0.01,"***",IF('Estimates-split'!AW11<0.05,"**",IF('Estimates-split'!AW11<0.1,"*","")))) -> -0.087
B21: =IF('Estimates-split'!AJ11="","(n/a)","("&TEXT('Estimates-split'!AJ11,"0.00")&")") -> (-0.90) | C21: =IF('Estimates-split'!AN11="","(n/a)","("&TEXT('Estimates-split'!AN11,"0.00")&")") -> (-1.08) | D21: =IF('Estimates-split'!AR11="","(n/a)","("&TEXT('Estimates-split'!AR11,"0.00")&")") -> (-1.45) | E21: =IF('Estimates-split'!AV11="","(n/a)","("&TEXT('Estimates-split'!AV11,"0.00")&")") -> (-1.59)
A22: Private Equity Allocation (%) | B22: =TEXT('Estimates-split'!AH12,"0.000")&IF('Estimates-split'!AK12="","",IF('Estimates-split'!AK12<0.01,"***",IF('Estimates-split'!AK12<0.05,"**",IF('Estimates-split'!AK12<0.1,"*","")))) -> -0.034 | C22: =TEXT('Estimates-split'!AL12,"0.000")&IF('Estimates-split'!AO12="","",IF('Estimates-split'!AO12<0.01,"***",IF('Estimates-split'!AO12<0.05,"**",IF('Estimates-split'!AO12<0.1,"*","")))) -> -0.077 | D22: =TEXT('Estimates-split'!AP12,"0.000")&IF('Estimates-split'!AS12="","",IF('Estimates-split'!AS12<0.01,"***",IF('Estimates-split'!AS12<0.05,"**",IF('Estimates-split'!AS12<0.1,"*","")))) -> -0.067 | E22: =TEXT('Estimates-split'!AT12,"0.000")&IF('Estimates-split'!AW12="","",IF('Estimates-split'!AW12<0.01,"***",IF('Estimates-split'!AW12<0.05,"**",IF('Estimates-split'!AW12<0.1,"*","")))) -> -0.065
B23: =IF('Estimates-split'!AJ12="","(n/a)","("&TEXT('Estimates-split'!AJ12,"0.00")&")") -> (-0.98) | C23: =IF('Estimates-split'!AN12="","(n/a)","("&TEXT('Estimates-split'!AN12,"0.00")&")") -> (-1.11) | D23: =IF('Estimates-split'!AR12="","(n/a)","("&TEXT('Estimates-split'!AR12,"0.00")&")") -> (-1.13) | E23: =IF('Estimates-split'!AV12="","(n/a)","("&TEXT('Estimates-split'!AV12,"0.00")&")") -> (-1.16)
A24: Hedge Fund Allocation (%) | B24: =TEXT('Estimates-split'!AH13,"0.000")&IF('Estimates-split'!AK13="","",IF('Estimates-split'!AK13<0.01,"***",IF('Estimates-split'!AK13<0.05,"**",IF('Estimates-split'!AK13<0.1,"*","")))) -> -0.022 | C24: =TEXT('Estimates-split'!AL13,"0.000")&IF('Estimates-split'!AO13="","",IF('Estimates-split'!AO13<0.01,"***",IF('Estimates-split'!AO13<0.05,"**",IF('Estimates-split'!AO13<0.1,"*","")))) -> -0.064 | D24: =TEXT('Estimates-split'!AP13,"0.000")&IF('Estimates-split'!AS13="","",IF('Estimates-split'!AS13<0.01,"***",IF('Estimates-split'!AS13<0.05,"**",IF('Estimates-split'!AS13<0.1,"*","")))) -> -0.069 | E24: =TEXT('Estimates-split'!AT13,"0.000")&IF('Estimates-split'!AW13="","",IF('Estimates-split'!AW13<0.01,"***",IF('Estimates-split'!AW13<0.05,"**",IF('Estimates-split'!AW13<0.1,"*","")))) -> -0.069
B25: =IF('Estimates-split'!AJ13="","(n/a)","("&TEXT('Estimates-split'!AJ13,"0.00")&")") -> (-0.62) | C25: =IF('Estimates-split'!AN13="","(n/a)","("&TEXT('Estimates-split'!AN13,"0.00")&")") -> (-0.92) | D25: =IF('Estimates-split'!AR13="","(n/a)","("&TEXT('Estimates-split'!AR13,"0.00")&")") -> (-1.17) | E25: =IF('Estimates-split'!AV13="","(n/a)","("&TEXT('Estimates-split'!AV13,"0.00")&")") -> (-1.25)
A26: Misc. Alternatives Allocation (%) | B26: =TEXT('Estimates-split'!AH14,"0.000")&IF('Estimates-split'!AK14="","",IF('Estimates-split'!AK14<0.01,"***",IF('Estimates-split'!AK14<0.05,"**",IF('Estimates-split'!AK14<0.1,"*","")))) -> -0.034 | C26: =TEXT('Estimates-split'!AL14,"0.000")&IF('Estimates-split'!AO14="","",IF('Estimates-split'!AO14<0.01,"***",IF('Estimates-split'!AO14<0.05,"**",IF('Estimates-split'!AO14<0.1,"*","")))) -> -0.075 | D26: =TEXT('Estimates-split'!AP14,"0.000")&IF('Estimates-split'!AS14="","",IF('Estimates-split'!AS14<0.01,"***",IF('Estimates-split'!AS14<0.05,"**",IF('Estimates-split'!AS14<0.1,"*","")))) -> -0.074 | E26: =TEXT('Estimates-split'!AT14,"0.000")&IF('Estimates-split'!AW14="","",IF('Estimates-split'!AW14<0.01,"***",IF('Estimates-split'!AW14<0.05,"**",IF('Estimates-split'!AW14<0.1,"*","")))) -> -0.073
B27: =IF('Estimates-split'!AJ14="","(n/a)","("&TEXT('Estimates-split'!AJ14,"0.00")&")") -> (-0.99) | C27: =IF('Estimates-split'!AN14="","(n/a)","("&TEXT('Estimates-split'!AN14,"0.00")&")") -> (-1.10) | D27: =IF('Estimates-split'!AR14="","(n/a)","("&TEXT('Estimates-split'!AR14,"0.00")&")") -> (-1.26) | E27: =IF('Estimates-split'!AV14="","(n/a)","("&TEXT('Estimates-split'!AV14,"0.00")&")") -> (-1.33)
A28: Commodities Allocation (%) | B28: =TEXT('Estimates-split'!AH15,"0.000")&IF('Estimates-split'!AK15="","",IF('Estimates-split'!AK15<0.01,"***",IF('Estimates-split'!AK15<0.05,"**",IF('Estimates-split'!AK15<0.1,"*","")))) -> -0.032 | C28: =TEXT('Estimates-split'!AL15,"0.000")&IF('Estimates-split'!AO15="","",IF('Estimates-split'!AO15<0.01,"***",IF('Estimates-split'!AO15<0.05,"**",IF('Estimates-split'!AO15<0.1,"*","")))) -> -0.073 | D28: =TEXT('Estimates-split'!AP15,"0.000")&IF('Estimates-split'!AS15="","",IF('Estimates-split'!AS15<0.01,"***",IF('Estimates-split'!AS15<0.05,"**",IF('Estimates-split'!AS15<0.1,"*","")))) -> -0.082 | E28: =TEXT('Estimates-split'!AT15,"0.000")&IF('Estimates-split'!AW15="","",IF('Estimates-split'!AW15<0.01,"***",IF('Estimates-split'!AW15<0.05,"**",IF('Estimates-split'!AW15<0.1,"*","")))) -> -0.083
B29: =IF('Estimates-split'!AJ15="","(n/a)","("&TEXT('Estimates-split'!AJ15,"0.00")&")") -> (-0.91) | C29: =IF('Estimates-split'!AN15="","(n/a)","("&TEXT('Estimates-split'!AN15,"0.00")&")") -> (-1.07) | D29: =IF('Estimates-split'!AR15="","(n/a)","("&TEXT('Estimates-split'!AR15,"0.00")&")") -> (-1.41) | E29: =IF('Estimates-split'!AV15="","(n/a)","("&TEXT('Estimates-split'!AV15,"0.00")&")") -> (-1.52)
A30: Cash Allocation (%) | B30: =TEXT('Estimates-split'!AH16,"0.000")&IF('Estimates-split'!AK16="","",IF('Estimates-split'!AK16<0.01,"***",IF('Estimates-split'!AK16<0.05,"**",IF('Estimates-split'!AK16<0.1,"*","")))) -> -0.036 | C30: =TEXT('Estimates-split'!AL16,"0.000")&IF('Estimates-split'!AO16="","",IF('Estimates-split'!AO16<0.01,"***",IF('Estimates-split'!AO16<0.05,"**",IF('Estimates-split'!AO16<0.1,"*","")))) -> -0.082 | D30: =TEXT('Estimates-split'!AP16,"0.000")&IF('Estimates-split'!AS16="","",IF('Estimates-split'!AS16<0.01,"***",IF('Estimates-split'!AS16<0.05,"**",IF('Estimates-split'!AS16<0.1,"*","")))) -> -0.080 | E30: =TEXT('Estimates-split'!AT16,"0.000")&IF('Estimates-split'!AW16="","",IF('Estimates-split'!AW16<0.01,"***",IF('Estimates-split'!AW16<0.05,"**",IF('Estimates-split'!AW16<0.1,"*","")))) -> -0.080
B31: =IF('Estimates-split'!AJ16="","(n/a)","("&TEXT('Estimates-split'!AJ16,"0.00")&")") -> (-1.04) | C31: =IF('Estimates-split'!AN16="","(n/a)","("&TEXT('Estimates-split'!AN16,"0.00")&")") -> (-1.17) | D31: =IF('Estimates-split'!AR16="","(n/a)","("&TEXT('Estimates-split'!AR16,"0.00")&")") -> (-1.35) | E31: =IF('Estimates-split'!AV16="","(n/a)","("&TEXT('Estimates-split'!AV16,"0.00")&")") -> (-1.44)
A32: Financial Center (0/1) | B32: =TEXT('Estimates-split'!AH17,"0.000")&IF('Estimates-split'!AK17="","",IF('Estimates-split'!AK17<0.01,"***",IF('Estimates-split'!AK17<0.05,"**",IF('Estimates-split'!AK17<0.1,"*","")))) -> -0.012 | C32: =TEXT('Estimates-split'!AL17,"0.000")&IF('Estimates-split'!AO17="","",IF('Estimates-split'!AO17<0.01,"***",IF('Estimates-split'!AO17<0.05,"**",IF('Estimates-split'!AO17<0.1,"*","")))) -> 0.033
B33: =IF('Estimates-split'!AJ17="","(n/a)","("&TEXT('Estimates-split'!AJ17,"0.00")&")") -> (-0.29) | C33: =IF('Estimates-split'!AN17="","(n/a)","("&TEXT('Estimates-split'!AN17,"0.00")&")") -> (0.81)
A34: Log (CIO Age) (t-1) | C34: =TEXT('Estimates-split'!AL18,"0.000")&IF('Estimates-split'!AO18="","",IF('Estimates-split'!AO18<0.01,"***",IF('Estimates-split'!AO18<0.05,"**",IF('Estimates-split'!AO18<0.1,"*","")))) -> 0.001 | D34: =TEXT('Estimates-split'!AP18,"0.000")&IF('Estimates-split'!AS18="","",IF('Estimates-split'!AS18<0.01,"***",IF('Estimates-split'!AS18<0.05,"**",IF('Estimates-split'!AS18<0.1,"*","")))) -> -0.185* | E34: =TEXT('Estimates-split'!AT18,"0.000")&IF('Estimates-split'!AW18="","",IF('Estimates-split'!AW18<0.01,"***",IF('Estimates-split'!AW18<0.05,"**",IF('Estimates-split'!AW18<0.1,"*","")))) -> -0.155
C35: =IF('Estimates-split'!AN18="","(n/a)","("&TEXT('Estimates-split'!AN18,"0.00")&")") -> (0.01) | D35: =IF('Estimates-split'!AR18="","(n/a)","("&TEXT('Estimates-split'!AR18,"0.00")&")") -> (-1.78) | E35: =IF('Estimates-split'!AV18="","(n/a)","("&TEXT('Estimates-split'!AV18,"0.00")&")") -> (-1.49)
A36: Log (CIO Tenure) (t-1) | C36: =TEXT('Estimates-split'!AL19,"0.000")&IF('Estimates-split'!AO19="","",IF('Estimates-split'!AO19<0.01,"***",IF('Estimates-split'!AO19<0.05,"**",IF('Estimates-split'!AO19<0.1,"*","")))) -> -0.015 | D36: =TEXT('Estimates-split'!AP19,"0.000")&IF('Estimates-split'!AS19="","",IF('Estimates-split'!AS19<0.01,"***",IF('Estimates-split'!AS19<0.05,"**",IF('Estimates-split'!AS19<0.1,"*","")))) -> 0.017 | E36: =TEXT('Estimates-split'!AT19,"0.000")&IF('Estimates-split'!AW19="","",IF('Estimates-split'!AW19<0.01,"***",IF('Estimates-split'!AW19<0.05,"**",IF('Estimates-split'!AW19<0.1,"*","")))) -> 0.014
C37: =IF('Estimates-split'!AN19="","(n/a)","("&TEXT('Estimates-split'!AN19,"0.00")&")") -> (-1.11) | D37: =IF('Estimates-split'!AR19="","(n/a)","("&TEXT('Estimates-split'!AR19,"0.00")&")") -> (1.57) | E37: =IF('Estimates-split'!AV19="","(n/a)","("&TEXT('Estimates-split'!AV19,"0.00")&")") -> (1.36)
A38: CIO Prior Private Experience (0/1) | C38: =TEXT('Estimates-split'!AL20,"0.000")&IF('Estimates-split'!AO20="","",IF('Estimates-split'!AO20<0.01,"***",IF('Estimates-split'!AO20<0.05,"**",IF('Estimates-split'!AO20<0.1,"*","")))) -> -0.056 | D38: =TEXT('Estimates-split'!AP20,"0.000")&IF('Estimates-split'!AS20="","",IF('Estimates-split'!AS20<0.01,"***",IF('Estimates-split'!AS20<0.05,"**",IF('Estimates-split'!AS20<0.1,"*","")))) -> -0.073 | E38: =TEXT('Estimates-split'!AT20,"0.000")&IF('Estimates-split'!AW20="","",IF('Estimates-split'!AW20<0.01,"***",IF('Estimates-split'!AW20<0.05,"**",IF('Estimates-split'!AW20<0.1,"*","")))) -> -0.067
C39: =IF('Estimates-split'!AN20="","(n/a)","("&TEXT('Estimates-split'!AN20,"0.00")&")") -> (-1.44) | D39: =IF('Estimates-split'!AR20="","(n/a)","("&TEXT('Estimates-split'!AR20,"0.00")&")") -> (-1.36) | E39: =IF('Estimates-split'!AV20="","(n/a)","("&TEXT('Estimates-split'!AV20,"0.00")&")") -> (-1.32)
A40: CIO Attended Elite College (0/1) | C40: =TEXT('Estimates-split'!AL21,"0.000")&IF('Estimates-split'!AO21="","",IF('Estimates-split'!AO21<0.01,"***",IF('Estimates-split'!AO21<0.05,"**",IF('Estimates-split'!AO21<0.1,"*","")))) -> 0.033 | D40: =TEXT('Estimates-split'!AP21,"0.000")&IF('Estimates-split'!AS21="","",IF('Estimates-split'!AS21<0.01,"***",IF('Estimates-split'!AS21<0.05,"**",IF('Estimates-split'!AS21<0.1,"*","")))) -> -0.059 | E40: =TEXT('Estimates-split'!AT21,"0.000")&IF('Estimates-split'!AW21="","",IF('Estimates-split'!AW21<0.01,"***",IF('Estimates-split'!AW21<0.05,"**",IF('Estimates-split'!AW21<0.1,"*","")))) -> -0.059
C41: =IF('Estimates-split'!AN21="","(n/a)","("&TEXT('Estimates-split'!AN21,"0.00")&")") -> (0.81) | D41: =IF('Estimates-split'!AR21="","(n/a)","("&TEXT('Estimates-split'!AR21,"0.00")&")") -> (-1.56) | E41: =IF('Estimates-split'!AV21="","(n/a)","("&TEXT('Estimates-split'!AV21,"0.00")&")") -> (-1.63)
A42: Separate Investment Board (0/1) | C42: =TEXT('Estimates-split'!AL22,"0.000")&IF('Estimates-split'!AO22="","",IF('Estimates-split'!AO22<0.01,"***",IF('Estimates-split'!AO22<0.05,"**",IF('Estimates-split'!AO22<0.1,"*","")))) -> 0.002 | D42: =TEXT('Estimates-split'!AP22,"0.000")&IF('Estimates-split'!AS22="","",IF('Estimates-split'!AS22<0.01,"***",IF('Estimates-split'!AS22<0.05,"**",IF('Estimates-split'!AS22<0.1,"*","")))) -> -0.277*** | E42: =TEXT('Estimates-split'!AT22,"0.000")&IF('Estimates-split'!AW22="","",IF('Estimates-split'!AW22<0.01,"***",IF('Estimates-split'!AW22<0.05,"**",IF('Estimates-split'!AW22<0.1,"*","")))) -> -0.256***
C43: =IF('Estimates-split'!AN22="","(n/a)","("&TEXT('Estimates-split'!AN22,"0.00")&")") -> (0.06) | D43: =IF('Estimates-split'!AR22="","(n/a)","("&TEXT('Estimates-split'!AR22,"0.00")&")") -> (-3.54) | E43: =IF('Estimates-split'!AV22="","(n/a)","("&TEXT('Estimates-split'!AV22,"0.00")&")") -> (-3.22)
A44: % Political Appointees on Board | C44: =TEXT('Estimates-split'!AL23,"0.000")&IF('Estimates-split'!AO23="","",IF('Estimates-split'!AO23<0.01,"***",IF('Estimates-split'!AO23<0.05,"**",IF('Estimates-split'!AO23<0.1,"*","")))) -> -0.077 | D44: =TEXT('Estimates-split'!AP23,"0.000")&IF('Estimates-split'!AS23="","",IF('Estimates-split'!AS23<0.01,"***",IF('Estimates-split'!AS23<0.05,"**",IF('Estimates-split'!AS23<0.1,"*","")))) -> -0.070 | E44: =TEXT('Estimates-split'!AT23,"0.000")&IF('Estimates-split'!AW23="","",IF('Estimates-split'!AW23<0.01,"***",IF('Estimates-split'!AW23<0.05,"**",IF('Estimates-split'!AW23<0.1,"*","")))) -> -0.118
C45: =IF('Estimates-split'!AN23="","(n/a)","("&TEXT('Estimates-split'!AN23,"0.00")&")") -> (-1.48) | D45: =IF('Estimates-split'!AR23="","(n/a)","("&TEXT('Estimates-split'!AR23,"0.00")&")") -> (-0.54) | E45: =IF('Estimates-split'!AV23="","(n/a)","("&TEXT('Estimates-split'!AV23,"0.00")&")") -> (-0.88)
A47: Observations | B47: ='Estimates-split'!AH26 -> 1485 | C47: ='Estimates-split'!AL26 -> 1301 | D47: ='Estimates-split'!AP26 -> 1299 | E47: ='Estimates-split'!AT26 -> 1299
A48: Adjusted R-squared | B48: ='Estimates-split'!AH29 -> 0.3426776 | C48: ='Estimates-split'!AL29 -> 0.36068689 | D48: ='Estimates-split'!AP29 -> 0.66165511 | E48: ='Estimates-split'!AT29 -> 0.67056452
A49: Plan FE | B49: No | C49: No | D49: Yes | E49: Yes
A50: Year FE | B50: Yes | C50: Yes | D50: No | E50: Yes
A51: p-value: First Half = Second Half | B51: ='Estimates-split'!AK24 -> 0.96092537 | C51: ='Estimates-split'!AO24 -> 0.87804384 | D51: ='Estimates-split'!AS24 -> 0.84941311 | E51: ='Estimates-split'!AW24 -> 0.82165115

Sheet Table XI
A1: Table XI: Conflicted CIOs: Plan Performance in the First versus Second Half of Tenure, Conflicted CIOs Only (updated benchmark)
A2: This table reports results of tests that regress the returns of public pension plans run by conflicted CIOs on an indicator variable, Second Half of Tenure, which is equal to 1 in the fiscal years in which the CIO's tenure exceeds one half of the CIO's tenure at departure and 0 otherwise. Conflicted CIOs are defined as in Table III, and the sample is restricted to their plan-years, so the coefficient compares the second half of a conflicted CIO's tenure with the first half. Tenure at departure is the CIO's tenure in the last fiscal year observed in the plan plus any gap to the departure year. The performance measure in Panel A is Peer-Adjusted Return, which is the difference of a plan's return and the average pension plan return each year. The performance measure in Panel B is Benchmark-Adjusted Return, which is calculated as the plan's return minus the return of its updated policy benchmark (the benchmark return reported in the plan's financial report or, where none is stated, an inferred value graded A or B). The other independent variables are as defined in Table I. Columns 5 and 6 include CIO fixed effects and omit the CIO-level controls; Column 6 restricts the sample to CIOs whose tenure at departure is at least four years, so that each half of tenure contains at least two fiscal years. The standard errors are double clustered by plan and year. Coefficients marked with ***, **, and * are significant at the 1%, 5%, and 10% level, respectively.
A4: Panel A. Peer-Adjusted Returns
B5: (1) | C5: (2) | D5: (3) | E5: (4) | F5: (5) | G5: (6)
B6: Peer-adj. Ret. (t) | C6: Peer-adj. Ret. (t) | D6: Peer-adj. Ret. (t) | E6: Peer-adj. Ret. (t) | F6: Peer-adj. Ret. (t) | G6: Peer-adj. Ret. (t)
A7: Second Half of Tenure (0/1) | B7: =TEXT(Estimates!B4,"0.000")&IF(Estimates!E4="","",IF(Estimates!E4<0.01,"***",IF(Estimates!E4<0.05,"**",IF(Estimates!E4<0.1,"*","")))) -> -0.229 | C7: =TEXT(Estimates!F4,"0.000")&IF(Estimates!I4="","",IF(Estimates!I4<0.01,"***",IF(Estimates!I4<0.05,"**",IF(Estimates!I4<0.1,"*","")))) -> -0.144 | D7: =TEXT(Estimates!J4,"0.000")&IF(Estimates!M4="","",IF(Estimates!M4<0.01,"***",IF(Estimates!M4<0.05,"**",IF(Estimates!M4<0.1,"*","")))) -> 0.044 | E7: =TEXT(Estimates!N4,"0.000")&IF(Estimates!Q4="","",IF(Estimates!Q4<0.01,"***",IF(Estimates!Q4<0.05,"**",IF(Estimates!Q4<0.1,"*","")))) -> -0.083 | F7: =TEXT(Estimates!R4,"0.000")&IF(Estimates!U4="","",IF(Estimates!U4<0.01,"***",IF(Estimates!U4<0.05,"**",IF(Estimates!U4<0.1,"*","")))) -> -0.969* | G7: =TEXT(Estimates!V4,"0.000")&IF(Estimates!Y4="","",IF(Estimates!Y4<0.01,"***",IF(Estimates!Y4<0.05,"**",IF(Estimates!Y4<0.1,"*","")))) -> -0.309
B8: =IF(Estimates!D4="","(n/a)","("&TEXT(Estimates!D4,"0.00")&")") -> (-1.25) | C8: =IF(Estimates!H4="","(n/a)","("&TEXT(Estimates!H4,"0.00")&")") -> (-0.68) | D8: =IF(Estimates!L4="","(n/a)","("&TEXT(Estimates!L4,"0.00")&")") -> (0.17) | E8: =IF(Estimates!P4="","(n/a)","("&TEXT(Estimates!P4,"0.00")&")") -> (-0.27) | F8: =IF(Estimates!T4="","(n/a)","("&TEXT(Estimates!T4,"0.00")&")") -> (-1.93) | G8: =IF(Estimates!X4="","(n/a)","("&TEXT(Estimates!X4,"0.00")&")") -> (-0.33)
A9: Investment Return (t - 1) | B9: =TEXT(Estimates!B5,"0.000")&IF(Estimates!E5="","",IF(Estimates!E5<0.01,"***",IF(Estimates!E5<0.05,"**",IF(Estimates!E5<0.1,"*","")))) -> 0.061 | C9: =TEXT(Estimates!F5,"0.000")&IF(Estimates!I5="","",IF(Estimates!I5<0.01,"***",IF(Estimates!I5<0.05,"**",IF(Estimates!I5<0.1,"*","")))) -> 0.032 | D9: =TEXT(Estimates!J5,"0.000")&IF(Estimates!M5="","",IF(Estimates!M5<0.01,"***",IF(Estimates!M5<0.05,"**",IF(Estimates!M5<0.1,"*","")))) -> -0.003 | E9: =TEXT(Estimates!N5,"0.000")&IF(Estimates!Q5="","",IF(Estimates!Q5<0.01,"***",IF(Estimates!Q5<0.05,"**",IF(Estimates!Q5<0.1,"*","")))) -> 0.015 | F9: =TEXT(Estimates!R5,"0.000")&IF(Estimates!U5="","",IF(Estimates!U5<0.01,"***",IF(Estimates!U5<0.05,"**",IF(Estimates!U5<0.1,"*","")))) -> -0.002 | G9: =TEXT(Estimates!V5,"0.000")&IF(Estimates!Y5="","",IF(Estimates!Y5<0.01,"***",IF(Estimates!Y5<0.05,"**",IF(Estimates!Y5<0.1,"*","")))) -> 0.030
B10: =IF(Estimates!D5="","(n/a)","("&TEXT(Estimates!D5,"0.00")&")") -> (0.88) | C10: =IF(Estimates!H5="","(n/a)","("&TEXT(Estimates!H5,"0.00")&")") -> (0.58) | D10: =IF(Estimates!L5="","(n/a)","("&TEXT(Estimates!L5,"0.00")&")") -> (-0.15) | E10: =IF(Estimates!P5="","(n/a)","("&TEXT(Estimates!P5,"0.00")&")") -> (0.41) | F10: =IF(Estimates!T5="","(n/a)","("&TEXT(Estimates!T5,"0.00")&")") -> (-0.05) | G10: =IF(Estimates!X5="","(n/a)","("&TEXT(Estimates!X5,"0.00")&")") -> (0.60)
A11: Log (Plan Size) (t-1) | B11: =TEXT(Estimates!B6,"0.000")&IF(Estimates!E6="","",IF(Estimates!E6<0.01,"***",IF(Estimates!E6<0.05,"**",IF(Estimates!E6<0.1,"*","")))) -> -0.046 | C11: =TEXT(Estimates!F6,"0.000")&IF(Estimates!I6="","",IF(Estimates!I6<0.01,"***",IF(Estimates!I6<0.05,"**",IF(Estimates!I6<0.1,"*","")))) -> -0.085 | D11: =TEXT(Estimates!J6,"0.000")&IF(Estimates!M6="","",IF(Estimates!M6<0.01,"***",IF(Estimates!M6<0.05,"**",IF(Estimates!M6<0.1,"*","")))) -> -0.405 | E11: =TEXT(Estimates!N6,"0.000")&IF(Estimates!Q6="","",IF(Estimates!Q6<0.01,"***",IF(Estimates!Q6<0.05,"**",IF(Estimates!Q6<0.1,"*","")))) -> 0.130 | F11: =TEXT(Estimates!R6,"0.000")&IF(Estimates!U6="","",IF(Estimates!U6<0.01,"***",IF(Estimates!U6<0.05,"**",IF(Estimates!U6<0.1,"*","")))) -> 1.409 | G11: =TEXT(Estimates!V6,"0.000")&IF(Estimates!Y6="","",IF(Estimates!Y6<0.01,"***",IF(Estimates!Y6<0.05,"**",IF(Estimates!Y6<0.1,"*","")))) -> 1.201
B12: =IF(Estimates!D6="","(n/a)","("&TEXT(Estimates!D6,"0.00")&")") -> (-0.42) | C12: =IF(Estimates!H6="","(n/a)","("&TEXT(Estimates!H6,"0.00")&")") -> (-0.77) | D12: =IF(Estimates!L6="","(n/a)","("&TEXT(Estimates!L6,"0.00")&")") -> (-0.43) | E12: =IF(Estimates!P6="","(n/a)","("&TEXT(Estimates!P6,"0.00")&")") -> (0.12) | F12: =IF(Estimates!T6="","(n/a)","("&TEXT(Estimates!T6,"0.00")&")") -> (0.64) | G12: =IF(Estimates!X6="","(n/a)","("&TEXT(Estimates!X6,"0.00")&")") -> (0.52)
A13: Funding Ratio (t-1) | B13: =TEXT(Estimates!B7,"0.000")&IF(Estimates!E7="","",IF(Estimates!E7<0.01,"***",IF(Estimates!E7<0.05,"**",IF(Estimates!E7<0.1,"*","")))) -> -0.019* | C13: =TEXT(Estimates!F7,"0.000")&IF(Estimates!I7="","",IF(Estimates!I7<0.01,"***",IF(Estimates!I7<0.05,"**",IF(Estimates!I7<0.1,"*","")))) -> -0.014 | D13: =TEXT(Estimates!J7,"0.000")&IF(Estimates!M7="","",IF(Estimates!M7<0.01,"***",IF(Estimates!M7<0.05,"**",IF(Estimates!M7<0.1,"*","")))) -> -0.016 | E13: =TEXT(Estimates!N7,"0.000")&IF(Estimates!Q7="","",IF(Estimates!Q7<0.01,"***",IF(Estimates!Q7<0.05,"**",IF(Estimates!Q7<0.1,"*","")))) -> -0.035 | F13: =TEXT(Estimates!R7,"0.000")&IF(Estimates!U7="","",IF(Estimates!U7<0.01,"***",IF(Estimates!U7<0.05,"**",IF(Estimates!U7<0.1,"*","")))) -> -0.093** | G13: =TEXT(Estimates!V7,"0.000")&IF(Estimates!Y7="","",IF(Estimates!Y7<0.01,"***",IF(Estimates!Y7<0.05,"**",IF(Estimates!Y7<0.1,"*","")))) -> -0.093*
B14: =IF(Estimates!D7="","(n/a)","("&TEXT(Estimates!D7,"0.00")&")") -> (-1.92) | C14: =IF(Estimates!H7="","(n/a)","("&TEXT(Estimates!H7,"0.00")&")") -> (-1.59) | D14: =IF(Estimates!L7="","(n/a)","("&TEXT(Estimates!L7,"0.00")&")") -> (-0.49) | E14: =IF(Estimates!P7="","(n/a)","("&TEXT(Estimates!P7,"0.00")&")") -> (-0.89) | F14: =IF(Estimates!T7="","(n/a)","("&TEXT(Estimates!T7,"0.00")&")") -> (-2.46) | G14: =IF(Estimates!X7="","(n/a)","("&TEXT(Estimates!X7,"0.00")&")") -> (-2.00)
A15: Equity Allocation (%) | B15: =TEXT(Estimates!B8,"0.000")&IF(Estimates!E8="","",IF(Estimates!E8<0.01,"***",IF(Estimates!E8<0.05,"**",IF(Estimates!E8<0.1,"*","")))) -> 0.076 | C15: =TEXT(Estimates!F8,"0.000")&IF(Estimates!I8="","",IF(Estimates!I8<0.01,"***",IF(Estimates!I8<0.05,"**",IF(Estimates!I8<0.1,"*","")))) -> 0.103 | D15: =TEXT(Estimates!J8,"0.000")&IF(Estimates!M8="","",IF(Estimates!M8<0.01,"***",IF(Estimates!M8<0.05,"**",IF(Estimates!M8<0.1,"*","")))) -> -0.629** | E15: =TEXT(Estimates!N8,"0.000")&IF(Estimates!Q8="","",IF(Estimates!Q8<0.01,"***",IF(Estimates!Q8<0.05,"**",IF(Estimates!Q8<0.1,"*","")))) -> -0.611 | F15: =TEXT(Estimates!R8,"0.000")&IF(Estimates!U8="","",IF(Estimates!U8<0.01,"***",IF(Estimates!U8<0.05,"**",IF(Estimates!U8<0.1,"*","")))) -> -1.558*** | G15: =TEXT(Estimates!V8,"0.000")&IF(Estimates!Y8="","",IF(Estimates!Y8<0.01,"***",IF(Estimates!Y8<0.05,"**",IF(Estimates!Y8<0.1,"*","")))) -> -2.156***
B16: =IF(Estimates!D8="","(n/a)","("&TEXT(Estimates!D8,"0.00")&")") -> (0.67) | C16: =IF(Estimates!H8="","(n/a)","("&TEXT(Estimates!H8,"0.00")&")") -> (0.89) | D16: =IF(Estimates!L8="","(n/a)","("&TEXT(Estimates!L8,"0.00")&")") -> (-2.14) | E16: =IF(Estimates!P8="","(n/a)","("&TEXT(Estimates!P8,"0.00")&")") -> (-1.63) | F16: =IF(Estimates!T8="","(n/a)","("&TEXT(Estimates!T8,"0.00")&")") -> (-3.47) | G16: =IF(Estimates!X8="","(n/a)","("&TEXT(Estimates!X8,"0.00")&")") -> (-3.71)
A17: Fixed Income Allocation (%) | B17: =TEXT(Estimates!B9,"0.000")&IF(Estimates!E9="","",IF(Estimates!E9<0.01,"***",IF(Estimates!E9<0.05,"**",IF(Estimates!E9<0.1,"*","")))) -> 0.037 | C17: =TEXT(Estimates!F9,"0.000")&IF(Estimates!I9="","",IF(Estimates!I9<0.01,"***",IF(Estimates!I9<0.05,"**",IF(Estimates!I9<0.1,"*","")))) -> 0.056 | D17: =TEXT(Estimates!J9,"0.000")&IF(Estimates!M9="","",IF(Estimates!M9<0.01,"***",IF(Estimates!M9<0.05,"**",IF(Estimates!M9<0.1,"*","")))) -> -0.658** | E17: =TEXT(Estimates!N9,"0.000")&IF(Estimates!Q9="","",IF(Estimates!Q9<0.01,"***",IF(Estimates!Q9<0.05,"**",IF(Estimates!Q9<0.1,"*","")))) -> -0.648* | F17: =TEXT(Estimates!R9,"0.000")&IF(Estimates!U9="","",IF(Estimates!U9<0.01,"***",IF(Estimates!U9<0.05,"**",IF(Estimates!U9<0.1,"*","")))) -> -1.619*** | G17: =TEXT(Estimates!V9,"0.000")&IF(Estimates!Y9="","",IF(Estimates!Y9<0.01,"***",IF(Estimates!Y9<0.05,"**",IF(Estimates!Y9<0.1,"*","")))) -> -2.255***
B18: =IF(Estimates!D9="","(n/a)","("&TEXT(Estimates!D9,"0.00")&")") -> (0.29) | C18: =IF(Estimates!H9="","(n/a)","("&TEXT(Estimates!H9,"0.00")&")") -> (0.46) | D18: =IF(Estimates!L9="","(n/a)","("&TEXT(Estimates!L9,"0.00")&")") -> (-2.15) | E18: =IF(Estimates!P9="","(n/a)","("&TEXT(Estimates!P9,"0.00")&")") -> (-1.74) | F18: =IF(Estimates!T9="","(n/a)","("&TEXT(Estimates!T9,"0.00")&")") -> (-3.54) | G18: =IF(Estimates!X9="","(n/a)","("&TEXT(Estimates!X9,"0.00")&")") -> (-3.82)
A19: Real Estate Allocation (%) | B19: =TEXT(Estimates!B10,"0.000")&IF(Estimates!E10="","",IF(Estimates!E10<0.01,"***",IF(Estimates!E10<0.05,"**",IF(Estimates!E10<0.1,"*","")))) -> 0.126 | C19: =TEXT(Estimates!F10,"0.000")&IF(Estimates!I10="","",IF(Estimates!I10<0.01,"***",IF(Estimates!I10<0.05,"**",IF(Estimates!I10<0.1,"*","")))) -> 0.154 | D19: =TEXT(Estimates!J10,"0.000")&IF(Estimates!M10="","",IF(Estimates!M10<0.01,"***",IF(Estimates!M10<0.05,"**",IF(Estimates!M10<0.1,"*","")))) -> -0.718* | E19: =TEXT(Estimates!N10,"0.000")&IF(Estimates!Q10="","",IF(Estimates!Q10<0.01,"***",IF(Estimates!Q10<0.05,"**",IF(Estimates!Q10<0.1,"*","")))) -> -0.658 | F19: =TEXT(Estimates!R10,"0.000")&IF(Estimates!U10="","",IF(Estimates!U10<0.01,"***",IF(Estimates!U10<0.05,"**",IF(Estimates!U10<0.1,"*","")))) -> -1.716** | G19: =TEXT(Estimates!V10,"0.000")&IF(Estimates!Y10="","",IF(Estimates!Y10<0.01,"***",IF(Estimates!Y10<0.05,"**",IF(Estimates!Y10<0.1,"*","")))) -> -2.645***
B20: =IF(Estimates!D10="","(n/a)","("&TEXT(Estimates!D10,"0.00")&")") -> (0.86) | C20: =IF(Estimates!H10="","(n/a)","("&TEXT(Estimates!H10,"0.00")&")") -> (1.20) | D20: =IF(Estimates!L10="","(n/a)","("&TEXT(Estimates!L10,"0.00")&")") -> (-2.06) | E20: =IF(Estimates!P10="","(n/a)","("&TEXT(Estimates!P10,"0.00")&")") -> (-1.63) | F20: =IF(Estimates!T10="","(n/a)","("&TEXT(Estimates!T10,"0.00")&")") -> (-2.56) | G20: =IF(Estimates!X10="","(n/a)","("&TEXT(Estimates!X10,"0.00")&")") -> (-3.38)
A21: Private Equity Allocation (%) | B21: =TEXT(Estimates!B11,"0.000")&IF(Estimates!E11="","",IF(Estimates!E11<0.01,"***",IF(Estimates!E11<0.05,"**",IF(Estimates!E11<0.1,"*","")))) -> 0.046 | C21: =TEXT(Estimates!F11,"0.000")&IF(Estimates!I11="","",IF(Estimates!I11<0.01,"***",IF(Estimates!I11<0.05,"**",IF(Estimates!I11<0.1,"*","")))) -> 0.097 | D21: =TEXT(Estimates!J11,"0.000")&IF(Estimates!M11="","",IF(Estimates!M11<0.01,"***",IF(Estimates!M11<0.05,"**",IF(Estimates!M11<0.1,"*","")))) -> -0.513 | E21: =TEXT(Estimates!N11,"0.000")&IF(Estimates!Q11="","",IF(Estimates!Q11<0.01,"***",IF(Estimates!Q11<0.05,"**",IF(Estimates!Q11<0.1,"*","")))) -> -0.553 | F21: =TEXT(Estimates!R11,"0.000")&IF(Estimates!U11="","",IF(Estimates!U11<0.01,"***",IF(Estimates!U11<0.05,"**",IF(Estimates!U11<0.1,"*","")))) -> -1.471*** | G21: =TEXT(Estimates!V11,"0.000")&IF(Estimates!Y11="","",IF(Estimates!Y11<0.01,"***",IF(Estimates!Y11<0.05,"**",IF(Estimates!Y11<0.1,"*","")))) -> -1.960***
B22: =IF(Estimates!D11="","(n/a)","("&TEXT(Estimates!D11,"0.00")&")") -> (0.33) | C22: =IF(Estimates!H11="","(n/a)","("&TEXT(Estimates!H11,"0.00")&")") -> (0.80) | D22: =IF(Estimates!L11="","(n/a)","("&TEXT(Estimates!L11,"0.00")&")") -> (-1.66) | E22: =IF(Estimates!P11="","(n/a)","("&TEXT(Estimates!P11,"0.00")&")") -> (-1.40) | F22: =IF(Estimates!T11="","(n/a)","("&TEXT(Estimates!T11,"0.00")&")") -> (-3.48) | G22: =IF(Estimates!X11="","(n/a)","("&TEXT(Estimates!X11,"0.00")&")") -> (-3.64)
A23: Hedge Fund Allocation (%) | B23: =TEXT(Estimates!B12,"0.000")&IF(Estimates!E12="","",IF(Estimates!E12<0.01,"***",IF(Estimates!E12<0.05,"**",IF(Estimates!E12<0.1,"*","")))) -> 0.043 | C23: =TEXT(Estimates!F12,"0.000")&IF(Estimates!I12="","",IF(Estimates!I12<0.01,"***",IF(Estimates!I12<0.05,"**",IF(Estimates!I12<0.1,"*","")))) -> 0.047 | D23: =TEXT(Estimates!J12,"0.000")&IF(Estimates!M12="","",IF(Estimates!M12<0.01,"***",IF(Estimates!M12<0.05,"**",IF(Estimates!M12<0.1,"*","")))) -> -0.679** | E23: =TEXT(Estimates!N12,"0.000")&IF(Estimates!Q12="","",IF(Estimates!Q12<0.01,"***",IF(Estimates!Q12<0.05,"**",IF(Estimates!Q12<0.1,"*","")))) -> -0.648* | F23: =TEXT(Estimates!R12,"0.000")&IF(Estimates!U12="","",IF(Estimates!U12<0.01,"***",IF(Estimates!U12<0.05,"**",IF(Estimates!U12<0.1,"*","")))) -> -1.566*** | G23: =TEXT(Estimates!V12,"0.000")&IF(Estimates!Y12="","",IF(Estimates!Y12<0.01,"***",IF(Estimates!Y12<0.05,"**",IF(Estimates!Y12<0.1,"*","")))) -> -2.101***
B24: =IF(Estimates!D12="","(n/a)","("&TEXT(Estimates!D12,"0.00")&")") -> (0.38) | C24: =IF(Estimates!H12="","(n/a)","("&TEXT(Estimates!H12,"0.00")&")") -> (0.46) | D24: =IF(Estimates!L12="","(n/a)","("&TEXT(Estimates!L12,"0.00")&")") -> (-2.42) | E24: =IF(Estimates!P12="","(n/a)","("&TEXT(Estimates!P12,"0.00")&")") -> (-2.01) | F24: =IF(Estimates!T12="","(n/a)","("&TEXT(Estimates!T12,"0.00")&")") -> (-3.43) | G24: =IF(Estimates!X12="","(n/a)","("&TEXT(Estimates!X12,"0.00")&")") -> (-3.61)
A25: Misc. Alternatives Allocation (%) | B25: =TEXT(Estimates!B13,"0.000")&IF(Estimates!E13="","",IF(Estimates!E13<0.01,"***",IF(Estimates!E13<0.05,"**",IF(Estimates!E13<0.1,"*","")))) -> 0.101 | C25: =TEXT(Estimates!F13,"0.000")&IF(Estimates!I13="","",IF(Estimates!I13<0.01,"***",IF(Estimates!I13<0.05,"**",IF(Estimates!I13<0.1,"*","")))) -> 0.137 | D25: =TEXT(Estimates!J13,"0.000")&IF(Estimates!M13="","",IF(Estimates!M13<0.01,"***",IF(Estimates!M13<0.05,"**",IF(Estimates!M13<0.1,"*","")))) -> -0.252 | E25: =TEXT(Estimates!N13,"0.000")&IF(Estimates!Q13="","",IF(Estimates!Q13<0.01,"***",IF(Estimates!Q13<0.05,"**",IF(Estimates!Q13<0.1,"*","")))) -> -0.311 | F25: =TEXT(Estimates!R13,"0.000")&IF(Estimates!U13="","",IF(Estimates!U13<0.01,"***",IF(Estimates!U13<0.05,"**",IF(Estimates!U13<0.1,"*","")))) -> -1.697* | G25: =TEXT(Estimates!V13,"0.000")&IF(Estimates!Y13="","",IF(Estimates!Y13<0.01,"***",IF(Estimates!Y13<0.05,"**",IF(Estimates!Y13<0.1,"*","")))) -> -2.538**
B26: =IF(Estimates!D13="","(n/a)","("&TEXT(Estimates!D13,"0.00")&")") -> (0.77) | C26: =IF(Estimates!H13="","(n/a)","("&TEXT(Estimates!H13,"0.00")&")") -> (1.62) | D26: =IF(Estimates!L13="","(n/a)","("&TEXT(Estimates!L13,"0.00")&")") -> (-0.32) | E26: =IF(Estimates!P13="","(n/a)","("&TEXT(Estimates!P13,"0.00")&")") -> (-0.30) | F26: =IF(Estimates!T13="","(n/a)","("&TEXT(Estimates!T13,"0.00")&")") -> (-1.81) | G26: =IF(Estimates!X13="","(n/a)","("&TEXT(Estimates!X13,"0.00")&")") -> (-2.74)
A27: Commodities Allocation (%) | B27: =TEXT(Estimates!B14,"0.000")&IF(Estimates!E14="","",IF(Estimates!E14<0.01,"***",IF(Estimates!E14<0.05,"**",IF(Estimates!E14<0.1,"*","")))) -> -0.136 | C27: =TEXT(Estimates!F14,"0.000")&IF(Estimates!I14="","",IF(Estimates!I14<0.01,"***",IF(Estimates!I14<0.05,"**",IF(Estimates!I14<0.1,"*","")))) -> -0.021 | D27: =TEXT(Estimates!J14,"0.000")&IF(Estimates!M14="","",IF(Estimates!M14<0.01,"***",IF(Estimates!M14<0.05,"**",IF(Estimates!M14<0.1,"*","")))) -> -0.684** | E27: =TEXT(Estimates!N14,"0.000")&IF(Estimates!Q14="","",IF(Estimates!Q14<0.01,"***",IF(Estimates!Q14<0.05,"**",IF(Estimates!Q14<0.1,"*","")))) -> -0.702* | F27: =TEXT(Estimates!R14,"0.000")&IF(Estimates!U14="","",IF(Estimates!U14<0.01,"***",IF(Estimates!U14<0.05,"**",IF(Estimates!U14<0.1,"*","")))) -> -1.472*** | G27: =TEXT(Estimates!V14,"0.000")&IF(Estimates!Y14="","",IF(Estimates!Y14<0.01,"***",IF(Estimates!Y14<0.05,"**",IF(Estimates!Y14<0.1,"*","")))) -> -1.744***
B28: =IF(Estimates!D14="","(n/a)","("&TEXT(Estimates!D14,"0.00")&")") -> (-0.93) | C28: =IF(Estimates!H14="","(n/a)","("&TEXT(Estimates!H14,"0.00")&")") -> (-0.20) | D28: =IF(Estimates!L14="","(n/a)","("&TEXT(Estimates!L14,"0.00")&")") -> (-2.17) | E28: =IF(Estimates!P14="","(n/a)","("&TEXT(Estimates!P14,"0.00")&")") -> (-1.76) | F28: =IF(Estimates!T14="","(n/a)","("&TEXT(Estimates!T14,"0.00")&")") -> (-3.58) | G28: =IF(Estimates!X14="","(n/a)","("&TEXT(Estimates!X14,"0.00")&")") -> (-3.91)
A29: Cash Allocation (%) | B29: =TEXT(Estimates!B15,"0.000")&IF(Estimates!E15="","",IF(Estimates!E15<0.01,"***",IF(Estimates!E15<0.05,"**",IF(Estimates!E15<0.1,"*","")))) -> 0.080 | C29: =TEXT(Estimates!F15,"0.000")&IF(Estimates!I15="","",IF(Estimates!I15<0.01,"***",IF(Estimates!I15<0.05,"**",IF(Estimates!I15<0.1,"*","")))) -> 0.126 | D29: =TEXT(Estimates!J15,"0.000")&IF(Estimates!M15="","",IF(Estimates!M15<0.01,"***",IF(Estimates!M15<0.05,"**",IF(Estimates!M15<0.1,"*","")))) -> -0.518 | E29: =TEXT(Estimates!N15,"0.000")&IF(Estimates!Q15="","",IF(Estimates!Q15<0.01,"***",IF(Estimates!Q15<0.05,"**",IF(Estimates!Q15<0.1,"*","")))) -> -0.504 | F29: =TEXT(Estimates!R15,"0.000")&IF(Estimates!U15="","",IF(Estimates!U15<0.01,"***",IF(Estimates!U15<0.05,"**",IF(Estimates!U15<0.1,"*","")))) -> -1.425*** | G29: =TEXT(Estimates!V15,"0.000")&IF(Estimates!Y15="","",IF(Estimates!Y15<0.01,"***",IF(Estimates!Y15<0.05,"**",IF(Estimates!Y15<0.1,"*","")))) -> -2.206***
B30: =IF(Estimates!D15="","(n/a)","("&TEXT(Estimates!D15,"0.00")&")") -> (0.63) | C30: =IF(Estimates!H15="","(n/a)","("&TEXT(Estimates!H15,"0.00")&")") -> (0.84) | D30: =IF(Estimates!L15="","(n/a)","("&TEXT(Estimates!L15,"0.00")&")") -> (-1.53) | E30: =IF(Estimates!P15="","(n/a)","("&TEXT(Estimates!P15,"0.00")&")") -> (-1.22) | F30: =IF(Estimates!T15="","(n/a)","("&TEXT(Estimates!T15,"0.00")&")") -> (-2.98) | G30: =IF(Estimates!X15="","(n/a)","("&TEXT(Estimates!X15,"0.00")&")") -> (-3.63)
A31: Financial Center (0/1) | B31: =TEXT(Estimates!B16,"0.000")&IF(Estimates!E16="","",IF(Estimates!E16<0.01,"***",IF(Estimates!E16<0.05,"**",IF(Estimates!E16<0.1,"*","")))) -> 0.488 | C31: =TEXT(Estimates!F16,"0.000")&IF(Estimates!I16="","",IF(Estimates!I16<0.01,"***",IF(Estimates!I16<0.05,"**",IF(Estimates!I16<0.1,"*","")))) -> 0.475
B32: =IF(Estimates!D16="","(n/a)","("&TEXT(Estimates!D16,"0.00")&")") -> (1.08) | C32: =IF(Estimates!H16="","(n/a)","("&TEXT(Estimates!H16,"0.00")&")") -> (1.42)
A33: Log (CIO Age) (t-1) | C33: =TEXT(Estimates!F17,"0.000")&IF(Estimates!I17="","",IF(Estimates!I17<0.01,"***",IF(Estimates!I17<0.05,"**",IF(Estimates!I17<0.1,"*","")))) -> -0.369 | D33: =TEXT(Estimates!J17,"0.000")&IF(Estimates!M17="","",IF(Estimates!M17<0.01,"***",IF(Estimates!M17<0.05,"**",IF(Estimates!M17<0.1,"*","")))) -> 1.685 | E33: =TEXT(Estimates!N17,"0.000")&IF(Estimates!Q17="","",IF(Estimates!Q17<0.01,"***",IF(Estimates!Q17<0.05,"**",IF(Estimates!Q17<0.1,"*","")))) -> 0.858
C34: =IF(Estimates!H17="","(n/a)","("&TEXT(Estimates!H17,"0.00")&")") -> (-0.44) | D34: =IF(Estimates!L17="","(n/a)","("&TEXT(Estimates!L17,"0.00")&")") -> (1.08) | E34: =IF(Estimates!P17="","(n/a)","("&TEXT(Estimates!P17,"0.00")&")") -> (0.46)
A35: Log (CIO Tenure) (t-1) | C35: =TEXT(Estimates!F18,"0.000")&IF(Estimates!I18="","",IF(Estimates!I18<0.01,"***",IF(Estimates!I18<0.05,"**",IF(Estimates!I18<0.1,"*","")))) -> 0.070 | D35: =TEXT(Estimates!J18,"0.000")&IF(Estimates!M18="","",IF(Estimates!M18<0.01,"***",IF(Estimates!M18<0.05,"**",IF(Estimates!M18<0.1,"*","")))) -> -0.124 | E35: =TEXT(Estimates!N18,"0.000")&IF(Estimates!Q18="","",IF(Estimates!Q18<0.01,"***",IF(Estimates!Q18<0.05,"**",IF(Estimates!Q18<0.1,"*","")))) -> 0.006
C36: =IF(Estimates!H18="","(n/a)","("&TEXT(Estimates!H18,"0.00")&")") -> (0.41) | D36: =IF(Estimates!L18="","(n/a)","("&TEXT(Estimates!L18,"0.00")&")") -> (-0.45) | E36: =IF(Estimates!P18="","(n/a)","("&TEXT(Estimates!P18,"0.00")&")") -> (0.02)
A37: CIO Prior Private Experience (0/1) | C37: =TEXT(Estimates!F19,"0.000")&IF(Estimates!I19="","",IF(Estimates!I19<0.01,"***",IF(Estimates!I19<0.05,"**",IF(Estimates!I19<0.1,"*","")))) -> -0.028 | D37: =TEXT(Estimates!J19,"0.000")&IF(Estimates!M19="","",IF(Estimates!M19<0.01,"***",IF(Estimates!M19<0.05,"**",IF(Estimates!M19<0.1,"*","")))) -> -0.278 | E37: =TEXT(Estimates!N19,"0.000")&IF(Estimates!Q19="","",IF(Estimates!Q19<0.01,"***",IF(Estimates!Q19<0.05,"**",IF(Estimates!Q19<0.1,"*","")))) -> -0.067
C38: =IF(Estimates!H19="","(n/a)","("&TEXT(Estimates!H19,"0.00")&")") -> (-0.13) | D38: =IF(Estimates!L19="","(n/a)","("&TEXT(Estimates!L19,"0.00")&")") -> (-0.58) | E38: =IF(Estimates!P19="","(n/a)","("&TEXT(Estimates!P19,"0.00")&")") -> (-0.07)
A39: CIO Attended Elite College (0/1) | C39: =TEXT(Estimates!F20,"0.000")&IF(Estimates!I20="","",IF(Estimates!I20<0.01,"***",IF(Estimates!I20<0.05,"**",IF(Estimates!I20<0.1,"*","")))) -> -0.110 | D39: =TEXT(Estimates!J20,"0.000")&IF(Estimates!M20="","",IF(Estimates!M20<0.01,"***",IF(Estimates!M20<0.05,"**",IF(Estimates!M20<0.1,"*","")))) -> 0.173 | E39: =TEXT(Estimates!N20,"0.000")&IF(Estimates!Q20="","",IF(Estimates!Q20<0.01,"***",IF(Estimates!Q20<0.05,"**",IF(Estimates!Q20<0.1,"*","")))) -> 0.128
C40: =IF(Estimates!H20="","(n/a)","("&TEXT(Estimates!H20,"0.00")&")") -> (-0.76) | D40: =IF(Estimates!L20="","(n/a)","("&TEXT(Estimates!L20,"0.00")&")") -> (0.40) | E40: =IF(Estimates!P20="","(n/a)","("&TEXT(Estimates!P20,"0.00")&")") -> (0.23)
A41: Separate Investment Board (0/1) | C41: =TEXT(Estimates!F21,"0.000")&IF(Estimates!I21="","",IF(Estimates!I21<0.01,"***",IF(Estimates!I21<0.05,"**",IF(Estimates!I21<0.1,"*","")))) -> 0.205
C42: =IF(Estimates!H21="","(n/a)","("&TEXT(Estimates!H21,"0.00")&")") -> (0.61)
A43: % Political Appointees on Board | C43: =TEXT(Estimates!F22,"0.000")&IF(Estimates!I22="","",IF(Estimates!I22<0.01,"***",IF(Estimates!I22<0.05,"**",IF(Estimates!I22<0.1,"*","")))) -> -0.126 | D43: =TEXT(Estimates!J22,"0.000")&IF(Estimates!M22="","",IF(Estimates!M22<0.01,"***",IF(Estimates!M22<0.05,"**",IF(Estimates!M22<0.1,"*","")))) -> 1.441 | E43: =TEXT(Estimates!N22,"0.000")&IF(Estimates!Q22="","",IF(Estimates!Q22<0.01,"***",IF(Estimates!Q22<0.05,"**",IF(Estimates!Q22<0.1,"*","")))) -> 2.004
C44: =IF(Estimates!H22="","(n/a)","("&TEXT(Estimates!H22,"0.00")&")") -> (-0.18) | D44: =IF(Estimates!L22="","(n/a)","("&TEXT(Estimates!L22,"0.00")&")") -> (0.34) | E44: =IF(Estimates!P22="","(n/a)","("&TEXT(Estimates!P22,"0.00")&")") -> (0.42)
A46: Observations | B46: =Estimates!B24 -> 306 | C46: =Estimates!F24 -> 280 | D46: =Estimates!J24 -> 278 | E46: =Estimates!N24 -> 278 | F46: =Estimates!R24 -> 289 | G46: =Estimates!V24 -> 197
A47: Adjusted R-squared | B47: =Estimates!B27 -> 0.1038009 | C47: =Estimates!F27 -> 0.052377286 | D47: =Estimates!J27 -> 0.026864756 | E47: =Estimates!N27 -> 0.019608249 | F47: =Estimates!R27 -> 0.13917438 | G47: =Estimates!V27 -> 0.10433939
A48: Number of CIOs | B48: =Estimates!B28 -> 43 | C48: =Estimates!F28 -> 41 | D48: =Estimates!J28 -> 41 | E48: =Estimates!N28 -> 41 | F48: =Estimates!R28 -> 43 | G48: =Estimates!V28 -> 24
A49: Plan FE | B49: No | C49: No | D49: Yes | E49: Yes | F49: No | G49: No
A50: Year FE | B50: Yes | C50: Yes | D50: No | E50: Yes | F50: Yes | G50: Yes
A51: CIO FE | B51: No | C51: No | D51: No | E51: No | F51: Yes | G51: Yes
A52: Min. Tenure at Departure (years) | G52: 4
A55: Panel B. Benchmark-Adjusted Returns
B56: (1) | C56: (2) | D56: (3) | E56: (4) | F56: (5) | G56: (6)
B57: Bench-adj. Ret. (t) | C57: Bench-adj. Ret. (t) | D57: Bench-adj. Ret. (t) | E57: Bench-adj. Ret. (t) | F57: Bench-adj. Ret. (t) | G57: Bench-adj. Ret. (t)
A58: Second Half of Tenure (0/1) | B58: =TEXT(Estimates!Z4,"0.000")&IF(Estimates!AC4="","",IF(Estimates!AC4<0.01,"***",IF(Estimates!AC4<0.05,"**",IF(Estimates!AC4<0.1,"*","")))) -> 0.094 | C58: =TEXT(Estimates!AD4,"0.000")&IF(Estimates!AG4="","",IF(Estimates!AG4<0.01,"***",IF(Estimates!AG4<0.05,"**",IF(Estimates!AG4<0.1,"*","")))) -> 0.255 | D58: =TEXT(Estimates!AH4,"0.000")&IF(Estimates!AK4="","",IF(Estimates!AK4<0.01,"***",IF(Estimates!AK4<0.05,"**",IF(Estimates!AK4<0.1,"*","")))) -> 0.282 | E58: =TEXT(Estimates!AL4,"0.000")&IF(Estimates!AO4="","",IF(Estimates!AO4<0.01,"***",IF(Estimates!AO4<0.05,"**",IF(Estimates!AO4<0.1,"*","")))) -> 0.565** | F58: =TEXT(Estimates!AP4,"0.000")&IF(Estimates!AS4="","",IF(Estimates!AS4<0.01,"***",IF(Estimates!AS4<0.05,"**",IF(Estimates!AS4<0.1,"*","")))) -> -0.166 | G58: =TEXT(Estimates!AT4,"0.000")&IF(Estimates!AW4="","",IF(Estimates!AW4<0.01,"***",IF(Estimates!AW4<0.05,"**",IF(Estimates!AW4<0.1,"*","")))) -> -0.087
B59: =IF(Estimates!AB4="","(n/a)","("&TEXT(Estimates!AB4,"0.00")&")") -> (0.31) | C59: =IF(Estimates!AF4="","(n/a)","("&TEXT(Estimates!AF4,"0.00")&")") -> (0.88) | D59: =IF(Estimates!AJ4="","(n/a)","("&TEXT(Estimates!AJ4,"0.00")&")") -> (0.98) | E59: =IF(Estimates!AN4="","(n/a)","("&TEXT(Estimates!AN4,"0.00")&")") -> (2.14) | F59: =IF(Estimates!AR4="","(n/a)","("&TEXT(Estimates!AR4,"0.00")&")") -> (-0.42) | G59: =IF(Estimates!AV4="","(n/a)","("&TEXT(Estimates!AV4,"0.00")&")") -> (-0.23)
A60: Investment Return (t - 1) | B60: =TEXT(Estimates!Z5,"0.000")&IF(Estimates!AC5="","",IF(Estimates!AC5<0.01,"***",IF(Estimates!AC5<0.05,"**",IF(Estimates!AC5<0.1,"*","")))) -> 0.084 | C60: =TEXT(Estimates!AD5,"0.000")&IF(Estimates!AG5="","",IF(Estimates!AG5<0.01,"***",IF(Estimates!AG5<0.05,"**",IF(Estimates!AG5<0.1,"*","")))) -> 0.039 | D60: =TEXT(Estimates!AH5,"0.000")&IF(Estimates!AK5="","",IF(Estimates!AK5<0.01,"***",IF(Estimates!AK5<0.05,"**",IF(Estimates!AK5<0.1,"*","")))) -> -0.004 | E60: =TEXT(Estimates!AL5,"0.000")&IF(Estimates!AO5="","",IF(Estimates!AO5<0.01,"***",IF(Estimates!AO5<0.05,"**",IF(Estimates!AO5<0.1,"*","")))) -> 0.012 | F60: =TEXT(Estimates!AP5,"0.000")&IF(Estimates!AS5="","",IF(Estimates!AS5<0.01,"***",IF(Estimates!AS5<0.05,"**",IF(Estimates!AS5<0.1,"*","")))) -> -0.041 | G60: =TEXT(Estimates!AT5,"0.000")&IF(Estimates!AW5="","",IF(Estimates!AW5<0.01,"***",IF(Estimates!AW5<0.05,"**",IF(Estimates!AW5<0.1,"*","")))) -> -0.012
B61: =IF(Estimates!AB5="","(n/a)","("&TEXT(Estimates!AB5,"0.00")&")") -> (0.96) | C61: =IF(Estimates!AF5="","(n/a)","("&TEXT(Estimates!AF5,"0.00")&")") -> (0.67) | D61: =IF(Estimates!AJ5="","(n/a)","("&TEXT(Estimates!AJ5,"0.00")&")") -> (-0.13) | E61: =IF(Estimates!AN5="","(n/a)","("&TEXT(Estimates!AN5,"0.00")&")") -> (0.23) | F61: =IF(Estimates!AR5="","(n/a)","("&TEXT(Estimates!AR5,"0.00")&")") -> (-1.10) | G61: =IF(Estimates!AV5="","(n/a)","("&TEXT(Estimates!AV5,"0.00")&")") -> (-0.27)
A62: Log (Plan Size) (t-1) | B62: =TEXT(Estimates!Z6,"0.000")&IF(Estimates!AC6="","",IF(Estimates!AC6<0.01,"***",IF(Estimates!AC6<0.05,"**",IF(Estimates!AC6<0.1,"*","")))) -> 0.107 | C62: =TEXT(Estimates!AD6,"0.000")&IF(Estimates!AG6="","",IF(Estimates!AG6<0.01,"***",IF(Estimates!AG6<0.05,"**",IF(Estimates!AG6<0.1,"*","")))) -> 0.084 | D62: =TEXT(Estimates!AH6,"0.000")&IF(Estimates!AK6="","",IF(Estimates!AK6<0.01,"***",IF(Estimates!AK6<0.05,"**",IF(Estimates!AK6<0.1,"*","")))) -> -0.905 | E62: =TEXT(Estimates!AL6,"0.000")&IF(Estimates!AO6="","",IF(Estimates!AO6<0.01,"***",IF(Estimates!AO6<0.05,"**",IF(Estimates!AO6<0.1,"*","")))) -> 0.351 | F62: =TEXT(Estimates!AP6,"0.000")&IF(Estimates!AS6="","",IF(Estimates!AS6<0.01,"***",IF(Estimates!AS6<0.05,"**",IF(Estimates!AS6<0.1,"*","")))) -> -0.044 | G62: =TEXT(Estimates!AT6,"0.000")&IF(Estimates!AW6="","",IF(Estimates!AW6<0.01,"***",IF(Estimates!AW6<0.05,"**",IF(Estimates!AW6<0.1,"*","")))) -> 1.652
B63: =IF(Estimates!AB6="","(n/a)","("&TEXT(Estimates!AB6,"0.00")&")") -> (1.17) | C63: =IF(Estimates!AF6="","(n/a)","("&TEXT(Estimates!AF6,"0.00")&")") -> (0.77) | D63: =IF(Estimates!AJ6="","(n/a)","("&TEXT(Estimates!AJ6,"0.00")&")") -> (-0.77) | E63: =IF(Estimates!AN6="","(n/a)","("&TEXT(Estimates!AN6,"0.00")&")") -> (0.34) | F63: =IF(Estimates!AR6="","(n/a)","("&TEXT(Estimates!AR6,"0.00")&")") -> (-0.02) | G63: =IF(Estimates!AV6="","(n/a)","("&TEXT(Estimates!AV6,"0.00")&")") -> (1.53)
A64: Funding Ratio (t-1) | B64: =TEXT(Estimates!Z7,"0.000")&IF(Estimates!AC7="","",IF(Estimates!AC7<0.01,"***",IF(Estimates!AC7<0.05,"**",IF(Estimates!AC7<0.1,"*","")))) -> -0.010 | C64: =TEXT(Estimates!AD7,"0.000")&IF(Estimates!AG7="","",IF(Estimates!AG7<0.01,"***",IF(Estimates!AG7<0.05,"**",IF(Estimates!AG7<0.1,"*","")))) -> -0.006 | D64: =TEXT(Estimates!AH7,"0.000")&IF(Estimates!AK7="","",IF(Estimates!AK7<0.01,"***",IF(Estimates!AK7<0.05,"**",IF(Estimates!AK7<0.1,"*","")))) -> -0.016 | E64: =TEXT(Estimates!AL7,"0.000")&IF(Estimates!AO7="","",IF(Estimates!AO7<0.01,"***",IF(Estimates!AO7<0.05,"**",IF(Estimates!AO7<0.1,"*","")))) -> -0.010 | F64: =TEXT(Estimates!AP7,"0.000")&IF(Estimates!AS7="","",IF(Estimates!AS7<0.01,"***",IF(Estimates!AS7<0.05,"**",IF(Estimates!AS7<0.1,"*","")))) -> -0.022 | G64: =TEXT(Estimates!AT7,"0.000")&IF(Estimates!AW7="","",IF(Estimates!AW7<0.01,"***",IF(Estimates!AW7<0.05,"**",IF(Estimates!AW7<0.1,"*","")))) -> -0.045
B65: =IF(Estimates!AB7="","(n/a)","("&TEXT(Estimates!AB7,"0.00")&")") -> (-0.98) | C65: =IF(Estimates!AF7="","(n/a)","("&TEXT(Estimates!AF7,"0.00")&")") -> (-0.55) | D65: =IF(Estimates!AJ7="","(n/a)","("&TEXT(Estimates!AJ7,"0.00")&")") -> (-0.49) | E65: =IF(Estimates!AN7="","(n/a)","("&TEXT(Estimates!AN7,"0.00")&")") -> (-0.35) | F65: =IF(Estimates!AR7="","(n/a)","("&TEXT(Estimates!AR7,"0.00")&")") -> (-0.62) | G65: =IF(Estimates!AV7="","(n/a)","("&TEXT(Estimates!AV7,"0.00")&")") -> (-1.26)
A66: Equity Allocation (%) | B66: =TEXT(Estimates!Z8,"0.000")&IF(Estimates!AC8="","",IF(Estimates!AC8<0.01,"***",IF(Estimates!AC8<0.05,"**",IF(Estimates!AC8<0.1,"*","")))) -> -0.300 | C66: =TEXT(Estimates!AD8,"0.000")&IF(Estimates!AG8="","",IF(Estimates!AG8<0.01,"***",IF(Estimates!AG8<0.05,"**",IF(Estimates!AG8<0.1,"*","")))) -> -0.182 | D66: =TEXT(Estimates!AH8,"0.000")&IF(Estimates!AK8="","",IF(Estimates!AK8<0.01,"***",IF(Estimates!AK8<0.05,"**",IF(Estimates!AK8<0.1,"*","")))) -> -0.527 | E66: =TEXT(Estimates!AL8,"0.000")&IF(Estimates!AO8="","",IF(Estimates!AO8<0.01,"***",IF(Estimates!AO8<0.05,"**",IF(Estimates!AO8<0.1,"*","")))) -> -0.561 | F66: =TEXT(Estimates!AP8,"0.000")&IF(Estimates!AS8="","",IF(Estimates!AS8<0.01,"***",IF(Estimates!AS8<0.05,"**",IF(Estimates!AS8<0.1,"*","")))) -> -0.740 | G66: =TEXT(Estimates!AT8,"0.000")&IF(Estimates!AW8="","",IF(Estimates!AW8<0.01,"***",IF(Estimates!AW8<0.05,"**",IF(Estimates!AW8<0.1,"*","")))) -> -1.190*
B67: =IF(Estimates!AB8="","(n/a)","("&TEXT(Estimates!AB8,"0.00")&")") -> (-1.32) | C67: =IF(Estimates!AF8="","(n/a)","("&TEXT(Estimates!AF8,"0.00")&")") -> (-0.90) | D67: =IF(Estimates!AJ8="","(n/a)","("&TEXT(Estimates!AJ8,"0.00")&")") -> (-1.09) | E67: =IF(Estimates!AN8="","(n/a)","("&TEXT(Estimates!AN8,"0.00")&")") -> (-1.02) | F67: =IF(Estimates!AR8="","(n/a)","("&TEXT(Estimates!AR8,"0.00")&")") -> (-1.51) | G67: =IF(Estimates!AV8="","(n/a)","("&TEXT(Estimates!AV8,"0.00")&")") -> (-1.84)
A68: Fixed Income Allocation (%) | B68: =TEXT(Estimates!Z9,"0.000")&IF(Estimates!AC9="","",IF(Estimates!AC9<0.01,"***",IF(Estimates!AC9<0.05,"**",IF(Estimates!AC9<0.1,"*","")))) -> -0.294 | C68: =TEXT(Estimates!AD9,"0.000")&IF(Estimates!AG9="","",IF(Estimates!AG9<0.01,"***",IF(Estimates!AG9<0.05,"**",IF(Estimates!AG9<0.1,"*","")))) -> -0.170 | D68: =TEXT(Estimates!AH9,"0.000")&IF(Estimates!AK9="","",IF(Estimates!AK9<0.01,"***",IF(Estimates!AK9<0.05,"**",IF(Estimates!AK9<0.1,"*","")))) -> -0.501 | E68: =TEXT(Estimates!AL9,"0.000")&IF(Estimates!AO9="","",IF(Estimates!AO9<0.01,"***",IF(Estimates!AO9<0.05,"**",IF(Estimates!AO9<0.1,"*","")))) -> -0.511 | F68: =TEXT(Estimates!AP9,"0.000")&IF(Estimates!AS9="","",IF(Estimates!AS9<0.01,"***",IF(Estimates!AS9<0.05,"**",IF(Estimates!AS9<0.1,"*","")))) -> -0.687 | G68: =TEXT(Estimates!AT9,"0.000")&IF(Estimates!AW9="","",IF(Estimates!AW9<0.01,"***",IF(Estimates!AW9<0.05,"**",IF(Estimates!AW9<0.1,"*","")))) -> -1.173*
B69: =IF(Estimates!AB9="","(n/a)","("&TEXT(Estimates!AB9,"0.00")&")") -> (-1.29) | C69: =IF(Estimates!AF9="","(n/a)","("&TEXT(Estimates!AF9,"0.00")&")") -> (-0.91) | D69: =IF(Estimates!AJ9="","(n/a)","("&TEXT(Estimates!AJ9,"0.00")&")") -> (-1.12) | E69: =IF(Estimates!AN9="","(n/a)","("&TEXT(Estimates!AN9,"0.00")&")") -> (-0.97) | F69: =IF(Estimates!AR9="","(n/a)","("&TEXT(Estimates!AR9,"0.00")&")") -> (-1.45) | G69: =IF(Estimates!AV9="","(n/a)","("&TEXT(Estimates!AV9,"0.00")&")") -> (-1.83)
A70: Real Estate Allocation (%) | B70: =TEXT(Estimates!Z10,"0.000")&IF(Estimates!AC10="","",IF(Estimates!AC10<0.01,"***",IF(Estimates!AC10<0.05,"**",IF(Estimates!AC10<0.1,"*","")))) -> -0.338 | C70: =TEXT(Estimates!AD10,"0.000")&IF(Estimates!AG10="","",IF(Estimates!AG10<0.01,"***",IF(Estimates!AG10<0.05,"**",IF(Estimates!AG10<0.1,"*","")))) -> -0.204 | D70: =TEXT(Estimates!AH10,"0.000")&IF(Estimates!AK10="","",IF(Estimates!AK10<0.01,"***",IF(Estimates!AK10<0.05,"**",IF(Estimates!AK10<0.1,"*","")))) -> -0.513 | E70: =TEXT(Estimates!AL10,"0.000")&IF(Estimates!AO10="","",IF(Estimates!AO10<0.01,"***",IF(Estimates!AO10<0.05,"**",IF(Estimates!AO10<0.1,"*","")))) -> -0.471 | F70: =TEXT(Estimates!AP10,"0.000")&IF(Estimates!AS10="","",IF(Estimates!AS10<0.01,"***",IF(Estimates!AS10<0.05,"**",IF(Estimates!AS10<0.1,"*","")))) -> -0.646 | G70: =TEXT(Estimates!AT10,"0.000")&IF(Estimates!AW10="","",IF(Estimates!AW10<0.01,"***",IF(Estimates!AW10<0.05,"**",IF(Estimates!AW10<0.1,"*","")))) -> -1.419*
B71: =IF(Estimates!AB10="","(n/a)","("&TEXT(Estimates!AB10,"0.00")&")") -> (-1.44) | C71: =IF(Estimates!AF10="","(n/a)","("&TEXT(Estimates!AF10,"0.00")&")") -> (-1.09) | D71: =IF(Estimates!AJ10="","(n/a)","("&TEXT(Estimates!AJ10,"0.00")&")") -> (-1.01) | E71: =IF(Estimates!AN10="","(n/a)","("&TEXT(Estimates!AN10,"0.00")&")") -> (-0.94) | F71: =IF(Estimates!AR10="","(n/a)","("&TEXT(Estimates!AR10,"0.00")&")") -> (-1.12) | G71: =IF(Estimates!AV10="","(n/a)","("&TEXT(Estimates!AV10,"0.00")&")") -> (-1.91)
A72: Private Equity Allocation (%) | B72: =TEXT(Estimates!Z11,"0.000")&IF(Estimates!AC11="","",IF(Estimates!AC11<0.01,"***",IF(Estimates!AC11<0.05,"**",IF(Estimates!AC11<0.1,"*","")))) -> -0.348 | C72: =TEXT(Estimates!AD11,"0.000")&IF(Estimates!AG11="","",IF(Estimates!AG11<0.01,"***",IF(Estimates!AG11<0.05,"**",IF(Estimates!AG11<0.1,"*","")))) -> -0.188 | D72: =TEXT(Estimates!AH11,"0.000")&IF(Estimates!AK11="","",IF(Estimates!AK11<0.01,"***",IF(Estimates!AK11<0.05,"**",IF(Estimates!AK11<0.1,"*","")))) -> -0.544 | E72: =TEXT(Estimates!AL11,"0.000")&IF(Estimates!AO11="","",IF(Estimates!AO11<0.01,"***",IF(Estimates!AO11<0.05,"**",IF(Estimates!AO11<0.1,"*","")))) -> -0.486 | F72: =TEXT(Estimates!AP11,"0.000")&IF(Estimates!AS11="","",IF(Estimates!AS11<0.01,"***",IF(Estimates!AS11<0.05,"**",IF(Estimates!AS11<0.1,"*","")))) -> -0.735 | G72: =TEXT(Estimates!AT11,"0.000")&IF(Estimates!AW11="","",IF(Estimates!AW11<0.01,"***",IF(Estimates!AW11<0.05,"**",IF(Estimates!AW11<0.1,"*","")))) -> -1.037*
B73: =IF(Estimates!AB11="","(n/a)","("&TEXT(Estimates!AB11,"0.00")&")") -> (-1.45) | C73: =IF(Estimates!AF11="","(n/a)","("&TEXT(Estimates!AF11,"0.00")&")") -> (-0.95) | D73: =IF(Estimates!AJ11="","(n/a)","("&TEXT(Estimates!AJ11,"0.00")&")") -> (-1.22) | E73: =IF(Estimates!AN11="","(n/a)","("&TEXT(Estimates!AN11,"0.00")&")") -> (-0.94) | F73: =IF(Estimates!AR11="","(n/a)","("&TEXT(Estimates!AR11,"0.00")&")") -> (-1.66) | G73: =IF(Estimates!AV11="","(n/a)","("&TEXT(Estimates!AV11,"0.00")&")") -> (-1.88)
A74: Hedge Fund Allocation (%) | B74: =TEXT(Estimates!Z12,"0.000")&IF(Estimates!AC12="","",IF(Estimates!AC12<0.01,"***",IF(Estimates!AC12<0.05,"**",IF(Estimates!AC12<0.1,"*","")))) -> -0.253 | C74: =TEXT(Estimates!AD12,"0.000")&IF(Estimates!AG12="","",IF(Estimates!AG12<0.01,"***",IF(Estimates!AG12<0.05,"**",IF(Estimates!AG12<0.1,"*","")))) -> -0.154 | D74: =TEXT(Estimates!AH12,"0.000")&IF(Estimates!AK12="","",IF(Estimates!AK12<0.01,"***",IF(Estimates!AK12<0.05,"**",IF(Estimates!AK12<0.1,"*","")))) -> -0.491 | E74: =TEXT(Estimates!AL12,"0.000")&IF(Estimates!AO12="","",IF(Estimates!AO12<0.01,"***",IF(Estimates!AO12<0.05,"**",IF(Estimates!AO12<0.1,"*","")))) -> -0.560 | F74: =TEXT(Estimates!AP12,"0.000")&IF(Estimates!AS12="","",IF(Estimates!AS12<0.01,"***",IF(Estimates!AS12<0.05,"**",IF(Estimates!AS12<0.1,"*","")))) -> -0.694 | G74: =TEXT(Estimates!AT12,"0.000")&IF(Estimates!AW12="","",IF(Estimates!AW12<0.01,"***",IF(Estimates!AW12<0.05,"**",IF(Estimates!AW12<0.1,"*","")))) -> -1.243*
B75: =IF(Estimates!AB12="","(n/a)","("&TEXT(Estimates!AB12,"0.00")&")") -> (-1.11) | C75: =IF(Estimates!AF12="","(n/a)","("&TEXT(Estimates!AF12,"0.00")&")") -> (-0.82) | D75: =IF(Estimates!AJ12="","(n/a)","("&TEXT(Estimates!AJ12,"0.00")&")") -> (-1.08) | E75: =IF(Estimates!AN12="","(n/a)","("&TEXT(Estimates!AN12,"0.00")&")") -> (-1.08) | F75: =IF(Estimates!AR12="","(n/a)","("&TEXT(Estimates!AR12,"0.00")&")") -> (-1.45) | G75: =IF(Estimates!AV12="","(n/a)","("&TEXT(Estimates!AV12,"0.00")&")") -> (-1.94)
A76: Misc. Alternatives Allocation (%) | B76: =TEXT(Estimates!Z13,"0.000")&IF(Estimates!AC13="","",IF(Estimates!AC13<0.01,"***",IF(Estimates!AC13<0.05,"**",IF(Estimates!AC13<0.1,"*","")))) -> -0.314 | C76: =TEXT(Estimates!AD13,"0.000")&IF(Estimates!AG13="","",IF(Estimates!AG13<0.01,"***",IF(Estimates!AG13<0.05,"**",IF(Estimates!AG13<0.1,"*","")))) -> -0.166 | D76: =TEXT(Estimates!AH13,"0.000")&IF(Estimates!AK13="","",IF(Estimates!AK13<0.01,"***",IF(Estimates!AK13<0.05,"**",IF(Estimates!AK13<0.1,"*","")))) -> -0.263 | E76: =TEXT(Estimates!AL13,"0.000")&IF(Estimates!AO13="","",IF(Estimates!AO13<0.01,"***",IF(Estimates!AO13<0.05,"**",IF(Estimates!AO13<0.1,"*","")))) -> -0.013 | F76: =TEXT(Estimates!AP13,"0.000")&IF(Estimates!AS13="","",IF(Estimates!AS13<0.01,"***",IF(Estimates!AS13<0.05,"**",IF(Estimates!AS13<0.1,"*","")))) -> -0.222 | G76: =TEXT(Estimates!AT13,"0.000")&IF(Estimates!AW13="","",IF(Estimates!AW13<0.01,"***",IF(Estimates!AW13<0.05,"**",IF(Estimates!AW13<0.1,"*","")))) -> -0.618
B77: =IF(Estimates!AB13="","(n/a)","("&TEXT(Estimates!AB13,"0.00")&")") -> (-1.35) | C77: =IF(Estimates!AF13="","(n/a)","("&TEXT(Estimates!AF13,"0.00")&")") -> (-0.82) | D77: =IF(Estimates!AJ13="","(n/a)","("&TEXT(Estimates!AJ13,"0.00")&")") -> (-0.49) | E77: =IF(Estimates!AN13="","(n/a)","("&TEXT(Estimates!AN13,"0.00")&")") -> (-0.01) | F77: =IF(Estimates!AR13="","(n/a)","("&TEXT(Estimates!AR13,"0.00")&")") -> (-0.31) | G77: =IF(Estimates!AV13="","(n/a)","("&TEXT(Estimates!AV13,"0.00")&")") -> (-0.60)
A78: Commodities Allocation (%) | B78: =TEXT(Estimates!Z14,"0.000")&IF(Estimates!AC14="","",IF(Estimates!AC14<0.01,"***",IF(Estimates!AC14<0.05,"**",IF(Estimates!AC14<0.1,"*","")))) -> -0.482* | C78: =TEXT(Estimates!AD14,"0.000")&IF(Estimates!AG14="","",IF(Estimates!AG14<0.01,"***",IF(Estimates!AG14<0.05,"**",IF(Estimates!AG14<0.1,"*","")))) -> -0.238 | D78: =TEXT(Estimates!AH14,"0.000")&IF(Estimates!AK14="","",IF(Estimates!AK14<0.01,"***",IF(Estimates!AK14<0.05,"**",IF(Estimates!AK14<0.1,"*","")))) -> -0.468 | E78: =TEXT(Estimates!AL14,"0.000")&IF(Estimates!AO14="","",IF(Estimates!AO14<0.01,"***",IF(Estimates!AO14<0.05,"**",IF(Estimates!AO14<0.1,"*","")))) -> -0.440 | F78: =TEXT(Estimates!AP14,"0.000")&IF(Estimates!AS14="","",IF(Estimates!AS14<0.01,"***",IF(Estimates!AS14<0.05,"**",IF(Estimates!AS14<0.1,"*","")))) -> -0.586 | G78: =TEXT(Estimates!AT14,"0.000")&IF(Estimates!AW14="","",IF(Estimates!AW14<0.01,"***",IF(Estimates!AW14<0.05,"**",IF(Estimates!AW14<0.1,"*","")))) -> -0.909
B79: =IF(Estimates!AB14="","(n/a)","("&TEXT(Estimates!AB14,"0.00")&")") -> (-1.74) | C79: =IF(Estimates!AF14="","(n/a)","("&TEXT(Estimates!AF14,"0.00")&")") -> (-1.07) | D79: =IF(Estimates!AJ14="","(n/a)","("&TEXT(Estimates!AJ14,"0.00")&")") -> (-0.93) | E79: =IF(Estimates!AN14="","(n/a)","("&TEXT(Estimates!AN14,"0.00")&")") -> (-0.80) | F79: =IF(Estimates!AR14="","(n/a)","("&TEXT(Estimates!AR14,"0.00")&")") -> (-1.16) | G79: =IF(Estimates!AV14="","(n/a)","("&TEXT(Estimates!AV14,"0.00")&")") -> (-1.44)
A80: Cash Allocation (%) | B80: =TEXT(Estimates!Z15,"0.000")&IF(Estimates!AC15="","",IF(Estimates!AC15<0.01,"***",IF(Estimates!AC15<0.05,"**",IF(Estimates!AC15<0.1,"*","")))) -> -0.326 | C80: =TEXT(Estimates!AD15,"0.000")&IF(Estimates!AG15="","",IF(Estimates!AG15<0.01,"***",IF(Estimates!AG15<0.05,"**",IF(Estimates!AG15<0.1,"*","")))) -> -0.191 | D80: =TEXT(Estimates!AH15,"0.000")&IF(Estimates!AK15="","",IF(Estimates!AK15<0.01,"***",IF(Estimates!AK15<0.05,"**",IF(Estimates!AK15<0.1,"*","")))) -> -0.447 | E80: =TEXT(Estimates!AL15,"0.000")&IF(Estimates!AO15="","",IF(Estimates!AO15<0.01,"***",IF(Estimates!AO15<0.05,"**",IF(Estimates!AO15<0.1,"*","")))) -> -0.441 | F80: =TEXT(Estimates!AP15,"0.000")&IF(Estimates!AS15="","",IF(Estimates!AS15<0.01,"***",IF(Estimates!AS15<0.05,"**",IF(Estimates!AS15<0.1,"*","")))) -> -0.588 | G80: =TEXT(Estimates!AT15,"0.000")&IF(Estimates!AW15="","",IF(Estimates!AW15<0.01,"***",IF(Estimates!AW15<0.05,"**",IF(Estimates!AW15<0.1,"*","")))) -> -0.999
B81: =IF(Estimates!AB15="","(n/a)","("&TEXT(Estimates!AB15,"0.00")&")") -> (-1.46) | C81: =IF(Estimates!AF15="","(n/a)","("&TEXT(Estimates!AF15,"0.00")&")") -> (-0.94) | D81: =IF(Estimates!AJ15="","(n/a)","("&TEXT(Estimates!AJ15,"0.00")&")") -> (-0.94) | E81: =IF(Estimates!AN15="","(n/a)","("&TEXT(Estimates!AN15,"0.00")&")") -> (-0.82) | F81: =IF(Estimates!AR15="","(n/a)","("&TEXT(Estimates!AR15,"0.00")&")") -> (-1.24) | G81: =IF(Estimates!AV15="","(n/a)","("&TEXT(Estimates!AV15,"0.00")&")") -> (-1.59)
A82: Financial Center (0/1) | B82: =TEXT(Estimates!Z16,"0.000")&IF(Estimates!AC16="","",IF(Estimates!AC16<0.01,"***",IF(Estimates!AC16<0.05,"**",IF(Estimates!AC16<0.1,"*","")))) -> -0.185 | C82: =TEXT(Estimates!AD16,"0.000")&IF(Estimates!AG16="","",IF(Estimates!AG16<0.01,"***",IF(Estimates!AG16<0.05,"**",IF(Estimates!AG16<0.1,"*","")))) -> -0.291 | F82: =TEXT(Estimates!AP16,"0.000")&IF(Estimates!AS16="","",IF(Estimates!AS16<0.01,"***",IF(Estimates!AS16<0.05,"**",IF(Estimates!AS16<0.1,"*","")))) -> -2.013
B83: =IF(Estimates!AB16="","(n/a)","("&TEXT(Estimates!AB16,"0.00")&")") -> (-0.43) | C83: =IF(Estimates!AF16="","(n/a)","("&TEXT(Estimates!AF16,"0.00")&")") -> (-0.98) | F83: =IF(Estimates!AR16="","(n/a)","("&TEXT(Estimates!AR16,"0.00")&")") -> (0.00)
A84: Log (CIO Age) (t-1) | C84: =TEXT(Estimates!AD17,"0.000")&IF(Estimates!AG17="","",IF(Estimates!AG17<0.01,"***",IF(Estimates!AG17<0.05,"**",IF(Estimates!AG17<0.1,"*","")))) -> 0.222 | D84: =TEXT(Estimates!AH17,"0.000")&IF(Estimates!AK17="","",IF(Estimates!AK17<0.01,"***",IF(Estimates!AK17<0.05,"**",IF(Estimates!AK17<0.1,"*","")))) -> 1.532 | E84: =TEXT(Estimates!AL17,"0.000")&IF(Estimates!AO17="","",IF(Estimates!AO17<0.01,"***",IF(Estimates!AO17<0.05,"**",IF(Estimates!AO17<0.1,"*","")))) -> 4.118***
C85: =IF(Estimates!AF17="","(n/a)","("&TEXT(Estimates!AF17,"0.00")&")") -> (0.59) | D85: =IF(Estimates!AJ17="","(n/a)","("&TEXT(Estimates!AJ17,"0.00")&")") -> (1.44) | E85: =IF(Estimates!AN17="","(n/a)","("&TEXT(Estimates!AN17,"0.00")&")") -> (3.07)
A86: Log (CIO Tenure) (t-1) | C86: =TEXT(Estimates!AD18,"0.000")&IF(Estimates!AG18="","",IF(Estimates!AG18<0.01,"***",IF(Estimates!AG18<0.05,"**",IF(Estimates!AG18<0.1,"*","")))) -> -0.114 | D86: =TEXT(Estimates!AH18,"0.000")&IF(Estimates!AK18="","",IF(Estimates!AK18<0.01,"***",IF(Estimates!AK18<0.05,"**",IF(Estimates!AK18<0.1,"*","")))) -> -0.252 | E86: =TEXT(Estimates!AL18,"0.000")&IF(Estimates!AO18="","",IF(Estimates!AO18<0.01,"***",IF(Estimates!AO18<0.05,"**",IF(Estimates!AO18<0.1,"*","")))) -> -0.817**
C87: =IF(Estimates!AF18="","(n/a)","("&TEXT(Estimates!AF18,"0.00")&")") -> (-0.48) | D87: =IF(Estimates!AJ18="","(n/a)","("&TEXT(Estimates!AJ18,"0.00")&")") -> (-0.96) | E87: =IF(Estimates!AN18="","(n/a)","("&TEXT(Estimates!AN18,"0.00")&")") -> (-2.23)
A88: CIO Prior Private Experience (0/1) | C88: =TEXT(Estimates!AD19,"0.000")&IF(Estimates!AG19="","",IF(Estimates!AG19<0.01,"***",IF(Estimates!AG19<0.05,"**",IF(Estimates!AG19<0.1,"*","")))) -> 0.035 | D88: =TEXT(Estimates!AH19,"0.000")&IF(Estimates!AK19="","",IF(Estimates!AK19<0.01,"***",IF(Estimates!AK19<0.05,"**",IF(Estimates!AK19<0.1,"*","")))) -> -0.426 | E88: =TEXT(Estimates!AL19,"0.000")&IF(Estimates!AO19="","",IF(Estimates!AO19<0.01,"***",IF(Estimates!AO19<0.05,"**",IF(Estimates!AO19<0.1,"*","")))) -> -1.381*
C89: =IF(Estimates!AF19="","(n/a)","("&TEXT(Estimates!AF19,"0.00")&")") -> (0.07) | D89: =IF(Estimates!AJ19="","(n/a)","("&TEXT(Estimates!AJ19,"0.00")&")") -> (-0.68) | E89: =IF(Estimates!AN19="","(n/a)","("&TEXT(Estimates!AN19,"0.00")&")") -> (-1.80)
A90: CIO Attended Elite College (0/1) | C90: =TEXT(Estimates!AD20,"0.000")&IF(Estimates!AG20="","",IF(Estimates!AG20<0.01,"***",IF(Estimates!AG20<0.05,"**",IF(Estimates!AG20<0.1,"*","")))) -> -0.466 | D90: =TEXT(Estimates!AH20,"0.000")&IF(Estimates!AK20="","",IF(Estimates!AK20<0.01,"***",IF(Estimates!AK20<0.05,"**",IF(Estimates!AK20<0.1,"*","")))) -> -0.105 | E90: =TEXT(Estimates!AL20,"0.000")&IF(Estimates!AO20="","",IF(Estimates!AO20<0.01,"***",IF(Estimates!AO20<0.05,"**",IF(Estimates!AO20<0.1,"*","")))) -> -0.005
C91: =IF(Estimates!AF20="","(n/a)","("&TEXT(Estimates!AF20,"0.00")&")") -> (-1.72) | D91: =IF(Estimates!AJ20="","(n/a)","("&TEXT(Estimates!AJ20,"0.00")&")") -> (-0.22) | E91: =IF(Estimates!AN20="","(n/a)","("&TEXT(Estimates!AN20,"0.00")&")") -> (-0.01)
A92: Separate Investment Board (0/1) | C92: =TEXT(Estimates!AD21,"0.000")&IF(Estimates!AG21="","",IF(Estimates!AG21<0.01,"***",IF(Estimates!AG21<0.05,"**",IF(Estimates!AG21<0.1,"*","")))) -> 0.242
C93: =IF(Estimates!AF21="","(n/a)","("&TEXT(Estimates!AF21,"0.00")&")") -> (0.92)
A94: % Political Appointees on Board | C94: =TEXT(Estimates!AD22,"0.000")&IF(Estimates!AG22="","",IF(Estimates!AG22<0.01,"***",IF(Estimates!AG22<0.05,"**",IF(Estimates!AG22<0.1,"*","")))) -> -0.236 | D94: =TEXT(Estimates!AH22,"0.000")&IF(Estimates!AK22="","",IF(Estimates!AK22<0.01,"***",IF(Estimates!AK22<0.05,"**",IF(Estimates!AK22<0.1,"*","")))) -> -3.493 | E94: =TEXT(Estimates!AL22,"0.000")&IF(Estimates!AO22="","",IF(Estimates!AO22<0.01,"***",IF(Estimates!AO22<0.05,"**",IF(Estimates!AO22<0.1,"*","")))) -> -4.547*
C95: =IF(Estimates!AF22="","(n/a)","("&TEXT(Estimates!AF22,"0.00")&")") -> (-0.42) | D95: =IF(Estimates!AJ22="","(n/a)","("&TEXT(Estimates!AJ22,"0.00")&")") -> (-0.84) | E95: =IF(Estimates!AN22="","(n/a)","("&TEXT(Estimates!AN22,"0.00")&")") -> (-1.83)
A97: Observations | B97: =Estimates!Z24 -> 277 | C97: =Estimates!AD24 -> 255 | D97: =Estimates!AH24 -> 251 | E97: =Estimates!AL24 -> 251 | F97: =Estimates!AP24 -> 261 | G97: =Estimates!AT24 -> 177
A98: Adjusted R-squared | B98: =Estimates!Z27 -> 0.20614724 | C98: =Estimates!AD27 -> 0.13653672 | D98: =Estimates!AH27 -> -0.0090982717 | E98: =Estimates!AL27 -> 0.1710196 | F98: =Estimates!AP27 -> 0.53599786 | G98: =Estimates!AT27 -> 0.51380975
A99: Number of CIOs | B99: =Estimates!Z28 -> 42 | C99: =Estimates!AD28 -> 40 | D99: =Estimates!AH28 -> 40 | E99: =Estimates!AL28 -> 40 | F99: =Estimates!AP28 -> 42 | G99: =Estimates!AT28 -> 23
A100: Plan FE | B100: No | C100: No | D100: Yes | E100: Yes | F100: No | G100: No
A101: Year FE | B101: Yes | C101: Yes | D101: No | E101: Yes | F101: Yes | G101: Yes
A102: CIO FE | B102: No | C102: No | D102: No | E102: No | F102: Yes | G102: Yes
A103: Min. Tenure at Departure (years) | G103: 4

Sheet Table XII
A1: Table XII: Conflicted CIOs: Fee Ratio in the First versus Second Half of Tenure
A2: This table repeats the tests of Table XI with Fee Ratio as the dependent variable. Fee Ratio is the plan's total investment fees as a percentage of plan assets. The sample is restricted to plan-years of conflicted CIOs, and Second Half of Tenure is equal to 1 in the fiscal years in which the CIO's tenure exceeds one half of the CIO's tenure at departure and 0 otherwise. The other independent variables are as defined in Table I. Columns 5 and 6 include CIO fixed effects and omit the CIO-level controls; Column 6 restricts the sample to CIOs whose tenure at departure is at least four years. The standard errors are double clustered by plan and year. Coefficients marked with ***, **, and * are significant at the 1%, 5%, and 10% level, respectively.
B4: (1) | C4: (2) | D4: (3) | E4: (4) | F4: (5) | G4: (6)
B5: Fee Ratio (t) | C5: Fee Ratio (t) | D5: Fee Ratio (t) | E5: Fee Ratio (t) | F5: Fee Ratio (t) | G5: Fee Ratio (t)
A6: Second Half of Tenure (0/1) | B6: =TEXT(Estimates!AX4,"0.000")&IF(Estimates!BA4="","",IF(Estimates!BA4<0.01,"***",IF(Estimates!BA4<0.05,"**",IF(Estimates!BA4<0.1,"*","")))) -> -0.059 | C6: =TEXT(Estimates!BB4,"0.000")&IF(Estimates!BE4="","",IF(Estimates!BE4<0.01,"***",IF(Estimates!BE4<0.05,"**",IF(Estimates!BE4<0.1,"*","")))) -> -0.077 | D6: =TEXT(Estimates!BF4,"0.000")&IF(Estimates!BI4="","",IF(Estimates!BI4<0.01,"***",IF(Estimates!BI4<0.05,"**",IF(Estimates!BI4<0.1,"*","")))) -> -0.018 | E6: =TEXT(Estimates!BJ4,"0.000")&IF(Estimates!BM4="","",IF(Estimates!BM4<0.01,"***",IF(Estimates!BM4<0.05,"**",IF(Estimates!BM4<0.1,"*","")))) -> -0.053 | F6: =TEXT(Estimates!BN4,"0.000")&IF(Estimates!BQ4="","",IF(Estimates!BQ4<0.01,"***",IF(Estimates!BQ4<0.05,"**",IF(Estimates!BQ4<0.1,"*","")))) -> -0.060 | G6: =TEXT(Estimates!BR4,"0.000")&IF(Estimates!BU4="","",IF(Estimates!BU4<0.01,"***",IF(Estimates!BU4<0.05,"**",IF(Estimates!BU4<0.1,"*","")))) -> -0.027
B7: =IF(Estimates!AZ4="","(n/a)","("&TEXT(Estimates!AZ4,"0.00")&")") -> (-1.70) | C7: =IF(Estimates!BD4="","(n/a)","("&TEXT(Estimates!BD4,"0.00")&")") -> (-1.37) | D7: =IF(Estimates!BH4="","(n/a)","("&TEXT(Estimates!BH4,"0.00")&")") -> (-0.39) | E7: =IF(Estimates!BL4="","(n/a)","("&TEXT(Estimates!BL4,"0.00")&")") -> (-1.29) | F7: =IF(Estimates!BP4="","(n/a)","("&TEXT(Estimates!BP4,"0.00")&")") -> (-1.09) | G7: =IF(Estimates!BT4="","(n/a)","("&TEXT(Estimates!BT4,"0.00")&")") -> (-0.42)
A8: Investment Return (t - 1) | B8: =TEXT(Estimates!AX5,"0.000")&IF(Estimates!BA5="","",IF(Estimates!BA5<0.01,"***",IF(Estimates!BA5<0.05,"**",IF(Estimates!BA5<0.1,"*","")))) -> 0.000 | C8: =TEXT(Estimates!BB5,"0.000")&IF(Estimates!BE5="","",IF(Estimates!BE5<0.01,"***",IF(Estimates!BE5<0.05,"**",IF(Estimates!BE5<0.1,"*","")))) -> 0.001 | D8: =TEXT(Estimates!BF5,"0.000")&IF(Estimates!BI5="","",IF(Estimates!BI5<0.01,"***",IF(Estimates!BI5<0.05,"**",IF(Estimates!BI5<0.1,"*","")))) -> -0.002 | E8: =TEXT(Estimates!BJ5,"0.000")&IF(Estimates!BM5="","",IF(Estimates!BM5<0.01,"***",IF(Estimates!BM5<0.05,"**",IF(Estimates!BM5<0.1,"*","")))) -> 0.000 | F8: =TEXT(Estimates!BN5,"0.000")&IF(Estimates!BQ5="","",IF(Estimates!BQ5<0.01,"***",IF(Estimates!BQ5<0.05,"**",IF(Estimates!BQ5<0.1,"*","")))) -> -0.001 | G8: =TEXT(Estimates!BR5,"0.000")&IF(Estimates!BU5="","",IF(Estimates!BU5<0.01,"***",IF(Estimates!BU5<0.05,"**",IF(Estimates!BU5<0.1,"*","")))) -> 0.000
B9: =IF(Estimates!AZ5="","(n/a)","("&TEXT(Estimates!AZ5,"0.00")&")") -> (0.12) | C9: =IF(Estimates!BD5="","(n/a)","("&TEXT(Estimates!BD5,"0.00")&")") -> (0.48) | D9: =IF(Estimates!BH5="","(n/a)","("&TEXT(Estimates!BH5,"0.00")&")") -> (-0.73) | E9: =IF(Estimates!BL5="","(n/a)","("&TEXT(Estimates!BL5,"0.00")&")") -> (-0.21) | F9: =IF(Estimates!BP5="","(n/a)","("&TEXT(Estimates!BP5,"0.00")&")") -> (-0.67) | G9: =IF(Estimates!BT5="","(n/a)","("&TEXT(Estimates!BT5,"0.00")&")") -> (0.18)
A10: Log (Plan Size) (t-1) | B10: =TEXT(Estimates!AX6,"0.000")&IF(Estimates!BA6="","",IF(Estimates!BA6<0.01,"***",IF(Estimates!BA6<0.05,"**",IF(Estimates!BA6<0.1,"*","")))) -> -0.038* | C10: =TEXT(Estimates!BB6,"0.000")&IF(Estimates!BE6="","",IF(Estimates!BE6<0.01,"***",IF(Estimates!BE6<0.05,"**",IF(Estimates!BE6<0.1,"*","")))) -> -0.046** | D10: =TEXT(Estimates!BF6,"0.000")&IF(Estimates!BI6="","",IF(Estimates!BI6<0.01,"***",IF(Estimates!BI6<0.05,"**",IF(Estimates!BI6<0.1,"*","")))) -> -0.043 | E10: =TEXT(Estimates!BJ6,"0.000")&IF(Estimates!BM6="","",IF(Estimates!BM6<0.01,"***",IF(Estimates!BM6<0.05,"**",IF(Estimates!BM6<0.1,"*","")))) -> -0.284** | F10: =TEXT(Estimates!BN6,"0.000")&IF(Estimates!BQ6="","",IF(Estimates!BQ6<0.01,"***",IF(Estimates!BQ6<0.05,"**",IF(Estimates!BQ6<0.1,"*","")))) -> -0.169 | G10: =TEXT(Estimates!BR6,"0.000")&IF(Estimates!BU6="","",IF(Estimates!BU6<0.01,"***",IF(Estimates!BU6<0.05,"**",IF(Estimates!BU6<0.1,"*","")))) -> -0.077
B11: =IF(Estimates!AZ6="","(n/a)","("&TEXT(Estimates!AZ6,"0.00")&")") -> (-1.98) | C11: =IF(Estimates!BD6="","(n/a)","("&TEXT(Estimates!BD6,"0.00")&")") -> (-2.26) | D11: =IF(Estimates!BH6="","(n/a)","("&TEXT(Estimates!BH6,"0.00")&")") -> (-0.40) | E11: =IF(Estimates!BL6="","(n/a)","("&TEXT(Estimates!BL6,"0.00")&")") -> (-2.11) | F11: =IF(Estimates!BP6="","(n/a)","("&TEXT(Estimates!BP6,"0.00")&")") -> (-0.86) | G11: =IF(Estimates!BT6="","(n/a)","("&TEXT(Estimates!BT6,"0.00")&")") -> (-0.40)
A12: Funding Ratio (t-1) | B12: =TEXT(Estimates!AX7,"0.000")&IF(Estimates!BA7="","",IF(Estimates!BA7<0.01,"***",IF(Estimates!BA7<0.05,"**",IF(Estimates!BA7<0.1,"*","")))) -> -0.002*** | C12: =TEXT(Estimates!BB7,"0.000")&IF(Estimates!BE7="","",IF(Estimates!BE7<0.01,"***",IF(Estimates!BE7<0.05,"**",IF(Estimates!BE7<0.1,"*","")))) -> -0.002*** | D12: =TEXT(Estimates!BF7,"0.000")&IF(Estimates!BI7="","",IF(Estimates!BI7<0.01,"***",IF(Estimates!BI7<0.05,"**",IF(Estimates!BI7<0.1,"*","")))) -> -0.006 | E12: =TEXT(Estimates!BJ7,"0.000")&IF(Estimates!BM7="","",IF(Estimates!BM7<0.01,"***",IF(Estimates!BM7<0.05,"**",IF(Estimates!BM7<0.1,"*","")))) -> -0.001 | F12: =TEXT(Estimates!BN7,"0.000")&IF(Estimates!BQ7="","",IF(Estimates!BQ7<0.01,"***",IF(Estimates!BQ7<0.05,"**",IF(Estimates!BQ7<0.1,"*","")))) -> -0.001 | G12: =TEXT(Estimates!BR7,"0.000")&IF(Estimates!BU7="","",IF(Estimates!BU7<0.01,"***",IF(Estimates!BU7<0.05,"**",IF(Estimates!BU7<0.1,"*","")))) -> -0.001
B13: =IF(Estimates!AZ7="","(n/a)","("&TEXT(Estimates!AZ7,"0.00")&")") -> (-3.01) | C13: =IF(Estimates!BD7="","(n/a)","("&TEXT(Estimates!BD7,"0.00")&")") -> (-3.00) | D13: =IF(Estimates!BH7="","(n/a)","("&TEXT(Estimates!BH7,"0.00")&")") -> (-1.64) | E13: =IF(Estimates!BL7="","(n/a)","("&TEXT(Estimates!BL7,"0.00")&")") -> (-0.43) | F13: =IF(Estimates!BP7="","(n/a)","("&TEXT(Estimates!BP7,"0.00")&")") -> (-0.33) | G13: =IF(Estimates!BT7="","(n/a)","("&TEXT(Estimates!BT7,"0.00")&")") -> (-0.69)
A14: Equity Allocation (%) | B14: =TEXT(Estimates!AX8,"0.000")&IF(Estimates!BA8="","",IF(Estimates!BA8<0.01,"***",IF(Estimates!BA8<0.05,"**",IF(Estimates!BA8<0.1,"*","")))) -> -0.085 | C14: =TEXT(Estimates!BB8,"0.000")&IF(Estimates!BE8="","",IF(Estimates!BE8<0.01,"***",IF(Estimates!BE8<0.05,"**",IF(Estimates!BE8<0.1,"*","")))) -> -0.038 | D14: =TEXT(Estimates!BF8,"0.000")&IF(Estimates!BI8="","",IF(Estimates!BI8<0.01,"***",IF(Estimates!BI8<0.05,"**",IF(Estimates!BI8<0.1,"*","")))) -> -0.082 | E14: =TEXT(Estimates!BJ8,"0.000")&IF(Estimates!BM8="","",IF(Estimates!BM8<0.01,"***",IF(Estimates!BM8<0.05,"**",IF(Estimates!BM8<0.1,"*","")))) -> -0.056* | F14: =TEXT(Estimates!BN8,"0.000")&IF(Estimates!BQ8="","",IF(Estimates!BQ8<0.01,"***",IF(Estimates!BQ8<0.05,"**",IF(Estimates!BQ8<0.1,"*","")))) -> -0.055 | G14: =TEXT(Estimates!BR8,"0.000")&IF(Estimates!BU8="","",IF(Estimates!BU8<0.01,"***",IF(Estimates!BU8<0.05,"**",IF(Estimates!BU8<0.1,"*","")))) -> 0.006
B15: =IF(Estimates!AZ8="","(n/a)","("&TEXT(Estimates!AZ8,"0.00")&")") -> (-1.18) | C15: =IF(Estimates!BD8="","(n/a)","("&TEXT(Estimates!BD8,"0.00")&")") -> (-0.62) | D15: =IF(Estimates!BH8="","(n/a)","("&TEXT(Estimates!BH8,"0.00")&")") -> (-1.36) | E15: =IF(Estimates!BL8="","(n/a)","("&TEXT(Estimates!BL8,"0.00")&")") -> (-1.99) | F15: =IF(Estimates!BP8="","(n/a)","("&TEXT(Estimates!BP8,"0.00")&")") -> (-1.22) | G15: =IF(Estimates!BT8="","(n/a)","("&TEXT(Estimates!BT8,"0.00")&")") -> (0.09)
A16: Fixed Income Allocation (%) | B16: =TEXT(Estimates!AX9,"0.000")&IF(Estimates!BA9="","",IF(Estimates!BA9<0.01,"***",IF(Estimates!BA9<0.05,"**",IF(Estimates!BA9<0.1,"*","")))) -> -0.094 | C16: =TEXT(Estimates!BB9,"0.000")&IF(Estimates!BE9="","",IF(Estimates!BE9<0.01,"***",IF(Estimates!BE9<0.05,"**",IF(Estimates!BE9<0.1,"*","")))) -> -0.048 | D16: =TEXT(Estimates!BF9,"0.000")&IF(Estimates!BI9="","",IF(Estimates!BI9<0.01,"***",IF(Estimates!BI9<0.05,"**",IF(Estimates!BI9<0.1,"*","")))) -> -0.092 | E16: =TEXT(Estimates!BJ9,"0.000")&IF(Estimates!BM9="","",IF(Estimates!BM9<0.01,"***",IF(Estimates!BM9<0.05,"**",IF(Estimates!BM9<0.1,"*","")))) -> -0.064** | F16: =TEXT(Estimates!BN9,"0.000")&IF(Estimates!BQ9="","",IF(Estimates!BQ9<0.01,"***",IF(Estimates!BQ9<0.05,"**",IF(Estimates!BQ9<0.1,"*","")))) -> -0.065 | G16: =TEXT(Estimates!BR9,"0.000")&IF(Estimates!BU9="","",IF(Estimates!BU9<0.01,"***",IF(Estimates!BU9<0.05,"**",IF(Estimates!BU9<0.1,"*","")))) -> -0.001
B17: =IF(Estimates!AZ9="","(n/a)","("&TEXT(Estimates!AZ9,"0.00")&")") -> (-1.29) | C17: =IF(Estimates!BD9="","(n/a)","("&TEXT(Estimates!BD9,"0.00")&")") -> (-0.79) | D17: =IF(Estimates!BH9="","(n/a)","("&TEXT(Estimates!BH9,"0.00")&")") -> (-1.53) | E17: =IF(Estimates!BL9="","(n/a)","("&TEXT(Estimates!BL9,"0.00")&")") -> (-2.25) | F17: =IF(Estimates!BP9="","(n/a)","("&TEXT(Estimates!BP9,"0.00")&")") -> (-1.37) | G17: =IF(Estimates!BT9="","(n/a)","("&TEXT(Estimates!BT9,"0.00")&")") -> (-0.01)
A18: Real Estate Allocation (%) | B18: =TEXT(Estimates!AX10,"0.000")&IF(Estimates!BA10="","",IF(Estimates!BA10<0.01,"***",IF(Estimates!BA10<0.05,"**",IF(Estimates!BA10<0.1,"*","")))) -> -0.075 | C18: =TEXT(Estimates!BB10,"0.000")&IF(Estimates!BE10="","",IF(Estimates!BE10<0.01,"***",IF(Estimates!BE10<0.05,"**",IF(Estimates!BE10<0.1,"*","")))) -> -0.032 | D18: =TEXT(Estimates!BF10,"0.000")&IF(Estimates!BI10="","",IF(Estimates!BI10<0.01,"***",IF(Estimates!BI10<0.05,"**",IF(Estimates!BI10<0.1,"*","")))) -> -0.078 | E18: =TEXT(Estimates!BJ10,"0.000")&IF(Estimates!BM10="","",IF(Estimates!BM10<0.01,"***",IF(Estimates!BM10<0.05,"**",IF(Estimates!BM10<0.1,"*","")))) -> -0.075* | F18: =TEXT(Estimates!BN10,"0.000")&IF(Estimates!BQ10="","",IF(Estimates!BQ10<0.01,"***",IF(Estimates!BQ10<0.05,"**",IF(Estimates!BQ10<0.1,"*","")))) -> -0.077 | G18: =TEXT(Estimates!BR10,"0.000")&IF(Estimates!BU10="","",IF(Estimates!BU10<0.01,"***",IF(Estimates!BU10<0.05,"**",IF(Estimates!BU10<0.1,"*","")))) -> -0.011
B19: =IF(Estimates!AZ10="","(n/a)","("&TEXT(Estimates!AZ10,"0.00")&")") -> (-1.01) | C19: =IF(Estimates!BD10="","(n/a)","("&TEXT(Estimates!BD10,"0.00")&")") -> (-0.51) | D19: =IF(Estimates!BH10="","(n/a)","("&TEXT(Estimates!BH10,"0.00")&")") -> (-1.31) | E19: =IF(Estimates!BL10="","(n/a)","("&TEXT(Estimates!BL10,"0.00")&")") -> (-1.93) | F19: =IF(Estimates!BP10="","(n/a)","("&TEXT(Estimates!BP10,"0.00")&")") -> (-1.23) | G19: =IF(Estimates!BT10="","(n/a)","("&TEXT(Estimates!BT10,"0.00")&")") -> (-0.13)
A20: Private Equity Allocation (%) | B20: =TEXT(Estimates!AX11,"0.000")&IF(Estimates!BA11="","",IF(Estimates!BA11<0.01,"***",IF(Estimates!BA11<0.05,"**",IF(Estimates!BA11<0.1,"*","")))) -> -0.083 | C20: =TEXT(Estimates!BB11,"0.000")&IF(Estimates!BE11="","",IF(Estimates!BE11<0.01,"***",IF(Estimates!BE11<0.05,"**",IF(Estimates!BE11<0.1,"*","")))) -> -0.038 | D20: =TEXT(Estimates!BF11,"0.000")&IF(Estimates!BI11="","",IF(Estimates!BI11<0.01,"***",IF(Estimates!BI11<0.05,"**",IF(Estimates!BI11<0.1,"*","")))) -> -0.065 | E20: =TEXT(Estimates!BJ11,"0.000")&IF(Estimates!BM11="","",IF(Estimates!BM11<0.01,"***",IF(Estimates!BM11<0.05,"**",IF(Estimates!BM11<0.1,"*","")))) -> -0.033 | F20: =TEXT(Estimates!BN11,"0.000")&IF(Estimates!BQ11="","",IF(Estimates!BQ11<0.01,"***",IF(Estimates!BQ11<0.05,"**",IF(Estimates!BQ11<0.1,"*","")))) -> -0.041 | G20: =TEXT(Estimates!BR11,"0.000")&IF(Estimates!BU11="","",IF(Estimates!BU11<0.01,"***",IF(Estimates!BU11<0.05,"**",IF(Estimates!BU11<0.1,"*","")))) -> 0.016
B21: =IF(Estimates!AZ11="","(n/a)","("&TEXT(Estimates!AZ11,"0.00")&")") -> (-1.16) | C21: =IF(Estimates!BD11="","(n/a)","("&TEXT(Estimates!BD11,"0.00")&")") -> (-0.63) | D21: =IF(Estimates!BH11="","(n/a)","("&TEXT(Estimates!BH11,"0.00")&")") -> (-1.06) | E21: =IF(Estimates!BL11="","(n/a)","("&TEXT(Estimates!BL11,"0.00")&")") -> (-1.20) | F21: =IF(Estimates!BP11="","(n/a)","("&TEXT(Estimates!BP11,"0.00")&")") -> (-0.95) | G21: =IF(Estimates!BT11="","(n/a)","("&TEXT(Estimates!BT11,"0.00")&")") -> (0.25)
A22: Hedge Fund Allocation (%) | B22: =TEXT(Estimates!AX12,"0.000")&IF(Estimates!BA12="","",IF(Estimates!BA12<0.01,"***",IF(Estimates!BA12<0.05,"**",IF(Estimates!BA12<0.1,"*","")))) -> -0.090 | C22: =TEXT(Estimates!BB12,"0.000")&IF(Estimates!BE12="","",IF(Estimates!BE12<0.01,"***",IF(Estimates!BE12<0.05,"**",IF(Estimates!BE12<0.1,"*","")))) -> -0.048 | D22: =TEXT(Estimates!BF12,"0.000")&IF(Estimates!BI12="","",IF(Estimates!BI12<0.01,"***",IF(Estimates!BI12<0.05,"**",IF(Estimates!BI12<0.1,"*","")))) -> -0.079 | E22: =TEXT(Estimates!BJ12,"0.000")&IF(Estimates!BM12="","",IF(Estimates!BM12<0.01,"***",IF(Estimates!BM12<0.05,"**",IF(Estimates!BM12<0.1,"*","")))) -> -0.052* | F22: =TEXT(Estimates!BN12,"0.000")&IF(Estimates!BQ12="","",IF(Estimates!BQ12<0.01,"***",IF(Estimates!BQ12<0.05,"**",IF(Estimates!BQ12<0.1,"*","")))) -> -0.056 | G22: =TEXT(Estimates!BR12,"0.000")&IF(Estimates!BU12="","",IF(Estimates!BU12<0.01,"***",IF(Estimates!BU12<0.05,"**",IF(Estimates!BU12<0.1,"*","")))) -> -0.003
B23: =IF(Estimates!AZ12="","(n/a)","("&TEXT(Estimates!AZ12,"0.00")&")") -> (-1.32) | C23: =IF(Estimates!BD12="","(n/a)","("&TEXT(Estimates!BD12,"0.00")&")") -> (-0.83) | D23: =IF(Estimates!BH12="","(n/a)","("&TEXT(Estimates!BH12,"0.00")&")") -> (-1.29) | E23: =IF(Estimates!BL12="","(n/a)","("&TEXT(Estimates!BL12,"0.00")&")") -> (-1.92) | F23: =IF(Estimates!BP12="","(n/a)","("&TEXT(Estimates!BP12,"0.00")&")") -> (-1.29) | G23: =IF(Estimates!BT12="","(n/a)","("&TEXT(Estimates!BT12,"0.00")&")") -> (-0.05)
A24: Misc. Alternatives Allocation (%) | B24: =TEXT(Estimates!AX13,"0.000")&IF(Estimates!BA13="","",IF(Estimates!BA13<0.01,"***",IF(Estimates!BA13<0.05,"**",IF(Estimates!BA13<0.1,"*","")))) -> -0.092 | C24: =TEXT(Estimates!BB13,"0.000")&IF(Estimates!BE13="","",IF(Estimates!BE13<0.01,"***",IF(Estimates!BE13<0.05,"**",IF(Estimates!BE13<0.1,"*","")))) -> -0.065 | D24: =TEXT(Estimates!BF13,"0.000")&IF(Estimates!BI13="","",IF(Estimates!BI13<0.01,"***",IF(Estimates!BI13<0.05,"**",IF(Estimates!BI13<0.1,"*","")))) -> -0.082 | E24: =TEXT(Estimates!BJ13,"0.000")&IF(Estimates!BM13="","",IF(Estimates!BM13<0.01,"***",IF(Estimates!BM13<0.05,"**",IF(Estimates!BM13<0.1,"*","")))) -> -0.089* | F24: =TEXT(Estimates!BN13,"0.000")&IF(Estimates!BQ13="","",IF(Estimates!BQ13<0.01,"***",IF(Estimates!BQ13<0.05,"**",IF(Estimates!BQ13<0.1,"*","")))) -> -0.105 | G24: =TEXT(Estimates!BR13,"0.000")&IF(Estimates!BU13="","",IF(Estimates!BU13<0.01,"***",IF(Estimates!BU13<0.05,"**",IF(Estimates!BU13<0.1,"*","")))) -> 0.005
B25: =IF(Estimates!AZ13="","(n/a)","("&TEXT(Estimates!AZ13,"0.00")&")") -> (-1.30) | C25: =IF(Estimates!BD13="","(n/a)","("&TEXT(Estimates!BD13,"0.00")&")") -> (-1.05) | D25: =IF(Estimates!BH13="","(n/a)","("&TEXT(Estimates!BH13,"0.00")&")") -> (-1.32) | E25: =IF(Estimates!BL13="","(n/a)","("&TEXT(Estimates!BL13,"0.00")&")") -> (-1.87) | F25: =IF(Estimates!BP13="","(n/a)","("&TEXT(Estimates!BP13,"0.00")&")") -> (-1.53) | G25: =IF(Estimates!BT13="","(n/a)","("&TEXT(Estimates!BT13,"0.00")&")") -> (0.05)
A26: Commodities Allocation (%) | B26: =TEXT(Estimates!AX14,"0.000")&IF(Estimates!BA14="","",IF(Estimates!BA14<0.01,"***",IF(Estimates!BA14<0.05,"**",IF(Estimates!BA14<0.1,"*","")))) -> -0.099 | C26: =TEXT(Estimates!BB14,"0.000")&IF(Estimates!BE14="","",IF(Estimates!BE14<0.01,"***",IF(Estimates!BE14<0.05,"**",IF(Estimates!BE14<0.1,"*","")))) -> -0.050 | D26: =TEXT(Estimates!BF14,"0.000")&IF(Estimates!BI14="","",IF(Estimates!BI14<0.01,"***",IF(Estimates!BI14<0.05,"**",IF(Estimates!BI14<0.1,"*","")))) -> -0.080 | E26: =TEXT(Estimates!BJ14,"0.000")&IF(Estimates!BM14="","",IF(Estimates!BM14<0.01,"***",IF(Estimates!BM14<0.05,"**",IF(Estimates!BM14<0.1,"*","")))) -> -0.096*** | F26: =TEXT(Estimates!BN14,"0.000")&IF(Estimates!BQ14="","",IF(Estimates!BQ14<0.01,"***",IF(Estimates!BQ14<0.05,"**",IF(Estimates!BQ14<0.1,"*","")))) -> -0.103 | G26: =TEXT(Estimates!BR14,"0.000")&IF(Estimates!BU14="","",IF(Estimates!BU14<0.01,"***",IF(Estimates!BU14<0.05,"**",IF(Estimates!BU14<0.1,"*","")))) -> -0.054
B27: =IF(Estimates!AZ14="","(n/a)","("&TEXT(Estimates!AZ14,"0.00")&")") -> (-1.38) | C27: =IF(Estimates!BD14="","(n/a)","("&TEXT(Estimates!BD14,"0.00")&")") -> (-0.78) | D27: =IF(Estimates!BH14="","(n/a)","("&TEXT(Estimates!BH14,"0.00")&")") -> (-1.26) | E27: =IF(Estimates!BL14="","(n/a)","("&TEXT(Estimates!BL14,"0.00")&")") -> (-3.00) | F27: =IF(Estimates!BP14="","(n/a)","("&TEXT(Estimates!BP14,"0.00")&")") -> (-1.57) | G27: =IF(Estimates!BT14="","(n/a)","("&TEXT(Estimates!BT14,"0.00")&")") -> (-0.73)
A28: Cash Allocation (%) | B28: =TEXT(Estimates!AX15,"0.000")&IF(Estimates!BA15="","",IF(Estimates!BA15<0.01,"***",IF(Estimates!BA15<0.05,"**",IF(Estimates!BA15<0.1,"*","")))) -> -0.068 | C28: =TEXT(Estimates!BB15,"0.000")&IF(Estimates!BE15="","",IF(Estimates!BE15<0.01,"***",IF(Estimates!BE15<0.05,"**",IF(Estimates!BE15<0.1,"*","")))) -> -0.029 | D28: =TEXT(Estimates!BF15,"0.000")&IF(Estimates!BI15="","",IF(Estimates!BI15<0.01,"***",IF(Estimates!BI15<0.05,"**",IF(Estimates!BI15<0.1,"*","")))) -> -0.086 | E28: =TEXT(Estimates!BJ15,"0.000")&IF(Estimates!BM15="","",IF(Estimates!BM15<0.01,"***",IF(Estimates!BM15<0.05,"**",IF(Estimates!BM15<0.1,"*","")))) -> -0.066** | F28: =TEXT(Estimates!BN15,"0.000")&IF(Estimates!BQ15="","",IF(Estimates!BQ15<0.01,"***",IF(Estimates!BQ15<0.05,"**",IF(Estimates!BQ15<0.1,"*","")))) -> -0.062 | G28: =TEXT(Estimates!BR15,"0.000")&IF(Estimates!BU15="","",IF(Estimates!BU15<0.01,"***",IF(Estimates!BU15<0.05,"**",IF(Estimates!BU15<0.1,"*","")))) -> 0.009
B29: =IF(Estimates!AZ15="","(n/a)","("&TEXT(Estimates!AZ15,"0.00")&")") -> (-0.97) | C29: =IF(Estimates!BD15="","(n/a)","("&TEXT(Estimates!BD15,"0.00")&")") -> (-0.46) | D29: =IF(Estimates!BH15="","(n/a)","("&TEXT(Estimates!BH15,"0.00")&")") -> (-1.43) | E29: =IF(Estimates!BL15="","(n/a)","("&TEXT(Estimates!BL15,"0.00")&")") -> (-2.18) | F29: =IF(Estimates!BP15="","(n/a)","("&TEXT(Estimates!BP15,"0.00")&")") -> (-1.36) | G29: =IF(Estimates!BT15="","(n/a)","("&TEXT(Estimates!BT15,"0.00")&")") -> (0.14)
A30: Financial Center (0/1) | B30: =TEXT(Estimates!AX16,"0.000")&IF(Estimates!BA16="","",IF(Estimates!BA16<0.01,"***",IF(Estimates!BA16<0.05,"**",IF(Estimates!BA16<0.1,"*","")))) -> 0.017 | C30: =TEXT(Estimates!BB16,"0.000")&IF(Estimates!BE16="","",IF(Estimates!BE16<0.01,"***",IF(Estimates!BE16<0.05,"**",IF(Estimates!BE16<0.1,"*","")))) -> 0.020
B31: =IF(Estimates!AZ16="","(n/a)","("&TEXT(Estimates!AZ16,"0.00")&")") -> (0.35) | C31: =IF(Estimates!BD16="","(n/a)","("&TEXT(Estimates!BD16,"0.00")&")") -> (0.40)
A32: Log (CIO Age) (t-1) | C32: =TEXT(Estimates!BB17,"0.000")&IF(Estimates!BE17="","",IF(Estimates!BE17<0.01,"***",IF(Estimates!BE17<0.05,"**",IF(Estimates!BE17<0.1,"*","")))) -> 0.038 | D32: =TEXT(Estimates!BF17,"0.000")&IF(Estimates!BI17="","",IF(Estimates!BI17<0.01,"***",IF(Estimates!BI17<0.05,"**",IF(Estimates!BI17<0.1,"*","")))) -> -0.205 | E32: =TEXT(Estimates!BJ17,"0.000")&IF(Estimates!BM17="","",IF(Estimates!BM17<0.01,"***",IF(Estimates!BM17<0.05,"**",IF(Estimates!BM17<0.1,"*","")))) -> -0.484**
C33: =IF(Estimates!BD17="","(n/a)","("&TEXT(Estimates!BD17,"0.00")&")") -> (0.17) | D33: =IF(Estimates!BH17="","(n/a)","("&TEXT(Estimates!BH17,"0.00")&")") -> (-1.06) | E33: =IF(Estimates!BL17="","(n/a)","("&TEXT(Estimates!BL17,"0.00")&")") -> (-2.36)
A34: Log (CIO Tenure) (t-1) | C34: =TEXT(Estimates!BB18,"0.000")&IF(Estimates!BE18="","",IF(Estimates!BE18<0.01,"***",IF(Estimates!BE18<0.05,"**",IF(Estimates!BE18<0.1,"*","")))) -> -0.001 | D34: =TEXT(Estimates!BF18,"0.000")&IF(Estimates!BI18="","",IF(Estimates!BI18<0.01,"***",IF(Estimates!BI18<0.05,"**",IF(Estimates!BI18<0.1,"*","")))) -> 0.007 | E34: =TEXT(Estimates!BJ18,"0.000")&IF(Estimates!BM18="","",IF(Estimates!BM18<0.01,"***",IF(Estimates!BM18<0.05,"**",IF(Estimates!BM18<0.1,"*","")))) -> 0.064*
C35: =IF(Estimates!BD18="","(n/a)","("&TEXT(Estimates!BD18,"0.00")&")") -> (-0.03) | D35: =IF(Estimates!BH18="","(n/a)","("&TEXT(Estimates!BH18,"0.00")&")") -> (0.29) | E35: =IF(Estimates!BL18="","(n/a)","("&TEXT(Estimates!BL18,"0.00")&")") -> (1.90)
A36: CIO Prior Private Experience (0/1) | C36: =TEXT(Estimates!BB19,"0.000")&IF(Estimates!BE19="","",IF(Estimates!BE19<0.01,"***",IF(Estimates!BE19<0.05,"**",IF(Estimates!BE19<0.1,"*","")))) -> -0.211*** | D36: =TEXT(Estimates!BF19,"0.000")&IF(Estimates!BI19="","",IF(Estimates!BI19<0.01,"***",IF(Estimates!BI19<0.05,"**",IF(Estimates!BI19<0.1,"*","")))) -> -0.202** | E36: =TEXT(Estimates!BJ19,"0.000")&IF(Estimates!BM19="","",IF(Estimates!BM19<0.01,"***",IF(Estimates!BM19<0.05,"**",IF(Estimates!BM19<0.1,"*","")))) -> -0.010
C37: =IF(Estimates!BD19="","(n/a)","("&TEXT(Estimates!BD19,"0.00")&")") -> (-3.77) | D37: =IF(Estimates!BH19="","(n/a)","("&TEXT(Estimates!BH19,"0.00")&")") -> (-2.30) | E37: =IF(Estimates!BL19="","(n/a)","("&TEXT(Estimates!BL19,"0.00")&")") -> (-0.13)
A38: CIO Attended Elite College (0/1) | C38: =TEXT(Estimates!BB20,"0.000")&IF(Estimates!BE20="","",IF(Estimates!BE20<0.01,"***",IF(Estimates!BE20<0.05,"**",IF(Estimates!BE20<0.1,"*","")))) -> -0.070 | D38: =TEXT(Estimates!BF20,"0.000")&IF(Estimates!BI20="","",IF(Estimates!BI20<0.01,"***",IF(Estimates!BI20<0.05,"**",IF(Estimates!BI20<0.1,"*","")))) -> -0.092 | E38: =TEXT(Estimates!BJ20,"0.000")&IF(Estimates!BM20="","",IF(Estimates!BM20<0.01,"***",IF(Estimates!BM20<0.05,"**",IF(Estimates!BM20<0.1,"*","")))) -> -0.115**
C39: =IF(Estimates!BD20="","(n/a)","("&TEXT(Estimates!BD20,"0.00")&")") -> (-1.28) | D39: =IF(Estimates!BH20="","(n/a)","("&TEXT(Estimates!BH20,"0.00")&")") -> (-1.59) | E39: =IF(Estimates!BL20="","(n/a)","("&TEXT(Estimates!BL20,"0.00")&")") -> (-2.17)
A40: Separate Investment Board (0/1) | C40: =TEXT(Estimates!BB21,"0.000")&IF(Estimates!BE21="","",IF(Estimates!BE21<0.01,"***",IF(Estimates!BE21<0.05,"**",IF(Estimates!BE21<0.1,"*","")))) -> 0.056
C41: =IF(Estimates!BD21="","(n/a)","("&TEXT(Estimates!BD21,"0.00")&")") -> (0.95)
A42: % Political Appointees on Board | C42: =TEXT(Estimates!BB22,"0.000")&IF(Estimates!BE22="","",IF(Estimates!BE22<0.01,"***",IF(Estimates!BE22<0.05,"**",IF(Estimates!BE22<0.1,"*","")))) -> -0.030 | D42: =TEXT(Estimates!BF22,"0.000")&IF(Estimates!BI22="","",IF(Estimates!BI22<0.01,"***",IF(Estimates!BI22<0.05,"**",IF(Estimates!BI22<0.1,"*","")))) -> 0.041 | E42: =TEXT(Estimates!BJ22,"0.000")&IF(Estimates!BM22="","",IF(Estimates!BM22<0.01,"***",IF(Estimates!BM22<0.05,"**",IF(Estimates!BM22<0.1,"*","")))) -> 1.130*
C43: =IF(Estimates!BD22="","(n/a)","("&TEXT(Estimates!BD22,"0.00")&")") -> (-0.38) | D43: =IF(Estimates!BH22="","(n/a)","("&TEXT(Estimates!BH22,"0.00")&")") -> (0.10) | E43: =IF(Estimates!BL22="","(n/a)","("&TEXT(Estimates!BL22,"0.00")&")") -> (1.84)
A45: Observations | B45: =Estimates!AX24 -> 273 | C45: =Estimates!BB24 -> 257 | D45: =Estimates!BF24 -> 255 | E45: =Estimates!BJ24 -> 255 | F45: =Estimates!BN24 -> 257 | G45: =Estimates!BR24 -> 169
A46: Adjusted R-squared | B46: =Estimates!AX27 -> 0.46952812 | C46: =Estimates!BB27 -> 0.5463401 | D46: =Estimates!BF27 -> 0.54739316 | E46: =Estimates!BJ27 -> 0.72204993 | F46: =Estimates!BN27 -> 0.78672007 | G46: =Estimates!BR27 -> 0.81611704
A47: Number of CIOs | B47: =Estimates!AX28 -> 40 | C47: =Estimates!BB28 -> 37 | D47: =Estimates!BF28 -> 37 | E47: =Estimates!BJ28 -> 37 | F47: =Estimates!BN28 -> 40 | G47: =Estimates!BR28 -> 20
A48: Plan FE | B48: No | C48: No | D48: Yes | E48: Yes | F48: No | G48: No
A49: Year FE | B49: Yes | C49: Yes | D49: No | E49: Yes | F49: Yes | G49: Yes
A50: CIO FE | B50: No | C50: No | D50: No | E50: No | F50: Yes | G50: Yes
A51: Min. Tenure at Departure (years) | G51: 4

Sheet Table XIII
A1: Table XIII: Conflicted CIOs: Univariate Comparison of the First and Second Half of Tenure (updated benchmark)
A2: This table compares the average outcomes of conflicted CIOs in the first and second half of their tenure with one observation per CIO. Plan-years are first averaged within CIO-year for CIOs who run several plans, then averaged within each half of tenure. Difference is the mean within-CIO change from the first to the second half; the t-statistic tests whether this mean change is zero, and the last column reports the p-value of a Wilcoxon signed-rank test of the same hypothesis. Coefficients marked with ***, **, and * are significant at the 1%, 5%, and 10% level, respectively.
B4: N (CIOs) | C4: First Half | D4: Second Half | E4: Difference | F4: t-stat | G4: % Improving | H4: Wilcoxon p-value | J4: SD of change | K4: t (helper) | L4: p (helper)
A5: Peer-Adjusted Return (%) | B5: 37 | C5: -0.49672251 | D5: -0.2354691 | E5: =TEXT(D5-C5,"0.000")&IF(L5<0.01,"***",IF(L5<0.05,"**",IF(L5<0.1,"*",""))) -> 0.261 | F5: =TEXT(K5,"0.00") -> 0.59 | G5: 0.62162162 | H5: 0.37772693 | J5: 2.6863822 | K5: =(D5-C5)/(J5/SQRT(B5)) -> 0.59155486 | L5: =TDIST(ABS(K5),B5-1,2) -> 0.55784542
A6: Benchmark-Adjusted Return (%) | B6: 30 | C6: 0.044924868 | D6: 0.18198519 | E6: =TEXT(D6-C6,"0.000")&IF(L6<0.01,"***",IF(L6<0.05,"**",IF(L6<0.1,"*",""))) -> 0.137 | F6: =TEXT(K6,"0.00") -> 0.29 | G6: 0.5 | H6: 1 | J6: 2.5905276 | K6: =(D6-C6)/(J6/SQRT(B6)) -> 0.28979049 | L6: =TDIST(ABS(K6),B6-1,2) -> 0.77403846
A7: Fee Ratio (%) | B7: 35 | C7: 0.29333454 | D7: 0.35688809 | E7: =TEXT(D7-C7,"0.000")&IF(L7<0.01,"***",IF(L7<0.05,"**",IF(L7<0.1,"*",""))) -> 0.064** | F7: =TEXT(K7,"0.00") -> 2.24 | G7: 0.65714286 | H7: 0.030007007 | J7: 0.16810236 | K7: =(D7-C7)/(J7/SQRT(B7)) -> 2.2366603 | L7: =TDIST(ABS(K7),B7-1,2) -> 0.031975505

Sheet Estimates-split
A1: Estimates behind the split tables (blue = regression output; t and p are formulas). Full Table III sample; SE double clustered by plan and year (PSD-corrected); p-values use the t distribution with min(plan clusters, year clusters) - 1 df.
A3: Variable | B3: S1A(1) coef | C3: S1A(1) se | D3: S1A(1) t | E3: S1A(1) p | F3: S1A(2) coef | G3: S1A(2) se | H3: S1A(2) t | I3: S1A(2) p | J3: S1A(3) coef | K3: S1A(3) se | L3: S1A(3) t | M3: S1A(3) p | N3: S1A(4) coef | O3: S1A(4) se | P3: S1A(4) t | Q3: S1A(4) p | R3: S1B(1) coef | S3: S1B(1) se | T3: S1B(1) t | U3: S1B(1) p | V3: S1B(2) coef | W3: S1B(2) se | X3: S1B(2) t | Y3: S1B(2) p | Z3: S1B(3) coef | AA3: S1B(3) se | AB3: S1B(3) t | AC3: S1B(3) p | AD3: S1B(4) coef | AE3: S1B(4) se | AF3: S1B(4) t | AG3: S1B(4) p | AH3: S2A(1) coef | AI3: S2A(1) se | AJ3: S2A(1) t | AK3: S2A(1) p | AL3: S2A(2) coef | AM3: S2A(2) se | AN3: S2A(2) t | AO3: S2A(2) p | AP3: S2A(3) coef | AQ3: S2A(3) se | AR3: S2A(3) t | AS3: S2A(3) p | AT3: S2A(4) coef | AU3: S2A(4) se | AV3: S2A(4) t | AW3: S2A(4) p
A4: Conflicted CIO x First Half of Tenure (0/1) | B4: -0.51025132 | C4: 0.17631601 | D4: =IF(C4>0,B4/C4,"") -> -2.8939591 | E4: =IF(C4>0,TDIST(ABS(D4),MIN(B27,B28)-1,2),"") -> 0.0096707204 | F4: -0.6047878 | G4: 0.2135415 | H4: =IF(G4>0,F4/G4,"") -> -2.8321793 | I4: =IF(G4>0,TDIST(ABS(H4),MIN(F27,F28)-1,2),"") -> 0.011047011 | J4: -0.77346757 | K4: 0.33729254 | L4: =IF(K4>0,J4/K4,"") -> -2.2931654 | M4: =IF(K4>0,TDIST(ABS(L4),MIN(J27,J28)-1,2),"") -> 0.034096301 | N4: -0.86086678 | O4: 0.35088691 | P4: =IF(O4>0,N4/O4,"") -> -2.4534023 | Q4: =IF(O4>0,TDIST(ABS(P4),MIN(N27,N28)-1,2),"") -> 0.024570119 | R4: -0.48615359 | S4: 0.19730765 | T4: =IF(S4>0,R4/S4,"") -> -2.4639369 | U4: =IF(S4>0,TDIST(ABS(T4),MIN(R27,R28)-1,2),"") -> 0.024040606 | V4: -0.61053083 | W4: 0.15847171 | X4: =IF(W4>0,V4/W4,"") -> -3.8526171 | Y4: =IF(W4>0,TDIST(ABS(X4),MIN(V27,V28)-1,2),"") -> 0.001166291 | Z4: -0.58382516 | AA4: 0.23251189 | AB4: =IF(AA4>0,Z4/AA4,"") -> -2.5109476 | AC4: =IF(AA4>0,TDIST(ABS(AB4),MIN(Z27,Z28)-1,2),"") -> 0.021805787 | AD4: -0.68434461 | AE4: 0.23927765 | AF4: =IF(AE4>0,AD4/AE4,"") -> -2.860044 | AG4: =IF(AE4>0,TDIST(ABS(AF4),MIN(AD27,AD28)-1,2),"") -> 0.010404366 | AH4: -0.044620674 | AI4: 0.034318194 | AJ4: =IF(AI4>0,AH4/AI4,"") -> -1.3002046 | AK4: =IF(AI4>0,TDIST(ABS(AJ4),MIN(AH27,AH28)-1,2),"") -> 0.20993379 | AL4: -0.02837968 | AM4: 0.045708992 | AN4: =IF(AM4>0,AL4/AM4,"") -> -0.62087741 | AO4: =IF(AM4>0,TDIST(ABS(AN4),MIN(AL27,AL28)-1,2),"") -> 0.5424631 | AP4: 0.038864146 | AQ4: 0.054359378 | AR4: =IF(AQ4>0,AP4/AQ4,"") -> 0.71494831 | AS4: =IF(AQ4>0,TDIST(ABS(AR4),MIN(AP27,AP28)-1,2),"") -> 0.48381159 | AT4: 0.036565047 | AU4: 0.05464667 | AV4: =IF(AU4>0,AT4/AU4,"") -> 0.66911756 | AW4: =IF(AU4>0,TDIST(ABS(AV4),MIN(AT27,AT28)-1,2),"") -> 0.51191208
A5: Conflicted CIO x Second Half of Tenure (0/1) | B5: -0.61527783 | C5: 0.20601068 | D5: =IF(C5>0,B5/C5,"") -> -2.9866307 | E5: =IF(C5>0,TDIST(ABS(D5),MIN(B27,B28)-1,2),"") -> 0.0079120298 | F5: -0.58119177 | G5: 0.21706904 | H5: =IF(G5>0,F5/G5,"") -> -2.6774513 | I5: =IF(G5>0,TDIST(ABS(H5),MIN(F27,F28)-1,2),"") -> 0.015369568 | J5: -0.55273538 | K5: 0.30036203 | L5: =IF(K5>0,J5/K5,"") -> -1.8402306 | M5: =IF(K5>0,TDIST(ABS(L5),MIN(J27,J28)-1,2),"") -> 0.082283308 | N5: -0.57856322 | O5: 0.29354915 | P5: =IF(O5>0,N5/O5,"") -> -1.9709245 | Q5: =IF(O5>0,TDIST(ABS(P5),MIN(N27,N28)-1,2),"") -> 0.064308278 | R5: -0.33026488 | S5: 0.21524752 | T5: =IF(S5>0,R5/S5,"") -> -1.5343493 | U5: =IF(S5>0,TDIST(ABS(T5),MIN(R27,R28)-1,2),"") -> 0.1423333 | V5: -0.42406468 | W5: 0.16112568 | X5: =IF(W5>0,V5/W5,"") -> -2.6318877 | Y5: =IF(W5>0,TDIST(ABS(X5),MIN(V27,V28)-1,2),"") -> 0.016923866 | Z5: -0.2266274 | AA5: 0.22168968 | AB5: =IF(AA5>0,Z5/AA5,"") -> -1.0222731 | AC5: =IF(AA5>0,TDIST(ABS(AB5),MIN(Z27,Z28)-1,2),"") -> 0.32019532 | AD5: -0.24798928 | AE5: 0.23057162 | AF5: =IF(AE5>0,AD5/AE5,"") -> -1.0755412 | AG5: =IF(AE5>0,TDIST(ABS(AF5),MIN(AD27,AD28)-1,2),"") -> 0.2963383 | AH5: -0.046707549 | AI5: 0.039872582 | AJ5: =IF(AI5>0,AH5/AI5,"") -> -1.1714202 | AK5: =IF(AI5>0,TDIST(ABS(AJ5),MIN(AH27,AH28)-1,2),"") -> 0.25670343 | AL5: -0.035185123 | AM5: 0.03890883 | AN5: =IF(AM5>0,AL5/AM5,"") -> -0.90429661 | AO5: =IF(AM5>0,TDIST(ABS(AN5),MIN(AL27,AL28)-1,2),"") -> 0.37778252 | AP5: 0.031099026 | AQ5: 0.058504576 | AR5: =IF(AQ5>0,AP5/AQ5,"") -> 0.53156569 | AS5: =IF(AQ5>0,TDIST(ABS(AR5),MIN(AP27,AP28)-1,2),"") -> 0.60152606 | AT5: 0.027893701 | AU5: 0.056293203 | AV5: =IF(AU5>0,AT5/AU5,"") -> 0.49550745 | AW5: =IF(AU5>0,TDIST(ABS(AV5),MIN(AT27,AT28)-1,2),"") -> 0.62623704
A6: Investment Return (t - 1) | B6: 0.013889989 | C6: 0.021445634 | D6: =IF(C6>0,B6/C6,"") -> 0.64768378 | E6: =IF(C6>0,TDIST(ABS(D6),MIN(B27,B28)-1,2),"") -> 0.52536518 | F6: 0.0041384728 | G6: 0.020675258 | H6: =IF(G6>0,F6/G6,"") -> 0.20016547 | I6: =IF(G6>0,TDIST(ABS(H6),MIN(F27,F28)-1,2),"") -> 0.84359527 | J6: 0.010690678 | K6: 0.0089652928 | L6: =IF(K6>0,J6/K6,"") -> 1.1924517 | M6: =IF(K6>0,TDIST(ABS(L6),MIN(J27,J28)-1,2),"") -> 0.24856761 | N6: 0.00022269744 | O6: 0.016456384 | P6: =IF(O6>0,N6/O6,"") -> 0.013532586 | Q6: =IF(O6>0,TDIST(ABS(P6),MIN(N27,N28)-1,2),"") -> 0.98935175 | R6: -0.003148108 | S6: 0.016640169 | T6: =IF(S6>0,R6/S6,"") -> -0.18918726 | U6: =IF(S6>0,TDIST(ABS(T6),MIN(R27,R28)-1,2),"") -> 0.85206292 | V6: -0.012243747 | W6: 0.020468222 | X6: =IF(W6>0,V6/W6,"") -> -0.59818324 | Y6: =IF(W6>0,TDIST(ABS(X6),MIN(V27,V28)-1,2),"") -> 0.55717026 | Z6: 0.0062503948 | AA6: 0.018515891 | AB6: =IF(AA6>0,Z6/AA6,"") -> 0.33756921 | AC6: =IF(AA6>0,TDIST(ABS(AB6),MIN(Z27,Z28)-1,2),"") -> 0.73959258 | AD6: -0.017024454 | AE6: 0.016408912 | AF6: =IF(AE6>0,AD6/AE6,"") -> -1.0375127 | AG6: =IF(AE6>0,TDIST(ABS(AF6),MIN(AD27,AD28)-1,2),"") -> 0.31323453 | AH6: -0.00025334338 | AI6: 0.00063577385 | AJ6: =IF(AI6>0,AH6/AI6,"") -> -0.39848034 | AK6: =IF(AI6>0,TDIST(ABS(AJ6),MIN(AH27,AH28)-1,2),"") -> 0.69496329 | AL6: -0.00046527308 | AM6: 0.00083722051 | AN6: =IF(AM6>0,AL6/AM6,"") -> -0.55573541 | AO6: =IF(AM6>0,TDIST(ABS(AN6),MIN(AL27,AL28)-1,2),"") -> 0.58523381 | AP6: -0.00080790848 | AQ6: 0.00067533922 | AR6: =IF(AQ6>0,AP6/AQ6,"") -> -1.1963003 | AS6: =IF(AQ6>0,TDIST(ABS(AR6),MIN(AP27,AP28)-1,2),"") -> 0.24710022 | AT6: -0.0012110495 | AU6: 0.00050705174 | AV6: =IF(AU6>0,AT6/AU6,"") -> -2.388414 | AW6: =IF(AU6>0,TDIST(ABS(AV6),MIN(AT27,AT28)-1,2),"") -> 0.028086382
A7: Log (Plan Size) (t-1) | B7: 0.0071309288 | C7: 0.055956136 | D7: =IF(C7>0,B7/C7,"") -> 0.12743783 | E7: =IF(C7>0,TDIST(ABS(D7),MIN(B27,B28)-1,2),"") -> 0.90000677 | F7: 0.067798328 | G7: 0.065128963 | H7: =IF(G7>0,F7/G7,"") -> 1.0409858 | I7: =IF(G7>0,TDIST(ABS(H7),MIN(F27,F28)-1,2),"") -> 0.31166337 | J7: -0.9446113 | K7: 0.38138231 | L7: =IF(K7>0,J7/K7,"") -> -2.4768094 | M7: =IF(K7>0,TDIST(ABS(L7),MIN(J27,J28)-1,2),"") -> 0.02340813 | N7: -1.417701 | O7: 0.72580436 | P7: =IF(O7>0,N7/O7,"") -> -1.9532825 | Q7: =IF(O7>0,TDIST(ABS(P7),MIN(N27,N28)-1,2),"") -> 0.066510191 | R7: -0.050361658 | S7: 0.039422899 | T7: =IF(S7>0,R7/S7,"") -> -1.2774722 | U7: =IF(S7>0,TDIST(ABS(T7),MIN(R27,R28)-1,2),"") -> 0.21766731 | V7: -0.0022758288 | W7: 0.047927611 | X7: =IF(W7>0,V7/W7,"") -> -0.047484713 | Y7: =IF(W7>0,TDIST(ABS(X7),MIN(V27,V28)-1,2),"") -> 0.96264981 | Z7: -1.1421316 | AA7: 0.62669187 | AB7: =IF(AA7>0,Z7/AA7,"") -> -1.8224772 | AC7: =IF(AA7>0,TDIST(ABS(AB7),MIN(Z27,Z28)-1,2),"") -> 0.085039232 | AD7: -0.2421691 | AE7: 0.71804139 | AF7: =IF(AE7>0,AD7/AE7,"") -> -0.33726343 | AG7: =IF(AE7>0,TDIST(ABS(AF7),MIN(AD27,AD28)-1,2),"") -> 0.73981921 | AH7: -0.022274763 | AI7: 0.013720352 | AJ7: =IF(AI7>0,AH7/AI7,"") -> -1.6234834 | AK7: =IF(AI7>0,TDIST(ABS(AJ7),MIN(AH27,AH28)-1,2),"") -> 0.12186871 | AL7: -0.019319237 | AM7: 0.014622707 | AN7: =IF(AM7>0,AL7/AM7,"") -> -1.3211806 | AO7: =IF(AM7>0,TDIST(ABS(AN7),MIN(AL27,AL28)-1,2),"") -> 0.20299074 | AP7: 0.0077898096 | AQ7: 0.049866785 | AR7: =IF(AQ7>0,AP7/AQ7,"") -> 0.15621239 | AS7: =IF(AQ7>0,TDIST(ABS(AR7),MIN(AP27,AP28)-1,2),"") -> 0.87760426 | AT7: 0.042342005 | AU7: 0.10303649 | AV7: =IF(AU7>0,AT7/AU7,"") -> 0.41094182 | AW7: =IF(AU7>0,TDIST(ABS(AV7),MIN(AT27,AT28)-1,2),"") -> 0.68596613
A8: Funding Ratio (t-1) | B8: -0.0052366866 | C8: 0.0044739612 | D8: =IF(C8>0,B8/C8,"") -> -1.170481 | E8: =IF(C8>0,TDIST(ABS(D8),MIN(B27,B28)-1,2),"") -> 0.25707138 | F8: -0.0057719033 | G8: 0.0048209584 | H8: =IF(G8>0,F8/G8,"") -> -1.1972523 | I8: =IF(G8>0,TDIST(ABS(H8),MIN(F27,F28)-1,2),"") -> 0.24673826 | J8: -0.0270861 | K8: 0.0085192346 | L8: =IF(K8>0,J8/K8,"") -> -3.1794054 | M8: =IF(K8>0,TDIST(ABS(L8),MIN(J27,J28)-1,2),"") -> 0.0051922092 | N8: -0.03039125 | O8: 0.010301072 | P8: =IF(O8>0,N8/O8,"") -> -2.9502996 | Q8: =IF(O8>0,TDIST(ABS(P8),MIN(N27,N28)-1,2),"") -> 0.0085610886 | R8: 0.0032835699 | S8: 0.0053019544 | T8: =IF(S8>0,R8/S8,"") -> 0.61931311 | U8: =IF(S8>0,TDIST(ABS(T8),MIN(R27,R28)-1,2),"") -> 0.54347008 | V8: 0.0035029024 | W8: 0.0048760154 | X8: =IF(W8>0,V8/W8,"") -> 0.71839444 | Y8: =IF(W8>0,TDIST(ABS(X8),MIN(V27,V28)-1,2),"") -> 0.48173589 | Z8: -0.020302422 | AA8: 0.013076476 | AB8: =IF(AA8>0,Z8/AA8,"") -> -1.5525912 | AC8: =IF(AA8>0,TDIST(ABS(AB8),MIN(Z27,Z28)-1,2),"") -> 0.137926 | AD8: -0.017078367 | AE8: 0.011500248 | AF8: =IF(AE8>0,AD8/AE8,"") -> -1.4850434 | AG8: =IF(AE8>0,TDIST(ABS(AF8),MIN(AD27,AD28)-1,2),"") -> 0.15483519 | AH8: -0.00082022219 | AI8: 0.00087033404 | AJ8: =IF(AI8>0,AH8/AI8,"") -> -0.94242227 | AK8: =IF(AI8>0,TDIST(ABS(AJ8),MIN(AH27,AH28)-1,2),"") -> 0.35845435 | AL8: -0.0010702996 | AM8: 0.00090594765 | AN8: =IF(AM8>0,AL8/AM8,"") -> -1.1814144 | AO8: =IF(AM8>0,TDIST(ABS(AN8),MIN(AL27,AL28)-1,2),"") -> 0.25281256 | AP8: -0.0012437693 | AQ8: 0.001087881 | AR8: =IF(AQ8>0,AP8/AQ8,"") -> -1.1432953 | AS8: =IF(AQ8>0,TDIST(ABS(AR8),MIN(AP27,AP28)-1,2),"") -> 0.26789451 | AT8: -0.0023546248 | AU8: 0.00098800305 | AV8: =IF(AU8>0,AT8/AU8,"") -> -2.3832161 | AW8: =IF(AU8>0,TDIST(ABS(AV8),MIN(AT27,AT28)-1,2),"") -> 0.028387056
A9: Equity Allocation (%) | B9: -0.082286602 | C9: 0.13437846 | D9: =IF(C9>0,B9/C9,"") -> -0.61234965 | E9: =IF(C9>0,TDIST(ABS(D9),MIN(B27,B28)-1,2),"") -> 0.54796489 | F9: 0.0046531107 | G9: 0.064876351 | H9: =IF(G9>0,F9/G9,"") -> 0.071722757 | I9: =IF(G9>0,TDIST(ABS(H9),MIN(F27,F28)-1,2),"") -> 0.94361347 | J9: -0.048326903 | K9: 0.082808225 | L9: =IF(K9>0,J9/K9,"") -> -0.58360027 | M9: =IF(K9>0,TDIST(ABS(L9),MIN(J27,J28)-1,2),"") -> 0.566731 | N9: -0.028865402 | O9: 0.086040598 | P9: =IF(O9>0,N9/O9,"") -> -0.33548583 | Q9: =IF(O9>0,TDIST(ABS(P9),MIN(N27,N28)-1,2),"") -> 0.74113713 | R9: -0.17100283 | S9: 0.13211907 | T9: =IF(S9>0,R9/S9,"") -> -1.2943084 | U9: =IF(S9>0,TDIST(ABS(T9),MIN(R27,R28)-1,2),"") -> 0.21191865 | V9: -0.010313801 | W9: 0.11984066 | X9: =IF(W9>0,V9/W9,"") -> -0.086062619 | Y9: =IF(W9>0,TDIST(ABS(X9),MIN(V27,V28)-1,2),"") -> 0.93236674 | Z9: -0.0024396749 | AA9: 0.17183159 | AB9: =IF(AA9>0,Z9/AA9,"") -> -0.014198058 | AC9: =IF(AA9>0,TDIST(ABS(AB9),MIN(Z27,Z28)-1,2),"") -> 0.98882816 | AD9: 0.019929336 | AE9: 0.17184376 | AF9: =IF(AE9>0,AD9/AE9,"") -> 0.11597357 | AG9: =IF(AE9>0,TDIST(ABS(AF9),MIN(AD27,AD28)-1,2),"") -> 0.90895756 | AH9: -0.039361117 | AI9: 0.035202052 | AJ9: =IF(AI9>0,AH9/AI9,"") -> -1.1181484 | AK9: =IF(AI9>0,TDIST(ABS(AJ9),MIN(AH27,AH28)-1,2),"") -> 0.27820519 | AL9: -0.082416251 | AM9: 0.069231728 | AN9: =IF(AM9>0,AL9/AM9,"") -> -1.1904405 | AO9: =IF(AM9>0,TDIST(ABS(AN9),MIN(AL27,AL28)-1,2),"") -> 0.24933707 | AP9: -0.08518039 | AQ9: 0.059262623 | AR9: =IF(AQ9>0,AP9/AQ9,"") -> -1.4373375 | AS9: =IF(AQ9>0,TDIST(ABS(AR9),MIN(AP27,AP28)-1,2),"") -> 0.16777905 | AT9: -0.085981747 | AU9: 0.055452755 | AV9: =IF(AU9>0,AT9/AU9,"") -> -1.5505406 | AW9: =IF(AU9>0,TDIST(ABS(AV9),MIN(AT27,AT28)-1,2),"") -> 0.13841568
A10: Fixed Income Allocation (%) | B10: -0.090925069 | C10: 0.1440639 | D10: =IF(C10>0,B10/C10,"") -> -0.63114402 | E10: =IF(C10>0,TDIST(ABS(D10),MIN(B27,B28)-1,2),"") -> 0.53587931 | F10: 0.00011712826 | G10: 0.078759868 | H10: =IF(G10>0,F10/G10,"") -> 0.0014871566 | I10: =IF(G10>0,TDIST(ABS(H10),MIN(F27,F28)-1,2),"") -> 0.99882978 | J10: -0.058788706 | K10: 0.095832135 | L10: =IF(K10>0,J10/K10,"") -> -0.61345504 | M10: =IF(K10>0,TDIST(ABS(L10),MIN(J27,J28)-1,2),"") -> 0.54725005 | N10: -0.035065367 | O10: 0.096834535 | P10: =IF(O10>0,N10/O10,"") -> -0.36211634 | Q10: =IF(O10>0,TDIST(ABS(P10),MIN(N27,N28)-1,2),"") -> 0.72148152 | R10: -0.15916302 | S10: 0.13291933 | T10: =IF(S10>0,R10/S10,"") -> -1.1974408 | U10: =IF(S10>0,TDIST(ABS(T10),MIN(R27,R28)-1,2),"") -> 0.24666663 | V10: -0.0061396503 | W10: 0.12502455 | X10: =IF(W10>0,V10/W10,"") -> -0.049107557 | Y10: =IF(W10>0,TDIST(ABS(X10),MIN(V27,V28)-1,2),"") -> 0.96137439 | Z10: -0.018997507 | AA10: 0.17635913 | AB10: =IF(AA10>0,Z10/AA10,"") -> -0.10772058 | AC10: =IF(AA10>0,TDIST(ABS(AB10),MIN(Z27,Z28)-1,2),"") -> 0.91540898 | AD10: 0.017683477 | AE10: 0.17870562 | AF10: =IF(AE10>0,AD10/AE10,"") -> 0.098953113 | AG10: =IF(AE10>0,TDIST(ABS(AF10),MIN(AD27,AD28)-1,2),"") -> 0.92226918 | AH10: -0.043431169 | AI10: 0.035360474 | AJ10: =IF(AI10>0,AH10/AI10,"") -> -1.2282406 | AK10: =IF(AI10>0,TDIST(ABS(AJ10),MIN(AH27,AH28)-1,2),"") -> 0.23517523 | AL10: -0.086545414 | AM10: 0.069192604 | AN10: =IF(AM10>0,AL10/AM10,"") -> -1.2507899 | AO10: =IF(AM10>0,TDIST(ABS(AN10),MIN(AL27,AL28)-1,2),"") -> 0.22702598 | AP10: -0.090287175 | AQ10: 0.059351459 | AR10: =IF(AQ10>0,AP10/AQ10,"") -> -1.5212293 | AS10: =IF(AQ10>0,TDIST(ABS(AR10),MIN(AP27,AP28)-1,2),"") -> 0.14557517 | AT10: -0.091305655 | AU10: 0.055632 | AV10: =IF(AU10>0,AT10/AU10,"") -> -1.6412434 | AW10: =IF(AU10>0,TDIST(ABS(AV10),MIN(AT27,AT28)-1,2),"") -> 0.11810345
A11: Real Estate Allocation (%) | B11: -0.061891133 | C11: 0.13365074 | D11: =IF(C11>0,B11/C11,"") -> -0.46308112 | E11: =IF(C11>0,TDIST(ABS(D11),MIN(B27,B28)-1,2),"") -> 0.64885599 | F11: 0.026261569 | G11: 0.060707408 | H11: =IF(G11>0,F11/G11,"") -> 0.4325925 | I11: =IF(G11>0,TDIST(ABS(H11),MIN(F27,F28)-1,2),"") -> 0.67044933 | J11: -0.090777669 | K11: 0.07995813 | L11: =IF(K11>0,J11/K11,"") -> -1.1353151 | M11: =IF(K11>0,TDIST(ABS(L11),MIN(J27,J28)-1,2),"") -> 0.27113528 | N11: -0.078606452 | O11: 0.087121225 | P11: =IF(O11>0,N11/O11,"") -> -0.90226523 | Q11: =IF(O11>0,TDIST(ABS(P11),MIN(N27,N28)-1,2),"") -> 0.37883158 | R11: -0.18436024 | S11: 0.12330925 | T11: =IF(S11>0,R11/S11,"") -> -1.4951046 | U11: =IF(S11>0,TDIST(ABS(T11),MIN(R27,R28)-1,2),"") -> 0.15221298 | V11: -0.013602577 | W11: 0.1076549 | X11: =IF(W11>0,V11/W11,"") -> -0.12635354 | Y11: =IF(W11>0,TDIST(ABS(X11),MIN(V27,V28)-1,2),"") -> 0.90085277 | Z11: -0.048770719 | AA11: 0.17475848 | AB11: =IF(AA11>0,Z11/AA11,"") -> -0.27907498 | AC11: =IF(AA11>0,TDIST(ABS(AB11),MIN(Z27,Z28)-1,2),"") -> 0.78336842 | AD11: -0.01825433 | AE11: 0.16888016 | AF11: =IF(AE11>0,AD11/AE11,"") -> -0.10809044 | AG11: =IF(AE11>0,TDIST(ABS(AF11),MIN(AD27,AD28)-1,2),"") -> 0.91511972 | AH11: -0.032436247 | AI11: 0.036035744 | AJ11: =IF(AI11>0,AH11/AI11,"") -> -0.90011316 | AK11: =IF(AI11>0,TDIST(ABS(AJ11),MIN(AH27,AH28)-1,2),"") -> 0.37994509 | AL11: -0.074937079 | AM11: 0.069280059 | AN11: =IF(AM11>0,AL11/AM11,"") -> -1.0816544 | AO11: =IF(AM11>0,TDIST(ABS(AN11),MIN(AL27,AL28)-1,2),"") -> 0.29368501 | AP11: -0.084868289 | AQ11: 0.058356016 | AR11: =IF(AQ11>0,AP11/AQ11,"") -> -1.4543194 | AS11: =IF(AQ11>0,TDIST(ABS(AR11),MIN(AP27,AP28)-1,2),"") -> 0.16307363 | AT11: -0.086994032 | AU11: 0.054718757 | AV11: =IF(AU11>0,AT11/AU11,"") -> -1.5898393 | AW11: =IF(AU11>0,TDIST(ABS(AV11),MIN(AT27,AT28)-1,2),"") -> 0.12928071
A12: Private Equity Allocation (%) | B12: -0.072716344 | C12: 0.14282976 | D12: =IF(C12>0,B12/C12,"") -> -0.509112 | E12: =IF(C12>0,TDIST(ABS(D12),MIN(B27,B28)-1,2),"") -> 0.61685793 | F12: 0.025051815 | G12: 0.065017539 | H12: =IF(G12>0,F12/G12,"") -> 0.38530857 | I12: =IF(G12>0,TDIST(ABS(H12),MIN(F27,F28)-1,2),"") -> 0.7045242 | J12: -0.042350774 | K12: 0.090568755 | L12: =IF(K12>0,J12/K12,"") -> -0.4676091 | M12: =IF(K12>0,TDIST(ABS(L12),MIN(J27,J28)-1,2),"") -> 0.64567563 | N12: 0.010930896 | O12: 0.094123263 | P12: =IF(O12>0,N12/O12,"") -> 0.11613384 | Q12: =IF(O12>0,TDIST(ABS(P12),MIN(N27,N28)-1,2),"") -> 0.90883234 | R12: -0.15767129 | S12: 0.13070689 | T12: =IF(S12>0,R12/S12,"") -> -1.2062967 | U12: =IF(S12>0,TDIST(ABS(T12),MIN(R27,R28)-1,2),"") -> 0.24331955 | V12: 0.0039913155 | W12: 0.11476597 | X12: =IF(W12>0,V12/W12,"") -> 0.034777866 | Y12: =IF(W12>0,TDIST(ABS(X12),MIN(V27,V28)-1,2),"") -> 0.97263964 | Z12: -0.021373058 | AA12: 0.16870616 | AB12: =IF(AA12>0,Z12/AA12,"") -> -0.12668807 | AC12: =IF(AA12>0,TDIST(ABS(AB12),MIN(Z27,Z28)-1,2),"") -> 0.90059175 | AD12: 0.029712608 | AE12: 0.1740243 | AF12: =IF(AE12>0,AD12/AE12,"") -> 0.17073827 | AG12: =IF(AE12>0,TDIST(ABS(AF12),MIN(AD27,AD28)-1,2),"") -> 0.86633413 | AH12: -0.034079724 | AI12: 0.034883877 | AJ12: =IF(AI12>0,AH12/AI12,"") -> -0.97694773 | AK12: =IF(AI12>0,TDIST(ABS(AJ12),MIN(AH27,AH28)-1,2),"") -> 0.34154323 | AL12: -0.076506722 | AM12: 0.06893126 | AN12: =IF(AM12>0,AL12/AM12,"") -> -1.1098988 | AO12: =IF(AM12>0,TDIST(ABS(AN12),MIN(AL27,AL28)-1,2),"") -> 0.28165075 | AP12: -0.067217544 | AQ12: 0.059672057 | AR12: =IF(AQ12>0,AP12/AQ12,"") -> -1.1264493 | AS12: =IF(AQ12>0,TDIST(ABS(AR12),MIN(AP27,AP28)-1,2),"") -> 0.27476973 | AT12: -0.064659902 | AU12: 0.05590979 | AV12: =IF(AU12>0,AT12/AU12,"") -> -1.1565041 | AW12: =IF(AU12>0,TDIST(ABS(AV12),MIN(AT27,AT28)-1,2),"") -> 0.26259407
A13: Hedge Fund Allocation (%) | B13: -0.12929756 | C13: 0.13420023 | D13: =IF(C13>0,B13/C13,"") -> -0.96346747 | E13: =IF(C13>0,TDIST(ABS(D13),MIN(B27,B28)-1,2),"") -> 0.34807913 | F13: -0.038702827 | G13: 0.065575749 | H13: =IF(G13>0,F13/G13,"") -> -0.59020031 | I13: =IF(G13>0,TDIST(ABS(H13),MIN(F27,F28)-1,2),"") -> 0.56239338 | J13: -0.096852072 | K13: 0.076048359 | L13: =IF(K13>0,J13/K13,"") -> -1.273559 | M13: =IF(K13>0,TDIST(ABS(L13),MIN(J27,J28)-1,2),"") -> 0.21902073 | N13: -0.082713805 | O13: 0.07406113 | P13: =IF(O13>0,N13/O13,"") -> -1.1168315 | Q13: =IF(O13>0,TDIST(ABS(P13),MIN(N27,N28)-1,2),"") -> 0.27875309 | R13: -0.16141361 | S13: 0.12738665 | T13: =IF(S13>0,R13/S13,"") -> -1.2671156 | U13: =IF(S13>0,TDIST(ABS(T13),MIN(R27,R28)-1,2),"") -> 0.22126353 | V13: -0.0031076386 | W13: 0.11880598 | X13: =IF(W13>0,V13/W13,"") -> -0.026157256 | Y13: =IF(W13>0,TDIST(ABS(X13),MIN(V27,V28)-1,2),"") -> 0.97941972 | Z13: -0.0068532111 | AA13: 0.18077069 | AB13: =IF(AA13>0,Z13/AA13,"") -> -0.037911075 | AC13: =IF(AA13>0,TDIST(ABS(AB13),MIN(Z27,Z28)-1,2),"") -> 0.97017588 | AD13: 0.011879483 | AE13: 0.1704588 | AF13: =IF(AE13>0,AD13/AE13,"") -> 0.069691228 | AG13: =IF(AE13>0,TDIST(ABS(AF13),MIN(AD27,AD28)-1,2),"") -> 0.94520783 | AH13: -0.021807451 | AI13: 0.035167535 | AJ13: =IF(AI13>0,AH13/AI13,"") -> -0.62010178 | AK13: =IF(AI13>0,TDIST(ABS(AJ13),MIN(AH27,AH28)-1,2),"") -> 0.54296227 | AL13: -0.064481839 | AM13: 0.0701919 | AN13: =IF(AM13>0,AL13/AM13,"") -> -0.91865071 | AO13: =IF(AM13>0,TDIST(ABS(AN13),MIN(AL27,AL28)-1,2),"") -> 0.3704251 | AP13: -0.068596924 | AQ13: 0.058754625 | AR13: =IF(AQ13>0,AP13/AQ13,"") -> -1.1675153 | AS13: =IF(AQ13>0,TDIST(ABS(AR13),MIN(AP27,AP28)-1,2),"") -> 0.25823586 | AT13: -0.069015544 | AU13: 0.055018451 | AV13: =IF(AU13>0,AT13/AU13,"") -> -1.2544073 | AW13: =IF(AU13>0,TDIST(ABS(AV13),MIN(AT27,AT28)-1,2),"") -> 0.22573926
A14: Misc. Alternatives Allocation (%) | B14: -0.096303639 | C14: 0.14039822 | D14: =IF(C14>0,B14/C14,"") -> -0.68593204 | E14: =IF(C14>0,TDIST(ABS(D14),MIN(B27,B28)-1,2),"") -> 0.50149624 | F14: -0.0096522556 | G14: 0.061478152 | H14: =IF(G14>0,F14/G14,"") -> -0.15700302 | I14: =IF(G14>0,TDIST(ABS(H14),MIN(F27,F28)-1,2),"") -> 0.87699012 | J14: -0.11490407 | K14: 0.085471862 | L14: =IF(K14>0,J14/K14,"") -> -1.3443497 | M14: =IF(K14>0,TDIST(ABS(L14),MIN(J27,J28)-1,2),"") -> 0.19553404 | N14: -0.07582374 | O14: 0.08625355 | P14: =IF(O14>0,N14/O14,"") -> -0.87907965 | Q14: =IF(O14>0,TDIST(ABS(P14),MIN(N27,N28)-1,2),"") -> 0.39094282 | R14: -0.17865802 | S14: 0.12460079 | T14: =IF(S14>0,R14/S14,"") -> -1.4338435 | U14: =IF(S14>0,TDIST(ABS(T14),MIN(R27,R28)-1,2),"") -> 0.16876078 | V14: -0.011492747 | W14: 0.11592401 | X14: =IF(W14>0,V14/W14,"") -> -0.099140351 | Y14: =IF(W14>0,TDIST(ABS(X14),MIN(V27,V28)-1,2),"") -> 0.9221226 | Z14: -0.023620011 | AA14: 0.17882034 | AB14: =IF(AA14>0,Z14/AA14,"") -> -0.13208794 | AC14: =IF(AA14>0,TDIST(ABS(AB14),MIN(Z27,Z28)-1,2),"") -> 0.89638003 | AD14: 0.033775635 | AE14: 0.18073299 | AF14: =IF(AE14>0,AD14/AE14,"") -> 0.1868814 | AG14: =IF(AE14>0,TDIST(ABS(AF14),MIN(AD27,AD28)-1,2),"") -> 0.85384385 | AH14: -0.033957851 | AI14: 0.034408725 | AJ14: =IF(AI14>0,AH14/AI14,"") -> -0.98689655 | AK14: =IF(AI14>0,TDIST(ABS(AJ14),MIN(AH27,AH28)-1,2),"") -> 0.33677454 | AL14: -0.074769695 | AM14: 0.068246664 | AN14: =IF(AM14>0,AL14/AM14,"") -> -1.0955802 | AO14: =IF(AM14>0,TDIST(ABS(AN14),MIN(AL27,AL28)-1,2),"") -> 0.28770548 | AP14: -0.074345683 | AQ14: 0.05884401 | AR14: =IF(AQ14>0,AP14/AQ14,"") -> -1.2634367 | AS14: =IF(AQ14>0,TDIST(ABS(AR14),MIN(AP27,AP28)-1,2),"") -> 0.22255203 | AT14: -0.073188888 | AU14: 0.055149306 | AV14: =IF(AU14>0,AT14/AU14,"") -> -1.3271044 | AW14: =IF(AU14>0,TDIST(ABS(AV14),MIN(AT27,AT28)-1,2),"") -> 0.20106316
A15: Commodities Allocation (%) | B15: -0.1433442 | C15: 0.13893591 | D15: =IF(C15>0,B15/C15,"") -> -1.0317289 | E15: =IF(C15>0,TDIST(ABS(D15),MIN(B27,B28)-1,2),"") -> 0.3158635 | F15: -0.046958739 | G15: 0.06091266 | H15: =IF(G15>0,F15/G15,"") -> -0.7709192 | I15: =IF(G15>0,TDIST(ABS(H15),MIN(F27,F28)-1,2),"") -> 0.45075641 | J15: -0.13899506 | K15: 0.095340844 | L15: =IF(K15>0,J15/K15,"") -> -1.4578752 | M15: =IF(K15>0,TDIST(ABS(L15),MIN(J27,J28)-1,2),"") -> 0.16210217 | N15: -0.12340499 | O15: 0.098337921 | P15: =IF(O15>0,N15/O15,"") -> -1.2549074 | Q15: =IF(O15>0,TDIST(ABS(P15),MIN(N27,N28)-1,2),"") -> 0.22556178 | R15: -0.19781249 | S15: 0.13572738 | T15: =IF(S15>0,R15/S15,"") -> -1.4574252 | U15: =IF(S15>0,TDIST(ABS(T15),MIN(R27,R28)-1,2),"") -> 0.16222486 | V15: -0.021385507 | W15: 0.1184658 | X15: =IF(W15>0,V15/W15,"") -> -0.18052051 | Y15: =IF(W15>0,TDIST(ABS(X15),MIN(V27,V28)-1,2),"") -> 0.85876086 | Z15: -0.032445921 | AA15: 0.18482315 | AB15: =IF(AA15>0,Z15/AA15,"") -> -0.17555118 | AC15: =IF(AA15>0,TDIST(ABS(AB15),MIN(Z27,Z28)-1,2),"") -> 0.86260633 | AD15: 0.0033396544 | AE15: 0.17318826 | AF15: =IF(AE15>0,AD15/AE15,"") -> 0.019283377 | AG15: =IF(AE15>0,TDIST(ABS(AF15),MIN(AD27,AD28)-1,2),"") -> 0.98482719 | AH15: -0.032079189 | AI15: 0.035410813 | AJ15: =IF(AI15>0,AH15/AI15,"") -> -0.90591507 | AK15: =IF(AI15>0,TDIST(ABS(AJ15),MIN(AH27,AH28)-1,2),"") -> 0.3769481 | AL15: -0.072878799 | AM15: 0.067887186 | AN15: =IF(AM15>0,AL15/AM15,"") -> -1.073528 | AO15: =IF(AM15>0,TDIST(ABS(AN15),MIN(AL27,AL28)-1,2),"") -> 0.29721585 | AP15: -0.081669982 | AQ15: 0.057888325 | AR15: =IF(AQ15>0,AP15/AQ15,"") -> -1.4108196 | AS15: =IF(AQ15>0,TDIST(ABS(AR15),MIN(AP27,AP28)-1,2),"") -> 0.17534731 | AT15: -0.082552744 | AU15: 0.054167042 | AV15: =IF(AU15>0,AT15/AU15,"") -> -1.5240401 | AW15: =IF(AU15>0,TDIST(ABS(AV15),MIN(AT27,AT28)-1,2),"") -> 0.14487551
A16: Cash Allocation (%) | B16: -0.10151423 | C16: 0.14736609 | D16: =IF(C16>0,B16/C16,"") -> -0.68885748 | E16: =IF(C16>0,TDIST(ABS(D16),MIN(B27,B28)-1,2),"") -> 0.49969656 | F16: -0.018336567 | G16: 0.080228757 | H16: =IF(G16>0,F16/G16,"") -> -0.22855355 | I16: =IF(G16>0,TDIST(ABS(H16),MIN(F27,F28)-1,2),"") -> 0.82179238 | J16: -0.068369031 | K16: 0.11200054 | L16: =IF(K16>0,J16/K16,"") -> -0.6104348 | M16: =IF(K16>0,TDIST(ABS(L16),MIN(J27,J28)-1,2),"") -> 0.54920438 | N16: -0.04619576 | O16: 0.11372925 | P16: =IF(O16>0,N16/O16,"") -> -0.40619066 | Q16: =IF(O16>0,TDIST(ABS(P16),MIN(N27,N28)-1,2),"") -> 0.68939085 | R16: -0.12568516 | S16: 0.14686987 | T16: =IF(S16>0,R16/S16,"") -> -0.85575867 | U16: =IF(S16>0,TDIST(ABS(T16),MIN(R27,R28)-1,2),"") -> 0.40337942 | V16: 0.021207609 | W16: 0.1366987 | X16: =IF(W16>0,V16/W16,"") -> 0.15514127 | Y16: =IF(W16>0,TDIST(ABS(X16),MIN(V27,V28)-1,2),"") -> 0.87843641 | Z16: 0.037082908 | AA16: 0.19863037 | AB16: =IF(AA16>0,Z16/AA16,"") -> 0.18669304 | AC16: =IF(AA16>0,TDIST(ABS(AB16),MIN(Z27,Z28)-1,2),"") -> 0.85398937 | AD16: 0.063448942 | AE16: 0.18694441 | AF16: =IF(AE16>0,AD16/AE16,"") -> 0.33940005 | AG16: =IF(AE16>0,TDIST(ABS(AF16),MIN(AD27,AD28)-1,2),"") -> 0.73823619 | AH16: -0.036315935 | AI16: 0.034871265 | AJ16: =IF(AI16>0,AH16/AI16,"") -> -1.0414287 | AK16: =IF(AI16>0,TDIST(ABS(AJ16),MIN(AH27,AH28)-1,2),"") -> 0.31146344 | AL16: -0.081780912 | AM16: 0.069884101 | AN16: =IF(AM16>0,AL16/AM16,"") -> -1.1702363 | AO16: =IF(AM16>0,TDIST(ABS(AN16),MIN(AL27,AL28)-1,2),"") -> 0.25716731 | AP16: -0.079814127 | AQ16: 0.059151413 | AR16: =IF(AQ16>0,AP16/AQ16,"") -> -1.349319 | AS16: =IF(AQ16>0,TDIST(ABS(AR16),MIN(AP27,AP28)-1,2),"") -> 0.19396342 | AT16: -0.079754068 | AU16: 0.055404945 | AV16: =IF(AU16>0,AT16/AU16,"") -> -1.4394756 | AW16: =IF(AU16>0,TDIST(ABS(AV16),MIN(AT27,AT28)-1,2),"") -> 0.16718058
A17: Financial Center (0/1) | B17: 0.11025077 | C17: 0.14297328 | D17: =IF(C17>0,B17/C17,"") -> 0.77112851 | E17: =IF(C17>0,TDIST(ABS(D17),MIN(B27,B28)-1,2),"") -> 0.45063545 | F17: 0.14446752 | G17: 0.14201096 | H17: =IF(G17>0,F17/G17,"") -> 1.0172984 | I17: =IF(G17>0,TDIST(ABS(H17),MIN(F27,F28)-1,2),"") -> 0.32249118 | R17: -0.11955044 | S17: 0.066354047 | T17: =IF(S17>0,R17/S17,"") -> -1.8017053 | U17: =IF(S17>0,TDIST(ABS(T17),MIN(R27,R28)-1,2),"") -> 0.088366206 | V17: -0.12350677 | W17: 0.079121768 | X17: =IF(W17>0,V17/W17,"") -> -1.5609709 | Y17: =IF(W17>0,TDIST(ABS(X17),MIN(V27,V28)-1,2),"") -> 0.13594001 | AH17: -0.012494921 | AI17: 0.043048167 | AJ17: =IF(AI17>0,AH17/AI17,"") -> -0.29025442 | AK17: =IF(AI17>0,TDIST(ABS(AJ17),MIN(AH27,AH28)-1,2),"") -> 0.77493901 | AL17: 0.033164302 | AM17: 0.04076174 | AN17: =IF(AM17>0,AL17/AM17,"") -> 0.81361352 | AO17: =IF(AM17>0,TDIST(ABS(AN17),MIN(AL27,AL28)-1,2),"") -> 0.42649865
A18: Log (CIO Age) (t-1) | F18: -0.4044463 | G18: 0.52847673 | H18: =IF(G18>0,F18/G18,"") -> -0.76530579 | I18: =IF(G18>0,TDIST(ABS(H18),MIN(F27,F28)-1,2),"") -> 0.45400783 | J18: 0.82100037 | K18: 0.6435601 | L18: =IF(K18>0,J18/K18,"") -> 1.2757167 | M18: =IF(K18>0,TDIST(ABS(L18),MIN(J27,J28)-1,2),"") -> 0.21827365 | N18: 0.91611206 | O18: 0.66954779 | P18: =IF(O18>0,N18/O18,"") -> 1.3682549 | Q18: =IF(O18>0,TDIST(ABS(P18),MIN(N27,N28)-1,2),"") -> 0.18807043 | V18: -1.2097086 | W18: 0.365611 | X18: =IF(W18>0,V18/W18,"") -> -3.3087316 | Y18: =IF(W18>0,TDIST(ABS(X18),MIN(V27,V28)-1,2),"") -> 0.0039052951 | Z18: -0.15491543 | AA18: 0.68228393 | AB18: =IF(AA18>0,Z18/AA18,"") -> -0.22705419 | AC18: =IF(AA18>0,TDIST(ABS(AB18),MIN(Z27,Z28)-1,2),"") -> 0.82294038 | AD18: 0.21110129 | AE18: 0.6888396 | AF18: =IF(AE18>0,AD18/AE18,"") -> 0.30645928 | AG18: =IF(AE18>0,TDIST(ABS(AF18),MIN(AD27,AD28)-1,2),"") -> 0.76277158 | AL18: 0.00065732087 | AM18: 0.094284967 | AN18: =IF(AM18>0,AL18/AM18,"") -> 0.0069716402 | AO18: =IF(AM18>0,TDIST(ABS(AN18),MIN(AL27,AL28)-1,2),"") -> 0.99451417 | AP18: -0.18464322 | AQ18: 0.10376362 | AR18: =IF(AQ18>0,AP18/AQ18,"") -> -1.7794601 | AS18: =IF(AQ18>0,TDIST(ABS(AR18),MIN(AP27,AP28)-1,2),"") -> 0.092054781 | AT18: -0.15493505 | AU18: 0.10376284 | AV18: =IF(AU18>0,AT18/AU18,"") -> -1.4931651 | AW18: =IF(AU18>0,TDIST(ABS(AV18),MIN(AT27,AT28)-1,2),"") -> 0.1527156
A19: Log (CIO Tenure) (t-1) | F19: 0.036113187 | G19: 0.095607206 | H19: =IF(G19>0,F19/G19,"") -> 0.37772453 | I19: =IF(G19>0,TDIST(ABS(H19),MIN(F27,F28)-1,2),"") -> 0.71005239 | J19: -0.012180883 | K19: 0.11872344 | L19: =IF(K19>0,J19/K19,"") -> -0.1025988 | M19: =IF(K19>0,TDIST(ABS(L19),MIN(J27,J28)-1,2),"") -> 0.91941578 | N19: -0.036556547 | O19: 0.128748 | P19: =IF(O19>0,N19/O19,"") -> -0.28393876 | Q19: =IF(O19>0,TDIST(ABS(P19),MIN(N27,N28)-1,2),"") -> 0.77969762 | V19: -0.011542423 | W19: 0.10268615 | X19: =IF(W19>0,V19/W19,"") -> -0.11240487 | Y19: =IF(W19>0,TDIST(ABS(X19),MIN(V27,V28)-1,2),"") -> 0.91174647 | Z19: -0.076737676 | AA19: 0.11979333 | AB19: =IF(AA19>0,Z19/AA19,"") -> -0.64058387 | AC19: =IF(AA19>0,TDIST(ABS(AB19),MIN(Z27,Z28)-1,2),"") -> 0.52986445 | AD19: -0.19292803 | AE19: 0.13156205 | AF19: =IF(AE19>0,AD19/AE19,"") -> -1.4664413 | AG19: =IF(AE19>0,TDIST(ABS(AF19),MIN(AD27,AD28)-1,2),"") -> 0.15978131 | AL19: -0.01488663 | AM19: 0.01344319 | AN19: =IF(AM19>0,AL19/AM19,"") -> -1.1073733 | AO19: =IF(AM19>0,TDIST(ABS(AN19),MIN(AL27,AL28)-1,2),"") -> 0.28271182 | AP19: 0.017099349 | AQ19: 0.010921605 | AR19: =IF(AQ19>0,AP19/AQ19,"") -> 1.5656443 | AS19: =IF(AQ19>0,TDIST(ABS(AR19),MIN(AP27,AP28)-1,2),"") -> 0.13484282 | AT19: 0.013568296 | AU19: 0.0099798461 | AV19: =IF(AU19>0,AT19/AU19,"") -> 1.3595696 | AW19: =IF(AU19>0,TDIST(ABS(AV19),MIN(AT27,AT28)-1,2),"") -> 0.19075534
A20: CIO Prior Private Experience (0/1) | F20: 0.031262074 | G20: 0.10695409 | H20: =IF(G20>0,F20/G20,"") -> 0.29229433 | I20: =IF(G20>0,TDIST(ABS(H20),MIN(F27,F28)-1,2),"") -> 0.77340397 | J20: -0.036698887 | K20: 0.16421949 | L20: =IF(K20>0,J20/K20,"") -> -0.22347461 | M20: =IF(K20>0,TDIST(ABS(L20),MIN(J27,J28)-1,2),"") -> 0.82568276 | N20: 0.004111521 | O20: 0.15702155 | P20: =IF(O20>0,N20/O20,"") -> 0.026184437 | Q20: =IF(O20>0,TDIST(ABS(P20),MIN(N27,N28)-1,2),"") -> 0.97939834 | V20: 0.10229034 | W20: 0.10405789 | X20: =IF(W20>0,V20/W20,"") -> 0.98301377 | Y20: =IF(W20>0,TDIST(ABS(X20),MIN(V27,V28)-1,2),"") -> 0.33863009 | Z20: 0.13368087 | AA20: 0.20111761 | AB20: =IF(AA20>0,Z20/AA20,"") -> 0.66469006 | AC20: =IF(AA20>0,TDIST(ABS(AB20),MIN(Z27,Z28)-1,2),"") -> 0.51467498 | AD20: 0.10730598 | AE20: 0.21012428 | AF20: =IF(AE20>0,AD20/AE20,"") -> 0.51067861 | AG20: =IF(AE20>0,TDIST(ABS(AF20),MIN(AD27,AD28)-1,2),"") -> 0.61578219 | AL20: -0.056164663 | AM20: 0.039045014 | AN20: =IF(AM20>0,AL20/AM20,"") -> -1.4384593 | AO20: =IF(AM20>0,TDIST(ABS(AN20),MIN(AL27,AL28)-1,2),"") -> 0.16746484 | AP20: -0.072865231 | AQ20: 0.053415844 | AR20: =IF(AQ20>0,AP20/AQ20,"") -> -1.3641127 | AS20: =IF(AQ20>0,TDIST(ABS(AR20),MIN(AP27,AP28)-1,2),"") -> 0.18934713 | AT20: -0.067428007 | AU20: 0.051151241 | AV20: =IF(AU20>0,AT20/AU20,"") -> -1.3182086 | AW20: =IF(AU20>0,TDIST(ABS(AV20),MIN(AT27,AT28)-1,2),"") -> 0.2039633
A21: CIO Attended Elite College (0/1) | F21: -0.11171902 | G21: 0.1404292 | H21: =IF(G21>0,F21/G21,"") -> -0.79555406 | I21: =IF(G21>0,TDIST(ABS(H21),MIN(F27,F28)-1,2),"") -> 0.43665738 | J21: 0.24368029 | K21: 0.24226694 | L21: =IF(K21>0,J21/K21,"") -> 1.0058339 | M21: =IF(K21>0,TDIST(ABS(L21),MIN(J27,J28)-1,2),"") -> 0.32782633 | N21: 0.28856215 | O21: 0.23971428 | P21: =IF(O21>0,N21/O21,"") -> 1.2037754 | Q21: =IF(O21>0,TDIST(ABS(P21),MIN(N27,N28)-1,2),"") -> 0.24426892 | V21: -0.15406979 | W21: 0.15715197 | X21: =IF(W21>0,V21/W21,"") -> -0.98038724 | Y21: =IF(W21>0,TDIST(ABS(X21),MIN(V27,V28)-1,2),"") -> 0.33988932 | Z21: 0.10338719 | AA21: 0.20082557 | AB21: =IF(AA21>0,Z21/AA21,"") -> 0.51481087 | AC21: =IF(AA21>0,TDIST(ABS(AB21),MIN(Z27,Z28)-1,2),"") -> 0.61294902 | AD21: -0.016584159 | AE21: 0.2112982 | AF21: =IF(AE21>0,AD21/AE21,"") -> -0.078486986 | AG21: =IF(AE21>0,TDIST(ABS(AF21),MIN(AD27,AD28)-1,2),"") -> 0.93830663 | AL21: 0.032696962 | AM21: 0.040517043 | AN21: =IF(AM21>0,AL21/AM21,"") -> 0.80699281 | AO21: =IF(AM21>0,TDIST(ABS(AN21),MIN(AL27,AL28)-1,2),"") -> 0.43020543 | AP21: -0.058504395 | AQ21: 0.037463938 | AR21: =IF(AQ21>0,AP21/AQ21,"") -> -1.5616189 | AS21: =IF(AQ21>0,TDIST(ABS(AR21),MIN(AP27,AP28)-1,2),"") -> 0.13578741 | AT21: -0.058622546 | AU21: 0.035888635 | AV21: =IF(AU21>0,AT21/AU21,"") -> -1.6334571 | AW21: =IF(AU21>0,TDIST(ABS(AV21),MIN(AT27,AT28)-1,2),"") -> 0.11974186
A22: Separate Investment Board (0/1) | F22: 0.26907701 | G22: 0.13163311 | H22: =IF(G22>0,F22/G22,"") -> 2.0441438 | I22: =IF(G22>0,TDIST(ABS(H22),MIN(F27,F28)-1,2),"") -> 0.055851799 | J22: -0.2597805 | K22: 0.84862175 | L22: =IF(K22>0,J22/K22,"") -> -0.30612048 | M22: =IF(K22>0,TDIST(ABS(L22),MIN(J27,J28)-1,2),"") -> 0.76302534 | N22: -0.18690328 | O22: 0.98629075 | P22: =IF(O22>0,N22/O22,"") -> -0.1895012 | Q22: =IF(O22>0,TDIST(ABS(P22),MIN(N27,N28)-1,2),"") -> 0.85182051 | V22: 0.31423655 | W22: 0.16832032 | X22: =IF(W22>0,V22/W22,"") -> 1.8668961 | Y22: =IF(W22>0,TDIST(ABS(X22),MIN(V27,V28)-1,2),"") -> 0.078291493 | Z22: -0.047686049 | AA22: 0.94104424 | AB22: =IF(AA22>0,Z22/AA22,"") -> -0.050673546 | AC22: =IF(AA22>0,TDIST(ABS(AB22),MIN(Z27,Z28)-1,2),"") -> 0.96014375 | AD22: 0.5407547 | AE22: 0.75374332 | AF22: =IF(AE22>0,AD22/AE22,"") -> 0.71742553 | AG22: =IF(AE22>0,TDIST(ABS(AF22),MIN(AD27,AD28)-1,2),"") -> 0.48231896 | AL22: 0.0024690392 | AM22: 0.042418137 | AN22: =IF(AM22>0,AL22/AM22,"") -> 0.058207159 | AO22: =IF(AM22>0,TDIST(ABS(AN22),MIN(AL27,AL28)-1,2),"") -> 0.95422494 | AP22: -0.27675177 | AQ22: 0.078098488 | AR22: =IF(AQ22>0,AP22/AQ22,"") -> -3.5436252 | AS22: =IF(AQ22>0,TDIST(ABS(AR22),MIN(AP27,AP28)-1,2),"") -> 0.0023205863 | AT22: -0.2555062 | AU22: 0.079368522 | AV22: =IF(AU22>0,AT22/AU22,"") -> -3.2192384 | AW22: =IF(AU22>0,TDIST(ABS(AV22),MIN(AT27,AT28)-1,2),"") -> 0.0047569073
A23: % Political Appointees on Board | F23: -0.37280752 | G23: 0.24291746 | H23: =IF(G23>0,F23/G23,"") -> -1.5347086 | I23: =IF(G23>0,TDIST(ABS(H23),MIN(F27,F28)-1,2),"") -> 0.14224537 | J23: -0.06750698 | K23: 1.6282309 | L23: =IF(K23>0,J23/K23,"") -> -0.041460324 | M23: =IF(K23>0,TDIST(ABS(L23),MIN(J27,J28)-1,2),"") -> 0.96738535 | N23: -0.46646178 | O23: 1.6517789 | P23: =IF(O23>0,N23/O23,"") -> -0.28239966 | Q23: =IF(O23>0,TDIST(ABS(P23),MIN(N27,N28)-1,2),"") -> 0.78085864 | V23: -0.041892559 | W23: 0.21114788 | X23: =IF(W23>0,V23/W23,"") -> -0.19840389 | Y23: =IF(W23>0,TDIST(ABS(X23),MIN(V27,V28)-1,2),"") -> 0.84495271 | Z23: 0.38797759 | AA23: 1.6291916 | AB23: =IF(AA23>0,Z23/AA23,"") -> 0.23814116 | AC23: =IF(AA23>0,TDIST(ABS(AB23),MIN(Z27,Z28)-1,2),"") -> 0.81446147 | AD23: -0.32220331 | AE23: 1.327345 | AF23: =IF(AE23>0,AD23/AE23,"") -> -0.2427427 | AG23: =IF(AE23>0,TDIST(ABS(AF23),MIN(AD27,AD28)-1,2),"") -> 0.81094923 | AL23: -0.076753694 | AM23: 0.0517804 | AN23: =IF(AM23>0,AL23/AM23,"") -> -1.4822924 | AO23: =IF(AM23>0,TDIST(ABS(AN23),MIN(AL27,AL28)-1,2),"") -> 0.15555862 | AP23: -0.069850014 | AQ23: 0.13047108 | AR23: =IF(AQ23>0,AP23/AQ23,"") -> -0.53536779 | AS23: =IF(AQ23>0,TDIST(ABS(AR23),MIN(AP27,AP28)-1,2),"") -> 0.59894847 | AT23: -0.11842319 | AU23: 0.1345148 | AV23: =IF(AU23>0,AT23/AU23,"") -> -0.88037297 | AW23: =IF(AU23>0,TDIST(ABS(AV23),MIN(AT27,AT28)-1,2),"") -> 0.39026059
A24: First Half minus Second Half | B24: 0.10502651 | C24: 0.23284521 | D24: =IF(C24>0,B24/C24,"") -> 0.45105719 | E24: =IF(C24>0,TDIST(ABS(D24),MIN(B27,B28)-1,2),"") -> 0.65733503 | F24: -0.02359603 | G24: 0.20940675 | H24: =IF(G24>0,F24/G24,"") -> -0.11268037 | I24: =IF(G24>0,TDIST(ABS(H24),MIN(F27,F28)-1,2),"") -> 0.91153112 | J24: -0.22073218 | K24: 0.21615199 | L24: =IF(K24>0,J24/K24,"") -> -1.0211897 | M24: =IF(K24>0,TDIST(ABS(L24),MIN(J27,J28)-1,2),"") -> 0.32069434 | N24: -0.28230355 | O24: 0.23333526 | P24: =IF(O24>0,N24/O24,"") -> -1.2098624 | Q24: =IF(O24>0,TDIST(ABS(P24),MIN(N27,N28)-1,2),"") -> 0.2419817 | R24: -0.15588871 | S24: 0.27113282 | T24: =IF(S24>0,R24/S24,"") -> -0.57495329 | U24: =IF(S24>0,TDIST(ABS(T24),MIN(R27,R28)-1,2),"") -> 0.57244011 | V24: -0.18646614 | W24: 0.20993802 | X24: =IF(W24>0,V24/W24,"") -> -0.88819616 | Y24: =IF(W24>0,TDIST(ABS(X24),MIN(V27,V28)-1,2),"") -> 0.38615056 | Z24: -0.35719776 | AA24: 0.2625704 | AB24: =IF(AA24>0,Z24/AA24,"") -> -1.3603885 | AC24: =IF(AA24>0,TDIST(ABS(AB24),MIN(Z27,Z28)-1,2),"") -> 0.19050089 | AD24: -0.43635534 | AE24: 0.24810727 | AF24: =IF(AE24>0,AD24/AE24,"") -> -1.7587366 | AG24: =IF(AE24>0,TDIST(ABS(AF24),MIN(AD27,AD28)-1,2),"") -> 0.095611012 | AH24: 0.0020868749 | AI24: 0.042007258 | AJ24: =IF(AI24>0,AH24/AI24,"") -> 0.049678913 | AK24: =IF(AI24>0,TDIST(ABS(AJ24),MIN(AH27,AH28)-1,2),"") -> 0.96092537 | AL24: 0.0068054426 | AM24: 0.043723696 | AN24: =IF(AM24>0,AL24/AM24,"") -> 0.15564655 | AO24: =IF(AM24>0,TDIST(ABS(AN24),MIN(AL27,AL28)-1,2),"") -> 0.87804384 | AP24: 0.00776512 | AQ24: 0.040313143 | AR24: =IF(AQ24>0,AP24/AQ24,"") -> 0.19262006 | AS24: =IF(AQ24>0,TDIST(ABS(AR24),MIN(AP27,AP28)-1,2),"") -> 0.84941311 | AT24: 0.0086713455 | AU24: 0.037909501 | AV24: =IF(AU24>0,AT24/AU24,"") -> 0.22873805 | AW24: =IF(AU24>0,TDIST(ABS(AV24),MIN(AT27,AT28)-1,2),"") -> 0.82165115
A26: Observations | B26: 1727 | F26: 1483 | J26: 1482 | N26: 1482 | R26: 1538 | V26: 1320 | Z26: 1319 | AD26: 1319 | AH26: 1485 | AL26: 1301 | AP26: 1299 | AT26: 1299
A27: Plan clusters | B27: 19 | F27: 19 | J27: 19 | N27: 19 | R27: 19 | V27: 19 | Z27: 19 | AD27: 19 | AH27: 19 | AL27: 19 | AP27: 19 | AT27: 19
A28: Year clusters | B28: 19 | F28: 19 | J28: 19 | N28: 19 | R28: 19 | V28: 19 | Z28: 19 | AD28: 19 | AH28: 19 | AL28: 19 | AP28: 19 | AT28: 19
A29: Adjusted R-squared | B29: 0.048732205 | F29: 0.058351239 | J29: 0.080509584 | N29: 0.095258826 | R29: 0.11857809 | V29: 0.12810988 | Z29: 0.020791442 | AD29: 0.1239048 | AH29: 0.3426776 | AL29: 0.36068689 | AP29: 0.66165511 | AT29: 0.67056452

Sheet Estimates
A1: Estimates behind the tables (blue = regression output; t and p are formulas). Standard errors double clustered by plan and year; p-values use the t distribution with min(plan clusters, year clusters) - 1 degrees of freedom.
A3: Variable | B3: T1A(1) coef | C3: T1A(1) se | D3: T1A(1) t | E3: T1A(1) p | F3: T1A(2) coef | G3: T1A(2) se | H3: T1A(2) t | I3: T1A(2) p | J3: T1A(3) coef | K3: T1A(3) se | L3: T1A(3) t | M3: T1A(3) p | N3: T1A(4) coef | O3: T1A(4) se | P3: T1A(4) t | Q3: T1A(4) p | R3: T1A(5) coef | S3: T1A(5) se | T3: T1A(5) t | U3: T1A(5) p | V3: T1A(6) coef | W3: T1A(6) se | X3: T1A(6) t | Y3: T1A(6) p | Z3: T1B(1) coef | AA3: T1B(1) se | AB3: T1B(1) t | AC3: T1B(1) p | AD3: T1B(2) coef | AE3: T1B(2) se | AF3: T1B(2) t | AG3: T1B(2) p | AH3: T1B(3) coef | AI3: T1B(3) se | AJ3: T1B(3) t | AK3: T1B(3) p | AL3: T1B(4) coef | AM3: T1B(4) se | AN3: T1B(4) t | AO3: T1B(4) p | AP3: T1B(5) coef | AQ3: T1B(5) se | AR3: T1B(5) t | AS3: T1B(5) p | AT3: T1B(6) coef | AU3: T1B(6) se | AV3: T1B(6) t | AW3: T1B(6) p | AX3: T2A(1) coef | AY3: T2A(1) se | AZ3: T2A(1) t | BA3: T2A(1) p | BB3: T2A(2) coef | BC3: T2A(2) se | BD3: T2A(2) t | BE3: T2A(2) p | BF3: T2A(3) coef | BG3: T2A(3) se | BH3: T2A(3) t | BI3: T2A(3) p | BJ3: T2A(4) coef | BK3: T2A(4) se | BL3: T2A(4) t | BM3: T2A(4) p | BN3: T2A(5) coef | BO3: T2A(5) se | BP3: T2A(5) t | BQ3: T2A(5) p | BR3: T2A(6) coef | BS3: T2A(6) se | BT3: T2A(6) t | BU3: T2A(6) p
A4: Second Half of Tenure (0/1) | B4: -0.22887653 | C4: 0.18249366 | D4: =IF(C4>0,B4/C4,"") -> -1.2541615 | E4: =IF(C4>0,TDIST(ABS(D4),MIN(B25,B26)-1,2),"") -> 0.22675494 | F4: -0.14397428 | G4: 0.21203028 | H4: =IF(G4>0,F4/G4,"") -> -0.67902696 | I4: =IF(G4>0,TDIST(ABS(H4),MIN(F25,F26)-1,2),"") -> 0.50626104 | J4: 0.044293501 | K4: 0.26814517 | L4: =IF(K4>0,J4/K4,"") -> 0.16518478 | M4: =IF(K4>0,TDIST(ABS(L4),MIN(J25,J26)-1,2),"") -> 0.87074692 | N4: -0.082519505 | O4: 0.30530506 | P4: =IF(O4>0,N4/O4,"") -> -0.27028542 | Q4: =IF(O4>0,TDIST(ABS(P4),MIN(N25,N26)-1,2),"") -> 0.7901946 | R4: -0.96946968 | S4: 0.50165456 | T4: =IF(S4>0,R4/S4,"") -> -1.9325443 | U4: =IF(S4>0,TDIST(ABS(T4),MIN(R25,R26)-1,2),"") -> 0.070129588 | V4: -0.30855713 | W4: 0.93734336 | X4: =IF(W4>0,V4/W4,"") -> -0.3291826 | Y4: =IF(W4>0,TDIST(ABS(X4),MIN(V25,V26)-1,2),"") -> 0.7460385 | Z4: 0.093598382 | AA4: 0.30247419 | AB4: =IF(AA4>0,Z4/AA4,"") -> 0.30944254 | AC4: =IF(AA4>0,TDIST(ABS(AB4),MIN(Z25,Z26)-1,2),"") -> 0.76074558 | AD4: 0.25540757 | AE4: 0.28871268 | AF4: =IF(AE4>0,AD4/AE4,"") -> 0.88464272 | AG4: =IF(AE4>0,TDIST(ABS(AF4),MIN(AD25,AD26)-1,2),"") -> 0.38869037 | AH4: 0.28191135 | AI4: 0.28858908 | AJ4: =IF(AI4>0,AH4/AI4,"") -> 0.97686076 | AK4: =IF(AI4>0,TDIST(ABS(AJ4),MIN(AH25,AH26)-1,2),"") -> 0.34233532 | AL4: 0.56530506 | AM4: 0.26448909 | AN4: =IF(AM4>0,AL4/AM4,"") -> 2.1373473 | AO4: =IF(AM4>0,TDIST(ABS(AN4),MIN(AL25,AL26)-1,2),"") -> 0.047395185 | AP4: -0.16615809 | AQ4: 0.39832748 | AR4: =IF(AQ4>0,AP4/AQ4,"") -> -0.41713942 | AS4: =IF(AQ4>0,TDIST(ABS(AR4),MIN(AP25,AP26)-1,2),"") -> 0.68179672 | AT4: -0.087371497 | AU4: 0.38334522 | AV4: =IF(AU4>0,AT4/AU4,"") -> -0.22791858 | AW4: =IF(AU4>0,TDIST(ABS(AV4),MIN(AT25,AT26)-1,2),"") -> 0.82242831 | AX4: -0.058629413 | AY4: 0.03450197 | AZ4: =IF(AY4>0,AX4/AY4,"") -> -1.6993062 | BA4: =IF(AY4>0,TDIST(ABS(AZ4),MIN(AX25,AX26)-1,2),"") -> 0.10748504 | BB4: -0.076618983 | BC4: 0.055777393 | BD4: =IF(BC4>0,BB4/BC4,"") -> -1.3736566 | BE4: =IF(BC4>0,TDIST(ABS(BD4),MIN(BB25,BB26)-1,2),"") -> 0.18739297 | BF4: -0.018051521 | BG4: 0.045807405 | BH4: =IF(BG4>0,BF4/BG4,"") -> -0.3940743 | BI4: =IF(BG4>0,TDIST(ABS(BH4),MIN(BF25,BF26)-1,2),"") -> 0.6984255 | BJ4: -0.053352622 | BK4: 0.041472616 | BL4: =IF(BK4>0,BJ4/BK4,"") -> -1.2864542 | BM4: =IF(BK4>0,TDIST(ABS(BL4),MIN(BJ25,BJ26)-1,2),"") -> 0.21552897 | BN4: -0.059546676 | BO4: 0.054436338 | BP4: =IF(BO4>0,BN4/BO4,"") -> -1.0938773 | BQ4: =IF(BO4>0,TDIST(ABS(BP4),MIN(BN25,BN26)-1,2),"") -> 0.2892668 | BR4: -0.026764986 | BS4: 0.063848482 | BT4: =IF(BS4>0,BR4/BS4,"") -> -0.41919534 | BU4: =IF(BS4>0,TDIST(ABS(BT4),MIN(BR25,BR26)-1,2),"") -> 0.68032249
A5: Investment Return (t - 1) | B5: 0.061228728 | C5: 0.069690157 | D5: =IF(C5>0,B5/C5,"") -> 0.87858502 | E5: =IF(C5>0,TDIST(ABS(D5),MIN(B25,B26)-1,2),"") -> 0.39187549 | F5: 0.031826021 | G5: 0.055252585 | H5: =IF(G5>0,F5/G5,"") -> 0.57600963 | I5: =IF(G5>0,TDIST(ABS(H5),MIN(F25,F26)-1,2),"") -> 0.57215616 | J5: -0.0025119261 | K5: 0.016401967 | L5: =IF(K5>0,J5/K5,"") -> -0.15314786 | M5: =IF(K5>0,TDIST(ABS(L5),MIN(J25,J26)-1,2),"") -> 0.88008482 | N5: 0.015491243 | O5: 0.037637147 | P5: =IF(O5>0,N5/O5,"") -> 0.41159451 | Q5: =IF(O5>0,TDIST(ABS(P5),MIN(N25,N26)-1,2),"") -> 0.68577936 | R5: -0.0018191722 | S5: 0.034225273 | T5: =IF(S5>0,R5/S5,"") -> -0.053152892 | U5: =IF(S5>0,TDIST(ABS(T5),MIN(R25,R26)-1,2),"") -> 0.95822971 | V5: 0.029650105 | W5: 0.049238398 | X5: =IF(W5>0,V5/W5,"") -> 0.60217445 | Y5: =IF(W5>0,TDIST(ABS(X5),MIN(V25,V26)-1,2),"") -> 0.55500549 | Z5: 0.084492794 | AA5: 0.088395792 | AB5: =IF(AA5>0,Z5/AA5,"") -> 0.95584634 | AC5: =IF(AA5>0,TDIST(ABS(AB5),MIN(Z25,Z26)-1,2),"") -> 0.35254602 | AD5: 0.038887182 | AE5: 0.05787087 | AF5: =IF(AE5>0,AD5/AE5,"") -> 0.6719647 | AG5: =IF(AE5>0,TDIST(ABS(AF5),MIN(AD25,AD26)-1,2),"") -> 0.51063598 | AH5: -0.0036412941 | AI5: 0.027117283 | AJ5: =IF(AI5>0,AH5/AI5,"") -> -0.13427946 | AK5: =IF(AI5>0,TDIST(ABS(AJ5),MIN(AH25,AH26)-1,2),"") -> 0.89475853 | AL5: 0.012268565 | AM5: 0.052913361 | AN5: =IF(AM5>0,AL5/AM5,"") -> 0.23186138 | AO5: =IF(AM5>0,TDIST(ABS(AN5),MIN(AL25,AL26)-1,2),"") -> 0.81941371 | AP5: -0.040951884 | AQ5: 0.037114247 | AR5: =IF(AQ5>0,AP5/AQ5,"") -> -1.1034007 | AS5: =IF(AQ5>0,TDIST(ABS(AR5),MIN(AP25,AP26)-1,2),"") -> 0.28522812 | AT5: -0.012281387 | AU5: 0.04547114 | AV5: =IF(AU5>0,AT5/AU5,"") -> -0.2700919 | AW5: =IF(AU5>0,TDIST(ABS(AV5),MIN(AT25,AT26)-1,2),"") -> 0.79034099 | AX5: 0.00021063521 | AY5: 0.0017446559 | AZ5: =IF(AY5>0,AX5/AY5,"") -> 0.12073167 | BA5: =IF(AY5>0,TDIST(ABS(AZ5),MIN(AX25,AX26)-1,2),"") -> 0.90531906 | BB5: 0.00075188784 | BC5: 0.0015759879 | BD5: =IF(BC5>0,BB5/BC5,"") -> 0.47708987 | BE5: =IF(BC5>0,TDIST(ABS(BD5),MIN(BB25,BB26)-1,2),"") -> 0.6393737 | BF5: -0.0015513247 | BG5: 0.002130287 | BH5: =IF(BG5>0,BF5/BG5,"") -> -0.72822334 | BI5: =IF(BG5>0,TDIST(ABS(BH5),MIN(BF25,BF26)-1,2),"") -> 0.47638895 | BJ5: -0.00039348255 | BK5: 0.0018949119 | BL5: =IF(BK5>0,BJ5/BK5,"") -> -0.20765216 | BM5: =IF(BK5>0,TDIST(ABS(BL5),MIN(BJ25,BJ26)-1,2),"") -> 0.83796779 | BN5: -0.0011635613 | BO5: 0.0017242442 | BP5: =IF(BO5>0,BN5/BO5,"") -> -0.67482397 | BQ5: =IF(BO5>0,TDIST(ABS(BP5),MIN(BN25,BN26)-1,2),"") -> 0.50886212 | BR5: 0.00017737771 | BS5: 0.00098274821 | BT5: =IF(BS5>0,BR5/BS5,"") -> 0.18049152 | BU5: =IF(BS5>0,TDIST(ABS(BT5),MIN(BR25,BR26)-1,2),"") -> 0.85890089
A6: Log (Plan Size) (t-1) | B6: -0.046189167 | C6: 0.10927714 | D6: =IF(C6>0,B6/C6,"") -> -0.42267912 | E6: =IF(C6>0,TDIST(ABS(D6),MIN(B25,B26)-1,2),"") -> 0.67782744 | F6: -0.084835285 | G6: 0.10959584 | H6: =IF(G6>0,F6/G6,"") -> -0.77407395 | I6: =IF(G6>0,TDIST(ABS(H6),MIN(F25,F26)-1,2),"") -> 0.44951894 | J6: -0.40549078 | K6: 0.95046452 | L6: =IF(K6>0,J6/K6,"") -> -0.4266238 | M6: =IF(K6>0,TDIST(ABS(L6),MIN(J25,J26)-1,2),"") -> 0.67500695 | N6: 0.12978778 | O6: 1.0513618 | P6: =IF(O6>0,N6/O6,"") -> 0.1234473 | Q6: =IF(O6>0,TDIST(ABS(P6),MIN(N25,N26)-1,2),"") -> 0.90320069 | R6: 1.4089342 | S6: 2.1873898 | T6: =IF(S6>0,R6/S6,"") -> 0.64411665 | U6: =IF(S6>0,TDIST(ABS(T6),MIN(R25,R26)-1,2),"") -> 0.52809547 | V6: 1.2011995 | W6: 2.3082705 | X6: =IF(W6>0,V6/W6,"") -> 0.52038942 | Y6: =IF(W6>0,TDIST(ABS(X6),MIN(V25,V26)-1,2),"") -> 0.60950344 | Z6: 0.1071047 | AA6: 0.091456346 | AB6: =IF(AA6>0,Z6/AA6,"") -> 1.1711019 | AC6: =IF(AA6>0,TDIST(ABS(AB6),MIN(Z25,Z26)-1,2),"") -> 0.25771177 | AD6: 0.083577977 | AE6: 0.10906386 | AF6: =IF(AE6>0,AD6/AE6,"") -> 0.76632146 | AG6: =IF(AE6>0,TDIST(ABS(AF6),MIN(AD25,AD26)-1,2),"") -> 0.45399539 | AH6: -0.9052063 | AI6: 1.1775236 | AJ6: =IF(AI6>0,AH6/AI6,"") -> -0.76873726 | AK6: =IF(AI6>0,TDIST(ABS(AJ6),MIN(AH25,AH26)-1,2),"") -> 0.45259753 | AL6: 0.3505593 | AM6: 1.0385779 | AN6: =IF(AM6>0,AL6/AM6,"") -> 0.3375378 | AO6: =IF(AM6>0,TDIST(ABS(AN6),MIN(AL25,AL26)-1,2),"") -> 0.73984345 | AP6: -0.043536684 | AQ6: 1.7996749 | AR6: =IF(AQ6>0,AP6/AQ6,"") -> -0.024191416 | AS6: =IF(AQ6>0,TDIST(ABS(AR6),MIN(AP25,AP26)-1,2),"") -> 0.98098162 | AT6: 1.652412 | AU6: 1.0806601 | AV6: =IF(AU6>0,AT6/AU6,"") -> 1.5290766 | AW6: =IF(AU6>0,TDIST(ABS(AV6),MIN(AT25,AT26)-1,2),"") -> 0.144639 | AX6: -0.038316156 | AY6: 0.019329799 | AZ6: =IF(AY6>0,AX6/AY6,"") -> -1.9822325 | BA6: =IF(AY6>0,TDIST(ABS(AZ6),MIN(AX25,AX26)-1,2),"") -> 0.063856329 | BB6: -0.045970069 | BC6: 0.020351498 | BD6: =IF(BC6>0,BB6/BC6,"") -> -2.2588052 | BE6: =IF(BC6>0,TDIST(ABS(BD6),MIN(BB25,BB26)-1,2),"") -> 0.037325467 | BF6: -0.042676828 | BG6: 0.10771167 | BH6: =IF(BG6>0,BF6/BG6,"") -> -0.3962136 | BI6: =IF(BG6>0,TDIST(ABS(BH6),MIN(BF25,BF26)-1,2),"") -> 0.69687636 | BJ6: -0.28400556 | BK6: 0.13434061 | BL6: =IF(BK6>0,BJ6/BK6,"") -> -2.1140708 | BM6: =IF(BK6>0,TDIST(ABS(BL6),MIN(BJ25,BJ26)-1,2),"") -> 0.049589039 | BN6: -0.16856967 | BO6: 0.19681637 | BP6: =IF(BO6>0,BN6/BO6,"") -> -0.85648199 | BQ6: =IF(BO6>0,TDIST(ABS(BP6),MIN(BN25,BN26)-1,2),"") -> 0.40364307 | BR6: -0.077141604 | BS6: 0.19400495 | BT6: =IF(BS6>0,BR6/BS6,"") -> -0.39762698 | BU6: =IF(BS6>0,TDIST(ABS(BT6),MIN(BR25,BR26)-1,2),"") -> 0.69585363
A7: Funding Ratio (t-1) | B7: -0.01862138 | C7: 0.0097026798 | D7: =IF(C7>0,B7/C7,"") -> -1.9191996 | E7: =IF(C7>0,TDIST(ABS(D7),MIN(B25,B26)-1,2),"") -> 0.071905755 | F7: -0.013996776 | G7: 0.008802593 | H7: =IF(G7>0,F7/G7,"") -> -1.5900742 | I7: =IF(G7>0,TDIST(ABS(H7),MIN(F25,F26)-1,2),"") -> 0.13024136 | J7: -0.016050388 | K7: 0.033084988 | L7: =IF(K7>0,J7/K7,"") -> -0.48512602 | M7: =IF(K7>0,TDIST(ABS(L7),MIN(J25,J26)-1,2),"") -> 0.6337794 | N7: -0.034630374 | O7: 0.039111484 | P7: =IF(O7>0,N7/O7,"") -> -0.88542727 | Q7: =IF(O7>0,TDIST(ABS(P7),MIN(N25,N26)-1,2),"") -> 0.38827912 | R7: -0.093098425 | S7: 0.037860966 | T7: =IF(S7>0,R7/S7,"") -> -2.4589554 | U7: =IF(S7>0,TDIST(ABS(T7),MIN(R25,R26)-1,2),"") -> 0.024953972 | V7: -0.09264181 | W7: 0.046280446 | X7: =IF(W7>0,V7/W7,"") -> -2.0017484 | Y7: =IF(W7>0,TDIST(ABS(X7),MIN(V25,V26)-1,2),"") -> 0.061533669 | Z7: -0.010476009 | AA7: 0.010686658 | AB7: =IF(AA7>0,Z7/AA7,"") -> -0.98028867 | AC7: =IF(AA7>0,TDIST(ABS(AB7),MIN(Z25,Z26)-1,2),"") -> 0.34068947 | AD7: -0.0055404064 | AE7: 0.0101128 | AF7: =IF(AE7>0,AD7/AE7,"") -> -0.54786074 | AG7: =IF(AE7>0,TDIST(ABS(AF7),MIN(AD25,AD26)-1,2),"") -> 0.59090924 | AH7: -0.015557648 | AI7: 0.031467025 | AJ7: =IF(AI7>0,AH7/AI7,"") -> -0.49441115 | AK7: =IF(AI7>0,TDIST(ABS(AJ7),MIN(AH25,AH26)-1,2),"") -> 0.62734398 | AL7: -0.010487986 | AM7: 0.029701288 | AN7: =IF(AM7>0,AL7/AM7,"") -> -0.35311552 | AO7: =IF(AM7>0,TDIST(ABS(AN7),MIN(AL25,AL26)-1,2),"") -> 0.72834248 | AP7: -0.021927306 | AQ7: 0.035597592 | AR7: =IF(AQ7>0,AP7/AQ7,"") -> -0.61597723 | AS7: =IF(AQ7>0,TDIST(ABS(AR7),MIN(AP25,AP26)-1,2),"") -> 0.54606946 | AT7: -0.045399206 | AU7: 0.035976002 | AV7: =IF(AU7>0,AT7/AU7,"") -> -1.2619303 | AW7: =IF(AU7>0,TDIST(ABS(AV7),MIN(AT25,AT26)-1,2),"") -> 0.22401353 | AX7: -0.0022394213 | AY7: 0.00074413046 | AZ7: =IF(AY7>0,AX7/AY7,"") -> -3.0094471 | BA7: =IF(AY7>0,TDIST(ABS(AZ7),MIN(AX25,AX26)-1,2),"") -> 0.0078940463 | BB7: -0.0022557779 | BC7: 0.00075127315 | BD7: =IF(BC7>0,BB7/BC7,"") -> -3.0026068 | BE7: =IF(BC7>0,TDIST(ABS(BD7),MIN(BB25,BB26)-1,2),"") -> 0.0080100522 | BF7: -0.0055861203 | BG7: 0.0033983037 | BH7: =IF(BG7>0,BF7/BG7,"") -> -1.6437967 | BI7: =IF(BG7>0,TDIST(ABS(BH7),MIN(BF25,BF26)-1,2),"") -> 0.11858289 | BJ7: -0.0011901556 | BK7: 0.0027400148 | BL7: =IF(BK7>0,BJ7/BK7,"") -> -0.43436103 | BM7: =IF(BK7>0,TDIST(ABS(BL7),MIN(BJ25,BJ26)-1,2),"") -> 0.66948919 | BN7: -0.00072142462 | BO7: 0.0021895531 | BP7: =IF(BO7>0,BN7/BO7,"") -> -0.32948487 | BQ7: =IF(BO7>0,TDIST(ABS(BP7),MIN(BN25,BN26)-1,2),"") -> 0.74581407 | BR7: -0.0011252541 | BS7: 0.0016303165 | BT7: =IF(BS7>0,BR7/BS7,"") -> -0.69020592 | BU7: =IF(BS7>0,TDIST(ABS(BT7),MIN(BR25,BR26)-1,2),"") -> 0.49938003
A8: Equity Allocation (%) | B8: 0.075642712 | C8: 0.11267524 | D8: =IF(C8>0,B8/C8,"") -> 0.67133394 | E8: =IF(C8>0,TDIST(ABS(D8),MIN(B25,B26)-1,2),"") -> 0.51102777 | F8: 0.10325599 | G8: 0.11593821 | H8: =IF(G8>0,F8/G8,"") -> 0.8906123 | I8: =IF(G8>0,TDIST(ABS(H8),MIN(F25,F26)-1,2),"") -> 0.38556845 | J8: -0.62888686 | K8: 0.29426174 | L8: =IF(K8>0,J8/K8,"") -> -2.1371683 | M8: =IF(K8>0,TDIST(ABS(L8),MIN(J25,J26)-1,2),"") -> 0.047411716 | N8: -0.61116233 | O8: 0.37527786 | P8: =IF(O8>0,N8/O8,"") -> -1.6285595 | Q8: =IF(O8>0,TDIST(ABS(P8),MIN(N25,N26)-1,2),"") -> 0.12179554 | R8: -1.5577636 | S8: 0.44845433 | T8: =IF(S8>0,R8/S8,"") -> -3.4736283 | U8: =IF(S8>0,TDIST(ABS(T8),MIN(R25,R26)-1,2),"") -> 0.0029054774 | V8: -2.1559327 | W8: 0.58075672 | X8: =IF(W8>0,V8/W8,"") -> -3.7122821 | Y8: =IF(W8>0,TDIST(ABS(X8),MIN(V25,V26)-1,2),"") -> 0.0017310472 | Z8: -0.3003799 | AA8: 0.22799126 | AB8: =IF(AA8>0,Z8/AA8,"") -> -1.3175062 | AC8: =IF(AA8>0,TDIST(ABS(AB8),MIN(Z25,Z26)-1,2),"") -> 0.20515035 | AD8: -0.18154875 | AE8: 0.20177147 | AF8: =IF(AE8>0,AD8/AE8,"") -> -0.89977411 | AG8: =IF(AE8>0,TDIST(ABS(AF8),MIN(AD25,AD26)-1,2),"") -> 0.38080965 | AH8: -0.52657561 | AI8: 0.48273688 | AJ8: =IF(AI8>0,AH8/AI8,"") -> -1.0908129 | AK8: =IF(AI8>0,TDIST(ABS(AJ8),MIN(AH25,AH26)-1,2),"") -> 0.29057527 | AL8: -0.56102066 | AM8: 0.54760969 | AN8: =IF(AM8>0,AL8/AM8,"") -> -1.02449 | AO8: =IF(AM8>0,TDIST(ABS(AN8),MIN(AL25,AL26)-1,2),"") -> 0.31996204 | AP8: -0.7397276 | AQ8: 0.4910929 | AR8: =IF(AQ8>0,AP8/AQ8,"") -> -1.5062885 | AS8: =IF(AQ8>0,TDIST(ABS(AR8),MIN(AP25,AP26)-1,2),"") -> 0.1503488 | AT8: -1.1900167 | AU8: 0.64596804 | AV8: =IF(AU8>0,AT8/AU8,"") -> -1.8422223 | AW8: =IF(AU8>0,TDIST(ABS(AV8),MIN(AT25,AT26)-1,2),"") -> 0.082955265 | AX8: -0.084573043 | AY8: 0.071590278 | AZ8: =IF(AY8>0,AX8/AY8,"") -> -1.1813481 | BA8: =IF(AY8>0,TDIST(ABS(AZ8),MIN(AX25,AX26)-1,2),"") -> 0.25372789 | BB8: -0.038038932 | BC8: 0.060968018 | BD8: =IF(BC8>0,BB8/BC8,"") -> -0.62391615 | BE8: =IF(BC8>0,TDIST(ABS(BD8),MIN(BB25,BB26)-1,2),"") -> 0.54096516 | BF8: -0.08231137 | BG8: 0.060453418 | BH8: =IF(BG8>0,BF8/BG8,"") -> -1.3615669 | BI8: =IF(BG8>0,TDIST(ABS(BH8),MIN(BF25,BF26)-1,2),"") -> 0.19110827 | BJ8: -0.055595136 | BK8: 0.02800592 | BL8: =IF(BK8>0,BJ8/BK8,"") -> -1.9851208 | BM8: =IF(BK8>0,TDIST(ABS(BL8),MIN(BJ25,BJ26)-1,2),"") -> 0.063507673 | BN8: -0.054942758 | BO8: 0.045178931 | BP8: =IF(BO8>0,BN8/BO8,"") -> -1.2161146 | BQ8: =IF(BO8>0,TDIST(ABS(BP8),MIN(BN25,BN26)-1,2),"") -> 0.24055847 | BR8: 0.0059683833 | BS8: 0.066770923 | BT8: =IF(BS8>0,BR8/BS8,"") -> 0.089385963 | BU8: =IF(BS8>0,TDIST(ABS(BT8),MIN(BR25,BR26)-1,2),"") -> 0.92981982
