Workbook

Sheet A. vs rest of sample
A1: Conflicted CIOs, First vs. Second Half of Tenure, Relative to All Other Plan-Years
A2: Each row reports one regression on the Table III sample of the outcome on Conflicted CIO x First Half and Conflicted CIO x Second Half (non-conflicted plan-years are the omitted group; conflicted plan-years without departure information enter as a separate indicator), the controls, and fiscal-year-end date fixed effects (columns 1-4) or plan and fiscal-year-end date fixed effects (columns 5-6). The second half of a CIO's tenure is the years in which tenure exceeds half of tenure at departure (tenure at departure = the CIO's maximum tenure at the plan plus any gap to the departure year). Controls for returns and fees: lagged return, Size, lagged funding ratio, lagged allocations, Financial Center, prior private experience, elite college, separate investment board and political appointees; allocation outcomes omit the lagged allocations. Lagged log CIO tenure and age are omitted from all specifications because tenure rises mechanically from the first to the second half. Standard errors are double clustered by plan and year. Coefficients marked with ***, **, and * are significant at the 1%, 5%, and 10% level, respectively.
B4: Fiscal-Year-End FE | F4: Plan and Fiscal-Year-End FE
B5: Conflicted x First Half | C5: Conflicted x Second Half | D5: Second minus First | E5: p-value | F5: Second minus First | G5: p-value | H5: Observations
A6: Returns
A7: Peer-Adjusted Return (%) | B7: =IF(Estimates!I4="","",TEXT(Estimates!E4,"0.000")&IF(Estimates!I4<0.01,"***",IF(Estimates!I4<0.05,"**",IF(Estimates!I4<0.1,"*","")))) -> -0.648*** | C7: =IF(Estimates!I5="","",TEXT(Estimates!E5,"0.000")&IF(Estimates!I5<0.01,"***",IF(Estimates!I5<0.05,"**",IF(Estimates!I5<0.1,"*","")))) -> -0.529** | D7: =IF(Estimates!I6="","",TEXT(Estimates!E6,"0.000")&IF(Estimates!I6<0.01,"***",IF(Estimates!I6<0.05,"**",IF(Estimates!I6<0.1,"*","")))) -> 0.119 | E7: =Estimates!I6 -> 0.5669504 | F7: =IF(Estimates!I7="","",TEXT(Estimates!E7,"0.000")&IF(Estimates!I7<0.01,"***",IF(Estimates!I7<0.05,"**",IF(Estimates!I7<0.1,"*","")))) -> 0.285 | G7: =Estimates!I7 -> 0.17549705 | H7: 1529
B8: =IF(Estimates!H4="","","("&TEXT(Estimates!H4,"0.00")&")") -> (-2.96) | C8: =IF(Estimates!H5="","","("&TEXT(Estimates!H5,"0.00")&")") -> (-2.32) | D8: =IF(Estimates!H6="","","("&TEXT(Estimates!H6,"0.00")&")") -> (0.58) | F8: =IF(Estimates!H7="","","("&TEXT(Estimates!H7,"0.00")&")") -> (1.41)
A9: Benchmark-Adjusted Return (%) | B9: =IF(Estimates!I8="","",TEXT(Estimates!E8,"0.000")&IF(Estimates!I8<0.01,"***",IF(Estimates!I8<0.05,"**",IF(Estimates!I8<0.1,"*","")))) -> -0.681*** | C9: =IF(Estimates!I9="","",TEXT(Estimates!E9,"0.000")&IF(Estimates!I9<0.01,"***",IF(Estimates!I9<0.05,"**",IF(Estimates!I9<0.1,"*","")))) -> -0.307* | D9: =IF(Estimates!I10="","",TEXT(Estimates!E10,"0.000")&IF(Estimates!I10<0.01,"***",IF(Estimates!I10<0.05,"**",IF(Estimates!I10<0.1,"*","")))) -> 0.374* | E9: =Estimates!I10 -> 0.053017247 | F9: =IF(Estimates!I11="","",TEXT(Estimates!E11,"0.000")&IF(Estimates!I11<0.01,"***",IF(Estimates!I11<0.05,"**",IF(Estimates!I11<0.1,"*","")))) -> 0.446* | G9: =Estimates!I11 -> 0.059174055 | H9: 1353
B10: =IF(Estimates!H8="","","("&TEXT(Estimates!H8,"0.00")&")") -> (-2.94) | C10: =IF(Estimates!H9="","","("&TEXT(Estimates!H9,"0.00")&")") -> (-1.76) | D10: =IF(Estimates!H10="","","("&TEXT(Estimates!H10,"0.00")&")") -> (2.07) | F10: =IF(Estimates!H11="","","("&TEXT(Estimates!H11,"0.00")&")") -> (2.01)
A11: Fees
A12: Fee Ratio (%) | B12: =IF(Estimates!I12="","",TEXT(Estimates!E12,"0.000")&IF(Estimates!I12<0.01,"***",IF(Estimates!I12<0.05,"**",IF(Estimates!I12<0.1,"*","")))) -> -0.029 | C12: =IF(Estimates!I13="","",TEXT(Estimates!E13,"0.000")&IF(Estimates!I13<0.01,"***",IF(Estimates!I13<0.05,"**",IF(Estimates!I13<0.1,"*","")))) -> -0.043 | D12: =IF(Estimates!I14="","",TEXT(Estimates!E14,"0.000")&IF(Estimates!I14<0.01,"***",IF(Estimates!I14<0.05,"**",IF(Estimates!I14<0.1,"*","")))) -> -0.015 | E12: =Estimates!I14 -> 0.72790565 | F12: =IF(Estimates!I15="","",TEXT(Estimates!E15,"0.000")&IF(Estimates!I15<0.01,"***",IF(Estimates!I15<0.05,"**",IF(Estimates!I15<0.1,"*","")))) -> 0.004 | G12: =Estimates!I15 -> 0.92222074 | H12: 1333
B13: =IF(Estimates!H12="","","("&TEXT(Estimates!H12,"0.00")&")") -> (-0.55) | C13: =IF(Estimates!H13="","","("&TEXT(Estimates!H13,"0.00")&")") -> (-0.98) | D13: =IF(Estimates!H14="","","("&TEXT(Estimates!H14,"0.00")&")") -> (-0.35) | F13: =IF(Estimates!H15="","","("&TEXT(Estimates!H15,"0.00")&")") -> (0.10)
A14: Expense Ratio (%) | B14: =IF(Estimates!I16="","",TEXT(Estimates!E16,"0.000")&IF(Estimates!I16<0.01,"***",IF(Estimates!I16<0.05,"**",IF(Estimates!I16<0.1,"*","")))) -> -0.084 | C14: =IF(Estimates!I17="","",TEXT(Estimates!E17,"0.000")&IF(Estimates!I17<0.01,"***",IF(Estimates!I17<0.05,"**",IF(Estimates!I17<0.1,"*","")))) -> -0.102** | D14: =IF(Estimates!I18="","",TEXT(Estimates!E18,"0.000")&IF(Estimates!I18<0.01,"***",IF(Estimates!I18<0.05,"**",IF(Estimates!I18<0.1,"*","")))) -> -0.018 | E14: =Estimates!I18 -> 0.62351124 | F14: =IF(Estimates!I19="","",TEXT(Estimates!E19,"0.000")&IF(Estimates!I19<0.01,"***",IF(Estimates!I19<0.05,"**",IF(Estimates!I19<0.1,"*","")))) -> 0.019 | G14: =Estimates!I19 -> 0.57446093 | H14: 1476
B15: =IF(Estimates!H16="","","("&TEXT(Estimates!H16,"0.00")&")") -> (-1.70) | C15: =IF(Estimates!H17="","","("&TEXT(Estimates!H17,"0.00")&")") -> (-2.48) | D15: =IF(Estimates!H18="","","("&TEXT(Estimates!H18,"0.00")&")") -> (-0.50) | F15: =IF(Estimates!H19="","","("&TEXT(Estimates!H19,"0.00")&")") -> (0.57)
A16: Fee rates by asset class
A17: Equity Fee Rate (%) | B17: =IF(Estimates!I20="","",TEXT(Estimates!E20,"0.000")&IF(Estimates!I20<0.01,"***",IF(Estimates!I20<0.05,"**",IF(Estimates!I20<0.1,"*","")))) -> -0.030 | C17: =IF(Estimates!I21="","",TEXT(Estimates!E21,"0.000")&IF(Estimates!I21<0.01,"***",IF(Estimates!I21<0.05,"**",IF(Estimates!I21<0.1,"*","")))) -> -0.035 | D17: =IF(Estimates!I22="","",TEXT(Estimates!E22,"0.000")&IF(Estimates!I22<0.01,"***",IF(Estimates!I22<0.05,"**",IF(Estimates!I22<0.1,"*","")))) -> -0.005 | E17: =Estimates!I22 -> 0.76946635 | F17: =IF(Estimates!I23="","",TEXT(Estimates!E23,"0.000")&IF(Estimates!I23<0.01,"***",IF(Estimates!I23<0.05,"**",IF(Estimates!I23<0.1,"*","")))) -> -0.019 | G17: =Estimates!I23 -> 0.3121627 | H17: 1145
B18: =IF(Estimates!H20="","","("&TEXT(Estimates!H20,"0.00")&")") -> (-0.59) | C18: =IF(Estimates!H21="","","("&TEXT(Estimates!H21,"0.00")&")") -> (-0.66) | D18: =IF(Estimates!H22="","","("&TEXT(Estimates!H22,"0.00")&")") -> (-0.30) | F18: =IF(Estimates!H23="","","("&TEXT(Estimates!H23,"0.00")&")") -> (-1.04)
A19: Fixed Income Fee Rate (%) | B19: =IF(Estimates!I24="","",TEXT(Estimates!E24,"0.000")&IF(Estimates!I24<0.01,"***",IF(Estimates!I24<0.05,"**",IF(Estimates!I24<0.1,"*","")))) -> 0.061 | C19: =IF(Estimates!I25="","",TEXT(Estimates!E25,"0.000")&IF(Estimates!I25<0.01,"***",IF(Estimates!I25<0.05,"**",IF(Estimates!I25<0.1,"*","")))) -> 0.021 | D19: =IF(Estimates!I26="","",TEXT(Estimates!E26,"0.000")&IF(Estimates!I26<0.01,"***",IF(Estimates!I26<0.05,"**",IF(Estimates!I26<0.1,"*","")))) -> -0.040 | E19: =Estimates!I26 -> 0.21810851 | F19: =IF(Estimates!I27="","",TEXT(Estimates!E27,"0.000")&IF(Estimates!I27<0.01,"***",IF(Estimates!I27<0.05,"**",IF(Estimates!I27<0.1,"*","")))) -> -0.025 | G19: =Estimates!I27 -> 0.43430774 | H19: 1145
B20: =IF(Estimates!H24="","","("&TEXT(Estimates!H24,"0.00")&")") -> (1.31) | C20: =IF(Estimates!H25="","","("&TEXT(Estimates!H25,"0.00")&")") -> (0.49) | D20: =IF(Estimates!H26="","","("&TEXT(Estimates!H26,"0.00")&")") -> (-1.28) | F20: =IF(Estimates!H27="","","("&TEXT(Estimates!H27,"0.00")&")") -> (-0.80)
A21: Real Estate Fee Rate (%) | B21: =IF(Estimates!I28="","",TEXT(Estimates!E28,"0.000")&IF(Estimates!I28<0.01,"***",IF(Estimates!I28<0.05,"**",IF(Estimates!I28<0.1,"*","")))) -> -0.211 | C21: =IF(Estimates!I29="","",TEXT(Estimates!E29,"0.000")&IF(Estimates!I29<0.01,"***",IF(Estimates!I29<0.05,"**",IF(Estimates!I29<0.1,"*","")))) -> -0.146 | D21: =IF(Estimates!I30="","",TEXT(Estimates!E30,"0.000")&IF(Estimates!I30<0.01,"***",IF(Estimates!I30<0.05,"**",IF(Estimates!I30<0.1,"*","")))) -> 0.064 | E21: =Estimates!I30 -> 0.62276204 | F21: =IF(Estimates!I31="","",TEXT(Estimates!E31,"0.000")&IF(Estimates!I31<0.01,"***",IF(Estimates!I31<0.05,"**",IF(Estimates!I31<0.1,"*","")))) -> 0.054 | G21: =Estimates!I31 -> 0.67573216 | H21: 1221
B22: =IF(Estimates!H28="","","("&TEXT(Estimates!H28,"0.00")&")") -> (-1.19) | C22: =IF(Estimates!H29="","","("&TEXT(Estimates!H29,"0.00")&")") -> (-0.84) | D22: =IF(Estimates!H30="","","("&TEXT(Estimates!H30,"0.00")&")") -> (0.50) | F22: =IF(Estimates!H31="","","("&TEXT(Estimates!H31,"0.00")&")") -> (0.43)
A23: Private Equity Fee Rate (%) | B23: =IF(Estimates!I32="","",TEXT(Estimates!E32,"0.000")&IF(Estimates!I32<0.01,"***",IF(Estimates!I32<0.05,"**",IF(Estimates!I32<0.1,"*","")))) -> 0.023 | C23: =IF(Estimates!I33="","",TEXT(Estimates!E33,"0.000")&IF(Estimates!I33<0.01,"***",IF(Estimates!I33<0.05,"**",IF(Estimates!I33<0.1,"*","")))) -> -0.193 | D23: =IF(Estimates!I34="","",TEXT(Estimates!E34,"0.000")&IF(Estimates!I34<0.01,"***",IF(Estimates!I34<0.05,"**",IF(Estimates!I34<0.1,"*","")))) -> -0.215 | E23: =Estimates!I34 -> 0.36970643 | F23: =IF(Estimates!I35="","",TEXT(Estimates!E35,"0.000")&IF(Estimates!I35<0.01,"***",IF(Estimates!I35<0.05,"**",IF(Estimates!I35<0.1,"*","")))) -> -0.225 | G23: =Estimates!I35 -> 0.3706253 | H23: 1216
B24: =IF(Estimates!H32="","","("&TEXT(Estimates!H32,"0.00")&")") -> (0.09) | C24: =IF(Estimates!H33="","","("&TEXT(Estimates!H33,"0.00")&")") -> (-0.64) | D24: =IF(Estimates!H34="","","("&TEXT(Estimates!H34,"0.00")&")") -> (-0.92) | F24: =IF(Estimates!H35="","","("&TEXT(Estimates!H35,"0.00")&")") -> (-0.92)
A25: Hedge Fund Fee Rate (%) | B25: =IF(Estimates!I36="","",TEXT(Estimates!E36,"0.000")&IF(Estimates!I36<0.01,"***",IF(Estimates!I36<0.05,"**",IF(Estimates!I36<0.1,"*","")))) -> -0.244 | C25: =IF(Estimates!I37="","",TEXT(Estimates!E37,"0.000")&IF(Estimates!I37<0.01,"***",IF(Estimates!I37<0.05,"**",IF(Estimates!I37<0.1,"*","")))) -> -0.146 | D25: =IF(Estimates!I38="","",TEXT(Estimates!E38,"0.000")&IF(Estimates!I38<0.01,"***",IF(Estimates!I38<0.05,"**",IF(Estimates!I38<0.1,"*","")))) -> 0.098 | E25: =Estimates!I38 -> 0.5673215 | F25: =IF(Estimates!I39="","",TEXT(Estimates!E39,"0.000")&IF(Estimates!I39<0.01,"***",IF(Estimates!I39<0.05,"**",IF(Estimates!I39<0.1,"*","")))) -> 0.303 | G25: =Estimates!I39 -> 0.11305166 | H25: 1353
B26: =IF(Estimates!H36="","","("&TEXT(Estimates!H36,"0.00")&")") -> (-0.80) | C26: =IF(Estimates!H37="","","("&TEXT(Estimates!H37,"0.00")&")") -> (-0.47) | D26: =IF(Estimates!H38="","","("&TEXT(Estimates!H38,"0.00")&")") -> (0.58) | F26: =IF(Estimates!H39="","","("&TEXT(Estimates!H39,"0.00")&")") -> (1.67)
A27: Alternatives Share of Fees (%) | B27: =IF(Estimates!I40="","",TEXT(Estimates!E40,"0.000")&IF(Estimates!I40<0.01,"***",IF(Estimates!I40<0.05,"**",IF(Estimates!I40<0.1,"*","")))) -> 5.262 | C27: =IF(Estimates!I41="","",TEXT(Estimates!E41,"0.000")&IF(Estimates!I41<0.01,"***",IF(Estimates!I41<0.05,"**",IF(Estimates!I41<0.1,"*","")))) -> 5.406 | D27: =IF(Estimates!I42="","",TEXT(Estimates!E42,"0.000")&IF(Estimates!I42<0.01,"***",IF(Estimates!I42<0.05,"**",IF(Estimates!I42<0.1,"*","")))) -> 0.144 | E27: =Estimates!I42 -> 0.96534146 | F27: =IF(Estimates!I43="","",TEXT(Estimates!E43,"0.000")&IF(Estimates!I43<0.01,"***",IF(Estimates!I43<0.05,"**",IF(Estimates!I43<0.1,"*","")))) -> 1.034 | G27: =Estimates!I43 -> 0.77978495 | H27: 1109
B28: =IF(Estimates!H40="","","("&TEXT(Estimates!H40,"0.00")&")") -> (1.21) | C28: =IF(Estimates!H41="","","("&TEXT(Estimates!H41,"0.00")&")") -> (1.07) | D28: =IF(Estimates!H42="","","("&TEXT(Estimates!H42,"0.00")&")") -> (0.04) | F28: =IF(Estimates!H43="","","("&TEXT(Estimates!H43,"0.00")&")") -> (0.28)
A29: Allocations
A30: Alternatives Allocation (%) | B30: =IF(Estimates!I44="","",TEXT(Estimates!E44,"0.000")&IF(Estimates!I44<0.01,"***",IF(Estimates!I44<0.05,"**",IF(Estimates!I44<0.1,"*","")))) -> -3.914** | C30: =IF(Estimates!I45="","",TEXT(Estimates!E45,"0.000")&IF(Estimates!I45<0.01,"***",IF(Estimates!I45<0.05,"**",IF(Estimates!I45<0.1,"*","")))) -> -2.745 | D30: =IF(Estimates!I46="","",TEXT(Estimates!E46,"0.000")&IF(Estimates!I46<0.01,"***",IF(Estimates!I46<0.05,"**",IF(Estimates!I46<0.1,"*","")))) -> 1.169 | E30: =Estimates!I46 -> 0.51256164 | F30: =IF(Estimates!I47="","",TEXT(Estimates!E47,"0.000")&IF(Estimates!I47<0.01,"***",IF(Estimates!I47<0.05,"**",IF(Estimates!I47<0.1,"*","")))) -> 0.424 | G30: =Estimates!I47 -> 0.82927456 | H30: 1536
B31: =IF(Estimates!H44="","","("&TEXT(Estimates!H44,"0.00")&")") -> (-2.32) | C31: =IF(Estimates!H45="","","("&TEXT(Estimates!H45,"0.00")&")") -> (-1.57) | D31: =IF(Estimates!H46="","","("&TEXT(Estimates!H46,"0.00")&")") -> (0.67) | F31: =IF(Estimates!H47="","","("&TEXT(Estimates!H47,"0.00")&")") -> (0.22)
A32: Private Equity Allocation (%) | B32: =IF(Estimates!I48="","",TEXT(Estimates!E48,"0.000")&IF(Estimates!I48<0.01,"***",IF(Estimates!I48<0.05,"**",IF(Estimates!I48<0.1,"*","")))) -> 0.530 | C32: =IF(Estimates!I49="","",TEXT(Estimates!E49,"0.000")&IF(Estimates!I49<0.01,"***",IF(Estimates!I49<0.05,"**",IF(Estimates!I49<0.1,"*","")))) -> 0.326 | D32: =IF(Estimates!I50="","",TEXT(Estimates!E50,"0.000")&IF(Estimates!I50<0.01,"***",IF(Estimates!I50<0.05,"**",IF(Estimates!I50<0.1,"*","")))) -> -0.204 | E32: =Estimates!I50 -> 0.77860157 | F32: =IF(Estimates!I51="","",TEXT(Estimates!E51,"0.000")&IF(Estimates!I51<0.01,"***",IF(Estimates!I51<0.05,"**",IF(Estimates!I51<0.1,"*","")))) -> 0.261 | G32: =Estimates!I51 -> 0.6914002 | H32: 1536
B33: =IF(Estimates!H48="","","("&TEXT(Estimates!H48,"0.00")&")") -> (0.59) | C33: =IF(Estimates!H49="","","("&TEXT(Estimates!H49,"0.00")&")") -> (0.41) | D33: =IF(Estimates!H50="","","("&TEXT(Estimates!H50,"0.00")&")") -> (-0.29) | F33: =IF(Estimates!H51="","","("&TEXT(Estimates!H51,"0.00")&")") -> (0.40)
A34: Hedge Fund Allocation (%) | B34: =IF(Estimates!I52="","",TEXT(Estimates!E52,"0.000")&IF(Estimates!I52<0.01,"***",IF(Estimates!I52<0.05,"**",IF(Estimates!I52<0.1,"*","")))) -> -0.992 | C34: =IF(Estimates!I53="","",TEXT(Estimates!E53,"0.000")&IF(Estimates!I53<0.01,"***",IF(Estimates!I53<0.05,"**",IF(Estimates!I53<0.1,"*","")))) -> -0.865 | D34: =IF(Estimates!I54="","",TEXT(Estimates!E54,"0.000")&IF(Estimates!I54<0.01,"***",IF(Estimates!I54<0.05,"**",IF(Estimates!I54<0.1,"*","")))) -> 0.128 | E34: =Estimates!I54 -> 0.83929822 | F34: =IF(Estimates!I55="","",TEXT(Estimates!E55,"0.000")&IF(Estimates!I55<0.01,"***",IF(Estimates!I55<0.05,"**",IF(Estimates!I55<0.1,"*","")))) -> -0.458 | G34: =Estimates!I55 -> 0.59187377 | H34: 1536
B35: =IF(Estimates!H52="","","("&TEXT(Estimates!H52,"0.00")&")") -> (-1.19) | C35: =IF(Estimates!H53="","","("&TEXT(Estimates!H53,"0.00")&")") -> (-1.00) | D35: =IF(Estimates!H54="","","("&TEXT(Estimates!H54,"0.00")&")") -> (0.21) | F35: =IF(Estimates!H55="","","("&TEXT(Estimates!H55,"0.00")&")") -> (-0.55)

Sheet B. within conflicted CIOs
A1: Conflicted CIOs Compared With Themselves: Second Half of Tenure
A2: Sample: conflicted CIOs who have left (curr = 0) with defined halves (356 plan-years, 45 CIOs; 195 first-half and 161 second-half plan-years). Each cell is the coefficient on Second Half (0/1) from a regression of the outcome on Second Half, the controls, and the fixed effects shown; CIO fixed effects are CIO-by-plan spells, so columns 2-3 compare each CIO with themselves. Column 3 keeps CIOs with tenure at departure of at least four years (25 CIOs). Because a CIO's tenure and calendar time move together, CIO and fiscal-year-end fixed effects together leave only differences in when CIOs' halves fall to identify Second Half. The second half of a CIO's tenure is the years in which tenure exceeds half of tenure at departure (tenure at departure = the CIO's maximum tenure at the plan plus any gap to the departure year). Controls for returns and fees: lagged return, Size, lagged funding ratio, lagged allocations, Financial Center, prior private experience, elite college, separate investment board and political appointees; allocation outcomes omit the lagged allocations. Lagged log CIO tenure and age are omitted from all specifications because tenure rises mechanically from the first to the second half. Standard errors are double clustered by plan and year. Coefficients marked with ***, **, and * are significant at the 1%, 5%, and 10% level, respectively.
B4: Second Half of Tenure (0/1) | E4: Observations
B5: Fiscal-Year-End FE | C5: CIO and Fiscal-Year-End FE | D5: CIO and FYE FE, tenure >= 4 | E5: (1) | F5: (2)
A6: Returns
A7: Peer-Adjusted Return (%) | B7: =IF(Estimates!I56="","",TEXT(Estimates!E56,"0.000")&IF(Estimates!I56<0.01,"***",IF(Estimates!I56<0.05,"**",IF(Estimates!I56<0.1,"*","")))) -> -0.059 | C7: =IF(Estimates!I57="","",TEXT(Estimates!E57,"0.000")&IF(Estimates!I57<0.01,"***",IF(Estimates!I57<0.05,"**",IF(Estimates!I57<0.1,"*","")))) -> -0.776 | D7: =IF(Estimates!I58="","",TEXT(Estimates!E58,"0.000")&IF(Estimates!I58<0.01,"***",IF(Estimates!I58<0.05,"**",IF(Estimates!I58<0.1,"*","")))) -> -0.238 | E7: 274 | F7: 261
B8: =IF(Estimates!H56="","","("&TEXT(Estimates!H56,"0.00")&")") -> (-0.33) | C8: =IF(Estimates!H57="","","("&TEXT(Estimates!H57,"0.00")&")") -> (-1.41) | D8: =IF(Estimates!H58="","","("&TEXT(Estimates!H58,"0.00")&")") -> (-0.24)
A9: Benchmark-Adjusted Return (%) | B9: =IF(Estimates!I59="","",TEXT(Estimates!E59,"0.000")&IF(Estimates!I59<0.01,"***",IF(Estimates!I59<0.05,"**",IF(Estimates!I59<0.1,"*","")))) -> 0.197 | C9: =IF(Estimates!I60="","",TEXT(Estimates!E60,"0.000")&IF(Estimates!I60<0.01,"***",IF(Estimates!I60<0.05,"**",IF(Estimates!I60<0.1,"*","")))) -> -0.126 | D9: =IF(Estimates!I61="","",TEXT(Estimates!E61,"0.000")&IF(Estimates!I61<0.01,"***",IF(Estimates!I61<0.05,"**",IF(Estimates!I61<0.1,"*","")))) -> -0.170 | E9: 254 | F9: 242
B10: =IF(Estimates!H59="","","("&TEXT(Estimates!H59,"0.00")&")") -> (0.69) | C10: =IF(Estimates!H60="","","("&TEXT(Estimates!H60,"0.00")&")") -> (-0.30) | D10: =IF(Estimates!H61="","","("&TEXT(Estimates!H61,"0.00")&")") -> (-0.35)
A11: Fees
A12: Fee Ratio (%) | B12: =IF(Estimates!I62="","",TEXT(Estimates!E62,"0.000")&IF(Estimates!I62<0.01,"***",IF(Estimates!I62<0.05,"**",IF(Estimates!I62<0.1,"*","")))) -> -0.086* | C12: =IF(Estimates!I63="","",TEXT(Estimates!E63,"0.000")&IF(Estimates!I63<0.01,"***",IF(Estimates!I63<0.05,"**",IF(Estimates!I63<0.1,"*","")))) -> -0.068 | D12: =IF(Estimates!I64="","",TEXT(Estimates!E64,"0.000")&IF(Estimates!I64<0.01,"***",IF(Estimates!I64<0.05,"**",IF(Estimates!I64<0.1,"*","")))) -> -0.021 | E12: 251 | F12: 238
B13: =IF(Estimates!H62="","","("&TEXT(Estimates!H62,"0.00")&")") -> (-1.83) | C13: =IF(Estimates!H63="","","("&TEXT(Estimates!H63,"0.00")&")") -> (-1.12) | D13: =IF(Estimates!H64="","","("&TEXT(Estimates!H64,"0.00")&")") -> (-0.27)
A14: Expense Ratio (%) | B14: =IF(Estimates!I65="","",TEXT(Estimates!E65,"0.000")&IF(Estimates!I65<0.01,"***",IF(Estimates!I65<0.05,"**",IF(Estimates!I65<0.1,"*","")))) -> 0.006 | C14: =IF(Estimates!I66="","",TEXT(Estimates!E66,"0.000")&IF(Estimates!I66<0.01,"***",IF(Estimates!I66<0.05,"**",IF(Estimates!I66<0.1,"*","")))) -> 0.014 | D14: =IF(Estimates!I67="","",TEXT(Estimates!E67,"0.000")&IF(Estimates!I67<0.01,"***",IF(Estimates!I67<0.05,"**",IF(Estimates!I67<0.1,"*","")))) -> 0.032 | E14: 264 | F14: 250
B15: =IF(Estimates!H65="","","("&TEXT(Estimates!H65,"0.00")&")") -> (0.18) | C15: =IF(Estimates!H66="","","("&TEXT(Estimates!H66,"0.00")&")") -> (0.54) | D15: =IF(Estimates!H67="","","("&TEXT(Estimates!H67,"0.00")&")") -> (0.90)
A16: Fee rates by asset class
A17: Equity Fee Rate (%) | B17: =IF(Estimates!I68="","",TEXT(Estimates!E68,"0.000")&IF(Estimates!I68<0.01,"***",IF(Estimates!I68<0.05,"**",IF(Estimates!I68<0.1,"*","")))) -> -0.013 | C17: =IF(Estimates!I69="","",TEXT(Estimates!E69,"0.000")&IF(Estimates!I69<0.01,"***",IF(Estimates!I69<0.05,"**",IF(Estimates!I69<0.1,"*","")))) -> 0.012 | D17: =IF(Estimates!I70="","",TEXT(Estimates!E70,"0.000")&IF(Estimates!I70<0.01,"***",IF(Estimates!I70<0.05,"**",IF(Estimates!I70<0.1,"*","")))) -> 0.039** | E17: 229 | F17: 218
B18: =IF(Estimates!H68="","","("&TEXT(Estimates!H68,"0.00")&")") -> (-0.85) | C18: =IF(Estimates!H69="","","("&TEXT(Estimates!H69,"0.00")&")") -> (0.85) | D18: =IF(Estimates!H70="","","("&TEXT(Estimates!H70,"0.00")&")") -> (2.35)
A19: Fixed Income Fee Rate (%) | B19: =IF(Estimates!I71="","",TEXT(Estimates!E71,"0.000")&IF(Estimates!I71<0.01,"***",IF(Estimates!I71<0.05,"**",IF(Estimates!I71<0.1,"*","")))) -> -0.089 | C19: =IF(Estimates!I72="","",TEXT(Estimates!E72,"0.000")&IF(Estimates!I72<0.01,"***",IF(Estimates!I72<0.05,"**",IF(Estimates!I72<0.1,"*","")))) -> -0.062 | D19: =IF(Estimates!I73="","",TEXT(Estimates!E73,"0.000")&IF(Estimates!I73<0.01,"***",IF(Estimates!I73<0.05,"**",IF(Estimates!I73<0.1,"*","")))) -> 0.007 | E19: 229 | F19: 218
B20: =IF(Estimates!H71="","","("&TEXT(Estimates!H71,"0.00")&")") -> (-1.70) | C20: =IF(Estimates!H72="","","("&TEXT(Estimates!H72,"0.00")&")") -> (-1.13) | D20: =IF(Estimates!H73="","","("&TEXT(Estimates!H73,"0.00")&")") -> (0.09)
A21: Real Estate Fee Rate (%) | B21: =IF(Estimates!I74="","",TEXT(Estimates!E74,"0.000")&IF(Estimates!I74<0.01,"***",IF(Estimates!I74<0.05,"**",IF(Estimates!I74<0.1,"*","")))) -> -0.278** | C21: =IF(Estimates!I75="","",TEXT(Estimates!E75,"0.000")&IF(Estimates!I75<0.01,"***",IF(Estimates!I75<0.05,"**",IF(Estimates!I75<0.1,"*","")))) -> -0.243** | D21: =IF(Estimates!I76="","",TEXT(Estimates!E76,"0.000")&IF(Estimates!I76<0.01,"***",IF(Estimates!I76<0.05,"**",IF(Estimates!I76<0.1,"*","")))) -> -0.255 | E21: 252 | F21: 241
B22: =IF(Estimates!H74="","","("&TEXT(Estimates!H74,"0.00")&")") -> (-2.40) | C22: =IF(Estimates!H75="","","("&TEXT(Estimates!H75,"0.00")&")") -> (-2.17) | D22: =IF(Estimates!H76="","","("&TEXT(Estimates!H76,"0.00")&")") -> (-1.23)
A23: Private Equity Fee Rate (%) | B23: =IF(Estimates!I77="","",TEXT(Estimates!E77,"0.000")&IF(Estimates!I77<0.01,"***",IF(Estimates!I77<0.05,"**",IF(Estimates!I77<0.1,"*","")))) -> -0.676* | C23: =IF(Estimates!I78="","",TEXT(Estimates!E78,"0.000")&IF(Estimates!I78<0.01,"***",IF(Estimates!I78<0.05,"**",IF(Estimates!I78<0.1,"*","")))) -> -0.853** | D23: =IF(Estimates!I79="","",TEXT(Estimates!E79,"0.000")&IF(Estimates!I79<0.01,"***",IF(Estimates!I79<0.05,"**",IF(Estimates!I79<0.1,"*","")))) -> -1.760* | E23: 248 | F23: 237
B24: =IF(Estimates!H77="","","("&TEXT(Estimates!H77,"0.00")&")") -> (-1.97) | C24: =IF(Estimates!H78="","","("&TEXT(Estimates!H78,"0.00")&")") -> (-2.22) | D24: =IF(Estimates!H79="","","("&TEXT(Estimates!H79,"0.00")&")") -> (-1.82)
A25: Hedge Fund Fee Rate (%) | B25: =IF(Estimates!I80="","",TEXT(Estimates!E80,"0.000")&IF(Estimates!I80<0.01,"***",IF(Estimates!I80<0.05,"**",IF(Estimates!I80<0.1,"*","")))) -> -0.216 | C25: =IF(Estimates!I81="","",TEXT(Estimates!E81,"0.000")&IF(Estimates!I81<0.01,"***",IF(Estimates!I81<0.05,"**",IF(Estimates!I81<0.1,"*","")))) -> -0.119 | D25: =IF(Estimates!I82="","",TEXT(Estimates!E82,"0.000")&IF(Estimates!I82<0.01,"***",IF(Estimates!I82<0.05,"**",IF(Estimates!I82<0.1,"*","")))) -> -0.184 | E25: 270 | F25: 257
B26: =IF(Estimates!H80="","","("&TEXT(Estimates!H80,"0.00")&")") -> (-1.50) | C26: =IF(Estimates!H81="","","("&TEXT(Estimates!H81,"0.00")&")") -> (-0.53) | D26: =IF(Estimates!H82="","","("&TEXT(Estimates!H82,"0.00")&")") -> (-1.01)
A27: Alternatives Share of Fees (%) | B27: =IF(Estimates!I83="","",TEXT(Estimates!E83,"0.000")&IF(Estimates!I83<0.01,"***",IF(Estimates!I83<0.05,"**",IF(Estimates!I83<0.1,"*","")))) -> -4.381 | C27: =IF(Estimates!I84="","",TEXT(Estimates!E84,"0.000")&IF(Estimates!I84<0.01,"***",IF(Estimates!I84<0.05,"**",IF(Estimates!I84<0.1,"*","")))) -> -5.616 | D27: =IF(Estimates!I85="","",TEXT(Estimates!E85,"0.000")&IF(Estimates!I85<0.01,"***",IF(Estimates!I85<0.05,"**",IF(Estimates!I85<0.1,"*","")))) -> -16.568 | E27: 230 | F27: 218
B28: =IF(Estimates!H83="","","("&TEXT(Estimates!H83,"0.00")&")") -> (-1.05) | C28: =IF(Estimates!H84="","","("&TEXT(Estimates!H84,"0.00")&")") -> (-1.24) | D28: =IF(Estimates!H85="","","("&TEXT(Estimates!H85,"0.00")&")") -> (-1.56)
A29: Allocations
A30: Alternatives Allocation (%) | B30: =IF(Estimates!I86="","",TEXT(Estimates!E86,"0.000")&IF(Estimates!I86<0.01,"***",IF(Estimates!I86<0.05,"**",IF(Estimates!I86<0.1,"*","")))) -> 0.416 | C30: =IF(Estimates!I87="","",TEXT(Estimates!E87,"0.000")&IF(Estimates!I87<0.01,"***",IF(Estimates!I87<0.05,"**",IF(Estimates!I87<0.1,"*","")))) -> -2.229* | D30: =IF(Estimates!I88="","",TEXT(Estimates!E88,"0.000")&IF(Estimates!I88<0.01,"***",IF(Estimates!I88<0.05,"**",IF(Estimates!I88<0.1,"*","")))) -> -3.528** | E30: 277 | F30: 266
B31: =IF(Estimates!H86="","","("&TEXT(Estimates!H86,"0.00")&")") -> (0.29) | C31: =IF(Estimates!H87="","","("&TEXT(Estimates!H87,"0.00")&")") -> (-2.06) | D31: =IF(Estimates!H88="","","("&TEXT(Estimates!H88,"0.00")&")") -> (-2.39)
A32: Private Equity Allocation (%) | B32: =IF(Estimates!I89="","",TEXT(Estimates!E89,"0.000")&IF(Estimates!I89<0.01,"***",IF(Estimates!I89<0.05,"**",IF(Estimates!I89<0.1,"*","")))) -> 0.214 | C32: =IF(Estimates!I90="","",TEXT(Estimates!E90,"0.000")&IF(Estimates!I90<0.01,"***",IF(Estimates!I90<0.05,"**",IF(Estimates!I90<0.1,"*","")))) -> -0.819* | D32: =IF(Estimates!I91="","",TEXT(Estimates!E91,"0.000")&IF(Estimates!I91<0.01,"***",IF(Estimates!I91<0.05,"**",IF(Estimates!I91<0.1,"*","")))) -> -1.242* | E32: 277 | F32: 266
B33: =IF(Estimates!H89="","","("&TEXT(Estimates!H89,"0.00")&")") -> (0.40) | C33: =IF(Estimates!H90="","","("&TEXT(Estimates!H90,"0.00")&")") -> (-1.99) | D33: =IF(Estimates!H91="","","("&TEXT(Estimates!H91,"0.00")&")") -> (-1.80)
A34: Hedge Fund Allocation (%) | B34: =IF(Estimates!I92="","",TEXT(Estimates!E92,"0.000")&IF(Estimates!I92<0.01,"***",IF(Estimates!I92<0.05,"**",IF(Estimates!I92<0.1,"*","")))) -> -0.321 | C34: =IF(Estimates!I93="","",TEXT(Estimates!E93,"0.000")&IF(Estimates!I93<0.01,"***",IF(Estimates!I93<0.05,"**",IF(Estimates!I93<0.1,"*","")))) -> -0.802 | D34: =IF(Estimates!I94="","",TEXT(Estimates!E94,"0.000")&IF(Estimates!I94<0.01,"***",IF(Estimates!I94<0.05,"**",IF(Estimates!I94<0.1,"*","")))) -> -1.481* | E34: 277 | F34: 266
B35: =IF(Estimates!H92="","","("&TEXT(Estimates!H92,"0.00")&")") -> (-0.55) | C35: =IF(Estimates!H93="","","("&TEXT(Estimates!H93,"0.00")&")") -> (-1.25) | D35: =IF(Estimates!H94="","","("&TEXT(Estimates!H94,"0.00")&")") -> (-1.74)

Sheet C. CIO-level paired
A1: CIO-Level Paired Comparison: Second-Half Mean minus First-Half Mean
A2: Each conflicted CIO who has left contributes one observation: the outcome averaged over plans within each CIO-year, then over the years in each half of tenure. Columns report the number of CIOs observed in both halves, the mean of the first- and second-half averages, the mean difference, p-values from a paired t-test and a Wilcoxon signed-rank test, and the share of CIOs whose second-half average exceeds their first-half average. These comparisons do not adjust for calendar time, so they include sample-wide trends (fees and alternatives allocations rise over 2001-2020); Sheets A and B adjust for them with fiscal-year-end fixed effects. The second half of a CIO's tenure is the years in which tenure exceeds half of tenure at departure (tenure at departure = the CIO's maximum tenure at the plan plus any gap to the departure year).
B5: CIOs | C5: First-half mean | D5: Second-half mean | E5: Difference | F5: Paired t-test p | G5: Signed-rank p | H5: Share increasing
A6: Returns
A7: Peer-Adjusted Return (%) | B7: 37 | C7: -0.49672251 | D7: -0.2354691 | E7: 0.26125341 | F7: 0.55784542 | G7: 0.37772693 | H7: 0.62162162
A8: Benchmark-Adjusted Return (%) | B8: 30 | C8: 0.044924868 | D8: 0.18198519 | E8: 0.13706032 | F8: 0.77403846 | G8: 1 | H8: 0.5
A9: Fees
A10: Fee Ratio (%) | B10: 35 | C10: 0.29333454 | D10: 0.35688809 | E10: 0.06355355 | F10: 0.031975505 | G10: 0.030007007 | H10: 0.65714286
A11: Expense Ratio (%) | B11: 36 | C11: 0.28700929 | D11: 0.32957708 | E11: 0.042567794 | F11: 0.068700341 | G11: 0.069239827 | H11: 0.66666667
A12: Fee rates by asset class
A13: Equity Fee Rate (%) | B13: 28 | C13: 0.28606633 | D13: 0.32824674 | E13: 0.042180414 | F13: 0.40494142 | G13: 0.88417576 | H13: 0.53571429
A14: Fixed Income Fee Rate (%) | B14: 28 | C14: 0.24240105 | D14: 0.26126874 | E14: 0.018867688 | F14: 0.60019743 | G14: 0.30156882 | H14: 0.57142857
A15: Real Estate Fee Rate (%) | B15: 32 | C15: 0.51702696 | D15: 0.62188098 | E15: 0.10485403 | F15: 0.34421032 | G15: 0.2528129 | H15: 0.46875
A16: Private Equity Fee Rate (%) | B16: 29 | C16: 0.87678235 | D16: 1.0678516 | E16: 0.19106922 | F16: 0.22474371 | G16: 0.39053287 | H16: 0.37931034
A17: Hedge Fund Fee Rate (%) | B17: 34 | C17: 0.15590285 | D17: 0.46563609 | E17: 0.30973324 | F17: 0.058477576 | G17: 0.0035103637 | H17: 0.38235294
A18: Alternatives Share of Fees (%) | B18: 29 | C18: 33.351604 | D18: 41.526091 | E18: 8.1744874 | F18: 0.058094441 | G18: 0.0015273616 | H18: 0.82758621
A19: Allocations
A20: Alternatives Allocation (%) | B20: 34 | C20: 15.014747 | D20: 18.904284 | E20: 3.8895373 | F20: 0.0043396514 | G20: 0.012058423 | H20: 0.64705882
A21: Private Equity Allocation (%) | B21: 34 | C21: 5.4248331 | D21: 6.2383029 | E21: 0.81346982 | F21: 0.13600608 | G21: 0.19861021 | H21: 0.55882353
A22: Hedge Fund Allocation (%) | B22: 34 | C22: 3.2815091 | D22: 4.3442782 | E22: 1.0627691 | F22: 0.14616691 | G22: 0.15695519 | H22: 0.35294118

Sheet Estimates
A1: Estimates behind the tables. Blue = regression output (coefficient, SE, minimum cluster count). t and p are formulas; p uses the t distribution with (min clusters - 1) df. SE double clustered by plan and year, with the eigenvalue fix.
A3: Table | B3: Outcome | C3: Specification | D3: Term | E3: Coefficient | F3: SE | G3: Clusters (min) | H3: t | I3: p
A4: A | B4: Peer-Adjusted Return (%) | C4: FYE FE | D4: First half | E4: -0.64801235 | F4: 0.21867022 | G4: 19 | H4: =IF(AND(ISNUMBER(E4),F4>0),E4/F4,"") -> -2.9634229 | I4: =IF(H4="","",TDIST(ABS(H4),G4-1,2)) -> 0.0083208977
A5: A | B5: Peer-Adjusted Return (%) | C5: FYE FE | D5: Second half | E5: -0.52948833 | F5: 0.22789693 | G5: 19 | H5: =IF(AND(ISNUMBER(E5),F5>0),E5/F5,"") -> -2.3233675 | I5: =IF(H5="","",TDIST(ABS(H5),G5-1,2)) -> 0.032072184
A6: A | B6: Peer-Adjusted Return (%) | C6: FYE FE | D6: Second minus first | E6: 0.11852403 | F6: 0.20320711 | G6: 19 | H6: =IF(AND(ISNUMBER(E6),F6>0),E6/F6,"") -> 0.58326714 | I6: =IF(H6="","",TDIST(ABS(H6),G6-1,2)) -> 0.5669504
A7: A | B7: Peer-Adjusted Return (%) | C7: Plan + FYE FE | D7: Second minus first | E7: 0.28477446 | F7: 0.20192412 | G7: 19 | H7: =IF(AND(ISNUMBER(E7),F7>0),E7/F7,"") -> 1.4103043 | I7: =IF(H7="","",TDIST(ABS(H7),G7-1,2)) -> 0.17549705
A8: A | B8: Benchmark-Adjusted Return (%) | C8: FYE FE | D8: First half | E8: -0.6812582 | F8: 0.23192525 | G8: 19 | H8: =IF(AND(ISNUMBER(E8),F8>0),E8/F8,"") -> -2.9374042 | I8: =IF(H8="","",TDIST(ABS(H8),G8-1,2)) -> 0.0088036421
A9: A | B9: Benchmark-Adjusted Return (%) | C9: FYE FE | D9: Second half | E9: -0.30708833 | F9: 0.17428479 | G9: 19 | H9: =IF(AND(ISNUMBER(E9),F9>0),E9/F9,"") -> -1.7619915 | I9: =IF(H9="","",TDIST(ABS(H9),G9-1,2)) -> 0.095044673
A10: A | B10: Benchmark-Adjusted Return (%) | C10: FYE FE | D10: Second minus first | E10: 0.37416987 | F10: 0.18067663 | G10: 19 | H10: =IF(AND(ISNUMBER(E10),F10>0),E10/F10,"") -> 2.0709368 | I10: =IF(H10="","",TDIST(ABS(H10),G10-1,2)) -> 0.053017247
A11: A | B11: Benchmark-Adjusted Return (%) | C11: Plan + FYE FE | D11: Second minus first | E11: 0.44562218 | F11: 0.22123353 | G11: 19 | H11: =IF(AND(ISNUMBER(E11),F11>0),E11/F11,"") -> 2.0142614 | I11: =IF(H11="","",TDIST(ABS(H11),G11-1,2)) -> 0.059174055
A12: A | B12: Fee Ratio (%) | C12: FYE FE | D12: First half | E12: -0.02871574 | F12: 0.051760352 | G12: 19 | H12: =IF(AND(ISNUMBER(E12),F12>0),E12/F12,"") -> -0.55478255 | I12: =IF(H12="","",TDIST(ABS(H12),G12-1,2)) -> 0.58587188
A13: A | B13: Fee Ratio (%) | C13: FYE FE | D13: Second half | E13: -0.043311407 | F13: 0.044332179 | G13: 19 | H13: =IF(AND(ISNUMBER(E13),F13>0),E13/F13,"") -> -0.97697445 | I13: =IF(H13="","",TDIST(ABS(H13),G13-1,2)) -> 0.34153036
A14: A | B14: Fee Ratio (%) | C14: FYE FE | D14: Second minus first | E14: -0.014595666 | F14: 0.04130258 | G14: 19 | H14: =IF(AND(ISNUMBER(E14),F14>0),E14/F14,"") -> -0.35338389 | I14: =IF(H14="","",TDIST(ABS(H14),G14-1,2)) -> 0.72790565
A15: A | B15: Fee Ratio (%) | C15: Plan + FYE FE | D15: Second minus first | E15: 0.003770194 | F15: 0.038077003 | G15: 19 | H15: =IF(AND(ISNUMBER(E15),F15>0),E15/F15,"") -> 0.099014987 | I15: =IF(H15="","",TDIST(ABS(H15),G15-1,2)) -> 0.92222074
... A94: B | B94: Hedge Fund Allocation (%) | C94: CIO + FYE FE, tenure>=4 | D94: Second half | E94: -1.4809955 | F94: 0.84887515 | G94: 18 | H94: =IF(AND(ISNUMBER(E94),F94>0),E94/F94,"") -> -1.7446564 | I94: =IF(H94="","",TDIST(ABS(H94),G94-1,2)) -> 0.099094776
