Workbook

Sheet Table XI-split
A1: Table XI: Conflicted CIOs: Plan Performance in the First versus Second Half of Tenure (updated benchmark, fiscal-year-end fixed effects)
A2: This table repeats the regressions of Table III, splitting the Conflicted CIO indicator into two indicators: Conflicted CIO x First Half of Tenure, equal to 1 in the fiscal years in which a conflicted CIO's tenure is at most one half of the CIO's tenure at departure, and Conflicted CIO x Second Half of Tenure, equal to 1 in the remaining fiscal years of a conflicted CIO's tenure. The omitted category is all plan-years run by non-conflicted CIOs, so each coefficient is the performance differential of conflicted CIOs in that part of their tenure relative to non-conflicted CIOs. Tenure at departure is the CIO's tenure in the last fiscal year observed in the plan plus any gap to the departure year. 11 conflicted plan-years for which tenure at departure cannot be determined are absorbed by a separate indicator that is not reported. The performance measure in Panel A is Peer-Adjusted Return, which is the difference of a plan's return and the average pension plan return each year. The performance measure in Panel B is Benchmark-Adjusted Return, which is calculated as the plan's return minus the return of its updated policy benchmark (the benchmark return reported in the plan's financial report or, where none is stated, an inferred value graded A or B). The other independent variables are as defined in Table I. All columns include fiscal-year-end date fixed effects, so plans are compared only with plans whose fiscal year covers the same twelve months. Column 3 adds plan fixed effects. The last row reports the p-value of a test that the first-half and second-half coefficients are equal. The standard errors are double clustered by plan and year. Coefficients marked with ***, **, and * are significant at the 1%, 5%, and 10% level, respectively.
A4: Panel A. Peer-Adjusted Returns
B5: (1) | C5: (2) | D5: (3)
B6: Peer-adj. Ret. (t) | C6: Peer-adj. Ret. (t) | D6: Peer-adj. Ret. (t)
A7: Conflicted CIO x First Half of Tenure (0/1) | B7: =TEXT('Estimates-split'!B4,"0.000")&IF('Estimates-split'!E4="","",IF('Estimates-split'!E4<0.01,"***",IF('Estimates-split'!E4<0.05,"**",IF('Estimates-split'!E4<0.1,"*","")))) -> -0.474** | C7: =TEXT('Estimates-split'!F4,"0.000")&IF('Estimates-split'!I4="","",IF('Estimates-split'!I4<0.01,"***",IF('Estimates-split'!I4<0.05,"**",IF('Estimates-split'!I4<0.1,"*","")))) -> -0.497* | D7: =TEXT('Estimates-split'!J4,"0.000")&IF('Estimates-split'!M4="","",IF('Estimates-split'!M4<0.01,"***",IF('Estimates-split'!M4<0.05,"**",IF('Estimates-split'!M4<0.1,"*","")))) -> -0.845**
B8: =IF('Estimates-split'!D4="","(n/a)","("&TEXT('Estimates-split'!D4,"0.00")&")") -> (-2.51) | C8: =IF('Estimates-split'!H4="","(n/a)","("&TEXT('Estimates-split'!H4,"0.00")&")") -> (-2.10) | D8: =IF('Estimates-split'!L4="","(n/a)","("&TEXT('Estimates-split'!L4,"0.00")&")") -> (-2.29)
A9: Conflicted CIO x Second Half of Tenure (0/1) | B9: =TEXT('Estimates-split'!B5,"0.000")&IF('Estimates-split'!E5="","",IF('Estimates-split'!E5<0.01,"***",IF('Estimates-split'!E5<0.05,"**",IF('Estimates-split'!E5<0.1,"*","")))) -> -0.596*** | C9: =TEXT('Estimates-split'!F5,"0.000")&IF('Estimates-split'!I5="","",IF('Estimates-split'!I5<0.01,"***",IF('Estimates-split'!I5<0.05,"**",IF('Estimates-split'!I5<0.1,"*","")))) -> -0.536** | D9: =TEXT('Estimates-split'!J5,"0.000")&IF('Estimates-split'!M5="","",IF('Estimates-split'!M5<0.01,"***",IF('Estimates-split'!M5<0.05,"**",IF('Estimates-split'!M5<0.1,"*","")))) -> -0.644*
B10: =IF('Estimates-split'!D5="","(n/a)","("&TEXT('Estimates-split'!D5,"0.00")&")") -> (-3.32) | C10: =IF('Estimates-split'!H5="","(n/a)","("&TEXT('Estimates-split'!H5,"0.00")&")") -> (-2.56) | D10: =IF('Estimates-split'!L5="","(n/a)","("&TEXT('Estimates-split'!L5,"0.00")&")") -> (-2.02)
A11: Investment Return (t - 1) | B11: =TEXT('Estimates-split'!B6,"0.000")&IF('Estimates-split'!E6="","",IF('Estimates-split'!E6<0.01,"***",IF('Estimates-split'!E6<0.05,"**",IF('Estimates-split'!E6<0.1,"*","")))) -> 0.119 | C11: =TEXT('Estimates-split'!F6,"0.000")&IF('Estimates-split'!I6="","",IF('Estimates-split'!I6<0.01,"***",IF('Estimates-split'!I6<0.05,"**",IF('Estimates-split'!I6<0.1,"*","")))) -> 0.091 | D11: =TEXT('Estimates-split'!J6,"0.000")&IF('Estimates-split'!M6="","",IF('Estimates-split'!M6<0.01,"***",IF('Estimates-split'!M6<0.05,"**",IF('Estimates-split'!M6<0.1,"*","")))) -> 0.030
B12: =IF('Estimates-split'!D6="","(n/a)","("&TEXT('Estimates-split'!D6,"0.00")&")") -> (1.55) | C12: =IF('Estimates-split'!H6="","(n/a)","("&TEXT('Estimates-split'!H6,"0.00")&")") -> (1.16) | D12: =IF('Estimates-split'!L6="","(n/a)","("&TEXT('Estimates-split'!L6,"0.00")&")") -> (0.40)
A13: Log (Plan Size) (t-1) | B13: =TEXT('Estimates-split'!B7,"0.000")&IF('Estimates-split'!E7="","",IF('Estimates-split'!E7<0.01,"***",IF('Estimates-split'!E7<0.05,"**",IF('Estimates-split'!E7<0.1,"*","")))) -> 0.013 | C13: =TEXT('Estimates-split'!F7,"0.000")&IF('Estimates-split'!I7="","",IF('Estimates-split'!I7<0.01,"***",IF('Estimates-split'!I7<0.05,"**",IF('Estimates-split'!I7<0.1,"*","")))) -> 0.072 | D13: =TEXT('Estimates-split'!J7,"0.000")&IF('Estimates-split'!M7="","",IF('Estimates-split'!M7<0.01,"***",IF('Estimates-split'!M7<0.05,"**",IF('Estimates-split'!M7<0.1,"*","")))) -> -1.428*
B14: =IF('Estimates-split'!D7="","(n/a)","("&TEXT('Estimates-split'!D7,"0.00")&")") -> (0.26) | C14: =IF('Estimates-split'!H7="","(n/a)","("&TEXT('Estimates-split'!H7,"0.00")&")") -> (1.27) | D14: =IF('Estimates-split'!L7="","(n/a)","("&TEXT('Estimates-split'!L7,"0.00")&")") -> (-1.77)
A15: Funding Ratio (t-1) | B15: =TEXT('Estimates-split'!B8,"0.000")&IF('Estimates-split'!E8="","",IF('Estimates-split'!E8<0.01,"***",IF('Estimates-split'!E8<0.05,"**",IF('Estimates-split'!E8<0.1,"*","")))) -> -0.004 | C15: =TEXT('Estimates-split'!F8,"0.000")&IF('Estimates-split'!I8="","",IF('Estimates-split'!I8<0.01,"***",IF('Estimates-split'!I8<0.05,"**",IF('Estimates-split'!I8<0.1,"*","")))) -> -0.006 | D15: =TEXT('Estimates-split'!J8,"0.000")&IF('Estimates-split'!M8="","",IF('Estimates-split'!M8<0.01,"***",IF('Estimates-split'!M8<0.05,"**",IF('Estimates-split'!M8<0.1,"*","")))) -> -0.030**
B16: =IF('Estimates-split'!D8="","(n/a)","("&TEXT('Estimates-split'!D8,"0.00")&")") -> (-0.94) | C16: =IF('Estimates-split'!H8="","(n/a)","("&TEXT('Estimates-split'!H8,"0.00")&")") -> (-1.00) | D16: =IF('Estimates-split'!L8="","(n/a)","("&TEXT('Estimates-split'!L8,"0.00")&")") -> (-2.68)
A17: Equity Allocation (%) | B17: =TEXT('Estimates-split'!B9,"0.000")&IF('Estimates-split'!E9="","",IF('Estimates-split'!E9<0.01,"***",IF('Estimates-split'!E9<0.05,"**",IF('Estimates-split'!E9<0.1,"*","")))) -> -0.073 | C17: =TEXT('Estimates-split'!F9,"0.000")&IF('Estimates-split'!I9="","",IF('Estimates-split'!I9<0.01,"***",IF('Estimates-split'!I9<0.05,"**",IF('Estimates-split'!I9<0.1,"*","")))) -> -0.012 | D17: =TEXT('Estimates-split'!J9,"0.000")&IF('Estimates-split'!M9="","",IF('Estimates-split'!M9<0.01,"***",IF('Estimates-split'!M9<0.05,"**",IF('Estimates-split'!M9<0.1,"*","")))) -> -0.035
B18: =IF('Estimates-split'!D9="","(n/a)","("&TEXT('Estimates-split'!D9,"0.00")&")") -> (-0.58) | C18: =IF('Estimates-split'!H9="","(n/a)","("&TEXT('Estimates-split'!H9,"0.00")&")") -> (-0.21) | D18: =IF('Estimates-split'!L9="","(n/a)","("&TEXT('Estimates-split'!L9,"0.00")&")") -> (-0.40)
A19: Fixed Income Allocation (%) | B19: =TEXT('Estimates-split'!B10,"0.000")&IF('Estimates-split'!E10="","",IF('Estimates-split'!E10<0.01,"***",IF('Estimates-split'!E10<0.05,"**",IF('Estimates-split'!E10<0.1,"*","")))) -> -0.086 | C19: =TEXT('Estimates-split'!F10,"0.000")&IF('Estimates-split'!I10="","",IF('Estimates-split'!I10<0.01,"***",IF('Estimates-split'!I10<0.05,"**",IF('Estimates-split'!I10<0.1,"*","")))) -> -0.020 | D19: =TEXT('Estimates-split'!J10,"0.000")&IF('Estimates-split'!M10="","",IF('Estimates-split'!M10<0.01,"***",IF('Estimates-split'!M10<0.05,"**",IF('Estimates-split'!M10<0.1,"*","")))) -> -0.041
B20: =IF('Estimates-split'!D10="","(n/a)","("&TEXT('Estimates-split'!D10,"0.00")&")") -> (-0.64) | C20: =IF('Estimates-split'!H10="","(n/a)","("&TEXT('Estimates-split'!H10,"0.00")&")") -> (-0.26) | D20: =IF('Estimates-split'!L10="","(n/a)","("&TEXT('Estimates-split'!L10,"0.00")&")") -> (-0.42)
A21: Real Estate Allocation (%) | B21: =TEXT('Estimates-split'!B11,"0.000")&IF('Estimates-split'!E11="","",IF('Estimates-split'!E11<0.01,"***",IF('Estimates-split'!E11<0.05,"**",IF('Estimates-split'!E11<0.1,"*","")))) -> -0.067 | C21: =TEXT('Estimates-split'!F11,"0.000")&IF('Estimates-split'!I11="","",IF('Estimates-split'!I11<0.01,"***",IF('Estimates-split'!I11<0.05,"**",IF('Estimates-split'!I11<0.1,"*","")))) -> -0.005 | D21: =TEXT('Estimates-split'!J11,"0.000")&IF('Estimates-split'!M11="","",IF('Estimates-split'!M11<0.01,"***",IF('Estimates-split'!M11<0.05,"**",IF('Estimates-split'!M11<0.1,"*","")))) -> -0.082
B22: =IF('Estimates-split'!D11="","(n/a)","("&TEXT('Estimates-split'!D11,"0.00")&")") -> (-0.53) | C22: =IF('Estimates-split'!H11="","(n/a)","("&TEXT('Estimates-split'!H11,"0.00")&")") -> (-0.09) | D22: =IF('Estimates-split'!L11="","(n/a)","("&TEXT('Estimates-split'!L11,"0.00")&")") -> (-0.87)
A23: Private Equity Allocation (%) | B23: =TEXT('Estimates-split'!B12,"0.000")&IF('Estimates-split'!E12="","",IF('Estimates-split'!E12<0.01,"***",IF('Estimates-split'!E12<0.05,"**",IF('Estimates-split'!E12<0.1,"*","")))) -> -0.061 | C23: =TEXT('Estimates-split'!F12,"0.000")&IF('Estimates-split'!I12="","",IF('Estimates-split'!I12<0.01,"***",IF('Estimates-split'!I12<0.05,"**",IF('Estimates-split'!I12<0.1,"*","")))) -> 0.011 | D23: =TEXT('Estimates-split'!J12,"0.000")&IF('Estimates-split'!M12="","",IF('Estimates-split'!M12<0.01,"***",IF('Estimates-split'!M12<0.05,"**",IF('Estimates-split'!M12<0.1,"*","")))) -> 0.013
B24: =IF('Estimates-split'!D12="","(n/a)","("&TEXT('Estimates-split'!D12,"0.00")&")") -> (-0.45) | C24: =IF('Estimates-split'!H12="","(n/a)","("&TEXT('Estimates-split'!H12,"0.00")&")") -> (0.17) | D24: =IF('Estimates-split'!L12="","(n/a)","("&TEXT('Estimates-split'!L12,"0.00")&")") -> (0.14)
A25: Hedge Fund Allocation (%) | B25: =TEXT('Estimates-split'!B13,"0.000")&IF('Estimates-split'!E13="","",IF('Estimates-split'!E13<0.01,"***",IF('Estimates-split'!E13<0.05,"**",IF('Estimates-split'!E13<0.1,"*","")))) -> -0.117 | C25: =TEXT('Estimates-split'!F13,"0.000")&IF('Estimates-split'!I13="","",IF('Estimates-split'!I13<0.01,"***",IF('Estimates-split'!I13<0.05,"**",IF('Estimates-split'!I13<0.1,"*","")))) -> -0.053 | D25: =TEXT('Estimates-split'!J13,"0.000")&IF('Estimates-split'!M13="","",IF('Estimates-split'!M13<0.01,"***",IF('Estimates-split'!M13<0.05,"**",IF('Estimates-split'!M13<0.1,"*","")))) -> -0.087
B26: =IF('Estimates-split'!D13="","(n/a)","("&TEXT('Estimates-split'!D13,"0.00")&")") -> (-0.93) | C26: =IF('Estimates-split'!H13="","(n/a)","("&TEXT('Estimates-split'!H13,"0.00")&")") -> (-0.87) | D26: =IF('Estimates-split'!L13="","(n/a)","("&TEXT('Estimates-split'!L13,"0.00")&")") -> (-1.17)
A27: Misc. Alternatives Allocation (%) | B27: =TEXT('Estimates-split'!B14,"0.000")&IF('Estimates-split'!E14="","",IF('Estimates-split'!E14<0.01,"***",IF('Estimates-split'!E14<0.05,"**",IF('Estimates-split'!E14<0.1,"*","")))) -> -0.094 | C27: =TEXT('Estimates-split'!F14,"0.000")&IF('Estimates-split'!I14="","",IF('Estimates-split'!I14<0.01,"***",IF('Estimates-split'!I14<0.05,"**",IF('Estimates-split'!I14<0.1,"*","")))) -> -0.032 | D27: =TEXT('Estimates-split'!J14,"0.000")&IF('Estimates-split'!M14="","",IF('Estimates-split'!M14<0.01,"***",IF('Estimates-split'!M14<0.05,"**",IF('Estimates-split'!M14<0.1,"*","")))) -> -0.081
B28: =IF('Estimates-split'!D14="","(n/a)","("&TEXT('Estimates-split'!D14,"0.00")&")") -> (-0.72) | C28: =IF('Estimates-split'!H14="","(n/a)","("&TEXT('Estimates-split'!H14,"0.00")&")") -> (-0.55) | D28: =IF('Estimates-split'!L14="","(n/a)","("&TEXT('Estimates-split'!L14,"0.00")&")") -> (-0.90)
A29: Commodities Allocation (%) | B29: =TEXT('Estimates-split'!B15,"0.000")&IF('Estimates-split'!E15="","",IF('Estimates-split'!E15<0.01,"***",IF('Estimates-split'!E15<0.05,"**",IF('Estimates-split'!E15<0.1,"*","")))) -> -0.134 | C29: =TEXT('Estimates-split'!F15,"0.000")&IF('Estimates-split'!I15="","",IF('Estimates-split'!I15<0.01,"***",IF('Estimates-split'!I15<0.05,"**",IF('Estimates-split'!I15<0.1,"*","")))) -> -0.065 | D29: =TEXT('Estimates-split'!J15,"0.000")&IF('Estimates-split'!M15="","",IF('Estimates-split'!M15<0.01,"***",IF('Estimates-split'!M15<0.05,"**",IF('Estimates-split'!M15<0.1,"*","")))) -> -0.135
B30: =IF('Estimates-split'!D15="","(n/a)","("&TEXT('Estimates-split'!D15,"0.00")&")") -> (-1.02) | C30: =IF('Estimates-split'!H15="","(n/a)","("&TEXT('Estimates-split'!H15,"0.00")&")") -> (-1.14) | D30: =IF('Estimates-split'!L15="","(n/a)","("&TEXT('Estimates-split'!L15,"0.00")&")") -> (-1.34)
A31: Cash Allocation (%) | B31: =TEXT('Estimates-split'!B16,"0.000")&IF('Estimates-split'!E16="","",IF('Estimates-split'!E16<0.01,"***",IF('Estimates-split'!E16<0.05,"**",IF('Estimates-split'!E16<0.1,"*","")))) -> -0.094 | C31: =TEXT('Estimates-split'!F16,"0.000")&IF('Estimates-split'!I16="","",IF('Estimates-split'!I16<0.01,"***",IF('Estimates-split'!I16<0.05,"**",IF('Estimates-split'!I16<0.1,"*","")))) -> -0.039 | D31: =TEXT('Estimates-split'!J16,"0.000")&IF('Estimates-split'!M16="","",IF('Estimates-split'!M16<0.01,"***",IF('Estimates-split'!M16<0.05,"**",IF('Estimates-split'!M16<0.1,"*","")))) -> -0.056
B32: =IF('Estimates-split'!D16="","(n/a)","("&TEXT('Estimates-split'!D16,"0.00")&")") -> (-0.67) | C32: =IF('Estimates-split'!H16="","(n/a)","("&TEXT('Estimates-split'!H16,"0.00")&")") -> (-0.52) | D32: =IF('Estimates-split'!L16="","(n/a)","("&TEXT('Estimates-split'!L16,"0.00")&")") -> (-0.47)
A33: Financial Center (0/1) | B33: =TEXT('Estimates-split'!B17,"0.000")&IF('Estimates-split'!E17="","",IF('Estimates-split'!E17<0.01,"***",IF('Estimates-split'!E17<0.05,"**",IF('Estimates-split'!E17<0.1,"*","")))) -> 0.065 | C33: =TEXT('Estimates-split'!F17,"0.000")&IF('Estimates-split'!I17="","",IF('Estimates-split'!I17<0.01,"***",IF('Estimates-split'!I17<0.05,"**",IF('Estimates-split'!I17<0.1,"*","")))) -> 0.089
B34: =IF('Estimates-split'!D17="","(n/a)","("&TEXT('Estimates-split'!D17,"0.00")&")") -> (0.46) | C34: =IF('Estimates-split'!H17="","(n/a)","("&TEXT('Estimates-split'!H17,"0.00")&")") -> (0.58)
A35: Log (CIO Age) (t-1) | C35: =TEXT('Estimates-split'!F18,"0.000")&IF('Estimates-split'!I18="","",IF('Estimates-split'!I18<0.01,"***",IF('Estimates-split'!I18<0.05,"**",IF('Estimates-split'!I18<0.1,"*","")))) -> -0.270 | D35: =TEXT('Estimates-split'!J18,"0.000")&IF('Estimates-split'!M18="","",IF('Estimates-split'!M18<0.01,"***",IF('Estimates-split'!M18<0.05,"**",IF('Estimates-split'!M18<0.1,"*","")))) -> 0.793
C36: =IF('Estimates-split'!H18="","(n/a)","("&TEXT('Estimates-split'!H18,"0.00")&")") -> (-0.50) | D36: =IF('Estimates-split'!L18="","(n/a)","("&TEXT('Estimates-split'!L18,"0.00")&")") -> (0.96)
A37: Log (CIO Tenure) (t-1) | C37: =TEXT('Estimates-split'!F19,"0.000")&IF('Estimates-split'!I19="","",IF('Estimates-split'!I19<0.01,"***",IF('Estimates-split'!I19<0.05,"**",IF('Estimates-split'!I19<0.1,"*","")))) -> 0.066 | D37: =TEXT('Estimates-split'!J19,"0.000")&IF('Estimates-split'!M19="","",IF('Estimates-split'!M19<0.01,"***",IF('Estimates-split'!M19<0.05,"**",IF('Estimates-split'!M19<0.1,"*","")))) -> 0.008
C38: =IF('Estimates-split'!H19="","(n/a)","("&TEXT('Estimates-split'!H19,"0.00")&")") -> (0.79) | D38: =IF('Estimates-split'!L19="","(n/a)","("&TEXT('Estimates-split'!L19,"0.00")&")") -> (0.06)
A39: CIO Prior Private Experience (0/1) | C39: =TEXT('Estimates-split'!F20,"0.000")&IF('Estimates-split'!I20="","",IF('Estimates-split'!I20<0.01,"***",IF('Estimates-split'!I20<0.05,"**",IF('Estimates-split'!I20<0.1,"*","")))) -> 0.062 | D39: =TEXT('Estimates-split'!J20,"0.000")&IF('Estimates-split'!M20="","",IF('Estimates-split'!M20<0.01,"***",IF('Estimates-split'!M20<0.05,"**",IF('Estimates-split'!M20<0.1,"*","")))) -> 0.009
C40: =IF('Estimates-split'!H20="","(n/a)","("&TEXT('Estimates-split'!H20,"0.00")&")") -> (0.56) | D40: =IF('Estimates-split'!L20="","(n/a)","("&TEXT('Estimates-split'!L20,"0.00")&")") -> (0.04)
A41: CIO Attended Elite College (0/1) | C41: =TEXT('Estimates-split'!F21,"0.000")&IF('Estimates-split'!I21="","",IF('Estimates-split'!I21<0.01,"***",IF('Estimates-split'!I21<0.05,"**",IF('Estimates-split'!I21<0.1,"*","")))) -> -0.183 | D41: =TEXT('Estimates-split'!J21,"0.000")&IF('Estimates-split'!M21="","",IF('Estimates-split'!M21<0.01,"***",IF('Estimates-split'!M21<0.05,"**",IF('Estimates-split'!M21<0.1,"*","")))) -> 0.287
C42: =IF('Estimates-split'!H21="","(n/a)","("&TEXT('Estimates-split'!H21,"0.00")&")") -> (-1.31) | D42: =IF('Estimates-split'!L21="","(n/a)","("&TEXT('Estimates-split'!L21,"0.00")&")") -> (1.11)
A43: Separate Investment Board (0/1) | C43: =TEXT('Estimates-split'!F22,"0.000")&IF('Estimates-split'!I22="","",IF('Estimates-split'!I22<0.01,"***",IF('Estimates-split'!I22<0.05,"**",IF('Estimates-split'!I22<0.1,"*","")))) -> 0.281** | D43: =TEXT('Estimates-split'!J22,"0.000")&IF('Estimates-split'!M22="","",IF('Estimates-split'!M22<0.01,"***",IF('Estimates-split'!M22<0.05,"**",IF('Estimates-split'!M22<0.1,"*","")))) -> 0.258
C44: =IF('Estimates-split'!H22="","(n/a)","("&TEXT('Estimates-split'!H22,"0.00")&")") -> (2.31) | D44: =IF('Estimates-split'!L22="","(n/a)","("&TEXT('Estimates-split'!L22,"0.00")&")") -> (0.28)
A45: % Political Appointees on Board | C45: =TEXT('Estimates-split'!F23,"0.000")&IF('Estimates-split'!I23="","",IF('Estimates-split'!I23<0.01,"***",IF('Estimates-split'!I23<0.05,"**",IF('Estimates-split'!I23<0.1,"*","")))) -> -0.162 | D45: =TEXT('Estimates-split'!J23,"0.000")&IF('Estimates-split'!M23="","",IF('Estimates-split'!M23<0.01,"***",IF('Estimates-split'!M23<0.05,"**",IF('Estimates-split'!M23<0.1,"*","")))) -> 0.140
C46: =IF('Estimates-split'!H23="","(n/a)","("&TEXT('Estimates-split'!H23,"0.00")&")") -> (-0.57) | D46: =IF('Estimates-split'!L23="","(n/a)","("&TEXT('Estimates-split'!L23,"0.00")&")") -> (0.10)
A48: Observations | B48: ='Estimates-split'!B26 -> 1723 | C48: ='Estimates-split'!F26 -> 1478 | D48: ='Estimates-split'!J26 -> 1477
A49: Adjusted R-squared | B49: ='Estimates-split'!B29 -> 0.058220713 | C49: ='Estimates-split'!F29 -> 0.069521279 | D49: ='Estimates-split'!J29 -> 0.088644722
A50: Plan FE | B50: No | C50: No | D50: Yes
A51: Fiscal-Year-End FE | B51: Yes | C51: Yes | D51: Yes
A52: p-value: First Half = Second Half | B52: ='Estimates-split'!E24 -> 0.60250458 | C52: ='Estimates-split'!I24 -> 0.84652377 | D52: ='Estimates-split'!M24 -> 0.40111257
A54: Panel B. Benchmark-Adjusted Returns
B55: (1) | C55: (2) | D55: (3)
B56: Bench-adj. Ret. (t) | C56: Bench-adj. Ret. (t) | D56: Bench-adj. Ret. (t)
A57: Conflicted CIO x First Half of Tenure (0/1) | B57: =TEXT('Estimates-split'!N4,"0.000")&IF('Estimates-split'!Q4="","",IF('Estimates-split'!Q4<0.01,"***",IF('Estimates-split'!Q4<0.05,"**",IF('Estimates-split'!Q4<0.1,"*","")))) -> -0.526** | C57: =TEXT('Estimates-split'!R4,"0.000")&IF('Estimates-split'!U4="","",IF('Estimates-split'!U4<0.01,"***",IF('Estimates-split'!U4<0.05,"**",IF('Estimates-split'!U4<0.1,"*","")))) -> -0.575*** | D57: =TEXT('Estimates-split'!V4,"0.000")&IF('Estimates-split'!Y4="","",IF('Estimates-split'!Y4<0.01,"***",IF('Estimates-split'!Y4<0.05,"**",IF('Estimates-split'!Y4<0.1,"*","")))) -> -0.646**
B58: =IF('Estimates-split'!P4="","(n/a)","("&TEXT('Estimates-split'!P4,"0.00")&")") -> (-2.37) | C58: =IF('Estimates-split'!T4="","(n/a)","("&TEXT('Estimates-split'!T4,"0.00")&")") -> (-3.29) | D58: =IF('Estimates-split'!X4="","(n/a)","("&TEXT('Estimates-split'!X4,"0.00")&")") -> (-2.70)
A59: Conflicted CIO x Second Half of Tenure (0/1) | B59: =TEXT('Estimates-split'!N5,"0.000")&IF('Estimates-split'!Q5="","",IF('Estimates-split'!Q5<0.01,"***",IF('Estimates-split'!Q5<0.05,"**",IF('Estimates-split'!Q5<0.1,"*","")))) -> -0.338* | C59: =TEXT('Estimates-split'!R5,"0.000")&IF('Estimates-split'!U5="","",IF('Estimates-split'!U5<0.01,"***",IF('Estimates-split'!U5<0.05,"**",IF('Estimates-split'!U5<0.1,"*","")))) -> -0.388** | D59: =TEXT('Estimates-split'!V5,"0.000")&IF('Estimates-split'!Y5="","",IF('Estimates-split'!Y5<0.01,"***",IF('Estimates-split'!Y5<0.05,"**",IF('Estimates-split'!Y5<0.1,"*","")))) -> -0.219
B60: =IF('Estimates-split'!P5="","(n/a)","("&TEXT('Estimates-split'!P5,"0.00")&")") -> (-1.88) | C60: =IF('Estimates-split'!T5="","(n/a)","("&TEXT('Estimates-split'!T5,"0.00")&")") -> (-2.37) | D60: =IF('Estimates-split'!X5="","(n/a)","("&TEXT('Estimates-split'!X5,"0.00")&")") -> (-1.01)
A61: Investment Return (t - 1) | B61: =TEXT('Estimates-split'!N6,"0.000")&IF('Estimates-split'!Q6="","",IF('Estimates-split'!Q6<0.01,"***",IF('Estimates-split'!Q6<0.05,"**",IF('Estimates-split'!Q6<0.1,"*","")))) -> 0.066 | C61: =TEXT('Estimates-split'!R6,"0.000")&IF('Estimates-split'!U6="","",IF('Estimates-split'!U6<0.01,"***",IF('Estimates-split'!U6<0.05,"**",IF('Estimates-split'!U6<0.1,"*","")))) -> 0.036 | D61: =TEXT('Estimates-split'!V6,"0.000")&IF('Estimates-split'!Y6="","",IF('Estimates-split'!Y6<0.01,"***",IF('Estimates-split'!Y6<0.05,"**",IF('Estimates-split'!Y6<0.1,"*","")))) -> 0.020
B62: =IF('Estimates-split'!P6="","(n/a)","("&TEXT('Estimates-split'!P6,"0.00")&")") -> (0.95) | C62: =IF('Estimates-split'!T6="","(n/a)","("&TEXT('Estimates-split'!T6,"0.00")&")") -> (0.52) | D62: =IF('Estimates-split'!X6="","(n/a)","("&TEXT('Estimates-split'!X6,"0.00")&")") -> (0.32)
A63: Log (Plan Size) (t-1) | B63: =TEXT('Estimates-split'!N7,"0.000")&IF('Estimates-split'!Q7="","",IF('Estimates-split'!Q7<0.01,"***",IF('Estimates-split'!Q7<0.05,"**",IF('Estimates-split'!Q7<0.1,"*","")))) -> -0.051 | C63: =TEXT('Estimates-split'!R7,"0.000")&IF('Estimates-split'!U7="","",IF('Estimates-split'!U7<0.01,"***",IF('Estimates-split'!U7<0.05,"**",IF('Estimates-split'!U7<0.1,"*","")))) -> -0.004 | D63: =TEXT('Estimates-split'!V7,"0.000")&IF('Estimates-split'!Y7="","",IF('Estimates-split'!Y7<0.01,"***",IF('Estimates-split'!Y7<0.05,"**",IF('Estimates-split'!Y7<0.1,"*","")))) -> -0.002
B64: =IF('Estimates-split'!P7="","(n/a)","("&TEXT('Estimates-split'!P7,"0.00")&")") -> (-1.30) | C64: =IF('Estimates-split'!T7="","(n/a)","("&TEXT('Estimates-split'!T7,"0.00")&")") -> (-0.08) | D64: =IF('Estimates-split'!X7="","(n/a)","("&TEXT('Estimates-split'!X7,"0.00")&")") -> (0.00)
A65: Funding Ratio (t-1) | B65: =TEXT('Estimates-split'!N8,"0.000")&IF('Estimates-split'!Q8="","",IF('Estimates-split'!Q8<0.01,"***",IF('Estimates-split'!Q8<0.05,"**",IF('Estimates-split'!Q8<0.1,"*","")))) -> 0.005 | C65: =TEXT('Estimates-split'!R8,"0.000")&IF('Estimates-split'!U8="","",IF('Estimates-split'!U8<0.01,"***",IF('Estimates-split'!U8<0.05,"**",IF('Estimates-split'!U8<0.1,"*","")))) -> 0.005 | D65: =TEXT('Estimates-split'!V8,"0.000")&IF('Estimates-split'!Y8="","",IF('Estimates-split'!Y8<0.01,"***",IF('Estimates-split'!Y8<0.05,"**",IF('Estimates-split'!Y8<0.1,"*","")))) -> -0.017
B66: =IF('Estimates-split'!P8="","(n/a)","("&TEXT('Estimates-split'!P8,"0.00")&")") -> (1.13) | C66: =IF('Estimates-split'!T8="","(n/a)","("&TEXT('Estimates-split'!T8,"0.00")&")") -> (0.90) | D66: =IF('Estimates-split'!X8="","(n/a)","("&TEXT('Estimates-split'!X8,"0.00")&")") -> (-1.59)
A67: Equity Allocation (%) | B67: =TEXT('Estimates-split'!N9,"0.000")&IF('Estimates-split'!Q9="","",IF('Estimates-split'!Q9<0.01,"***",IF('Estimates-split'!Q9<0.05,"**",IF('Estimates-split'!Q9<0.1,"*","")))) -> -0.162 | C67: =TEXT('Estimates-split'!R9,"0.000")&IF('Estimates-split'!U9="","",IF('Estimates-split'!U9<0.01,"***",IF('Estimates-split'!U9<0.05,"**",IF('Estimates-split'!U9<0.1,"*","")))) -> -0.010 | D67: =TEXT('Estimates-split'!V9,"0.000")&IF('Estimates-split'!Y9="","",IF('Estimates-split'!Y9<0.01,"***",IF('Estimates-split'!Y9<0.05,"**",IF('Estimates-split'!Y9<0.1,"*","")))) -> 0.021
B68: =IF('Estimates-split'!P9="","(n/a)","("&TEXT('Estimates-split'!P9,"0.00")&")") -> (-1.23) | C68: =IF('Estimates-split'!T9="","(n/a)","("&TEXT('Estimates-split'!T9,"0.00")&")") -> (-0.09) | D68: =IF('Estimates-split'!X9="","(n/a)","("&TEXT('Estimates-split'!X9,"0.00")&")") -> (0.12)
A69: Fixed Income Allocation (%) | B69: =TEXT('Estimates-split'!N10,"0.000")&IF('Estimates-split'!Q10="","",IF('Estimates-split'!Q10<0.01,"***",IF('Estimates-split'!Q10<0.05,"**",IF('Estimates-split'!Q10<0.1,"*","")))) -> -0.154 | C69: =TEXT('Estimates-split'!R10,"0.000")&IF('Estimates-split'!U10="","",IF('Estimates-split'!U10<0.01,"***",IF('Estimates-split'!U10<0.05,"**",IF('Estimates-split'!U10<0.1,"*","")))) -> -0.012 | D69: =TEXT('Estimates-split'!V10,"0.000")&IF('Estimates-split'!Y10="","",IF('Estimates-split'!Y10<0.01,"***",IF('Estimates-split'!Y10<0.05,"**",IF('Estimates-split'!Y10<0.1,"*","")))) -> 0.010
B70: =IF('Estimates-split'!P10="","(n/a)","("&TEXT('Estimates-split'!P10,"0.00")&")") -> (-1.19) | C70: =IF('Estimates-split'!T10="","(n/a)","("&TEXT('Estimates-split'!T10,"0.00")&")") -> (-0.10) | D70: =IF('Estimates-split'!X10="","(n/a)","("&TEXT('Estimates-split'!X10,"0.00")&")") -> (0.06)
A71: Real Estate Allocation (%) | B71: =TEXT('Estimates-split'!N11,"0.000")&IF('Estimates-split'!Q11="","",IF('Estimates-split'!Q11<0.01,"***",IF('Estimates-split'!Q11<0.05,"**",IF('Estimates-split'!Q11<0.1,"*","")))) -> -0.192 | C71: =TEXT('Estimates-split'!R11,"0.000")&IF('Estimates-split'!U11="","",IF('Estimates-split'!U11<0.01,"***",IF('Estimates-split'!U11<0.05,"**",IF('Estimates-split'!U11<0.1,"*","")))) -> -0.031 | D71: =TEXT('Estimates-split'!V11,"0.000")&IF('Estimates-split'!Y11="","",IF('Estimates-split'!Y11<0.01,"***",IF('Estimates-split'!Y11<0.05,"**",IF('Estimates-split'!Y11<0.1,"*","")))) -> -0.042
B72: =IF('Estimates-split'!P11="","(n/a)","("&TEXT('Estimates-split'!P11,"0.00")&")") -> (-1.63) | C72: =IF('Estimates-split'!T11="","(n/a)","("&TEXT('Estimates-split'!T11,"0.00")&")") -> (-0.30) | D72: =IF('Estimates-split'!X11="","(n/a)","("&TEXT('Estimates-split'!X11,"0.00")&")") -> (-0.26)
A73: Private Equity Allocation (%) | B73: =TEXT('Estimates-split'!N12,"0.000")&IF('Estimates-split'!Q12="","",IF('Estimates-split'!Q12<0.01,"***",IF('Estimates-split'!Q12<0.05,"**",IF('Estimates-split'!Q12<0.1,"*","")))) -> -0.150 | C73: =TEXT('Estimates-split'!R12,"0.000")&IF('Estimates-split'!U12="","",IF('Estimates-split'!U12<0.01,"***",IF('Estimates-split'!U12<0.05,"**",IF('Estimates-split'!U12<0.1,"*","")))) -> 0.006 | D73: =TEXT('Estimates-split'!V12,"0.000")&IF('Estimates-split'!Y12="","",IF('Estimates-split'!Y12<0.01,"***",IF('Estimates-split'!Y12<0.05,"**",IF('Estimates-split'!Y12<0.1,"*","")))) -> 0.029
B74: =IF('Estimates-split'!P12="","(n/a)","("&TEXT('Estimates-split'!P12,"0.00")&")") -> (-1.16) | C74: =IF('Estimates-split'!T12="","(n/a)","("&TEXT('Estimates-split'!T12,"0.00")&")") -> (0.05) | D74: =IF('Estimates-split'!X12="","(n/a)","("&TEXT('Estimates-split'!X12,"0.00")&")") -> (0.17)
A75: Hedge Fund Allocation (%) | B75: =TEXT('Estimates-split'!N13,"0.000")&IF('Estimates-split'!Q13="","",IF('Estimates-split'!Q13<0.01,"***",IF('Estimates-split'!Q13<0.05,"**",IF('Estimates-split'!Q13<0.1,"*","")))) -> -0.150 | C75: =TEXT('Estimates-split'!R13,"0.000")&IF('Estimates-split'!U13="","",IF('Estimates-split'!U13<0.01,"***",IF('Estimates-split'!U13<0.05,"**",IF('Estimates-split'!U13<0.1,"*","")))) -> -0.001 | D75: =TEXT('Estimates-split'!V13,"0.000")&IF('Estimates-split'!Y13="","",IF('Estimates-split'!Y13<0.01,"***",IF('Estimates-split'!Y13<0.05,"**",IF('Estimates-split'!Y13<0.1,"*","")))) -> 0.013
B76: =IF('Estimates-split'!P13="","(n/a)","("&TEXT('Estimates-split'!P13,"0.00")&")") -> (-1.19) | C76: =IF('Estimates-split'!T13="","(n/a)","("&TEXT('Estimates-split'!T13,"0.00")&")") -> (-0.01) | D76: =IF('Estimates-split'!X13="","(n/a)","("&TEXT('Estimates-split'!X13,"0.00")&")") -> (0.08)
A77: Misc. Alternatives Allocation (%) | B77: =TEXT('Estimates-split'!N14,"0.000")&IF('Estimates-split'!Q14="","",IF('Estimates-split'!Q14<0.01,"***",IF('Estimates-split'!Q14<0.05,"**",IF('Estimates-split'!Q14<0.1,"*","")))) -> -0.178 | C77: =TEXT('Estimates-split'!R14,"0.000")&IF('Estimates-split'!U14="","",IF('Estimates-split'!U14<0.01,"***",IF('Estimates-split'!U14<0.05,"**",IF('Estimates-split'!U14<0.1,"*","")))) -> -0.017 | D77: =TEXT('Estimates-split'!V14,"0.000")&IF('Estimates-split'!Y14="","",IF('Estimates-split'!Y14<0.01,"***",IF('Estimates-split'!Y14<0.05,"**",IF('Estimates-split'!Y14<0.1,"*","")))) -> 0.025
B78: =IF('Estimates-split'!P14="","(n/a)","("&TEXT('Estimates-split'!P14,"0.00")&")") -> (-1.46) | C78: =IF('Estimates-split'!T14="","(n/a)","("&TEXT('Estimates-split'!T14,"0.00")&")") -> (-0.15) | D78: =IF('Estimates-split'!X14="","(n/a)","("&TEXT('Estimates-split'!X14,"0.00")&")") -> (0.14)
A79: Commodities Allocation (%) | B79: =TEXT('Estimates-split'!N15,"0.000")&IF('Estimates-split'!Q15="","",IF('Estimates-split'!Q15<0.01,"***",IF('Estimates-split'!Q15<0.05,"**",IF('Estimates-split'!Q15<0.1,"*","")))) -> -0.194 | C79: =TEXT('Estimates-split'!R15,"0.000")&IF('Estimates-split'!U15="","",IF('Estimates-split'!U15<0.01,"***",IF('Estimates-split'!U15<0.05,"**",IF('Estimates-split'!U15<0.1,"*","")))) -> -0.029 | D79: =TEXT('Estimates-split'!V15,"0.000")&IF('Estimates-split'!Y15="","",IF('Estimates-split'!Y15<0.01,"***",IF('Estimates-split'!Y15<0.05,"**",IF('Estimates-split'!Y15<0.1,"*","")))) -> -0.010
B80: =IF('Estimates-split'!P15="","(n/a)","("&TEXT('Estimates-split'!P15,"0.00")&")") -> (-1.46) | C80: =IF('Estimates-split'!T15="","(n/a)","("&TEXT('Estimates-split'!T15,"0.00")&")") -> (-0.25) | D80: =IF('Estimates-split'!X15="","(n/a)","("&TEXT('Estimates-split'!X15,"0.00")&")") -> (-0.06)
A81: Cash Allocation (%) | B81: =TEXT('Estimates-split'!N16,"0.000")&IF('Estimates-split'!Q16="","",IF('Estimates-split'!Q16<0.01,"***",IF('Estimates-split'!Q16<0.05,"**",IF('Estimates-split'!Q16<0.1,"*","")))) -> -0.125 | C81: =TEXT('Estimates-split'!R16,"0.000")&IF('Estimates-split'!U16="","",IF('Estimates-split'!U16<0.01,"***",IF('Estimates-split'!U16<0.05,"**",IF('Estimates-split'!U16<0.1,"*","")))) -> 0.010 | D81: =TEXT('Estimates-split'!V16,"0.000")&IF('Estimates-split'!Y16="","",IF('Estimates-split'!Y16<0.01,"***",IF('Estimates-split'!Y16<0.05,"**",IF('Estimates-split'!Y16<0.1,"*","")))) -> 0.040
B82: =IF('Estimates-split'!P16="","(n/a)","("&TEXT('Estimates-split'!P16,"0.00")&")") -> (-0.89) | C82: =IF('Estimates-split'!T16="","(n/a)","("&TEXT('Estimates-split'!T16,"0.00")&")") -> (0.08) | D82: =IF('Estimates-split'!X16="","(n/a)","("&TEXT('Estimates-split'!X16,"0.00")&")") -> (0.22)
A83: Financial Center (0/1) | B83: =TEXT('Estimates-split'!N17,"0.000")&IF('Estimates-split'!Q17="","",IF('Estimates-split'!Q17<0.01,"***",IF('Estimates-split'!Q17<0.05,"**",IF('Estimates-split'!Q17<0.1,"*","")))) -> -0.171 | C83: =TEXT('Estimates-split'!R17,"0.000")&IF('Estimates-split'!U17="","",IF('Estimates-split'!U17<0.01,"***",IF('Estimates-split'!U17<0.05,"**",IF('Estimates-split'!U17<0.1,"*","")))) -> -0.179*
B84: =IF('Estimates-split'!P17="","(n/a)","("&TEXT('Estimates-split'!P17,"0.00")&")") -> (-1.63) | C84: =IF('Estimates-split'!T17="","(n/a)","("&TEXT('Estimates-split'!T17,"0.00")&")") -> (-1.96)
A85: Log (CIO Age) (t-1) | C85: =TEXT('Estimates-split'!R18,"0.000")&IF('Estimates-split'!U18="","",IF('Estimates-split'!U18<0.01,"***",IF('Estimates-split'!U18<0.05,"**",IF('Estimates-split'!U18<0.1,"*","")))) -> -1.160** | D85: =TEXT('Estimates-split'!V18,"0.000")&IF('Estimates-split'!Y18="","",IF('Estimates-split'!Y18<0.01,"***",IF('Estimates-split'!Y18<0.05,"**",IF('Estimates-split'!Y18<0.1,"*","")))) -> 0.036
C86: =IF('Estimates-split'!T18="","(n/a)","("&TEXT('Estimates-split'!T18,"0.00")&")") -> (-2.31) | D86: =IF('Estimates-split'!X18="","(n/a)","("&TEXT('Estimates-split'!X18,"0.00")&")") -> (0.04)
A87: Log (CIO Tenure) (t-1) | C87: =TEXT('Estimates-split'!R19,"0.000")&IF('Estimates-split'!U19="","",IF('Estimates-split'!U19<0.01,"***",IF('Estimates-split'!U19<0.05,"**",IF('Estimates-split'!U19<0.1,"*","")))) -> -0.010 | D87: =TEXT('Estimates-split'!V19,"0.000")&IF('Estimates-split'!Y19="","",IF('Estimates-split'!Y19<0.01,"***",IF('Estimates-split'!Y19<0.05,"**",IF('Estimates-split'!Y19<0.1,"*","")))) -> -0.203
C88: =IF('Estimates-split'!T19="","(n/a)","("&TEXT('Estimates-split'!T19,"0.00")&")") -> (-0.09) | D88: =IF('Estimates-split'!X19="","(n/a)","("&TEXT('Estimates-split'!X19,"0.00")&")") -> (-1.47)
A89: CIO Prior Private Experience (0/1) | C89: =TEXT('Estimates-split'!R20,"0.000")&IF('Estimates-split'!U20="","",IF('Estimates-split'!U20<0.01,"***",IF('Estimates-split'!U20<0.05,"**",IF('Estimates-split'!U20<0.1,"*","")))) -> 0.079 | D89: =TEXT('Estimates-split'!V20,"0.000")&IF('Estimates-split'!Y20="","",IF('Estimates-split'!Y20<0.01,"***",IF('Estimates-split'!Y20<0.05,"**",IF('Estimates-split'!Y20<0.1,"*","")))) -> 0.061
C90: =IF('Estimates-split'!T20="","(n/a)","("&TEXT('Estimates-split'!T20,"0.00")&")") -> (0.54) | D90: =IF('Estimates-split'!X20="","(n/a)","("&TEXT('Estimates-split'!X20,"0.00")&")") -> (0.29)
A91: CIO Attended Elite College (0/1) | C91: =TEXT('Estimates-split'!R21,"0.000")&IF('Estimates-split'!U21="","",IF('Estimates-split'!U21<0.01,"***",IF('Estimates-split'!U21<0.05,"**",IF('Estimates-split'!U21<0.1,"*","")))) -> -0.176 | D91: =TEXT('Estimates-split'!V21,"0.000")&IF('Estimates-split'!Y21="","",IF('Estimates-split'!Y21<0.01,"***",IF('Estimates-split'!Y21<0.05,"**",IF('Estimates-split'!Y21<0.1,"*","")))) -> 0.022
C92: =IF('Estimates-split'!T21="","(n/a)","("&TEXT('Estimates-split'!T21,"0.00")&")") -> (-1.01) | D92: =IF('Estimates-split'!X21="","(n/a)","("&TEXT('Estimates-split'!X21,"0.00")&")") -> (0.11)
A93: Separate Investment Board (0/1) | C93: =TEXT('Estimates-split'!R22,"0.000")&IF('Estimates-split'!U22="","",IF('Estimates-split'!U22<0.01,"***",IF('Estimates-split'!U22<0.05,"**",IF('Estimates-split'!U22<0.1,"*","")))) -> 0.284 | D93: =TEXT('Estimates-split'!V22,"0.000")&IF('Estimates-split'!Y22="","",IF('Estimates-split'!Y22<0.01,"***",IF('Estimates-split'!Y22<0.05,"**",IF('Estimates-split'!Y22<0.1,"*","")))) -> 0.768
C94: =IF('Estimates-split'!T22="","(n/a)","("&TEXT('Estimates-split'!T22,"0.00")&")") -> (1.64) | D94: =IF('Estimates-split'!X22="","(n/a)","("&TEXT('Estimates-split'!X22,"0.00")&")") -> (1.31)
A95: % Political Appointees on Board | C95: =TEXT('Estimates-split'!R23,"0.000")&IF('Estimates-split'!U23="","",IF('Estimates-split'!U23<0.01,"***",IF('Estimates-split'!U23<0.05,"**",IF('Estimates-split'!U23<0.1,"*","")))) -> -0.064 | D95: =TEXT('Estimates-split'!V23,"0.000")&IF('Estimates-split'!Y23="","",IF('Estimates-split'!Y23<0.01,"***",IF('Estimates-split'!Y23<0.05,"**",IF('Estimates-split'!Y23<0.1,"*","")))) -> -0.228
C96: =IF('Estimates-split'!T23="","(n/a)","("&TEXT('Estimates-split'!T23,"0.00")&")") -> (-0.29) | D96: =IF('Estimates-split'!X23="","(n/a)","("&TEXT('Estimates-split'!X23,"0.00")&")") -> (-0.16)
A98: Observations | B98: ='Estimates-split'!N26 -> 1532 | C98: ='Estimates-split'!R26 -> 1313 | D98: ='Estimates-split'!V26 -> 1312
A99: Adjusted R-squared | B99: ='Estimates-split'!N29 -> 0.15153953 | C99: ='Estimates-split'!R29 -> 0.16779335 | D99: ='Estimates-split'!V29 -> 0.16301112
A100: Plan FE | B100: No | C100: No | D100: Yes
A101: Fiscal-Year-End FE | B101: Yes | C101: Yes | D101: Yes
A102: p-value: First Half = Second Half | B102: ='Estimates-split'!Q24 -> 0.46060888 | C102: ='Estimates-split'!U24 -> 0.38577751 | D102: ='Estimates-split'!Y24 -> 0.10182503

Sheet Table XII-split
A1: Table XII: Conflicted CIOs: Fee Ratio in the First versus Second Half of Tenure (fiscal-year-end fixed effects)
A2: This table repeats the regressions of Table XI with Fee Ratio as the dependent variable. Fee Ratio is the plan's total investment fees as a percentage of plan assets. Conflicted CIO x First Half of Tenure and Conflicted CIO x Second Half of Tenure are defined as in Table XI, and the omitted category is all plan-years run by non-conflicted CIOs. The other independent variables are as defined in Table I. All columns include fiscal-year-end date fixed effects, so plans are compared only with plans whose fiscal year covers the same twelve months. Column 3 adds plan fixed effects. The last row reports the p-value of a test that the first-half and second-half coefficients are equal. The standard errors are double clustered by plan and year. Coefficients marked with ***, **, and * are significant at the 1%, 5%, and 10% level, respectively.
B4: (1) | C4: (2) | D4: (3)
B5: Fee Ratio (t) | C5: Fee Ratio (t) | D5: Fee Ratio (t)
A6: Conflicted CIO x First Half of Tenure (0/1) | B6: =TEXT('Estimates-split'!Z4,"0.000")&IF('Estimates-split'!AC4="","",IF('Estimates-split'!AC4<0.01,"***",IF('Estimates-split'!AC4<0.05,"**",IF('Estimates-split'!AC4<0.1,"*","")))) -> -0.065 | C6: =TEXT('Estimates-split'!AD4,"0.000")&IF('Estimates-split'!AG4="","",IF('Estimates-split'!AG4<0.01,"***",IF('Estimates-split'!AG4<0.05,"**",IF('Estimates-split'!AG4<0.1,"*","")))) -> -0.027 | D6: =TEXT('Estimates-split'!AH4,"0.000")&IF('Estimates-split'!AK4="","",IF('Estimates-split'!AK4<0.01,"***",IF('Estimates-split'!AK4<0.05,"**",IF('Estimates-split'!AK4<0.1,"*","")))) -> 0.041
B7: =IF('Estimates-split'!AB4="","(n/a)","("&TEXT('Estimates-split'!AB4,"0.00")&")") -> (-1.68) | C7: =IF('Estimates-split'!AF4="","(n/a)","("&TEXT('Estimates-split'!AF4,"0.00")&")") -> (-0.52) | D7: =IF('Estimates-split'!AJ4="","(n/a)","("&TEXT('Estimates-split'!AJ4,"0.00")&")") -> (0.69)
A8: Conflicted CIO x Second Half of Tenure (0/1) | B8: =TEXT('Estimates-split'!Z5,"0.000")&IF('Estimates-split'!AC5="","",IF('Estimates-split'!AC5<0.01,"***",IF('Estimates-split'!AC5<0.05,"**",IF('Estimates-split'!AC5<0.1,"*","")))) -> -0.069 | C8: =TEXT('Estimates-split'!AD5,"0.000")&IF('Estimates-split'!AG5="","",IF('Estimates-split'!AG5<0.01,"***",IF('Estimates-split'!AG5<0.05,"**",IF('Estimates-split'!AG5<0.1,"*","")))) -> -0.042 | D8: =TEXT('Estimates-split'!AH5,"0.000")&IF('Estimates-split'!AK5="","",IF('Estimates-split'!AK5<0.01,"***",IF('Estimates-split'!AK5<0.05,"**",IF('Estimates-split'!AK5<0.1,"*","")))) -> 0.031
B9: =IF('Estimates-split'!AB5="","(n/a)","("&TEXT('Estimates-split'!AB5,"0.00")&")") -> (-1.61) | C9: =IF('Estimates-split'!AF5="","(n/a)","("&TEXT('Estimates-split'!AF5,"0.00")&")") -> (-0.91) | D9: =IF('Estimates-split'!AJ5="","(n/a)","("&TEXT('Estimates-split'!AJ5,"0.00")&")") -> (0.51)
A10: Investment Return (t - 1) | B10: =TEXT('Estimates-split'!Z6,"0.000")&IF('Estimates-split'!AC6="","",IF('Estimates-split'!AC6<0.01,"***",IF('Estimates-split'!AC6<0.05,"**",IF('Estimates-split'!AC6<0.1,"*","")))) -> 0.002 | C10: =TEXT('Estimates-split'!AD6,"0.000")&IF('Estimates-split'!AG6="","",IF('Estimates-split'!AG6<0.01,"***",IF('Estimates-split'!AG6<0.05,"**",IF('Estimates-split'!AG6<0.1,"*","")))) -> 0.001 | D10: =TEXT('Estimates-split'!AH6,"0.000")&IF('Estimates-split'!AK6="","",IF('Estimates-split'!AK6<0.01,"***",IF('Estimates-split'!AK6<0.05,"**",IF('Estimates-split'!AK6<0.1,"*","")))) -> -0.003
B11: =IF('Estimates-split'!AB6="","(n/a)","("&TEXT('Estimates-split'!AB6,"0.00")&")") -> (0.46) | C11: =IF('Estimates-split'!AF6="","(n/a)","("&TEXT('Estimates-split'!AF6,"0.00")&")") -> (0.22) | D11: =IF('Estimates-split'!AJ6="","(n/a)","("&TEXT('Estimates-split'!AJ6,"0.00")&")") -> (-0.82)
A12: Log (Plan Size) (t-1) | B12: =TEXT('Estimates-split'!Z7,"0.000")&IF('Estimates-split'!AC7="","",IF('Estimates-split'!AC7<0.01,"***",IF('Estimates-split'!AC7<0.05,"**",IF('Estimates-split'!AC7<0.1,"*","")))) -> -0.026* | C12: =TEXT('Estimates-split'!AD7,"0.000")&IF('Estimates-split'!AG7="","",IF('Estimates-split'!AG7<0.01,"***",IF('Estimates-split'!AG7<0.05,"**",IF('Estimates-split'!AG7<0.1,"*","")))) -> -0.030* | D12: =TEXT('Estimates-split'!AH7,"0.000")&IF('Estimates-split'!AK7="","",IF('Estimates-split'!AK7<0.01,"***",IF('Estimates-split'!AK7<0.05,"**",IF('Estimates-split'!AK7<0.1,"*","")))) -> 0.025
B13: =IF('Estimates-split'!AB7="","(n/a)","("&TEXT('Estimates-split'!AB7,"0.00")&")") -> (-1.78) | C13: =IF('Estimates-split'!AF7="","(n/a)","("&TEXT('Estimates-split'!AF7,"0.00")&")") -> (-2.01) | D13: =IF('Estimates-split'!AJ7="","(n/a)","("&TEXT('Estimates-split'!AJ7,"0.00")&")") -> (0.20)
A14: Funding Ratio (t-1) | B14: =TEXT('Estimates-split'!Z8,"0.000")&IF('Estimates-split'!AC8="","",IF('Estimates-split'!AC8<0.01,"***",IF('Estimates-split'!AC8<0.05,"**",IF('Estimates-split'!AC8<0.1,"*","")))) -> -0.001 | C14: =TEXT('Estimates-split'!AD8,"0.000")&IF('Estimates-split'!AG8="","",IF('Estimates-split'!AG8<0.01,"***",IF('Estimates-split'!AG8<0.05,"**",IF('Estimates-split'!AG8<0.1,"*","")))) -> -0.001 | D14: =TEXT('Estimates-split'!AH8,"0.000")&IF('Estimates-split'!AK8="","",IF('Estimates-split'!AK8<0.01,"***",IF('Estimates-split'!AK8<0.05,"**",IF('Estimates-split'!AK8<0.1,"*","")))) -> -0.002**
B15: =IF('Estimates-split'!AB8="","(n/a)","("&TEXT('Estimates-split'!AB8,"0.00")&")") -> (-0.69) | C15: =IF('Estimates-split'!AF8="","(n/a)","("&TEXT('Estimates-split'!AF8,"0.00")&")") -> (-1.36) | D15: =IF('Estimates-split'!AJ8="","(n/a)","("&TEXT('Estimates-split'!AJ8,"0.00")&")") -> (-2.71)
A16: Equity Allocation (%) | B16: =TEXT('Estimates-split'!Z9,"0.000")&IF('Estimates-split'!AC9="","",IF('Estimates-split'!AC9<0.01,"***",IF('Estimates-split'!AC9<0.05,"**",IF('Estimates-split'!AC9<0.1,"*","")))) -> -0.036 | C16: =TEXT('Estimates-split'!AD9,"0.000")&IF('Estimates-split'!AG9="","",IF('Estimates-split'!AG9<0.01,"***",IF('Estimates-split'!AG9<0.05,"**",IF('Estimates-split'!AG9<0.1,"*","")))) -> -0.084 | D16: =TEXT('Estimates-split'!AH9,"0.000")&IF('Estimates-split'!AK9="","",IF('Estimates-split'!AK9<0.01,"***",IF('Estimates-split'!AK9<0.05,"**",IF('Estimates-split'!AK9<0.1,"*","")))) -> -0.080
B17: =IF('Estimates-split'!AB9="","(n/a)","("&TEXT('Estimates-split'!AB9,"0.00")&")") -> (-1.06) | C17: =IF('Estimates-split'!AF9="","(n/a)","("&TEXT('Estimates-split'!AF9,"0.00")&")") -> (-1.25) | D17: =IF('Estimates-split'!AJ9="","(n/a)","("&TEXT('Estimates-split'!AJ9,"0.00")&")") -> (-1.55)
A18: Fixed Income Allocation (%) | B18: =TEXT('Estimates-split'!Z10,"0.000")&IF('Estimates-split'!AC10="","",IF('Estimates-split'!AC10<0.01,"***",IF('Estimates-split'!AC10<0.05,"**",IF('Estimates-split'!AC10<0.1,"*","")))) -> -0.040 | C18: =TEXT('Estimates-split'!AD10,"0.000")&IF('Estimates-split'!AG10="","",IF('Estimates-split'!AG10<0.01,"***",IF('Estimates-split'!AG10<0.05,"**",IF('Estimates-split'!AG10<0.1,"*","")))) -> -0.088 | D18: =TEXT('Estimates-split'!AH10,"0.000")&IF('Estimates-split'!AK10="","",IF('Estimates-split'!AK10<0.01,"***",IF('Estimates-split'!AK10<0.05,"**",IF('Estimates-split'!AK10<0.1,"*","")))) -> -0.086
B19: =IF('Estimates-split'!AB10="","(n/a)","("&TEXT('Estimates-split'!AB10,"0.00")&")") -> (-1.19) | C19: =IF('Estimates-split'!AF10="","(n/a)","("&TEXT('Estimates-split'!AF10,"0.00")&")") -> (-1.31) | D19: =IF('Estimates-split'!AJ10="","(n/a)","("&TEXT('Estimates-split'!AJ10,"0.00")&")") -> (-1.65)
A20: Real Estate Allocation (%) | B20: =TEXT('Estimates-split'!Z11,"0.000")&IF('Estimates-split'!AC11="","",IF('Estimates-split'!AC11<0.01,"***",IF('Estimates-split'!AC11<0.05,"**",IF('Estimates-split'!AC11<0.1,"*","")))) -> -0.034 | C20: =TEXT('Estimates-split'!AD11,"0.000")&IF('Estimates-split'!AG11="","",IF('Estimates-split'!AG11<0.01,"***",IF('Estimates-split'!AG11<0.05,"**",IF('Estimates-split'!AG11<0.1,"*","")))) -> -0.080 | D20: =TEXT('Estimates-split'!AH11,"0.000")&IF('Estimates-split'!AK11="","",IF('Estimates-split'!AK11<0.01,"***",IF('Estimates-split'!AK11<0.05,"**",IF('Estimates-split'!AK11<0.1,"*","")))) -> -0.084
B21: =IF('Estimates-split'!AB11="","(n/a)","("&TEXT('Estimates-split'!AB11,"0.00")&")") -> (-0.96) | C21: =IF('Estimates-split'!AF11="","(n/a)","("&TEXT('Estimates-split'!AF11,"0.00")&")") -> (-1.19) | D21: =IF('Estimates-split'!AJ11="","(n/a)","("&TEXT('Estimates-split'!AJ11,"0.00")&")") -> (-1.63)
A22: Private Equity Allocation (%) | B22: =TEXT('Estimates-split'!Z12,"0.000")&IF('Estimates-split'!AC12="","",IF('Estimates-split'!AC12<0.01,"***",IF('Estimates-split'!AC12<0.05,"**",IF('Estimates-split'!AC12<0.1,"*","")))) -> -0.030 | C22: =TEXT('Estimates-split'!AD12,"0.000")&IF('Estimates-split'!AG12="","",IF('Estimates-split'!AG12<0.01,"***",IF('Estimates-split'!AG12<0.05,"**",IF('Estimates-split'!AG12<0.1,"*","")))) -> -0.077 | D22: =TEXT('Estimates-split'!AH12,"0.000")&IF('Estimates-split'!AK12="","",IF('Estimates-split'!AK12<0.01,"***",IF('Estimates-split'!AK12<0.05,"**",IF('Estimates-split'!AK12<0.1,"*","")))) -> -0.059
B23: =IF('Estimates-split'!AB12="","(n/a)","("&TEXT('Estimates-split'!AB12,"0.00")&")") -> (-0.91) | C23: =IF('Estimates-split'!AF12="","(n/a)","("&TEXT('Estimates-split'!AF12,"0.00")&")") -> (-1.15) | D23: =IF('Estimates-split'!AJ12="","(n/a)","("&TEXT('Estimates-split'!AJ12,"0.00")&")") -> (-1.13)
A24: Hedge Fund Allocation (%) | B24: =TEXT('Estimates-split'!Z13,"0.000")&IF('Estimates-split'!AC13="","",IF('Estimates-split'!AC13<0.01,"***",IF('Estimates-split'!AC13<0.05,"**",IF('Estimates-split'!AC13<0.1,"*","")))) -> -0.019 | C24: =TEXT('Estimates-split'!AD13,"0.000")&IF('Estimates-split'!AG13="","",IF('Estimates-split'!AG13<0.01,"***",IF('Estimates-split'!AG13<0.05,"**",IF('Estimates-split'!AG13<0.1,"*","")))) -> -0.066 | D24: =TEXT('Estimates-split'!AH13,"0.000")&IF('Estimates-split'!AK13="","",IF('Estimates-split'!AK13<0.01,"***",IF('Estimates-split'!AK13<0.05,"**",IF('Estimates-split'!AK13<0.1,"*","")))) -> -0.063
B25: =IF('Estimates-split'!AB13="","(n/a)","("&TEXT('Estimates-split'!AB13,"0.00")&")") -> (-0.55) | C25: =IF('Estimates-split'!AF13="","(n/a)","("&TEXT('Estimates-split'!AF13,"0.00")&")") -> (-0.97) | D25: =IF('Estimates-split'!AJ13="","(n/a)","("&TEXT('Estimates-split'!AJ13,"0.00")&")") -> (-1.23)
A26: Misc. Alternatives Allocation (%) | B26: =TEXT('Estimates-split'!Z14,"0.000")&IF('Estimates-split'!AC14="","",IF('Estimates-split'!AC14<0.01,"***",IF('Estimates-split'!AC14<0.05,"**",IF('Estimates-split'!AC14<0.1,"*","")))) -> -0.033 | C26: =TEXT('Estimates-split'!AD14,"0.000")&IF('Estimates-split'!AG14="","",IF('Estimates-split'!AG14<0.01,"***",IF('Estimates-split'!AG14<0.05,"**",IF('Estimates-split'!AG14<0.1,"*","")))) -> -0.079 | D26: =TEXT('Estimates-split'!AH14,"0.000")&IF('Estimates-split'!AK14="","",IF('Estimates-split'!AK14<0.01,"***",IF('Estimates-split'!AK14<0.05,"**",IF('Estimates-split'!AK14<0.1,"*","")))) -> -0.068
B27: =IF('Estimates-split'!AB14="","(n/a)","("&TEXT('Estimates-split'!AB14,"0.00")&")") -> (-1.01) | C27: =IF('Estimates-split'!AF14="","(n/a)","("&TEXT('Estimates-split'!AF14,"0.00")&")") -> (-1.19) | D27: =IF('Estimates-split'!AJ14="","(n/a)","("&TEXT('Estimates-split'!AJ14,"0.00")&")") -> (-1.32)
A28: Commodities Allocation (%) | B28: =TEXT('Estimates-split'!Z15,"0.000")&IF('Estimates-split'!AC15="","",IF('Estimates-split'!AC15<0.01,"***",IF('Estimates-split'!AC15<0.05,"**",IF('Estimates-split'!AC15<0.1,"*","")))) -> -0.031 | C28: =TEXT('Estimates-split'!AD15,"0.000")&IF('Estimates-split'!AG15="","",IF('Estimates-split'!AG15<0.01,"***",IF('Estimates-split'!AG15<0.05,"**",IF('Estimates-split'!AG15<0.1,"*","")))) -> -0.076 | D28: =TEXT('Estimates-split'!AH15,"0.000")&IF('Estimates-split'!AK15="","",IF('Estimates-split'!AK15<0.01,"***",IF('Estimates-split'!AK15<0.05,"**",IF('Estimates-split'!AK15<0.1,"*","")))) -> -0.078
B29: =IF('Estimates-split'!AB15="","(n/a)","("&TEXT('Estimates-split'!AB15,"0.00")&")") -> (-0.89) | C29: =IF('Estimates-split'!AF15="","(n/a)","("&TEXT('Estimates-split'!AF15,"0.00")&")") -> (-1.16) | D29: =IF('Estimates-split'!AJ15="","(n/a)","("&TEXT('Estimates-split'!AJ15,"0.00")&")") -> (-1.54)
A30: Cash Allocation (%) | B30: =TEXT('Estimates-split'!Z16,"0.000")&IF('Estimates-split'!AC16="","",IF('Estimates-split'!AC16<0.01,"***",IF('Estimates-split'!AC16<0.05,"**",IF('Estimates-split'!AC16<0.1,"*","")))) -> -0.034 | C30: =TEXT('Estimates-split'!AD16,"0.000")&IF('Estimates-split'!AG16="","",IF('Estimates-split'!AG16<0.01,"***",IF('Estimates-split'!AG16<0.05,"**",IF('Estimates-split'!AG16<0.1,"*","")))) -> -0.082 | D30: =TEXT('Estimates-split'!AH16,"0.000")&IF('Estimates-split'!AK16="","",IF('Estimates-split'!AK16<0.01,"***",IF('Estimates-split'!AK16<0.05,"**",IF('Estimates-split'!AK16<0.1,"*","")))) -> -0.074
B31: =IF('Estimates-split'!AB16="","(n/a)","("&TEXT('Estimates-split'!AB16,"0.00")&")") -> (-1.01) | C31: =IF('Estimates-split'!AF16="","(n/a)","("&TEXT('Estimates-split'!AF16,"0.00")&")") -> (-1.22) | D31: =IF('Estimates-split'!AJ16="","(n/a)","("&TEXT('Estimates-split'!AJ16,"0.00")&")") -> (-1.43)
A32: Financial Center (0/1) | B32: =TEXT('Estimates-split'!Z17,"0.000")&IF('Estimates-split'!AC17="","",IF('Estimates-split'!AC17<0.01,"***",IF('Estimates-split'!AC17<0.05,"**",IF('Estimates-split'!AC17<0.1,"*","")))) -> -0.027 | C32: =TEXT('Estimates-split'!AD17,"0.000")&IF('Estimates-split'!AG17="","",IF('Estimates-split'!AG17<0.01,"***",IF('Estimates-split'!AG17<0.05,"**",IF('Estimates-split'!AG17<0.1,"*","")))) -> 0.027
B33: =IF('Estimates-split'!AB17="","(n/a)","("&TEXT('Estimates-split'!AB17,"0.00")&")") -> (-0.66) | C33: =IF('Estimates-split'!AF17="","(n/a)","("&TEXT('Estimates-split'!AF17,"0.00")&")") -> (0.74)
A34: Log (CIO Age) (t-1) | C34: =TEXT('Estimates-split'!AD18,"0.000")&IF('Estimates-split'!AG18="","",IF('Estimates-split'!AG18<0.01,"***",IF('Estimates-split'!AG18<0.05,"**",IF('Estimates-split'!AG18<0.1,"*","")))) -> 0.064 | D34: =TEXT('Estimates-split'!AH18,"0.000")&IF('Estimates-split'!AK18="","",IF('Estimates-split'!AK18<0.01,"***",IF('Estimates-split'!AK18<0.05,"**",IF('Estimates-split'!AK18<0.1,"*","")))) -> -0.188*
C35: =IF('Estimates-split'!AF18="","(n/a)","("&TEXT('Estimates-split'!AF18,"0.00")&")") -> (0.64) | D35: =IF('Estimates-split'!AJ18="","(n/a)","("&TEXT('Estimates-split'!AJ18,"0.00")&")") -> (-1.78)
A36: Log (CIO Tenure) (t-1) | C36: =TEXT('Estimates-split'!AD19,"0.000")&IF('Estimates-split'!AG19="","",IF('Estimates-split'!AG19<0.01,"***",IF('Estimates-split'!AG19<0.05,"**",IF('Estimates-split'!AG19<0.1,"*","")))) -> -0.004 | D36: =TEXT('Estimates-split'!AH19,"0.000")&IF('Estimates-split'!AK19="","",IF('Estimates-split'!AK19<0.01,"***",IF('Estimates-split'!AK19<0.05,"**",IF('Estimates-split'!AK19<0.1,"*","")))) -> 0.019
C37: =IF('Estimates-split'!AF19="","(n/a)","("&TEXT('Estimates-split'!AF19,"0.00")&")") -> (-0.32) | D37: =IF('Estimates-split'!AJ19="","(n/a)","("&TEXT('Estimates-split'!AJ19,"0.00")&")") -> (1.66)
A38: CIO Prior Private Experience (0/1) | C38: =TEXT('Estimates-split'!AD20,"0.000")&IF('Estimates-split'!AG20="","",IF('Estimates-split'!AG20<0.01,"***",IF('Estimates-split'!AG20<0.05,"**",IF('Estimates-split'!AG20<0.1,"*","")))) -> -0.070 | D38: =TEXT('Estimates-split'!AH20,"0.000")&IF('Estimates-split'!AK20="","",IF('Estimates-split'!AK20<0.01,"***",IF('Estimates-split'!AK20<0.05,"**",IF('Estimates-split'!AK20<0.1,"*","")))) -> -0.069
C39: =IF('Estimates-split'!AF20="","(n/a)","("&TEXT('Estimates-split'!AF20,"0.00")&")") -> (-1.63) | D39: =IF('Estimates-split'!AJ20="","(n/a)","("&TEXT('Estimates-split'!AJ20,"0.00")&")") -> (-1.22)
A40: CIO Attended Elite College (0/1) | C40: =TEXT('Estimates-split'!AD21,"0.000")&IF('Estimates-split'!AG21="","",IF('Estimates-split'!AG21<0.01,"***",IF('Estimates-split'!AG21<0.05,"**",IF('Estimates-split'!AG21<0.1,"*","")))) -> 0.026 | D40: =TEXT('Estimates-split'!AH21,"0.000")&IF('Estimates-split'!AK21="","",IF('Estimates-split'!AK21<0.01,"***",IF('Estimates-split'!AK21<0.05,"**",IF('Estimates-split'!AK21<0.1,"*","")))) -> -0.068*
C41: =IF('Estimates-split'!AF21="","(n/a)","("&TEXT('Estimates-split'!AF21,"0.00")&")") -> (0.66) | D41: =IF('Estimates-split'!AJ21="","(n/a)","("&TEXT('Estimates-split'!AJ21,"0.00")&")") -> (-1.90)
A42: Separate Investment Board (0/1) | C42: =TEXT('Estimates-split'!AD22,"0.000")&IF('Estimates-split'!AG22="","",IF('Estimates-split'!AG22<0.01,"***",IF('Estimates-split'!AG22<0.05,"**",IF('Estimates-split'!AG22<0.1,"*","")))) -> -0.020 | D42: =TEXT('Estimates-split'!AH22,"0.000")&IF('Estimates-split'!AK22="","",IF('Estimates-split'!AK22<0.01,"***",IF('Estimates-split'!AK22<0.05,"**",IF('Estimates-split'!AK22<0.1,"*","")))) -> -0.275***
C43: =IF('Estimates-split'!AF22="","(n/a)","("&TEXT('Estimates-split'!AF22,"0.00")&")") -> (-0.46) | D43: =IF('Estimates-split'!AJ22="","(n/a)","("&TEXT('Estimates-split'!AJ22,"0.00")&")") -> (-3.41)
A44: % Political Appointees on Board | C44: =TEXT('Estimates-split'!AD23,"0.000")&IF('Estimates-split'!AG23="","",IF('Estimates-split'!AG23<0.01,"***",IF('Estimates-split'!AG23<0.05,"**",IF('Estimates-split'!AG23<0.1,"*","")))) -> -0.094* | D44: =TEXT('Estimates-split'!AH23,"0.000")&IF('Estimates-split'!AK23="","",IF('Estimates-split'!AK23<0.01,"***",IF('Estimates-split'!AK23<0.05,"**",IF('Estimates-split'!AK23<0.1,"*","")))) -> -0.185
C45: =IF('Estimates-split'!AF23="","(n/a)","("&TEXT('Estimates-split'!AF23,"0.00")&")") -> (-1.79) | D45: =IF('Estimates-split'!AJ23="","(n/a)","("&TEXT('Estimates-split'!AJ23,"0.00")&")") -> (-1.03)
A47: Observations | B47: ='Estimates-split'!Z26 -> 1480 | C47: ='Estimates-split'!AD26 -> 1293 | D47: ='Estimates-split'!AH26 -> 1291
A48: Adjusted R-squared | B48: ='Estimates-split'!Z29 -> 0.35213737 | C48: ='Estimates-split'!AD29 -> 0.36348566 | D48: ='Estimates-split'!AH29 -> 0.65835334
A49: Plan FE | B49: No | C49: No | D49: Yes
A50: Fiscal-Year-End FE | B50: Yes | C50: Yes | D50: Yes
A51: p-value: First Half = Second Half | B51: ='Estimates-split'!AC24 -> 0.93030429 | C51: ='Estimates-split'!AG24 -> 0.72024481 | D51: ='Estimates-split'!AK24 -> 0.79480886

Sheet Table XI
A1: Table XI: Conflicted CIOs: Plan Performance in the First versus Second Half of Tenure, Conflicted CIOs Only (updated benchmark, fiscal-year-end fixed effects)
A2: This table reports results of tests that regress the returns of public pension plans run by conflicted CIOs on an indicator variable, Second Half of Tenure, which is equal to 1 in the fiscal years in which the CIO's tenure exceeds one half of the CIO's tenure at departure and 0 otherwise. Conflicted CIOs are defined as in Table III, and the sample is restricted to their plan-years, so the coefficient compares the second half of a conflicted CIO's tenure with the first half. Tenure at departure is the CIO's tenure in the last fiscal year observed in the plan plus any gap to the departure year. The performance measure in Panel A is Peer-Adjusted Return, which is the difference of a plan's return and the average pension plan return each year. The performance measure in Panel B is Benchmark-Adjusted Return, which is calculated as the plan's return minus the return of its updated policy benchmark (the benchmark return reported in the plan's financial report or, where none is stated, an inferred value graded A or B). The other independent variables are as defined in Table I. All columns include fiscal-year-end date fixed effects, so plans are compared only with plans whose fiscal year covers the same twelve months. Column 3 adds plan fixed effects. Columns 4 and 5 include CIO fixed effects and omit the CIO-level controls; Column 5 restricts the sample to CIOs whose tenure at departure is at least four years, so that each half of tenure contains at least two fiscal years. The standard errors are double clustered by plan and year. Coefficients marked with ***, **, and * are significant at the 1%, 5%, and 10% level, respectively.
A4: Panel A. Peer-Adjusted Returns
B5: (1) | C5: (2) | D5: (3) | E5: (4) | F5: (5)
B6: Peer-adj. Ret. (t) | C6: Peer-adj. Ret. (t) | D6: Peer-adj. Ret. (t) | E6: Peer-adj. Ret. (t) | F6: Peer-adj. Ret. (t)
A7: Second Half of Tenure (0/1) | B7: =TEXT(Estimates!B4,"0.000")&IF(Estimates!E4="","",IF(Estimates!E4<0.01,"***",IF(Estimates!E4<0.05,"**",IF(Estimates!E4<0.1,"*","")))) -> -0.214 | C7: =TEXT(Estimates!F4,"0.000")&IF(Estimates!I4="","",IF(Estimates!I4<0.01,"***",IF(Estimates!I4<0.05,"**",IF(Estimates!I4<0.1,"*","")))) -> -0.081 | D7: =TEXT(Estimates!J4,"0.000")&IF(Estimates!M4="","",IF(Estimates!M4<0.01,"***",IF(Estimates!M4<0.05,"**",IF(Estimates!M4<0.1,"*","")))) -> -0.088 | E7: =TEXT(Estimates!N4,"0.000")&IF(Estimates!Q4="","",IF(Estimates!Q4<0.01,"***",IF(Estimates!Q4<0.05,"**",IF(Estimates!Q4<0.1,"*","")))) -> -0.965* | F7: =TEXT(Estimates!R4,"0.000")&IF(Estimates!U4="","",IF(Estimates!U4<0.01,"***",IF(Estimates!U4<0.05,"**",IF(Estimates!U4<0.1,"*","")))) -> -0.267
B8: =IF(Estimates!D4="","(n/a)","("&TEXT(Estimates!D4,"0.00")&")") -> (-1.15) | C8: =IF(Estimates!H4="","(n/a)","("&TEXT(Estimates!H4,"0.00")&")") -> (-0.34) | D8: =IF(Estimates!L4="","(n/a)","("&TEXT(Estimates!L4,"0.00")&")") -> (-0.30) | E8: =IF(Estimates!P4="","(n/a)","("&TEXT(Estimates!P4,"0.00")&")") -> (-1.88) | F8: =IF(Estimates!T4="","(n/a)","("&TEXT(Estimates!T4,"0.00")&")") -> (-0.27)
A9: Investment Return (t - 1) | B9: =TEXT(Estimates!B5,"0.000")&IF(Estimates!E5="","",IF(Estimates!E5<0.01,"***",IF(Estimates!E5<0.05,"**",IF(Estimates!E5<0.1,"*","")))) -> 0.168 | C9: =TEXT(Estimates!F5,"0.000")&IF(Estimates!I5="","",IF(Estimates!I5<0.01,"***",IF(Estimates!I5<0.05,"**",IF(Estimates!I5<0.1,"*","")))) -> 0.118 | D9: =TEXT(Estimates!J5,"0.000")&IF(Estimates!M5="","",IF(Estimates!M5<0.01,"***",IF(Estimates!M5<0.05,"**",IF(Estimates!M5<0.1,"*","")))) -> 0.084 | E9: =TEXT(Estimates!N5,"0.000")&IF(Estimates!Q5="","",IF(Estimates!Q5<0.01,"***",IF(Estimates!Q5<0.05,"**",IF(Estimates!Q5<0.1,"*","")))) -> 0.099 | F9: =TEXT(Estimates!R5,"0.000")&IF(Estimates!U5="","",IF(Estimates!U5<0.01,"***",IF(Estimates!U5<0.05,"**",IF(Estimates!U5<0.1,"*","")))) -> 0.223
B10: =IF(Estimates!D5="","(n/a)","("&TEXT(Estimates!D5,"0.00")&")") -> (1.10) | C10: =IF(Estimates!H5="","(n/a)","("&TEXT(Estimates!H5,"0.00")&")") -> (0.72) | D10: =IF(Estimates!L5="","(n/a)","("&TEXT(Estimates!L5,"0.00")&")") -> (0.56) | E10: =IF(Estimates!P5="","(n/a)","("&TEXT(Estimates!P5,"0.00")&")") -> (0.75) | F10: =IF(Estimates!T5="","(n/a)","("&TEXT(Estimates!T5,"0.00")&")") -> (1.66)
A11: Log (Plan Size) (t-1) | B11: =TEXT(Estimates!B6,"0.000")&IF(Estimates!E6="","",IF(Estimates!E6<0.01,"***",IF(Estimates!E6<0.05,"**",IF(Estimates!E6<0.1,"*","")))) -> -0.075 | C11: =TEXT(Estimates!F6,"0.000")&IF(Estimates!I6="","",IF(Estimates!I6<0.01,"***",IF(Estimates!I6<0.05,"**",IF(Estimates!I6<0.1,"*","")))) -> -0.082 | D11: =TEXT(Estimates!J6,"0.000")&IF(Estimates!M6="","",IF(Estimates!M6<0.01,"***",IF(Estimates!M6<0.05,"**",IF(Estimates!M6<0.1,"*","")))) -> -0.080 | E11: =TEXT(Estimates!N6,"0.000")&IF(Estimates!Q6="","",IF(Estimates!Q6<0.01,"***",IF(Estimates!Q6<0.05,"**",IF(Estimates!Q6<0.1,"*","")))) -> 1.085 | F11: =TEXT(Estimates!R6,"0.000")&IF(Estimates!U6="","",IF(Estimates!U6<0.01,"***",IF(Estimates!U6<0.05,"**",IF(Estimates!U6<0.1,"*","")))) -> 0.656
B12: =IF(Estimates!D6="","(n/a)","("&TEXT(Estimates!D6,"0.00")&")") -> (-0.69) | C12: =IF(Estimates!H6="","(n/a)","("&TEXT(Estimates!H6,"0.00")&")") -> (-0.70) | D12: =IF(Estimates!L6="","(n/a)","("&TEXT(Estimates!L6,"0.00")&")") -> (-0.09) | E12: =IF(Estimates!P6="","(n/a)","("&TEXT(Estimates!P6,"0.00")&")") -> (0.59) | F12: =IF(Estimates!T6="","(n/a)","("&TEXT(Estimates!T6,"0.00")&")") -> (0.32)
A13: Funding Ratio (t-1) | B13: =TEXT(Estimates!B7,"0.000")&IF(Estimates!E7="","",IF(Estimates!E7<0.01,"***",IF(Estimates!E7<0.05,"**",IF(Estimates!E7<0.1,"*","")))) -> -0.016 | C13: =TEXT(Estimates!F7,"0.000")&IF(Estimates!I7="","",IF(Estimates!I7<0.01,"***",IF(Estimates!I7<0.05,"**",IF(Estimates!I7<0.1,"*","")))) -> -0.014* | D13: =TEXT(Estimates!J7,"0.000")&IF(Estimates!M7="","",IF(Estimates!M7<0.01,"***",IF(Estimates!M7<0.05,"**",IF(Estimates!M7<0.1,"*","")))) -> -0.027 | E13: =TEXT(Estimates!N7,"0.000")&IF(Estimates!Q7="","",IF(Estimates!Q7<0.01,"***",IF(Estimates!Q7<0.05,"**",IF(Estimates!Q7<0.1,"*","")))) -> -0.071** | F13: =TEXT(Estimates!R7,"0.000")&IF(Estimates!U7="","",IF(Estimates!U7<0.01,"***",IF(Estimates!U7<0.05,"**",IF(Estimates!U7<0.1,"*","")))) -> -0.077**
B14: =IF(Estimates!D7="","(n/a)","("&TEXT(Estimates!D7,"0.00")&")") -> (-1.63) | C14: =IF(Estimates!H7="","(n/a)","("&TEXT(Estimates!H7,"0.00")&")") -> (-2.06) | D14: =IF(Estimates!L7="","(n/a)","("&TEXT(Estimates!L7,"0.00")&")") -> (-0.97) | E14: =IF(Estimates!P7="","(n/a)","("&TEXT(Estimates!P7,"0.00")&")") -> (-2.61) | F14: =IF(Estimates!T7="","(n/a)","("&TEXT(Estimates!T7,"0.00")&")") -> (-2.25)
A15: Equity Allocation (%) | B15: =TEXT(Estimates!B8,"0.000")&IF(Estimates!E8="","",IF(Estimates!E8<0.01,"***",IF(Estimates!E8<0.05,"**",IF(Estimates!E8<0.1,"*","")))) -> 0.024 | C15: =TEXT(Estimates!F8,"0.000")&IF(Estimates!I8="","",IF(Estimates!I8<0.01,"***",IF(Estimates!I8<0.05,"**",IF(Estimates!I8<0.1,"*","")))) -> 0.051 | D15: =TEXT(Estimates!J8,"0.000")&IF(Estimates!M8="","",IF(Estimates!M8<0.01,"***",IF(Estimates!M8<0.05,"**",IF(Estimates!M8<0.1,"*","")))) -> -0.605 | E15: =TEXT(Estimates!N8,"0.000")&IF(Estimates!Q8="","",IF(Estimates!Q8<0.01,"***",IF(Estimates!Q8<0.05,"**",IF(Estimates!Q8<0.1,"*","")))) -> -1.644*** | F15: =TEXT(Estimates!R8,"0.000")&IF(Estimates!U8="","",IF(Estimates!U8<0.01,"***",IF(Estimates!U8<0.05,"**",IF(Estimates!U8<0.1,"*","")))) -> -2.006***
B16: =IF(Estimates!D8="","(n/a)","("&TEXT(Estimates!D8,"0.00")&")") -> (0.21) | C16: =IF(Estimates!H8="","(n/a)","("&TEXT(Estimates!H8,"0.00")&")") -> (0.43) | D16: =IF(Estimates!L8="","(n/a)","("&TEXT(Estimates!L8,"0.00")&")") -> (-1.59) | E16: =IF(Estimates!P8="","(n/a)","("&TEXT(Estimates!P8,"0.00")&")") -> (-3.94) | F16: =IF(Estimates!T8="","(n/a)","("&TEXT(Estimates!T8,"0.00")&")") -> (-4.22)
A17: Fixed Income Allocation (%) | B17: =TEXT(Estimates!B9,"0.000")&IF(Estimates!E9="","",IF(Estimates!E9<0.01,"***",IF(Estimates!E9<0.05,"**",IF(Estimates!E9<0.1,"*","")))) -> -0.006 | C17: =TEXT(Estimates!F9,"0.000")&IF(Estimates!I9="","",IF(Estimates!I9<0.01,"***",IF(Estimates!I9<0.05,"**",IF(Estimates!I9<0.1,"*","")))) -> 0.007 | D17: =TEXT(Estimates!J9,"0.000")&IF(Estimates!M9="","",IF(Estimates!M9<0.01,"***",IF(Estimates!M9<0.05,"**",IF(Estimates!M9<0.1,"*","")))) -> -0.640 | E17: =TEXT(Estimates!N9,"0.000")&IF(Estimates!Q9="","",IF(Estimates!Q9<0.01,"***",IF(Estimates!Q9<0.05,"**",IF(Estimates!Q9<0.1,"*","")))) -> -1.709*** | F17: =TEXT(Estimates!R9,"0.000")&IF(Estimates!U9="","",IF(Estimates!U9<0.01,"***",IF(Estimates!U9<0.05,"**",IF(Estimates!U9<0.1,"*","")))) -> -2.090***
B18: =IF(Estimates!D9="","(n/a)","("&TEXT(Estimates!D9,"0.00")&")") -> (-0.05) | C18: =IF(Estimates!H9="","(n/a)","("&TEXT(Estimates!H9,"0.00")&")") -> (0.07) | D18: =IF(Estimates!L9="","(n/a)","("&TEXT(Estimates!L9,"0.00")&")") -> (-1.70) | E18: =IF(Estimates!P9="","(n/a)","("&TEXT(Estimates!P9,"0.00")&")") -> (-3.94) | F18: =IF(Estimates!T9="","(n/a)","("&TEXT(Estimates!T9,"0.00")&")") -> (-4.33)
A19: Real Estate Allocation (%) | B19: =TEXT(Estimates!B10,"0.000")&IF(Estimates!E10="","",IF(Estimates!E10<0.01,"***",IF(Estimates!E10<0.05,"**",IF(Estimates!E10<0.1,"*","")))) -> 0.074 | C19: =TEXT(Estimates!F10,"0.000")&IF(Estimates!I10="","",IF(Estimates!I10<0.01,"***",IF(Estimates!I10<0.05,"**",IF(Estimates!I10<0.1,"*","")))) -> 0.100 | D19: =TEXT(Estimates!J10,"0.000")&IF(Estimates!M10="","",IF(Estimates!M10<0.01,"***",IF(Estimates!M10<0.05,"**",IF(Estimates!M10<0.1,"*","")))) -> -0.660 | E19: =TEXT(Estimates!N10,"0.000")&IF(Estimates!Q10="","",IF(Estimates!Q10<0.01,"***",IF(Estimates!Q10<0.05,"**",IF(Estimates!Q10<0.1,"*","")))) -> -2.007*** | F19: =TEXT(Estimates!R10,"0.000")&IF(Estimates!U10="","",IF(Estimates!U10<0.01,"***",IF(Estimates!U10<0.05,"**",IF(Estimates!U10<0.1,"*","")))) -> -2.539***
B20: =IF(Estimates!D10="","(n/a)","("&TEXT(Estimates!D10,"0.00")&")") -> (0.56) | C20: =IF(Estimates!H10="","(n/a)","("&TEXT(Estimates!H10,"0.00")&")") -> (0.89) | D20: =IF(Estimates!L10="","(n/a)","("&TEXT(Estimates!L10,"0.00")&")") -> (-1.66) | E20: =IF(Estimates!P10="","(n/a)","("&TEXT(Estimates!P10,"0.00")&")") -> (-3.21) | F20: =IF(Estimates!T10="","(n/a)","("&TEXT(Estimates!T10,"0.00")&")") -> (-3.81)
A21: Private Equity Allocation (%) | B21: =TEXT(Estimates!B11,"0.000")&IF(Estimates!E11="","",IF(Estimates!E11<0.01,"***",IF(Estimates!E11<0.05,"**",IF(Estimates!E11<0.1,"*","")))) -> 0.019 | C21: =TEXT(Estimates!F11,"0.000")&IF(Estimates!I11="","",IF(Estimates!I11<0.01,"***",IF(Estimates!I11<0.05,"**",IF(Estimates!I11<0.1,"*","")))) -> 0.043 | D21: =TEXT(Estimates!J11,"0.000")&IF(Estimates!M11="","",IF(Estimates!M11<0.01,"***",IF(Estimates!M11<0.05,"**",IF(Estimates!M11<0.1,"*","")))) -> -0.545 | E21: =TEXT(Estimates!N11,"0.000")&IF(Estimates!Q11="","",IF(Estimates!Q11<0.01,"***",IF(Estimates!Q11<0.05,"**",IF(Estimates!Q11<0.1,"*","")))) -> -1.504*** | F21: =TEXT(Estimates!R11,"0.000")&IF(Estimates!U11="","",IF(Estimates!U11<0.01,"***",IF(Estimates!U11<0.05,"**",IF(Estimates!U11<0.1,"*","")))) -> -1.739***
B22: =IF(Estimates!D11="","(n/a)","("&TEXT(Estimates!D11,"0.00")&")") -> (0.14) | C22: =IF(Estimates!H11="","(n/a)","("&TEXT(Estimates!H11,"0.00")&")") -> (0.36) | D22: =IF(Estimates!L11="","(n/a)","("&TEXT(Estimates!L11,"0.00")&")") -> (-1.33) | E22: =IF(Estimates!P11="","(n/a)","("&TEXT(Estimates!P11,"0.00")&")") -> (-3.80) | F22: =IF(Estimates!T11="","(n/a)","("&TEXT(Estimates!T11,"0.00")&")") -> (-3.83)
A23: Hedge Fund Allocation (%) | B23: =TEXT(Estimates!B12,"0.000")&IF(Estimates!E12="","",IF(Estimates!E12<0.01,"***",IF(Estimates!E12<0.05,"**",IF(Estimates!E12<0.1,"*","")))) -> -0.010 | C23: =TEXT(Estimates!F12,"0.000")&IF(Estimates!I12="","",IF(Estimates!I12<0.01,"***",IF(Estimates!I12<0.05,"**",IF(Estimates!I12<0.1,"*","")))) -> 0.003 | D23: =TEXT(Estimates!J12,"0.000")&IF(Estimates!M12="","",IF(Estimates!M12<0.01,"***",IF(Estimates!M12<0.05,"**",IF(Estimates!M12<0.1,"*","")))) -> -0.647* | E23: =TEXT(Estimates!N12,"0.000")&IF(Estimates!Q12="","",IF(Estimates!Q12<0.01,"***",IF(Estimates!Q12<0.05,"**",IF(Estimates!Q12<0.1,"*","")))) -> -1.699*** | F23: =TEXT(Estimates!R12,"0.000")&IF(Estimates!U12="","",IF(Estimates!U12<0.01,"***",IF(Estimates!U12<0.05,"**",IF(Estimates!U12<0.1,"*","")))) -> -2.055***
B24: =IF(Estimates!D12="","(n/a)","("&TEXT(Estimates!D12,"0.00")&")") -> (-0.09) | C24: =IF(Estimates!H12="","(n/a)","("&TEXT(Estimates!H12,"0.00")&")") -> (0.03) | D24: =IF(Estimates!L12="","(n/a)","("&TEXT(Estimates!L12,"0.00")&")") -> (-2.02) | E24: =IF(Estimates!P12="","(n/a)","("&TEXT(Estimates!P12,"0.00")&")") -> (-3.74) | F24: =IF(Estimates!T12="","(n/a)","("&TEXT(Estimates!T12,"0.00")&")") -> (-4.04)
A25: Misc. Alternatives Allocation (%) | B25: =TEXT(Estimates!B13,"0.000")&IF(Estimates!E13="","",IF(Estimates!E13<0.01,"***",IF(Estimates!E13<0.05,"**",IF(Estimates!E13<0.1,"*","")))) -> 0.077 | C25: =TEXT(Estimates!F13,"0.000")&IF(Estimates!I13="","",IF(Estimates!I13<0.01,"***",IF(Estimates!I13<0.05,"**",IF(Estimates!I13<0.1,"*","")))) -> 0.105 | D25: =TEXT(Estimates!J13,"0.000")&IF(Estimates!M13="","",IF(Estimates!M13<0.01,"***",IF(Estimates!M13<0.05,"**",IF(Estimates!M13<0.1,"*","")))) -> -0.253 | E25: =TEXT(Estimates!N13,"0.000")&IF(Estimates!Q13="","",IF(Estimates!Q13<0.01,"***",IF(Estimates!Q13<0.05,"**",IF(Estimates!Q13<0.1,"*","")))) -> -1.527 | F25: =TEXT(Estimates!R13,"0.000")&IF(Estimates!U13="","",IF(Estimates!U13<0.01,"***",IF(Estimates!U13<0.05,"**",IF(Estimates!U13<0.1,"*","")))) -> -2.017*
B26: =IF(Estimates!D13="","(n/a)","("&TEXT(Estimates!D13,"0.00")&")") -> (0.59) | C26: =IF(Estimates!H13="","(n/a)","("&TEXT(Estimates!H13,"0.00")&")") -> (1.14) | D26: =IF(Estimates!L13="","(n/a)","("&TEXT(Estimates!L13,"0.00")&")") -> (-0.22) | E26: =IF(Estimates!P13="","(n/a)","("&TEXT(Estimates!P13,"0.00")&")") -> (-1.39) | F26: =IF(Estimates!T13="","(n/a)","("&TEXT(Estimates!T13,"0.00")&")") -> (-1.86)
A27: Commodities Allocation (%) | B27: =TEXT(Estimates!B14,"0.000")&IF(Estimates!E14="","",IF(Estimates!E14<0.01,"***",IF(Estimates!E14<0.05,"**",IF(Estimates!E14<0.1,"*","")))) -> -0.027 | C27: =TEXT(Estimates!F14,"0.000")&IF(Estimates!I14="","",IF(Estimates!I14<0.01,"***",IF(Estimates!I14<0.05,"**",IF(Estimates!I14<0.1,"*","")))) -> -0.015 | D27: =TEXT(Estimates!J14,"0.000")&IF(Estimates!M14="","",IF(Estimates!M14<0.01,"***",IF(Estimates!M14<0.05,"**",IF(Estimates!M14<0.1,"*","")))) -> -0.702* | E27: =TEXT(Estimates!N14,"0.000")&IF(Estimates!Q14="","",IF(Estimates!Q14<0.01,"***",IF(Estimates!Q14<0.05,"**",IF(Estimates!Q14<0.1,"*","")))) -> -1.535*** | F27: =TEXT(Estimates!R14,"0.000")&IF(Estimates!U14="","",IF(Estimates!U14<0.01,"***",IF(Estimates!U14<0.05,"**",IF(Estimates!U14<0.1,"*","")))) -> -1.670***
B28: =IF(Estimates!D14="","(n/a)","("&TEXT(Estimates!D14,"0.00")&")") -> (-0.26) | C28: =IF(Estimates!H14="","(n/a)","("&TEXT(Estimates!H14,"0.00")&")") -> (-0.14) | D28: =IF(Estimates!L14="","(n/a)","("&TEXT(Estimates!L14,"0.00")&")") -> (-1.81) | E28: =IF(Estimates!P14="","(n/a)","("&TEXT(Estimates!P14,"0.00")&")") -> (-3.88) | F28: =IF(Estimates!T14="","(n/a)","("&TEXT(Estimates!T14,"0.00")&")") -> (-4.61)
A29: Cash Allocation (%) | B29: =TEXT(Estimates!B15,"0.000")&IF(Estimates!E15="","",IF(Estimates!E15<0.01,"***",IF(Estimates!E15<0.05,"**",IF(Estimates!E15<0.1,"*","")))) -> 0.033 | C29: =TEXT(Estimates!F15,"0.000")&IF(Estimates!I15="","",IF(Estimates!I15<0.01,"***",IF(Estimates!I15<0.05,"**",IF(Estimates!I15<0.1,"*","")))) -> 0.076 | D29: =TEXT(Estimates!J15,"0.000")&IF(Estimates!M15="","",IF(Estimates!M15<0.01,"***",IF(Estimates!M15<0.05,"**",IF(Estimates!M15<0.1,"*","")))) -> -0.499 | E29: =TEXT(Estimates!N15,"0.000")&IF(Estimates!Q15="","",IF(Estimates!Q15<0.01,"***",IF(Estimates!Q15<0.05,"**",IF(Estimates!Q15<0.1,"*","")))) -> -1.514*** | F29: =TEXT(Estimates!R15,"0.000")&IF(Estimates!U15="","",IF(Estimates!U15<0.01,"***",IF(Estimates!U15<0.05,"**",IF(Estimates!U15<0.1,"*","")))) -> -2.031***
B30: =IF(Estimates!D15="","(n/a)","("&TEXT(Estimates!D15,"0.00")&")") -> (0.28) | C30: =IF(Estimates!H15="","(n/a)","("&TEXT(Estimates!H15,"0.00")&")") -> (0.52) | D30: =IF(Estimates!L15="","(n/a)","("&TEXT(Estimates!L15,"0.00")&")") -> (-1.25) | E30: =IF(Estimates!P15="","(n/a)","("&TEXT(Estimates!P15,"0.00")&")") -> (-3.46) | F30: =IF(Estimates!T15="","(n/a)","("&TEXT(Estimates!T15,"0.00")&")") -> (-3.87)
A31: Financial Center (0/1) | B31: =TEXT(Estimates!B16,"0.000")&IF(Estimates!E16="","",IF(Estimates!E16<0.01,"***",IF(Estimates!E16<0.05,"**",IF(Estimates!E16<0.1,"*","")))) -> 0.435 | C31: =TEXT(Estimates!F16,"0.000")&IF(Estimates!I16="","",IF(Estimates!I16<0.01,"***",IF(Estimates!I16<0.05,"**",IF(Estimates!I16<0.1,"*","")))) -> 0.412 | E31: =TEXT(Estimates!N16,"0.000")&IF(Estimates!Q16="","",IF(Estimates!Q16<0.01,"***",IF(Estimates!Q16<0.05,"**",IF(Estimates!Q16<0.1,"*","")))) -> 0.550
B32: =IF(Estimates!D16="","(n/a)","("&TEXT(Estimates!D16,"0.00")&")") -> (1.06) | C32: =IF(Estimates!H16="","(n/a)","("&TEXT(Estimates!H16,"0.00")&")") -> (1.28) | E32: =IF(Estimates!P16="","(n/a)","("&TEXT(Estimates!P16,"0.00")&")") -> (0.00)
A33: Log (CIO Age) (t-1) | C33: =TEXT(Estimates!F17,"0.000")&IF(Estimates!I17="","",IF(Estimates!I17<0.01,"***",IF(Estimates!I17<0.05,"**",IF(Estimates!I17<0.1,"*","")))) -> -0.122 | D33: =TEXT(Estimates!J17,"0.000")&IF(Estimates!M17="","",IF(Estimates!M17<0.01,"***",IF(Estimates!M17<0.05,"**",IF(Estimates!M17<0.1,"*","")))) -> 0.733
C34: =IF(Estimates!H17="","(n/a)","("&TEXT(Estimates!H17,"0.00")&")") -> (-0.12) | D34: =IF(Estimates!L17="","(n/a)","("&TEXT(Estimates!L17,"0.00")&")") -> (0.40)
A35: Log (CIO Tenure) (t-1) | C35: =TEXT(Estimates!F18,"0.000")&IF(Estimates!I18="","",IF(Estimates!I18<0.01,"***",IF(Estimates!I18<0.05,"**",IF(Estimates!I18<0.1,"*","")))) -> 0.031 | D35: =TEXT(Estimates!J18,"0.000")&IF(Estimates!M18="","",IF(Estimates!M18<0.01,"***",IF(Estimates!M18<0.05,"**",IF(Estimates!M18<0.1,"*","")))) -> 0.025
C36: =IF(Estimates!H18="","(n/a)","("&TEXT(Estimates!H18,"0.00")&")") -> (0.17) | D36: =IF(Estimates!L18="","(n/a)","("&TEXT(Estimates!L18,"0.00")&")") -> (0.07)
A37: CIO Prior Private Experience (0/1) | C37: =TEXT(Estimates!F19,"0.000")&IF(Estimates!I19="","",IF(Estimates!I19<0.01,"***",IF(Estimates!I19<0.05,"**",IF(Estimates!I19<0.1,"*","")))) -> -0.034 | D37: =TEXT(Estimates!J19,"0.000")&IF(Estimates!M19="","",IF(Estimates!M19<0.01,"***",IF(Estimates!M19<0.05,"**",IF(Estimates!M19<0.1,"*","")))) -> -0.136
C38: =IF(Estimates!H19="","(n/a)","("&TEXT(Estimates!H19,"0.00")&")") -> (-0.18) | D38: =IF(Estimates!L19="","(n/a)","("&TEXT(Estimates!L19,"0.00")&")") -> (-0.16)
A39: CIO Attended Elite College (0/1) | C39: =TEXT(Estimates!F20,"0.000")&IF(Estimates!I20="","",IF(Estimates!I20<0.01,"***",IF(Estimates!I20<0.05,"**",IF(Estimates!I20<0.1,"*","")))) -> -0.134 | D39: =TEXT(Estimates!J20,"0.000")&IF(Estimates!M20="","",IF(Estimates!M20<0.01,"***",IF(Estimates!M20<0.05,"**",IF(Estimates!M20<0.1,"*","")))) -> 0.158
C40: =IF(Estimates!H20="","(n/a)","("&TEXT(Estimates!H20,"0.00")&")") -> (-0.71) | D40: =IF(Estimates!L20="","(n/a)","("&TEXT(Estimates!L20,"0.00")&")") -> (0.31)
A41: Separate Investment Board (0/1) | C41: =TEXT(Estimates!F21,"0.000")&IF(Estimates!I21="","",IF(Estimates!I21<0.01,"***",IF(Estimates!I21<0.05,"**",IF(Estimates!I21<0.1,"*","")))) -> 0.240
C42: =IF(Estimates!H21="","(n/a)","("&TEXT(Estimates!H21,"0.00")&")") -> (0.76)
A43: % Political Appointees on Board | C43: =TEXT(Estimates!F22,"0.000")&IF(Estimates!I22="","",IF(Estimates!I22<0.01,"***",IF(Estimates!I22<0.05,"**",IF(Estimates!I22<0.1,"*","")))) -> 0.034 | D43: =TEXT(Estimates!J22,"0.000")&IF(Estimates!M22="","",IF(Estimates!M22<0.01,"***",IF(Estimates!M22<0.05,"**",IF(Estimates!M22<0.1,"*","")))) -> 2.560
C44: =IF(Estimates!H22="","(n/a)","("&TEXT(Estimates!H22,"0.00")&")") -> (0.05) | D44: =IF(Estimates!L22="","(n/a)","("&TEXT(Estimates!L22,"0.00")&")") -> (0.56)
A46: Observations | B46: =Estimates!B24 -> 299 | C46: =Estimates!F24 -> 274 | D46: =Estimates!J24 -> 273 | E46: =Estimates!N24 -> 282 | F46: =Estimates!R24 -> 190
A47: Adjusted R-squared | B47: =Estimates!B27 -> 0.080956317 | C47: =Estimates!F27 -> 0.044884219 | D47: =Estimates!J27 -> -0.0031475011 | E47: =Estimates!N27 -> 0.04291211 | F47: =Estimates!R27 -> 0.11508256
A48: Number of CIOs | B48: =Estimates!B28 -> 43 | C48: =Estimates!F28 -> 41 | D48: =Estimates!J28 -> 41 | E48: =Estimates!N28 -> 43 | F48: =Estimates!R28 -> 24
A49: Plan FE | B49: No | C49: No | D49: Yes | E49: No | F49: No
A50: Fiscal-Year-End FE | B50: Yes | C50: Yes | D50: Yes | E50: Yes | F50: Yes
A51: CIO FE | B51: No | C51: No | D51: No | E51: Yes | F51: Yes
A52: Min. Tenure at Departure (years) | F52: 4
A55: Panel B. Benchmark-Adjusted Returns
B56: (1) | C56: (2) | D56: (3) | E56: (4) | F56: (5)
B57: Bench-adj. Ret. (t) | C57: Bench-adj. Ret. (t) | D57: Bench-adj. Ret. (t) | E57: Bench-adj. Ret. (t) | F57: Bench-adj. Ret. (t)
A58: Second Half of Tenure (0/1) | B58: =TEXT(Estimates!V4,"0.000")&IF(Estimates!Y4="","",IF(Estimates!Y4<0.01,"***",IF(Estimates!Y4<0.05,"**",IF(Estimates!Y4<0.1,"*","")))) -> 0.097 | C58: =TEXT(Estimates!Z4,"0.000")&IF(Estimates!AC4="","",IF(Estimates!AC4<0.01,"***",IF(Estimates!AC4<0.05,"**",IF(Estimates!AC4<0.1,"*","")))) -> 0.359 | D58: =TEXT(Estimates!AD4,"0.000")&IF(Estimates!AG4="","",IF(Estimates!AG4<0.01,"***",IF(Estimates!AG4<0.05,"**",IF(Estimates!AG4<0.1,"*","")))) -> 0.565* | E58: =TEXT(Estimates!AH4,"0.000")&IF(Estimates!AK4="","",IF(Estimates!AK4<0.01,"***",IF(Estimates!AK4<0.05,"**",IF(Estimates!AK4<0.1,"*","")))) -> -0.164 | F58: =TEXT(Estimates!AL4,"0.000")&IF(Estimates!AO4="","",IF(Estimates!AO4<0.01,"***",IF(Estimates!AO4<0.05,"**",IF(Estimates!AO4<0.1,"*","")))) -> 0.002
B59: =IF(Estimates!X4="","(n/a)","("&TEXT(Estimates!X4,"0.00")&")") -> (0.39) | C59: =IF(Estimates!AB4="","(n/a)","("&TEXT(Estimates!AB4,"0.00")&")") -> (1.22) | D59: =IF(Estimates!AF4="","(n/a)","("&TEXT(Estimates!AF4,"0.00")&")") -> (2.01) | E59: =IF(Estimates!AJ4="","(n/a)","("&TEXT(Estimates!AJ4,"0.00")&")") -> (-0.46) | F59: =IF(Estimates!AN4="","(n/a)","("&TEXT(Estimates!AN4,"0.00")&")") -> (0.00)
A60: Investment Return (t - 1) | B60: =TEXT(Estimates!V5,"0.000")&IF(Estimates!Y5="","",IF(Estimates!Y5<0.01,"***",IF(Estimates!Y5<0.05,"**",IF(Estimates!Y5<0.1,"*","")))) -> 0.136 | C60: =TEXT(Estimates!Z5,"0.000")&IF(Estimates!AC5="","",IF(Estimates!AC5<0.01,"***",IF(Estimates!AC5<0.05,"**",IF(Estimates!AC5<0.1,"*","")))) -> 0.050 | D60: =TEXT(Estimates!AD5,"0.000")&IF(Estimates!AG5="","",IF(Estimates!AG5<0.01,"***",IF(Estimates!AG5<0.05,"**",IF(Estimates!AG5<0.1,"*","")))) -> 0.015 | E60: =TEXT(Estimates!AH5,"0.000")&IF(Estimates!AK5="","",IF(Estimates!AK5<0.01,"***",IF(Estimates!AK5<0.05,"**",IF(Estimates!AK5<0.1,"*","")))) -> -0.132 | F60: =TEXT(Estimates!AL5,"0.000")&IF(Estimates!AO5="","",IF(Estimates!AO5<0.01,"***",IF(Estimates!AO5<0.05,"**",IF(Estimates!AO5<0.1,"*","")))) -> 0.060
B61: =IF(Estimates!X5="","(n/a)","("&TEXT(Estimates!X5,"0.00")&")") -> (0.63) | C61: =IF(Estimates!AB5="","(n/a)","("&TEXT(Estimates!AB5,"0.00")&")") -> (0.24) | D61: =IF(Estimates!AF5="","(n/a)","("&TEXT(Estimates!AF5,"0.00")&")") -> (0.08) | E61: =IF(Estimates!AJ5="","(n/a)","("&TEXT(Estimates!AJ5,"0.00")&")") -> (-1.24) | F61: =IF(Estimates!AN5="","(n/a)","("&TEXT(Estimates!AN5,"0.00")&")") -> (0.46)
A62: Log (Plan Size) (t-1) | B62: =TEXT(Estimates!V6,"0.000")&IF(Estimates!Y6="","",IF(Estimates!Y6<0.01,"***",IF(Estimates!Y6<0.05,"**",IF(Estimates!Y6<0.1,"*","")))) -> 0.035 | C62: =TEXT(Estimates!Z6,"0.000")&IF(Estimates!AC6="","",IF(Estimates!AC6<0.01,"***",IF(Estimates!AC6<0.05,"**",IF(Estimates!AC6<0.1,"*","")))) -> -0.010 | D62: =TEXT(Estimates!AD6,"0.000")&IF(Estimates!AG6="","",IF(Estimates!AG6<0.01,"***",IF(Estimates!AG6<0.05,"**",IF(Estimates!AG6<0.1,"*","")))) -> 0.336 | E62: =TEXT(Estimates!AH6,"0.000")&IF(Estimates!AK6="","",IF(Estimates!AK6<0.01,"***",IF(Estimates!AK6<0.05,"**",IF(Estimates!AK6<0.1,"*","")))) -> 0.356 | F62: =TEXT(Estimates!AL6,"0.000")&IF(Estimates!AO6="","",IF(Estimates!AO6<0.01,"***",IF(Estimates!AO6<0.05,"**",IF(Estimates!AO6<0.1,"*","")))) -> 1.443
B63: =IF(Estimates!X6="","(n/a)","("&TEXT(Estimates!X6,"0.00")&")") -> (0.45) | C63: =IF(Estimates!AB6="","(n/a)","("&TEXT(Estimates!AB6,"0.00")&")") -> (-0.10) | D63: =IF(Estimates!AF6="","(n/a)","("&TEXT(Estimates!AF6,"0.00")&")") -> (0.42) | E63: =IF(Estimates!AJ6="","(n/a)","("&TEXT(Estimates!AJ6,"0.00")&")") -> (0.40) | F63: =IF(Estimates!AN6="","(n/a)","("&TEXT(Estimates!AN6,"0.00")&")") -> (1.66)
A64: Funding Ratio (t-1) | B64: =TEXT(Estimates!V7,"0.000")&IF(Estimates!Y7="","",IF(Estimates!Y7<0.01,"***",IF(Estimates!Y7<0.05,"**",IF(Estimates!Y7<0.1,"*","")))) -> -0.008 | C64: =TEXT(Estimates!Z7,"0.000")&IF(Estimates!AC7="","",IF(Estimates!AC7<0.01,"***",IF(Estimates!AC7<0.05,"**",IF(Estimates!AC7<0.1,"*","")))) -> -0.007 | D64: =TEXT(Estimates!AD7,"0.000")&IF(Estimates!AG7="","",IF(Estimates!AG7<0.01,"***",IF(Estimates!AG7<0.05,"**",IF(Estimates!AG7<0.1,"*","")))) -> -0.010 | E64: =TEXT(Estimates!AH7,"0.000")&IF(Estimates!AK7="","",IF(Estimates!AK7<0.01,"***",IF(Estimates!AK7<0.05,"**",IF(Estimates!AK7<0.1,"*","")))) -> -0.010 | F64: =TEXT(Estimates!AL7,"0.000")&IF(Estimates!AO7="","",IF(Estimates!AO7<0.01,"***",IF(Estimates!AO7<0.05,"**",IF(Estimates!AO7<0.1,"*","")))) -> -0.041
B65: =IF(Estimates!X7="","(n/a)","("&TEXT(Estimates!X7,"0.00")&")") -> (-0.85) | C65: =IF(Estimates!AB7="","(n/a)","("&TEXT(Estimates!AB7,"0.00")&")") -> (-1.07) | D65: =IF(Estimates!AF7="","(n/a)","("&TEXT(Estimates!AF7,"0.00")&")") -> (-0.44) | E65: =IF(Estimates!AJ7="","(n/a)","("&TEXT(Estimates!AJ7,"0.00")&")") -> (-0.37) | F65: =IF(Estimates!AN7="","(n/a)","("&TEXT(Estimates!AN7,"0.00")&")") -> (-1.28)
A66: Equity Allocation (%) | B66: =TEXT(Estimates!V8,"0.000")&IF(Estimates!Y8="","",IF(Estimates!Y8<0.01,"***",IF(Estimates!Y8<0.05,"**",IF(Estimates!Y8<0.1,"*","")))) -> -0.344 | C66: =TEXT(Estimates!Z8,"0.000")&IF(Estimates!AC8="","",IF(Estimates!AC8<0.01,"***",IF(Estimates!AC8<0.05,"**",IF(Estimates!AC8<0.1,"*","")))) -> -0.198 | D66: =TEXT(Estimates!AD8,"0.000")&IF(Estimates!AG8="","",IF(Estimates!AG8<0.01,"***",IF(Estimates!AG8<0.05,"**",IF(Estimates!AG8<0.1,"*","")))) -> -0.560 | E66: =TEXT(Estimates!AH8,"0.000")&IF(Estimates!AK8="","",IF(Estimates!AK8<0.01,"***",IF(Estimates!AK8<0.05,"**",IF(Estimates!AK8<0.1,"*","")))) -> -0.887* | F66: =TEXT(Estimates!AL8,"0.000")&IF(Estimates!AO8="","",IF(Estimates!AO8<0.01,"***",IF(Estimates!AO8<0.05,"**",IF(Estimates!AO8<0.1,"*","")))) -> -1.111*
B67: =IF(Estimates!X8="","(n/a)","("&TEXT(Estimates!X8,"0.00")&")") -> (-1.48) | C67: =IF(Estimates!AB8="","(n/a)","("&TEXT(Estimates!AB8,"0.00")&")") -> (-0.80) | D67: =IF(Estimates!AF8="","(n/a)","("&TEXT(Estimates!AF8,"0.00")&")") -> (-1.09) | E67: =IF(Estimates!AJ8="","(n/a)","("&TEXT(Estimates!AJ8,"0.00")&")") -> (-1.97) | F67: =IF(Estimates!AN8="","(n/a)","("&TEXT(Estimates!AN8,"0.00")&")") -> (-1.80)
A68: Fixed Income Allocation (%) | B68: =TEXT(Estimates!V9,"0.000")&IF(Estimates!Y9="","",IF(Estimates!Y9<0.01,"***",IF(Estimates!Y9<0.05,"**",IF(Estimates!Y9<0.1,"*","")))) -> -0.325 | C68: =TEXT(Estimates!Z9,"0.000")&IF(Estimates!AC9="","",IF(Estimates!AC9<0.01,"***",IF(Estimates!AC9<0.05,"**",IF(Estimates!AC9<0.1,"*","")))) -> -0.183 | D68: =TEXT(Estimates!AD9,"0.000")&IF(Estimates!AG9="","",IF(Estimates!AG9<0.01,"***",IF(Estimates!AG9<0.05,"**",IF(Estimates!AG9<0.1,"*","")))) -> -0.510 | E68: =TEXT(Estimates!AH9,"0.000")&IF(Estimates!AK9="","",IF(Estimates!AK9<0.01,"***",IF(Estimates!AK9<0.05,"**",IF(Estimates!AK9<0.1,"*","")))) -> -0.856* | F68: =TEXT(Estimates!AL9,"0.000")&IF(Estimates!AO9="","",IF(Estimates!AO9<0.01,"***",IF(Estimates!AO9<0.05,"**",IF(Estimates!AO9<0.1,"*","")))) -> -1.082*
B69: =IF(Estimates!X9="","(n/a)","("&TEXT(Estimates!X9,"0.00")&")") -> (-1.45) | C69: =IF(Estimates!AB9="","(n/a)","("&TEXT(Estimates!AB9,"0.00")&")") -> (-0.84) | D69: =IF(Estimates!AF9="","(n/a)","("&TEXT(Estimates!AF9,"0.00")&")") -> (-1.06) | E69: =IF(Estimates!AJ9="","(n/a)","("&TEXT(Estimates!AJ9,"0.00")&")") -> (-1.97) | F69: =IF(Estimates!AN9="","(n/a)","("&TEXT(Estimates!AN9,"0.00")&")") -> (-1.76)
A70: Real Estate Allocation (%) | B70: =TEXT(Estimates!V10,"0.000")&IF(Estimates!Y10="","",IF(Estimates!Y10<0.01,"***",IF(Estimates!Y10<0.05,"**",IF(Estimates!Y10<0.1,"*","")))) -> -0.334 | C70: =TEXT(Estimates!Z10,"0.000")&IF(Estimates!AC10="","",IF(Estimates!AC10<0.01,"***",IF(Estimates!AC10<0.05,"**",IF(Estimates!AC10<0.1,"*","")))) -> -0.175 | D70: =TEXT(Estimates!AD10,"0.000")&IF(Estimates!AG10="","",IF(Estimates!AG10<0.01,"***",IF(Estimates!AG10<0.05,"**",IF(Estimates!AG10<0.1,"*","")))) -> -0.471 | E70: =TEXT(Estimates!AH10,"0.000")&IF(Estimates!AK10="","",IF(Estimates!AK10<0.01,"***",IF(Estimates!AK10<0.05,"**",IF(Estimates!AK10<0.1,"*","")))) -> -1.017* | F70: =TEXT(Estimates!AL10,"0.000")&IF(Estimates!AO10="","",IF(Estimates!AO10<0.01,"***",IF(Estimates!AO10<0.05,"**",IF(Estimates!AO10<0.1,"*","")))) -> -1.352*
B71: =IF(Estimates!X10="","(n/a)","("&TEXT(Estimates!X10,"0.00")&")") -> (-1.40) | C71: =IF(Estimates!AB10="","(n/a)","("&TEXT(Estimates!AB10,"0.00")&")") -> (-0.75) | D71: =IF(Estimates!AF10="","(n/a)","("&TEXT(Estimates!AF10,"0.00")&")") -> (-1.01) | E71: =IF(Estimates!AJ10="","(n/a)","("&TEXT(Estimates!AJ10,"0.00")&")") -> (-2.04) | F71: =IF(Estimates!AN10="","(n/a)","("&TEXT(Estimates!AN10,"0.00")&")") -> (-1.89)
A72: Private Equity Allocation (%) | B72: =TEXT(Estimates!V11,"0.000")&IF(Estimates!Y11="","",IF(Estimates!Y11<0.01,"***",IF(Estimates!Y11<0.05,"**",IF(Estimates!Y11<0.1,"*","")))) -> -0.343 | C72: =TEXT(Estimates!Z11,"0.000")&IF(Estimates!AC11="","",IF(Estimates!AC11<0.01,"***",IF(Estimates!AC11<0.05,"**",IF(Estimates!AC11<0.1,"*","")))) -> -0.191 | D72: =TEXT(Estimates!AD11,"0.000")&IF(Estimates!AG11="","",IF(Estimates!AG11<0.01,"***",IF(Estimates!AG11<0.05,"**",IF(Estimates!AG11<0.1,"*","")))) -> -0.485 | E72: =TEXT(Estimates!AH11,"0.000")&IF(Estimates!AK11="","",IF(Estimates!AK11<0.01,"***",IF(Estimates!AK11<0.05,"**",IF(Estimates!AK11<0.1,"*","")))) -> -0.852** | F72: =TEXT(Estimates!AL11,"0.000")&IF(Estimates!AO11="","",IF(Estimates!AO11<0.01,"***",IF(Estimates!AO11<0.05,"**",IF(Estimates!AO11<0.1,"*","")))) -> -0.931*
B73: =IF(Estimates!X11="","(n/a)","("&TEXT(Estimates!X11,"0.00")&")") -> (-1.44) | C73: =IF(Estimates!AB11="","(n/a)","("&TEXT(Estimates!AB11,"0.00")&")") -> (-0.80) | D73: =IF(Estimates!AF11="","(n/a)","("&TEXT(Estimates!AF11,"0.00")&")") -> (-1.03) | E73: =IF(Estimates!AJ11="","(n/a)","("&TEXT(Estimates!AJ11,"0.00")&")") -> (-2.15) | F73: =IF(Estimates!AN11="","(n/a)","("&TEXT(Estimates!AN11,"0.00")&")") -> (-1.76)
A74: Hedge Fund Allocation (%) | B74: =TEXT(Estimates!V12,"0.000")&IF(Estimates!Y12="","",IF(Estimates!Y12<0.01,"***",IF(Estimates!Y12<0.05,"**",IF(Estimates!Y12<0.1,"*","")))) -> -0.309 | C74: =TEXT(Estimates!Z12,"0.000")&IF(Estimates!AC12="","",IF(Estimates!AC12<0.01,"***",IF(Estimates!AC12<0.05,"**",IF(Estimates!AC12<0.1,"*","")))) -> -0.171 | D74: =TEXT(Estimates!AD12,"0.000")&IF(Estimates!AG12="","",IF(Estimates!AG12<0.01,"***",IF(Estimates!AG12<0.05,"**",IF(Estimates!AG12<0.1,"*","")))) -> -0.560 | E74: =TEXT(Estimates!AH12,"0.000")&IF(Estimates!AK12="","",IF(Estimates!AK12<0.01,"***",IF(Estimates!AK12<0.05,"**",IF(Estimates!AK12<0.1,"*","")))) -> -0.852* | F74: =TEXT(Estimates!AL12,"0.000")&IF(Estimates!AO12="","",IF(Estimates!AO12<0.01,"***",IF(Estimates!AO12<0.05,"**",IF(Estimates!AO12<0.1,"*","")))) -> -1.198*
B75: =IF(Estimates!X12="","(n/a)","("&TEXT(Estimates!X12,"0.00")&")") -> (-1.32) | C75: =IF(Estimates!AB12="","(n/a)","("&TEXT(Estimates!AB12,"0.00")&")") -> (-0.74) | D75: =IF(Estimates!AF12="","(n/a)","("&TEXT(Estimates!AF12,"0.00")&")") -> (-1.15) | E75: =IF(Estimates!AJ12="","(n/a)","("&TEXT(Estimates!AJ12,"0.00")&")") -> (-1.90) | F75: =IF(Estimates!AN12="","(n/a)","("&TEXT(Estimates!AN12,"0.00")&")") -> (-1.94)
A76: Misc. Alternatives Allocation (%) | B76: =TEXT(Estimates!V13,"0.000")&IF(Estimates!Y13="","",IF(Estimates!Y13<0.01,"***",IF(Estimates!Y13<0.05,"**",IF(Estimates!Y13<0.1,"*","")))) -> -0.312 | C76: =TEXT(Estimates!Z13,"0.000")&IF(Estimates!AC13="","",IF(Estimates!AC13<0.01,"***",IF(Estimates!AC13<0.05,"**",IF(Estimates!AC13<0.1,"*","")))) -> -0.182 | D76: =TEXT(Estimates!AD13,"0.000")&IF(Estimates!AG13="","",IF(Estimates!AG13<0.01,"***",IF(Estimates!AG13<0.05,"**",IF(Estimates!AG13<0.1,"*","")))) -> -0.011 | E76: =TEXT(Estimates!AH13,"0.000")&IF(Estimates!AK13="","",IF(Estimates!AK13<0.01,"***",IF(Estimates!AK13<0.05,"**",IF(Estimates!AK13<0.1,"*","")))) -> -0.293 | F76: =TEXT(Estimates!AL13,"0.000")&IF(Estimates!AO13="","",IF(Estimates!AO13<0.01,"***",IF(Estimates!AO13<0.05,"**",IF(Estimates!AO13<0.1,"*","")))) -> -0.388
B77: =IF(Estimates!X13="","(n/a)","("&TEXT(Estimates!X13,"0.00")&")") -> (-1.32) | C77: =IF(Estimates!AB13="","(n/a)","("&TEXT(Estimates!AB13,"0.00")&")") -> (-0.68) | D77: =IF(Estimates!AF13="","(n/a)","("&TEXT(Estimates!AF13,"0.00")&")") -> (-0.01) | E77: =IF(Estimates!AJ13="","(n/a)","("&TEXT(Estimates!AJ13,"0.00")&")") -> (-0.45) | F77: =IF(Estimates!AN13="","(n/a)","("&TEXT(Estimates!AN13,"0.00")&")") -> (-0.37)
A78: Commodities Allocation (%) | B78: =TEXT(Estimates!V14,"0.000")&IF(Estimates!Y14="","",IF(Estimates!Y14<0.01,"***",IF(Estimates!Y14<0.05,"**",IF(Estimates!Y14<0.1,"*","")))) -> -0.306 | C78: =TEXT(Estimates!Z14,"0.000")&IF(Estimates!AC14="","",IF(Estimates!AC14<0.01,"***",IF(Estimates!AC14<0.05,"**",IF(Estimates!AC14<0.1,"*","")))) -> -0.186 | D78: =TEXT(Estimates!AD14,"0.000")&IF(Estimates!AG14="","",IF(Estimates!AG14<0.01,"***",IF(Estimates!AG14<0.05,"**",IF(Estimates!AG14<0.1,"*","")))) -> -0.440 | E78: =TEXT(Estimates!AH14,"0.000")&IF(Estimates!AK14="","",IF(Estimates!AK14<0.01,"***",IF(Estimates!AK14<0.05,"**",IF(Estimates!AK14<0.1,"*","")))) -> -0.649 | F78: =TEXT(Estimates!AL14,"0.000")&IF(Estimates!AO14="","",IF(Estimates!AO14<0.01,"***",IF(Estimates!AO14<0.05,"**",IF(Estimates!AO14<0.1,"*","")))) -> -0.854
B79: =IF(Estimates!X14="","(n/a)","("&TEXT(Estimates!X14,"0.00")&")") -> (-1.37) | C79: =IF(Estimates!AB14="","(n/a)","("&TEXT(Estimates!AB14,"0.00")&")") -> (-0.70) | D79: =IF(Estimates!AF14="","(n/a)","("&TEXT(Estimates!AF14,"0.00")&")") -> (-0.84) | E79: =IF(Estimates!AJ14="","(n/a)","("&TEXT(Estimates!AJ14,"0.00")&")") -> (-1.37) | F79: =IF(Estimates!AN14="","(n/a)","("&TEXT(Estimates!AN14,"0.00")&")") -> (-1.41)
A80: Cash Allocation (%) | B80: =TEXT(Estimates!V15,"0.000")&IF(Estimates!Y15="","",IF(Estimates!Y15<0.01,"***",IF(Estimates!Y15<0.05,"**",IF(Estimates!Y15<0.1,"*","")))) -> -0.338 | C80: =TEXT(Estimates!Z15,"0.000")&IF(Estimates!AC15="","",IF(Estimates!AC15<0.01,"***",IF(Estimates!AC15<0.05,"**",IF(Estimates!AC15<0.1,"*","")))) -> -0.190 | D80: =TEXT(Estimates!AD15,"0.000")&IF(Estimates!AG15="","",IF(Estimates!AG15<0.01,"***",IF(Estimates!AG15<0.05,"**",IF(Estimates!AG15<0.1,"*","")))) -> -0.440 | E80: =TEXT(Estimates!AH15,"0.000")&IF(Estimates!AK15="","",IF(Estimates!AK15<0.01,"***",IF(Estimates!AK15<0.05,"**",IF(Estimates!AK15<0.1,"*","")))) -> -0.743 | F80: =TEXT(Estimates!AL15,"0.000")&IF(Estimates!AO15="","",IF(Estimates!AO15<0.01,"***",IF(Estimates!AO15<0.05,"**",IF(Estimates!AO15<0.1,"*","")))) -> -0.913
B81: =IF(Estimates!X15="","(n/a)","("&TEXT(Estimates!X15,"0.00")&")") -> (-1.46) | C81: =IF(Estimates!AB15="","(n/a)","("&TEXT(Estimates!AB15,"0.00")&")") -> (-0.76) | D81: =IF(Estimates!AF15="","(n/a)","("&TEXT(Estimates!AF15,"0.00")&")") -> (-0.88) | E81: =IF(Estimates!AJ15="","(n/a)","("&TEXT(Estimates!AJ15,"0.00")&")") -> (-1.73) | F81: =IF(Estimates!AN15="","(n/a)","("&TEXT(Estimates!AN15,"0.00")&")") -> (-1.52)
A82: Financial Center (0/1) | B82: =TEXT(Estimates!V16,"0.000")&IF(Estimates!Y16="","",IF(Estimates!Y16<0.01,"***",IF(Estimates!Y16<0.05,"**",IF(Estimates!Y16<0.1,"*","")))) -> -0.312 | C82: =TEXT(Estimates!Z16,"0.000")&IF(Estimates!AC16="","",IF(Estimates!AC16<0.01,"***",IF(Estimates!AC16<0.05,"**",IF(Estimates!AC16<0.1,"*","")))) -> -0.381
B83: =IF(Estimates!X16="","(n/a)","("&TEXT(Estimates!X16,"0.00")&")") -> (-0.85) | C83: =IF(Estimates!AB16="","(n/a)","("&TEXT(Estimates!AB16,"0.00")&")") -> (-1.22)
A84: Log (CIO Age) (t-1) | C84: =TEXT(Estimates!Z17,"0.000")&IF(Estimates!AC17="","",IF(Estimates!AC17<0.01,"***",IF(Estimates!AC17<0.05,"**",IF(Estimates!AC17<0.1,"*","")))) -> 0.809* | D84: =TEXT(Estimates!AD17,"0.000")&IF(Estimates!AG17="","",IF(Estimates!AG17<0.01,"***",IF(Estimates!AG17<0.05,"**",IF(Estimates!AG17<0.1,"*","")))) -> 4.113***
C85: =IF(Estimates!AB17="","(n/a)","("&TEXT(Estimates!AB17,"0.00")&")") -> (1.78) | D85: =IF(Estimates!AF17="","(n/a)","("&TEXT(Estimates!AF17,"0.00")&")") -> (3.22)
A86: Log (CIO Tenure) (t-1) | C86: =TEXT(Estimates!Z18,"0.000")&IF(Estimates!AC18="","",IF(Estimates!AC18<0.01,"***",IF(Estimates!AC18<0.05,"**",IF(Estimates!AC18<0.1,"*","")))) -> -0.255 | D86: =TEXT(Estimates!AD18,"0.000")&IF(Estimates!AG18="","",IF(Estimates!AG18<0.01,"***",IF(Estimates!AG18<0.05,"**",IF(Estimates!AG18<0.1,"*","")))) -> -0.818**
C87: =IF(Estimates!AB18="","(n/a)","("&TEXT(Estimates!AB18,"0.00")&")") -> (-1.13) | D87: =IF(Estimates!AF18="","(n/a)","("&TEXT(Estimates!AF18,"0.00")&")") -> (-2.20)
A88: CIO Prior Private Experience (0/1) | C88: =TEXT(Estimates!Z19,"0.000")&IF(Estimates!AC19="","",IF(Estimates!AC19<0.01,"***",IF(Estimates!AC19<0.05,"**",IF(Estimates!AC19<0.1,"*","")))) -> -0.257 | D88: =TEXT(Estimates!AD19,"0.000")&IF(Estimates!AG19="","",IF(Estimates!AG19<0.01,"***",IF(Estimates!AG19<0.05,"**",IF(Estimates!AG19<0.1,"*","")))) -> -1.383*
C89: =IF(Estimates!AB19="","(n/a)","("&TEXT(Estimates!AB19,"0.00")&")") -> (-0.55) | D89: =IF(Estimates!AF19="","(n/a)","("&TEXT(Estimates!AF19,"0.00")&")") -> (-1.77)
A90: CIO Attended Elite College (0/1) | C90: =TEXT(Estimates!Z20,"0.000")&IF(Estimates!AC20="","",IF(Estimates!AC20<0.01,"***",IF(Estimates!AC20<0.05,"**",IF(Estimates!AC20<0.1,"*","")))) -> -0.520* | D90: =TEXT(Estimates!AD20,"0.000")&IF(Estimates!AG20="","",IF(Estimates!AG20<0.01,"***",IF(Estimates!AG20<0.05,"**",IF(Estimates!AG20<0.1,"*","")))) -> -0.006
C91: =IF(Estimates!AB20="","(n/a)","("&TEXT(Estimates!AB20,"0.00")&")") -> (-1.89) | D91: =IF(Estimates!AF20="","(n/a)","("&TEXT(Estimates!AF20,"0.00")&")") -> (-0.01)
A92: Separate Investment Board (0/1) | C92: =TEXT(Estimates!Z21,"0.000")&IF(Estimates!AC21="","",IF(Estimates!AC21<0.01,"***",IF(Estimates!AC21<0.05,"**",IF(Estimates!AC21<0.1,"*","")))) -> 0.176
C93: =IF(Estimates!AB21="","(n/a)","("&TEXT(Estimates!AB21,"0.00")&")") -> (0.45)
A94: % Political Appointees on Board | C94: =TEXT(Estimates!Z22,"0.000")&IF(Estimates!AC22="","",IF(Estimates!AC22<0.01,"***",IF(Estimates!AC22<0.05,"**",IF(Estimates!AC22<0.1,"*","")))) -> -0.408 | D94: =TEXT(Estimates!AD22,"0.000")&IF(Estimates!AG22="","",IF(Estimates!AG22<0.01,"***",IF(Estimates!AG22<0.05,"**",IF(Estimates!AG22<0.1,"*","")))) -> -4.531*
C95: =IF(Estimates!AB22="","(n/a)","("&TEXT(Estimates!AB22,"0.00")&")") -> (-0.79) | D95: =IF(Estimates!AF22="","(n/a)","("&TEXT(Estimates!AF22,"0.00")&")") -> (-2.05)
A97: Observations | B97: =Estimates!V24 -> 275 | C97: =Estimates!Z24 -> 254 | D97: =Estimates!AD24 -> 251 | E97: =Estimates!AH24 -> 259 | F97: =Estimates!AL24 -> 175
A98: Adjusted R-squared | B98: =Estimates!V27 -> 0.16117624 | C98: =Estimates!Z27 -> 0.12811226 | D98: =Estimates!AD27 -> 0.16156138 | E98: =Estimates!AH27 -> 0.46213337 | F98: =Estimates!AL27 -> 0.5191564
A99: Number of CIOs | B99: =Estimates!V28 -> 42 | C99: =Estimates!Z28 -> 40 | D99: =Estimates!AD28 -> 40 | E99: =Estimates!AH28 -> 42 | F99: =Estimates!AL28 -> 23
A100: Plan FE | B100: No | C100: No | D100: Yes | E100: No | F100: No
A101: Fiscal-Year-End FE | B101: Yes | C101: Yes | D101: Yes | E101: Yes | F101: Yes
A102: CIO FE | B102: No | C102: No | D102: No | E102: Yes | F102: Yes
A103: Min. Tenure at Departure (years) | F103: 4

Sheet Table XII
A1: Table XII: Conflicted CIOs: Fee Ratio in the First versus Second Half of Tenure, Conflicted CIOs Only (fiscal-year-end fixed effects)
A2: This table repeats the tests of Table XI with Fee Ratio as the dependent variable. Fee Ratio is the plan's total investment fees as a percentage of plan assets. The sample is restricted to plan-years of conflicted CIOs, and Second Half of Tenure is equal to 1 in the fiscal years in which the CIO's tenure exceeds one half of the CIO's tenure at departure and 0 otherwise. The other independent variables are as defined in Table I. All columns include fiscal-year-end date fixed effects, so plans are compared only with plans whose fiscal year covers the same twelve months. Column 3 adds plan fixed effects. Columns 4 and 5 include CIO fixed effects and omit the CIO-level controls; Column 5 restricts the sample to CIOs whose tenure at departure is at least four years. The standard errors are double clustered by plan and year. Coefficients marked with ***, **, and * are significant at the 1%, 5%, and 10% level, respectively.
B4: (1) | C4: (2) | D4: (3) | E4: (4) | F4: (5)
B5: Fee Ratio (t) | C5: Fee Ratio (t) | D5: Fee Ratio (t) | E5: Fee Ratio (t) | F5: Fee Ratio (t)
A6: Second Half of Tenure (0/1) | B6: =TEXT(Estimates!AP4,"0.000")&IF(Estimates!AS4="","",IF(Estimates!AS4<0.01,"***",IF(Estimates!AS4<0.05,"**",IF(Estimates!AS4<0.1,"*","")))) -> -0.065 | C6: =TEXT(Estimates!AT4,"0.000")&IF(Estimates!AW4="","",IF(Estimates!AW4<0.01,"***",IF(Estimates!AW4<0.05,"**",IF(Estimates!AW4<0.1,"*","")))) -> -0.082 | D6: =TEXT(Estimates!AX4,"0.000")&IF(Estimates!BA4="","",IF(Estimates!BA4<0.01,"***",IF(Estimates!BA4<0.05,"**",IF(Estimates!BA4<0.1,"*","")))) -> -0.059 | E6: =TEXT(Estimates!BB4,"0.000")&IF(Estimates!BE4="","",IF(Estimates!BE4<0.01,"***",IF(Estimates!BE4<0.05,"**",IF(Estimates!BE4<0.1,"*","")))) -> -0.066 | F6: =TEXT(Estimates!BF4,"0.000")&IF(Estimates!BI4="","",IF(Estimates!BI4<0.01,"***",IF(Estimates!BI4<0.05,"**",IF(Estimates!BI4<0.1,"*","")))) -> -0.038
B7: =IF(Estimates!AR4="","(n/a)","("&TEXT(Estimates!AR4,"0.00")&")") -> (-1.62) | C7: =IF(Estimates!AV4="","(n/a)","("&TEXT(Estimates!AV4,"0.00")&")") -> (-1.41) | D7: =IF(Estimates!AZ4="","(n/a)","("&TEXT(Estimates!AZ4,"0.00")&")") -> (-1.38) | E7: =IF(Estimates!BD4="","(n/a)","("&TEXT(Estimates!BD4,"0.00")&")") -> (-1.21) | F7: =IF(Estimates!BH4="","(n/a)","("&TEXT(Estimates!BH4,"0.00")&")") -> (-0.54)
A8: Investment Return (t - 1) | B8: =TEXT(Estimates!AP5,"0.000")&IF(Estimates!AS5="","",IF(Estimates!AS5<0.01,"***",IF(Estimates!AS5<0.05,"**",IF(Estimates!AS5<0.1,"*","")))) -> 0.000 | C8: =TEXT(Estimates!AT5,"0.000")&IF(Estimates!AW5="","",IF(Estimates!AW5<0.01,"***",IF(Estimates!AW5<0.05,"**",IF(Estimates!AW5<0.1,"*","")))) -> 0.004 | D8: =TEXT(Estimates!AX5,"0.000")&IF(Estimates!BA5="","",IF(Estimates!BA5<0.01,"***",IF(Estimates!BA5<0.05,"**",IF(Estimates!BA5<0.1,"*","")))) -> 0.007 | E8: =TEXT(Estimates!BB5,"0.000")&IF(Estimates!BE5="","",IF(Estimates!BE5<0.01,"***",IF(Estimates!BE5<0.05,"**",IF(Estimates!BE5<0.1,"*","")))) -> 0.005 | F8: =TEXT(Estimates!BF5,"0.000")&IF(Estimates!BI5="","",IF(Estimates!BI5<0.01,"***",IF(Estimates!BI5<0.05,"**",IF(Estimates!BI5<0.1,"*","")))) -> 0.007*
B9: =IF(Estimates!AR5="","(n/a)","("&TEXT(Estimates!AR5,"0.00")&")") -> (0.03) | C9: =IF(Estimates!AV5="","(n/a)","("&TEXT(Estimates!AV5,"0.00")&")") -> (0.58) | D9: =IF(Estimates!AZ5="","(n/a)","("&TEXT(Estimates!AZ5,"0.00")&")") -> (1.28) | E9: =IF(Estimates!BD5="","(n/a)","("&TEXT(Estimates!BD5,"0.00")&")") -> (1.19) | F9: =IF(Estimates!BH5="","(n/a)","("&TEXT(Estimates!BH5,"0.00")&")") -> (2.00)
A10: Log (Plan Size) (t-1) | B10: =TEXT(Estimates!AP6,"0.000")&IF(Estimates!AS6="","",IF(Estimates!AS6<0.01,"***",IF(Estimates!AS6<0.05,"**",IF(Estimates!AS6<0.1,"*","")))) -> -0.034* | C10: =TEXT(Estimates!AT6,"0.000")&IF(Estimates!AW6="","",IF(Estimates!AW6<0.01,"***",IF(Estimates!AW6<0.05,"**",IF(Estimates!AW6<0.1,"*","")))) -> -0.044* | D10: =TEXT(Estimates!AX6,"0.000")&IF(Estimates!BA6="","",IF(Estimates!BA6<0.01,"***",IF(Estimates!BA6<0.05,"**",IF(Estimates!BA6<0.1,"*","")))) -> -0.348** | E10: =TEXT(Estimates!BB6,"0.000")&IF(Estimates!BE6="","",IF(Estimates!BE6<0.01,"***",IF(Estimates!BE6<0.05,"**",IF(Estimates!BE6<0.1,"*","")))) -> -0.243 | F10: =TEXT(Estimates!BF6,"0.000")&IF(Estimates!BI6="","",IF(Estimates!BI6<0.01,"***",IF(Estimates!BI6<0.05,"**",IF(Estimates!BI6<0.1,"*","")))) -> -0.090
B11: =IF(Estimates!AR6="","(n/a)","("&TEXT(Estimates!AR6,"0.00")&")") -> (-1.75) | C11: =IF(Estimates!AV6="","(n/a)","("&TEXT(Estimates!AV6,"0.00")&")") -> (-2.02) | D11: =IF(Estimates!AZ6="","(n/a)","("&TEXT(Estimates!AZ6,"0.00")&")") -> (-2.35) | E11: =IF(Estimates!BD6="","(n/a)","("&TEXT(Estimates!BD6,"0.00")&")") -> (-1.02) | F11: =IF(Estimates!BH6="","(n/a)","("&TEXT(Estimates!BH6,"0.00")&")") -> (-0.41)
A12: Funding Ratio (t-1) | B12: =TEXT(Estimates!AP7,"0.000")&IF(Estimates!AS7="","",IF(Estimates!AS7<0.01,"***",IF(Estimates!AS7<0.05,"**",IF(Estimates!AS7<0.1,"*","")))) -> -0.003*** | C12: =TEXT(Estimates!AT7,"0.000")&IF(Estimates!AW7="","",IF(Estimates!AW7<0.01,"***",IF(Estimates!AW7<0.05,"**",IF(Estimates!AW7<0.1,"*","")))) -> -0.002*** | D12: =TEXT(Estimates!AX7,"0.000")&IF(Estimates!BA7="","",IF(Estimates!BA7<0.01,"***",IF(Estimates!BA7<0.05,"**",IF(Estimates!BA7<0.1,"*","")))) -> 0.000 | E12: =TEXT(Estimates!BB7,"0.000")&IF(Estimates!BE7="","",IF(Estimates!BE7<0.01,"***",IF(Estimates!BE7<0.05,"**",IF(Estimates!BE7<0.1,"*","")))) -> 0.000 | F12: =TEXT(Estimates!BF7,"0.000")&IF(Estimates!BI7="","",IF(Estimates!BI7<0.01,"***",IF(Estimates!BI7<0.05,"**",IF(Estimates!BI7<0.1,"*","")))) -> -0.001
B13: =IF(Estimates!AR7="","(n/a)","("&TEXT(Estimates!AR7,"0.00")&")") -> (-3.03) | C13: =IF(Estimates!AV7="","(n/a)","("&TEXT(Estimates!AV7,"0.00")&")") -> (-3.17) | D13: =IF(Estimates!AZ7="","(n/a)","("&TEXT(Estimates!AZ7,"0.00")&")") -> (-0.07) | E13: =IF(Estimates!BD7="","(n/a)","("&TEXT(Estimates!BD7,"0.00")&")") -> (0.05) | F13: =IF(Estimates!BH7="","(n/a)","("&TEXT(Estimates!BH7,"0.00")&")") -> (-0.37)
A14: Equity Allocation (%) | B14: =TEXT(Estimates!AP8,"0.000")&IF(Estimates!AS8="","",IF(Estimates!AS8<0.01,"***",IF(Estimates!AS8<0.05,"**",IF(Estimates!AS8<0.1,"*","")))) -> -0.090 | C14: =TEXT(Estimates!AT8,"0.000")&IF(Estimates!AW8="","",IF(Estimates!AW8<0.01,"***",IF(Estimates!AW8<0.05,"**",IF(Estimates!AW8<0.1,"*","")))) -> -0.042 | D14: =TEXT(Estimates!AX8,"0.000")&IF(Estimates!BA8="","",IF(Estimates!BA8<0.01,"***",IF(Estimates!BA8<0.05,"**",IF(Estimates!BA8<0.1,"*","")))) -> -0.058* | E14: =TEXT(Estimates!BB8,"0.000")&IF(Estimates!BE8="","",IF(Estimates!BE8<0.01,"***",IF(Estimates!BE8<0.05,"**",IF(Estimates!BE8<0.1,"*","")))) -> -0.058 | F14: =TEXT(Estimates!BF8,"0.000")&IF(Estimates!BI8="","",IF(Estimates!BI8<0.01,"***",IF(Estimates!BI8<0.05,"**",IF(Estimates!BI8<0.1,"*","")))) -> 0.011
B15: =IF(Estimates!AR8="","(n/a)","("&TEXT(Estimates!AR8,"0.00")&")") -> (-1.30) | C15: =IF(Estimates!AV8="","(n/a)","("&TEXT(Estimates!AV8,"0.00")&")") -> (-0.70) | D15: =IF(Estimates!AZ8="","(n/a)","("&TEXT(Estimates!AZ8,"0.00")&")") -> (-2.03) | E15: =IF(Estimates!BD8="","(n/a)","("&TEXT(Estimates!BD8,"0.00")&")") -> (-1.23) | F15: =IF(Estimates!BH8="","(n/a)","("&TEXT(Estimates!BH8,"0.00")&")") -> (0.17)
A16: Fixed Income Allocation (%) | B16: =TEXT(Estimates!AP9,"0.000")&IF(Estimates!AS9="","",IF(Estimates!AS9<0.01,"***",IF(Estimates!AS9<0.05,"**",IF(Estimates!AS9<0.1,"*","")))) -> -0.098 | C16: =TEXT(Estimates!AT9,"0.000")&IF(Estimates!AW9="","",IF(Estimates!AW9<0.01,"***",IF(Estimates!AW9<0.05,"**",IF(Estimates!AW9<0.1,"*","")))) -> -0.052 | D16: =TEXT(Estimates!AX9,"0.000")&IF(Estimates!BA9="","",IF(Estimates!BA9<0.01,"***",IF(Estimates!BA9<0.05,"**",IF(Estimates!BA9<0.1,"*","")))) -> -0.065** | E16: =TEXT(Estimates!BB9,"0.000")&IF(Estimates!BE9="","",IF(Estimates!BE9<0.01,"***",IF(Estimates!BE9<0.05,"**",IF(Estimates!BE9<0.1,"*","")))) -> -0.067 | F16: =TEXT(Estimates!BF9,"0.000")&IF(Estimates!BI9="","",IF(Estimates!BI9<0.01,"***",IF(Estimates!BI9<0.05,"**",IF(Estimates!BI9<0.1,"*","")))) -> 0.005
B17: =IF(Estimates!AR9="","(n/a)","("&TEXT(Estimates!AR9,"0.00")&")") -> (-1.42) | C17: =IF(Estimates!AV9="","(n/a)","("&TEXT(Estimates!AV9,"0.00")&")") -> (-0.87) | D17: =IF(Estimates!AZ9="","(n/a)","("&TEXT(Estimates!AZ9,"0.00")&")") -> (-2.24) | E17: =IF(Estimates!BD9="","(n/a)","("&TEXT(Estimates!BD9,"0.00")&")") -> (-1.36) | F17: =IF(Estimates!BH9="","(n/a)","("&TEXT(Estimates!BH9,"0.00")&")") -> (0.07)
A18: Real Estate Allocation (%) | B18: =TEXT(Estimates!AP10,"0.000")&IF(Estimates!AS10="","",IF(Estimates!AS10<0.01,"***",IF(Estimates!AS10<0.05,"**",IF(Estimates!AS10<0.1,"*","")))) -> -0.085 | C18: =TEXT(Estimates!AT10,"0.000")&IF(Estimates!AW10="","",IF(Estimates!AW10<0.01,"***",IF(Estimates!AW10<0.05,"**",IF(Estimates!AW10<0.1,"*","")))) -> -0.036 | D18: =TEXT(Estimates!AX10,"0.000")&IF(Estimates!BA10="","",IF(Estimates!BA10<0.01,"***",IF(Estimates!BA10<0.05,"**",IF(Estimates!BA10<0.1,"*","")))) -> -0.077* | E18: =TEXT(Estimates!BB10,"0.000")&IF(Estimates!BE10="","",IF(Estimates!BE10<0.01,"***",IF(Estimates!BE10<0.05,"**",IF(Estimates!BE10<0.1,"*","")))) -> -0.080 | F18: =TEXT(Estimates!BF10,"0.000")&IF(Estimates!BI10="","",IF(Estimates!BI10<0.01,"***",IF(Estimates!BI10<0.05,"**",IF(Estimates!BI10<0.1,"*","")))) -> -0.007
B19: =IF(Estimates!AR10="","(n/a)","("&TEXT(Estimates!AR10,"0.00")&")") -> (-1.18) | C19: =IF(Estimates!AV10="","(n/a)","("&TEXT(Estimates!AV10,"0.00")&")") -> (-0.58) | D19: =IF(Estimates!AZ10="","(n/a)","("&TEXT(Estimates!AZ10,"0.00")&")") -> (-1.98) | E19: =IF(Estimates!BD10="","(n/a)","("&TEXT(Estimates!BD10,"0.00")&")") -> (-1.23) | F19: =IF(Estimates!BH10="","(n/a)","("&TEXT(Estimates!BH10,"0.00")&")") -> (-0.07)
A20: Private Equity Allocation (%) | B20: =TEXT(Estimates!AP11,"0.000")&IF(Estimates!AS11="","",IF(Estimates!AS11<0.01,"***",IF(Estimates!AS11<0.05,"**",IF(Estimates!AS11<0.1,"*","")))) -> -0.090 | C20: =TEXT(Estimates!AT11,"0.000")&IF(Estimates!AW11="","",IF(Estimates!AW11<0.01,"***",IF(Estimates!AW11<0.05,"**",IF(Estimates!AW11<0.1,"*","")))) -> -0.044 | D20: =TEXT(Estimates!AX11,"0.000")&IF(Estimates!BA11="","",IF(Estimates!BA11<0.01,"***",IF(Estimates!BA11<0.05,"**",IF(Estimates!BA11<0.1,"*","")))) -> -0.031 | E20: =TEXT(Estimates!BB11,"0.000")&IF(Estimates!BE11="","",IF(Estimates!BE11<0.01,"***",IF(Estimates!BE11<0.05,"**",IF(Estimates!BE11<0.1,"*","")))) -> -0.039 | F20: =TEXT(Estimates!BF11,"0.000")&IF(Estimates!BI11="","",IF(Estimates!BI11<0.01,"***",IF(Estimates!BI11<0.05,"**",IF(Estimates!BI11<0.1,"*","")))) -> 0.025
B21: =IF(Estimates!AR11="","(n/a)","("&TEXT(Estimates!AR11,"0.00")&")") -> (-1.30) | C21: =IF(Estimates!AV11="","(n/a)","("&TEXT(Estimates!AV11,"0.00")&")") -> (-0.73) | D21: =IF(Estimates!AZ11="","(n/a)","("&TEXT(Estimates!AZ11,"0.00")&")") -> (-1.09) | E21: =IF(Estimates!BD11="","(n/a)","("&TEXT(Estimates!BD11,"0.00")&")") -> (-0.88) | F21: =IF(Estimates!BH11="","(n/a)","("&TEXT(Estimates!BH11,"0.00")&")") -> (0.39)
A22: Hedge Fund Allocation (%) | B22: =TEXT(Estimates!AP12,"0.000")&IF(Estimates!AS12="","",IF(Estimates!AS12<0.01,"***",IF(Estimates!AS12<0.05,"**",IF(Estimates!AS12<0.1,"*","")))) -> -0.093 | C22: =TEXT(Estimates!AT12,"0.000")&IF(Estimates!AW12="","",IF(Estimates!AW12<0.01,"***",IF(Estimates!AW12<0.05,"**",IF(Estimates!AW12<0.1,"*","")))) -> -0.051 | D22: =TEXT(Estimates!AX12,"0.000")&IF(Estimates!BA12="","",IF(Estimates!BA12<0.01,"***",IF(Estimates!BA12<0.05,"**",IF(Estimates!BA12<0.1,"*","")))) -> -0.055* | E22: =TEXT(Estimates!BB12,"0.000")&IF(Estimates!BE12="","",IF(Estimates!BE12<0.01,"***",IF(Estimates!BE12<0.05,"**",IF(Estimates!BE12<0.1,"*","")))) -> -0.059 | F22: =TEXT(Estimates!BF12,"0.000")&IF(Estimates!BI12="","",IF(Estimates!BI12<0.01,"***",IF(Estimates!BI12<0.05,"**",IF(Estimates!BI12<0.1,"*","")))) -> -0.002
B23: =IF(Estimates!AR12="","(n/a)","("&TEXT(Estimates!AR12,"0.00")&")") -> (-1.42) | C23: =IF(Estimates!AV12="","(n/a)","("&TEXT(Estimates!AV12,"0.00")&")") -> (-0.89) | D23: =IF(Estimates!AZ12="","(n/a)","("&TEXT(Estimates!AZ12,"0.00")&")") -> (-1.98) | E23: =IF(Estimates!BD12="","(n/a)","("&TEXT(Estimates!BD12,"0.00")&")") -> (-1.30) | F23: =IF(Estimates!BH12="","(n/a)","("&TEXT(Estimates!BH12,"0.00")&")") -> (-0.03)
A24: Misc. Alternatives Allocation (%) | B24: =TEXT(Estimates!AP13,"0.000")&IF(Estimates!AS13="","",IF(Estimates!AS13<0.01,"***",IF(Estimates!AS13<0.05,"**",IF(Estimates!AS13<0.1,"*","")))) -> -0.097 | C24: =TEXT(Estimates!AT13,"0.000")&IF(Estimates!AW13="","",IF(Estimates!AW13<0.01,"***",IF(Estimates!AW13<0.05,"**",IF(Estimates!AW13<0.1,"*","")))) -> -0.066 | D24: =TEXT(Estimates!AX13,"0.000")&IF(Estimates!BA13="","",IF(Estimates!BA13<0.01,"***",IF(Estimates!BA13<0.05,"**",IF(Estimates!BA13<0.1,"*","")))) -> -0.092* | E24: =TEXT(Estimates!BB13,"0.000")&IF(Estimates!BE13="","",IF(Estimates!BE13<0.01,"***",IF(Estimates!BE13<0.05,"**",IF(Estimates!BE13<0.1,"*","")))) -> -0.109 | F24: =TEXT(Estimates!BF13,"0.000")&IF(Estimates!BI13="","",IF(Estimates!BI13<0.01,"***",IF(Estimates!BI13<0.05,"**",IF(Estimates!BI13<0.1,"*","")))) -> 0.023
B25: =IF(Estimates!AR13="","(n/a)","("&TEXT(Estimates!AR13,"0.00")&")") -> (-1.43) | C25: =IF(Estimates!AV13="","(n/a)","("&TEXT(Estimates!AV13,"0.00")&")") -> (-1.07) | D25: =IF(Estimates!AZ13="","(n/a)","("&TEXT(Estimates!AZ13,"0.00")&")") -> (-1.82) | E25: =IF(Estimates!BD13="","(n/a)","("&TEXT(Estimates!BD13,"0.00")&")") -> (-1.55) | F25: =IF(Estimates!BH13="","(n/a)","("&TEXT(Estimates!BH13,"0.00")&")") -> (0.23)
A26: Commodities Allocation (%) | B26: =TEXT(Estimates!AP14,"0.000")&IF(Estimates!AS14="","",IF(Estimates!AS14<0.01,"***",IF(Estimates!AS14<0.05,"**",IF(Estimates!AS14<0.1,"*","")))) -> -0.104 | C26: =TEXT(Estimates!AT14,"0.000")&IF(Estimates!AW14="","",IF(Estimates!AW14<0.01,"***",IF(Estimates!AW14<0.05,"**",IF(Estimates!AW14<0.1,"*","")))) -> -0.048 | D26: =TEXT(Estimates!AX14,"0.000")&IF(Estimates!BA14="","",IF(Estimates!BA14<0.01,"***",IF(Estimates!BA14<0.05,"**",IF(Estimates!BA14<0.1,"*","")))) -> -0.101*** | E26: =TEXT(Estimates!BB14,"0.000")&IF(Estimates!BE14="","",IF(Estimates!BE14<0.01,"***",IF(Estimates!BE14<0.05,"**",IF(Estimates!BE14<0.1,"*","")))) -> -0.110 | F26: =TEXT(Estimates!BF14,"0.000")&IF(Estimates!BI14="","",IF(Estimates!BI14<0.01,"***",IF(Estimates!BI14<0.05,"**",IF(Estimates!BI14<0.1,"*","")))) -> -0.054
B27: =IF(Estimates!AR14="","(n/a)","("&TEXT(Estimates!AR14,"0.00")&")") -> (-1.50) | C27: =IF(Estimates!AV14="","(n/a)","("&TEXT(Estimates!AV14,"0.00")&")") -> (-0.77) | D27: =IF(Estimates!AZ14="","(n/a)","("&TEXT(Estimates!AZ14,"0.00")&")") -> (-3.05) | E27: =IF(Estimates!BD14="","(n/a)","("&TEXT(Estimates!BD14,"0.00")&")") -> (-1.61) | F27: =IF(Estimates!BH14="","(n/a)","("&TEXT(Estimates!BH14,"0.00")&")") -> (-0.71)
A28: Cash Allocation (%) | B28: =TEXT(Estimates!AP15,"0.000")&IF(Estimates!AS15="","",IF(Estimates!AS15<0.01,"***",IF(Estimates!AS15<0.05,"**",IF(Estimates!AS15<0.1,"*","")))) -> -0.076 | C28: =TEXT(Estimates!AT15,"0.000")&IF(Estimates!AW15="","",IF(Estimates!AW15<0.01,"***",IF(Estimates!AW15<0.05,"**",IF(Estimates!AW15<0.1,"*","")))) -> -0.033 | D28: =TEXT(Estimates!AX15,"0.000")&IF(Estimates!BA15="","",IF(Estimates!BA15<0.01,"***",IF(Estimates!BA15<0.05,"**",IF(Estimates!BA15<0.1,"*","")))) -> -0.069** | E28: =TEXT(Estimates!BB15,"0.000")&IF(Estimates!BE15="","",IF(Estimates!BE15<0.01,"***",IF(Estimates!BE15<0.05,"**",IF(Estimates!BE15<0.1,"*","")))) -> -0.065 | F28: =TEXT(Estimates!BF15,"0.000")&IF(Estimates!BI15="","",IF(Estimates!BI15<0.01,"***",IF(Estimates!BI15<0.05,"**",IF(Estimates!BI15<0.1,"*","")))) -> 0.015
B29: =IF(Estimates!AR15="","(n/a)","("&TEXT(Estimates!AR15,"0.00")&")") -> (-1.12) | C29: =IF(Estimates!AV15="","(n/a)","("&TEXT(Estimates!AV15,"0.00")&")") -> (-0.54) | D29: =IF(Estimates!AZ15="","(n/a)","("&TEXT(Estimates!AZ15,"0.00")&")") -> (-2.23) | E29: =IF(Estimates!BD15="","(n/a)","("&TEXT(Estimates!BD15,"0.00")&")") -> (-1.36) | F29: =IF(Estimates!BH15="","(n/a)","("&TEXT(Estimates!BH15,"0.00")&")") -> (0.24)
A30: Financial Center (0/1) | B30: =TEXT(Estimates!AP16,"0.000")&IF(Estimates!AS16="","",IF(Estimates!AS16<0.01,"***",IF(Estimates!AS16<0.05,"**",IF(Estimates!AS16<0.1,"*","")))) -> 0.034 | C30: =TEXT(Estimates!AT16,"0.000")&IF(Estimates!AW16="","",IF(Estimates!AW16<0.01,"***",IF(Estimates!AW16<0.05,"**",IF(Estimates!AW16<0.1,"*","")))) -> 0.022
B31: =IF(Estimates!AR16="","(n/a)","("&TEXT(Estimates!AR16,"0.00")&")") -> (0.73) | C31: =IF(Estimates!AV16="","(n/a)","("&TEXT(Estimates!AV16,"0.00")&")") -> (0.40)
A32: Log (CIO Age) (t-1) | C32: =TEXT(Estimates!AT17,"0.000")&IF(Estimates!AW17="","",IF(Estimates!AW17<0.01,"***",IF(Estimates!AW17<0.05,"**",IF(Estimates!AW17<0.1,"*","")))) -> 0.044 | D32: =TEXT(Estimates!AX17,"0.000")&IF(Estimates!BA17="","",IF(Estimates!BA17<0.01,"***",IF(Estimates!BA17<0.05,"**",IF(Estimates!BA17<0.1,"*","")))) -> -0.461**
C33: =IF(Estimates!AV17="","(n/a)","("&TEXT(Estimates!AV17,"0.00")&")") -> (0.19) | D33: =IF(Estimates!AZ17="","(n/a)","("&TEXT(Estimates!AZ17,"0.00")&")") -> (-2.25)
A34: Log (CIO Tenure) (t-1) | C34: =TEXT(Estimates!AT18,"0.000")&IF(Estimates!AW18="","",IF(Estimates!AW18<0.01,"***",IF(Estimates!AW18<0.05,"**",IF(Estimates!AW18<0.1,"*","")))) -> -0.004 | D34: =TEXT(Estimates!AX18,"0.000")&IF(Estimates!BA18="","",IF(Estimates!BA18<0.01,"***",IF(Estimates!BA18<0.05,"**",IF(Estimates!BA18<0.1,"*","")))) -> 0.057*
C35: =IF(Estimates!AV18="","(n/a)","("&TEXT(Estimates!AV18,"0.00")&")") -> (-0.10) | D35: =IF(Estimates!AZ18="","(n/a)","("&TEXT(Estimates!AZ18,"0.00")&")") -> (1.76)
A36: CIO Prior Private Experience (0/1) | C36: =TEXT(Estimates!AT19,"0.000")&IF(Estimates!AW19="","",IF(Estimates!AW19<0.01,"***",IF(Estimates!AW19<0.05,"**",IF(Estimates!AW19<0.1,"*","")))) -> -0.201*** | D36: =TEXT(Estimates!AX19,"0.000")&IF(Estimates!BA19="","",IF(Estimates!BA19<0.01,"***",IF(Estimates!BA19<0.05,"**",IF(Estimates!BA19<0.1,"*","")))) -> -0.029
C37: =IF(Estimates!AV19="","(n/a)","("&TEXT(Estimates!AV19,"0.00")&")") -> (-2.92) | D37: =IF(Estimates!AZ19="","(n/a)","("&TEXT(Estimates!AZ19,"0.00")&")") -> (-0.35)
A38: CIO Attended Elite College (0/1) | C38: =TEXT(Estimates!AT20,"0.000")&IF(Estimates!AW20="","",IF(Estimates!AW20<0.01,"***",IF(Estimates!AW20<0.05,"**",IF(Estimates!AW20<0.1,"*","")))) -> -0.068 | D38: =TEXT(Estimates!AX20,"0.000")&IF(Estimates!BA20="","",IF(Estimates!BA20<0.01,"***",IF(Estimates!BA20<0.05,"**",IF(Estimates!BA20<0.1,"*","")))) -> -0.108*
C39: =IF(Estimates!AV20="","(n/a)","("&TEXT(Estimates!AV20,"0.00")&")") -> (-1.19) | D39: =IF(Estimates!AZ20="","(n/a)","("&TEXT(Estimates!AZ20,"0.00")&")") -> (-2.09)
A40: Separate Investment Board (0/1) | C40: =TEXT(Estimates!AT21,"0.000")&IF(Estimates!AW21="","",IF(Estimates!AW21<0.01,"***",IF(Estimates!AW21<0.05,"**",IF(Estimates!AW21<0.1,"*","")))) -> 0.073
C41: =IF(Estimates!AV21="","(n/a)","("&TEXT(Estimates!AV21,"0.00")&")") -> (1.20)
A42: % Political Appointees on Board | C42: =TEXT(Estimates!AT22,"0.000")&IF(Estimates!AW22="","",IF(Estimates!AW22<0.01,"***",IF(Estimates!AW22<0.05,"**",IF(Estimates!AW22<0.1,"*","")))) -> 0.003 | D42: =TEXT(Estimates!AX22,"0.000")&IF(Estimates!BA22="","",IF(Estimates!BA22<0.01,"***",IF(Estimates!BA22<0.05,"**",IF(Estimates!BA22<0.1,"*","")))) -> 1.197*
C43: =IF(Estimates!AV22="","(n/a)","("&TEXT(Estimates!AV22,"0.00")&")") -> (0.04) | D43: =IF(Estimates!AZ22="","(n/a)","("&TEXT(Estimates!AZ22,"0.00")&")") -> (1.85)
A45: Observations | B45: =Estimates!AP24 -> 266 | C45: =Estimates!AT24 -> 251 | D45: =Estimates!AX24 -> 250 | E45: =Estimates!BB24 -> 250 | F45: =Estimates!BF24 -> 162
A46: Adjusted R-squared | B46: =Estimates!AP27 -> 0.48282686 | C46: =Estimates!AT27 -> 0.54630344 | D46: =Estimates!AX27 -> 0.71872605 | E46: =Estimates!BB27 -> 0.78206403 | F46: =Estimates!BF27 -> 0.81172229
A47: Number of CIOs | B47: =Estimates!AP28 -> 40 | C47: =Estimates!AT28 -> 37 | D47: =Estimates!AX28 -> 37 | E47: =Estimates!BB28 -> 40 | F47: =Estimates!BF28 -> 20
A48: Plan FE | B48: No | C48: No | D48: Yes | E48: No | F48: No
A49: Fiscal-Year-End FE | B49: Yes | C49: Yes | D49: Yes | E49: Yes | F49: Yes
A50: CIO FE | B50: No | C50: No | D50: No | E50: Yes | F50: Yes
A51: Min. Tenure at Departure (years) | F51: 4

Sheet Table XIII
A1: Table XIII: Conflicted CIOs: Univariate Comparison of the First and Second Half of Tenure (updated benchmark)
A2: This table compares the average outcomes of conflicted CIOs in the first and second half of their tenure with one observation per CIO. Plan-years are first averaged within CIO-year for CIOs who run several plans, then averaged within each half of tenure. Difference is the mean within-CIO change from the first to the second half; the t-statistic tests whether this mean change is zero, and the last column reports the p-value of a Wilcoxon signed-rank test of the same hypothesis. Coefficients marked with ***, **, and * are significant at the 1%, 5%, and 10% level, respectively.
B4: N (CIOs) | C4: First Half | D4: Second Half | E4: Difference | F4: t-stat | G4: % Improving | H4: Wilcoxon p-value | J4: SD of change | K4: t (helper) | L4: p (helper)
A5: Peer-Adjusted Return (%) | B5: 37 | C5: -0.49672251 | D5: -0.2354691 | E5: =TEXT(D5-C5,"0.000")&IF(L5<0.01,"***",IF(L5<0.05,"**",IF(L5<0.1,"*",""))) -> 0.261 | F5: =TEXT(K5,"0.00") -> 0.59 | G5: 0.62162162 | H5: 0.37772693 | J5: 2.6863822 | K5: =(D5-C5)/(J5/SQRT(B5)) -> 0.59155486 | L5: =TDIST(ABS(K5),B5-1,2) -> 0.55784542
A6: Benchmark-Adjusted Return (%) | B6: 30 | C6: 0.044924868 | D6: 0.18198519 | E6: =TEXT(D6-C6,"0.000")&IF(L6<0.01,"***",IF(L6<0.05,"**",IF(L6<0.1,"*",""))) -> 0.137 | F6: =TEXT(K6,"0.00") -> 0.29 | G6: 0.5 | H6: 1 | J6: 2.5905276 | K6: =(D6-C6)/(J6/SQRT(B6)) -> 0.28979049 | L6: =TDIST(ABS(K6),B6-1,2) -> 0.77403846
A7: Fee Ratio (%) | B7: 35 | C7: 0.29333454 | D7: 0.35688809 | E7: =TEXT(D7-C7,"0.000")&IF(L7<0.01,"***",IF(L7<0.05,"**",IF(L7<0.1,"*",""))) -> 0.064** | F7: =TEXT(K7,"0.00") -> 2.24 | G7: 0.65714286 | H7: 0.030007007 | J7: 0.16810236 | K7: =(D7-C7)/(J7/SQRT(B7)) -> 2.2366603 | L7: =TDIST(ABS(K7),B7-1,2) -> 0.031975505

Sheet Estimates-split
A1: Estimates behind the split tables (blue = regression output; t and p are formulas). Full Table III sample; SE double clustered by plan and year (PSD-corrected); p-values use the t distribution with min(plan clusters, year clusters) - 1 df.
A3: Variable | B3: S1A(1) coef | C3: S1A(1) se | D3: S1A(1) t | E3: S1A(1) p | F3: S1A(2) coef | G3: S1A(2) se | H3: S1A(2) t | I3: S1A(2) p | J3: S1A(3) coef | K3: S1A(3) se | L3: S1A(3) t | M3: S1A(3) p | N3: S1B(1) coef | O3: S1B(1) se | P3: S1B(1) t | Q3: S1B(1) p | R3: S1B(2) coef | S3: S1B(2) se | T3: S1B(2) t | U3: S1B(2) p | V3: S1B(3) coef | W3: S1B(3) se | X3: S1B(3) t | Y3: S1B(3) p | Z3: S2A(1) coef | AA3: S2A(1) se | AB3: S2A(1) t | AC3: S2A(1) p | AD3: S2A(2) coef | AE3: S2A(2) se | AF3: S2A(2) t | AG3: S2A(2) p | AH3: S2A(3) coef | AI3: S2A(3) se | AJ3: S2A(3) t | AK3: S2A(3) p
A4: Conflicted CIO x First Half of Tenure (0/1) | B4: -0.47420282 | C4: 0.18894944 | D4: =IF(C4>0,B4/C4,"") -> -2.509681 | E4: =IF(C4>0,TDIST(ABS(D4),MIN(B27,B28)-1,2),"") -> 0.021863342 | F4: -0.49728715 | G4: 0.23674212 | H4: =IF(G4>0,F4/G4,"") -> -2.1005436 | I4: =IF(G4>0,TDIST(ABS(H4),MIN(F27,F28)-1,2),"") -> 0.05003709 | J4: -0.84483971 | K4: 0.36912583 | L4: =IF(K4>0,J4/K4,"") -> -2.288758 | M4: =IF(K4>0,TDIST(ABS(L4),MIN(J27,J28)-1,2),"") -> 0.03440139 | N4: -0.5260024 | O4: 0.22173217 | P4: =IF(O4>0,N4/O4,"") -> -2.3722421 | Q4: =IF(O4>0,TDIST(ABS(P4),MIN(N27,N28)-1,2),"") -> 0.029031743 | R4: -0.57505494 | S4: 0.17487734 | T4: =IF(S4>0,R4/S4,"") -> -3.288333 | U4: =IF(S4>0,TDIST(ABS(T4),MIN(R27,R28)-1,2),"") -> 0.0040851475 | V4: -0.64583169 | W4: 0.2391672 | X4: =IF(W4>0,V4/W4,"") -> -2.7003355 | Y4: =IF(W4>0,TDIST(ABS(X4),MIN(V27,V28)-1,2),"") -> 0.014641228 | Z4: -0.065260591 | AA4: 0.038877103 | AB4: =IF(AA4>0,Z4/AA4,"") -> -1.6786382 | AC4: =IF(AA4>0,TDIST(ABS(AB4),MIN(Z27,Z28)-1,2),"") -> 0.11049833 | AD4: -0.026851411 | AE4: 0.051146697 | AF4: =IF(AE4>0,AD4/AE4,"") -> -0.52498817 | AG4: =IF(AE4>0,TDIST(ABS(AF4),MIN(AD27,AD28)-1,2),"") -> 0.60599801 | AH4: 0.040859255 | AI4: 0.05940505 | AJ4: =IF(AI4>0,AH4/AI4,"") -> 0.68780777 | AK4: =IF(AI4>0,TDIST(ABS(AJ4),MIN(AH27,AH28)-1,2),"") -> 0.5003419
A5: Conflicted CIO x Second Half of Tenure (0/1) | B5: -0.59564086 | C5: 0.17914607 | D5: =IF(C5>0,B5/C5,"") -> -3.3248892 | E5: =IF(C5>0,TDIST(ABS(D5),MIN(B27,B28)-1,2),"") -> 0.0037683822 | F5: -0.53645021 | G5: 0.2091558 | H5: =IF(G5>0,F5/G5,"") -> -2.5648354 | I5: =IF(G5>0,TDIST(ABS(H5),MIN(F27,F28)-1,2),"") -> 0.019485381 | J5: -0.64408647 | K5: 0.3189791 | L5: =IF(K5>0,J5/K5,"") -> -2.0192122 | M5: =IF(K5>0,TDIST(ABS(L5),MIN(J27,J28)-1,2),"") -> 0.058611629 | N5: -0.33841226 | O5: 0.17954676 | P5: =IF(O5>0,N5/O5,"") -> -1.8848141 | Q5: =IF(O5>0,TDIST(ABS(P5),MIN(N27,N28)-1,2),"") -> 0.075706117 | R5: -0.38833376 | S5: 0.16356915 | T5: =IF(S5>0,R5/S5,"") -> -2.374126 | U5: =IF(S5>0,TDIST(ABS(T5),MIN(R27,R28)-1,2),"") -> 0.02892011 | V5: -0.21895376 | W5: 0.21668002 | X5: =IF(W5>0,V5/W5,"") -> -1.0104936 | Y5: =IF(W5>0,TDIST(ABS(X5),MIN(V27,V28)-1,2),"") -> 0.32565042 | Z5: -0.0688919 | AA5: 0.042717499 | AB5: =IF(AA5>0,Z5/AA5,"") -> -1.6127325 | AC5: =IF(AA5>0,TDIST(ABS(AB5),MIN(Z27,Z28)-1,2),"") -> 0.12419707 | AD5: -0.042296377 | AE5: 0.046561044 | AF5: =IF(AE5>0,AD5/AE5,"") -> -0.90840696 | AG5: =IF(AE5>0,TDIST(ABS(AF5),MIN(AD27,AD28)-1,2),"") -> 0.37566577 | AH5: 0.030948236 | AI5: 0.061210683 | AJ5: =IF(AI5>0,AH5/AI5,"") -> 0.50560188 | AK5: =IF(AI5>0,TDIST(ABS(AJ5),MIN(AH27,AH28)-1,2),"") -> 0.61927144
A6: Investment Return (t - 1) | B6: 0.11936909 | C6: 0.077179146 | D6: =IF(C6>0,B6/C6,"") -> 1.5466495 | E6: =IF(C6>0,TDIST(ABS(D6),MIN(B27,B28)-1,2),"") -> 0.13934885 | F6: 0.091103186 | G6: 0.078283479 | H6: =IF(G6>0,F6/G6,"") -> 1.1637601 | I6: =IF(G6>0,TDIST(ABS(H6),MIN(F27,F28)-1,2),"") -> 0.25971603 | J6: 0.029504311 | K6: 0.073128595 | L6: =IF(K6>0,J6/K6,"") -> 0.40345792 | M6: =IF(K6>0,TDIST(ABS(L6),MIN(J27,J28)-1,2),"") -> 0.6913638 | N6: 0.065833959 | O6: 0.069582982 | P6: =IF(O6>0,N6/O6,"") -> 0.94612155 | Q6: =IF(O6>0,TDIST(ABS(P6),MIN(N27,N28)-1,2),"") -> 0.35661547 | R6: 0.036398191 | S6: 0.070291475 | T6: =IF(S6>0,R6/S6,"") -> 0.517818 | U6: =IF(S6>0,TDIST(ABS(T6),MIN(R27,R28)-1,2),"") -> 0.6108912 | V6: 0.019983752 | W6: 0.061802828 | X6: =IF(W6>0,V6/W6,"") -> 0.32334688 | Y6: =IF(W6>0,TDIST(ABS(X6),MIN(V27,V28)-1,2),"") -> 0.75015891 | Z6: 0.0021350058 | AA6: 0.0046363158 | AB6: =IF(AA6>0,Z6/AA6,"") -> 0.4604962 | AC6: =IF(AA6>0,TDIST(ABS(AB6),MIN(Z27,Z28)-1,2),"") -> 0.65067472 | AD6: 0.0012106944 | AE6: 0.0054452759 | AF6: =IF(AE6>0,AD6/AE6,"") -> 0.22233848 | AG6: =IF(AE6>0,TDIST(ABS(AF6),MIN(AD27,AD28)-1,2),"") -> 0.82655366 | AH6: -0.0028335477 | AI6: 0.0034671024 | AJ6: =IF(AI6>0,AH6/AI6,"") -> -0.81726681 | AK6: =IF(AI6>0,TDIST(ABS(AJ6),MIN(AH27,AH28)-1,2),"") -> 0.42446193
A7: Log (Plan Size) (t-1) | B7: 0.013397039 | C7: 0.050768344 | D7: =IF(C7>0,B7/C7,"") -> 0.26388568 | E7: =IF(C7>0,TDIST(ABS(D7),MIN(B27,B28)-1,2),"") -> 0.79486547 | F7: 0.071972689 | G7: 0.056866528 | H7: =IF(G7>0,F7/G7,"") -> 1.2656424 | I7: =IF(G7>0,TDIST(ABS(H7),MIN(F27,F28)-1,2),"") -> 0.2217788 | J7: -1.4279265 | K7: 0.80598337 | L7: =IF(K7>0,J7/K7,"") -> -1.7716576 | M7: =IF(K7>0,TDIST(ABS(L7),MIN(J27,J28)-1,2),"") -> 0.093379985 | N7: -0.051302172 | O7: 0.039581458 | P7: =IF(O7>0,N7/O7,"") -> -1.2961163 | Q7: =IF(O7>0,TDIST(ABS(P7),MIN(N27,N28)-1,2),"") -> 0.21130851 | R7: -0.0035822864 | S7: 0.045413986 | T7: =IF(S7>0,R7/S7,"") -> -0.078880686 | U7: =IF(S7>0,TDIST(ABS(T7),MIN(R27,R28)-1,2),"") -> 0.93799784 | V7: -0.0015240765 | W7: 0.66172215 | X7: =IF(W7>0,V7/W7,"") -> -0.002303197 | Y7: =IF(W7>0,TDIST(ABS(X7),MIN(V27,V28)-1,2),"") -> 0.99818765 | Z7: -0.025792326 | AA7: 0.014471056 | AB7: =IF(AA7>0,Z7/AA7,"") -> -1.782339 | AC7: =IF(AA7>0,TDIST(ABS(AB7),MIN(Z27,Z28)-1,2),"") -> 0.091569987 | AD7: -0.030176486 | AE7: 0.014997869 | AF7: =IF(AE7>0,AD7/AE7,"") -> -2.0120515 | AG7: =IF(AE7>0,TDIST(ABS(AF7),MIN(AD27,AD28)-1,2),"") -> 0.059426677 | AH7: 0.024529563 | AI7: 0.12057378 | AJ7: =IF(AI7>0,AH7/AI7,"") -> 0.20344027 | AK7: =IF(AI7>0,TDIST(ABS(AJ7),MIN(AH27,AH28)-1,2),"") -> 0.84107311
A8: Funding Ratio (t-1) | B8: -0.0042562885 | C8: 0.0045366932 | D8: =IF(C8>0,B8/C8,"") -> -0.93819185 | E8: =IF(C8>0,TDIST(ABS(D8),MIN(B27,B28)-1,2),"") -> 0.36056517 | F8: -0.0056955355 | G8: 0.005705149 | H8: =IF(G8>0,F8/G8,"") -> -0.99831495 | I8: =IF(G8>0,TDIST(ABS(H8),MIN(F27,F28)-1,2),"") -> 0.33135893 | J8: -0.030078919 | K8: 0.011232246 | L8: =IF(K8>0,J8/K8,"") -> -2.6779078 | M8: =IF(K8>0,TDIST(ABS(L8),MIN(J27,J28)-1,2),"") -> 0.015354707 | N8: 0.0051706064 | O8: 0.0045912541 | P8: =IF(O8>0,N8/O8,"") -> 1.1261861 | Q8: =IF(O8>0,TDIST(ABS(P8),MIN(N27,N28)-1,2),"") -> 0.27487817 | R8: 0.0050088123 | S8: 0.0055711631 | T8: =IF(S8>0,R8/S8,"") -> 0.89906043 | U8: =IF(S8>0,TDIST(ABS(T8),MIN(R27,R28)-1,2),"") -> 0.38049058 | V8: -0.01682024 | W8: 0.010558111 | X8: =IF(W8>0,V8/W8,"") -> -1.5931107 | Y8: =IF(W8>0,TDIST(ABS(X8),MIN(V27,V28)-1,2),"") -> 0.1285437 | Z8: -0.00064245336 | AA8: 0.00092530396 | AB8: =IF(AA8>0,Z8/AA8,"") -> -0.69431602 | AC8: =IF(AA8>0,TDIST(ABS(AB8),MIN(Z27,Z28)-1,2),"") -> 0.49634854 | AD8: -0.0012444603 | AE8: 0.00091390558 | AF8: =IF(AE8>0,AD8/AE8,"") -> -1.3616946 | AG8: =IF(AE8>0,TDIST(ABS(AF8),MIN(AD27,AD28)-1,2),"") -> 0.19009564 | AH8: -0.0023222094 | AI8: 0.00085699422 | AJ8: =IF(AI8>0,AH8/AI8,"") -> -2.7097142 | AK8: =IF(AI8>0,TDIST(ABS(AJ8),MIN(AH27,AH28)-1,2),"") -> 0.014352357
A9: Equity Allocation (%) | B9: -0.072875496 | C9: 0.12633246 | D9: =IF(C9>0,B9/C9,"") -> -0.5768549 | E9: =IF(C9>0,TDIST(ABS(D9),MIN(B27,B28)-1,2),"") -> 0.57118205 | F9: -0.012186173 | G9: 0.058897763 | H9: =IF(G9>0,F9/G9,"") -> -0.20690384 | I9: =IF(G9>0,TDIST(ABS(H9),MIN(F27,F28)-1,2),"") -> 0.8384075 | J9: -0.034947795 | K9: 0.086344307 | L9: =IF(K9>0,J9/K9,"") -> -0.40474926 | M9: =IF(K9>0,TDIST(ABS(L9),MIN(J27,J28)-1,2),"") -> 0.69043121 | N9: -0.1619811 | O9: 0.13122157 | P9: =IF(O9>0,N9/O9,"") -> -1.2344091 | Q9: =IF(O9>0,TDIST(ABS(P9),MIN(N27,N28)-1,2),"") -> 0.23292393 | R9: -0.010099966 | S9: 0.11790449 | T9: =IF(S9>0,R9/S9,"") -> -0.085662271 | U9: =IF(S9>0,TDIST(ABS(T9),MIN(R27,R28)-1,2),"") -> 0.93268055 | V9: 0.020672139 | W9: 0.16766449 | X9: =IF(W9>0,V9/W9,"") -> 0.12329467 | Y9: =IF(W9>0,TDIST(ABS(X9),MIN(V27,V28)-1,2),"") -> 0.90324004 | Z9: -0.035990293 | AA9: 0.033832589 | AB9: =IF(AA9>0,Z9/AA9,"") -> -1.0637759 | AC9: =IF(AA9>0,TDIST(ABS(AB9),MIN(Z27,Z28)-1,2),"") -> 0.30149362 | AD9: -0.084099492 | AE9: 0.067316959 | AF9: =IF(AE9>0,AD9/AE9,"") -> -1.2493062 | AG9: =IF(AE9>0,TDIST(ABS(AF9),MIN(AD27,AD28)-1,2),"") -> 0.22755541 | AH9: -0.080010271 | AI9: 0.051782496 | AJ9: =IF(AI9>0,AH9/AI9,"") -> -1.5451219 | AK9: =IF(AI9>0,TDIST(ABS(AJ9),MIN(AH27,AH28)-1,2),"") -> 0.13971662
A10: Fixed Income Allocation (%) | B10: -0.085508288 | C10: 0.13437862 | D10: =IF(C10>0,B10/C10,"") -> -0.63632359 | E10: =IF(C10>0,TDIST(ABS(D10),MIN(B27,B28)-1,2),"") -> 0.53257439 | F10: -0.019882336 | G10: 0.076131767 | H10: =IF(G10>0,F10/G10,"") -> -0.26115689 | I10: =IF(G10>0,TDIST(ABS(H10),MIN(F27,F28)-1,2),"") -> 0.79693615 | J10: -0.040508295 | K10: 0.097476701 | L10: =IF(K10>0,J10/K10,"") -> -0.415569 | M10: =IF(K10>0,TDIST(ABS(L10),MIN(J27,J28)-1,2),"") -> 0.68263748 | N10: -0.15377575 | O10: 0.12953687 | P10: =IF(O10>0,N10/O10,"") -> -1.1871196 | Q10: =IF(O10>0,TDIST(ABS(P10),MIN(N27,N28)-1,2),"") -> 0.25061155 | R10: -0.012045202 | S10: 0.120093 | T10: =IF(S10>0,R10/S10,"") -> -0.10029895 | U10: =IF(S10>0,TDIST(ABS(T10),MIN(R27,R28)-1,2),"") -> 0.92121569 | V10: 0.0095474787 | W10: 0.17309697 | X10: =IF(W10>0,V10/W10,"") -> 0.055156821 | Y10: =IF(W10>0,TDIST(ABS(X10),MIN(V27,V28)-1,2),"") -> 0.95662114 | Z10: -0.040473062 | AA10: 0.034105487 | AB10: =IF(AA10>0,Z10/AA10,"") -> -1.1867024 | AC10: =IF(AA10>0,TDIST(ABS(AB10),MIN(Z27,Z28)-1,2),"") -> 0.250772 | AD10: -0.088017839 | AE10: 0.067397921 | AF10: =IF(AE10>0,AD10/AE10,"") -> -1.3059429 | AG10: =IF(AE10>0,TDIST(ABS(AF10),MIN(AD27,AD28)-1,2),"") -> 0.20801611 | AH10: -0.085559021 | AI10: 0.052003542 | AJ10: =IF(AI10>0,AH10/AI10,"") -> -1.6452537 | AK10: =IF(AI10>0,TDIST(ABS(AJ10),MIN(AH27,AH28)-1,2),"") -> 0.11726708
A11: Real Estate Allocation (%) | B11: -0.067185171 | C11: 0.12658227 | D11: =IF(C11>0,B11/C11,"") -> -0.53076288 | E11: =IF(C11>0,TDIST(ABS(D11),MIN(B27,B28)-1,2),"") -> 0.60207101 | F11: -0.0052818422 | G11: 0.056626519 | H11: =IF(G11>0,F11/G11,"") -> -0.093275064 | I11: =IF(G11>0,TDIST(ABS(H11),MIN(F27,F28)-1,2),"") -> 0.92671542 | J11: -0.081766249 | K11: 0.094378925 | L11: =IF(K11>0,J11/K11,"") -> -0.86636131 | M11: =IF(K11>0,TDIST(ABS(L11),MIN(J27,J28)-1,2),"") -> 0.39769365 | N11: -0.1915478 | O11: 0.11736371 | P11: =IF(O11>0,N11/O11,"") -> -1.6320872 | Q11: =IF(O11>0,TDIST(ABS(P11),MIN(N27,N28)-1,2),"") -> 0.12003212 | R11: -0.030775728 | S11: 0.10130453 | T11: =IF(S11>0,R11/S11,"") -> -0.30379419 | U11: =IF(S11>0,TDIST(ABS(T11),MIN(R27,R28)-1,2),"") -> 0.7647684 | V11: -0.04218333 | W11: 0.15981869 | X11: =IF(W11>0,V11/W11,"") -> -0.26394491 | Y11: =IF(W11>0,TDIST(ABS(X11),MIN(V27,V28)-1,2),"") -> 0.79482054 | Z11: -0.033616818 | AA11: 0.034973197 | AB11: =IF(AA11>0,Z11/AA11,"") -> -0.96121662 | AC11: =IF(AA11>0,TDIST(ABS(AB11),MIN(Z27,Z28)-1,2),"") -> 0.34917881 | AD11: -0.080430735 | AE11: 0.067404154 | AF11: =IF(AE11>0,AD11/AE11,"") -> -1.1932608 | AG11: =IF(AE11>0,TDIST(ABS(AF11),MIN(AD27,AD28)-1,2),"") -> 0.24825856 | AH11: -0.084224685 | AI11: 0.051613348 | AJ11: =IF(AI11>0,AH11/AI11,"") -> -1.6318392 | AK11: =IF(AI11>0,TDIST(ABS(AJ11),MIN(AH27,AH28)-1,2),"") -> 0.12008471
A12: Private Equity Allocation (%) | B12: -0.060823266 | C12: 0.13447475 | D12: =IF(C12>0,B12/C12,"") -> -0.45230248 | E12: =IF(C12>0,TDIST(ABS(D12),MIN(B27,B28)-1,2),"") -> 0.65645462 | F12: 0.010896224 | G12: 0.062624792 | H12: =IF(G12>0,F12/G12,"") -> 0.17399218 | I12: =IF(G12>0,TDIST(ABS(H12),MIN(F27,F28)-1,2),"") -> 0.86381348 | J12: 0.013066614 | K12: 0.095635542 | L12: =IF(K12>0,J12/K12,"") -> 0.13662927 | M12: =IF(K12>0,TDIST(ABS(L12),MIN(J27,J28)-1,2),"") -> 0.8928404 | N12: -0.14984428 | O12: 0.12945903 | P12: =IF(O12>0,N12/O12,"") -> -1.1574649 | Q12: =IF(O12>0,TDIST(ABS(P12),MIN(N27,N28)-1,2),"") -> 0.26221161 | R12: 0.0061524116 | S12: 0.11333637 | T12: =IF(S12>0,R12/S12,"") -> 0.05428453 | U12: =IF(S12>0,TDIST(ABS(T12),MIN(R27,R28)-1,2),"") -> 0.95730645 | V12: 0.029012495 | W12: 0.17042383 | X12: =IF(W12>0,V12/W12,"") -> 0.17023731 | Y12: =IF(W12>0,TDIST(ABS(X12),MIN(V27,V28)-1,2),"") -> 0.86672234 | Z12: -0.030472105 | AA12: 0.033401237 | AB12: =IF(AA12>0,Z12/AA12,"") -> -0.91230469 | AC12: =IF(AA12>0,TDIST(ABS(AB12),MIN(Z27,Z28)-1,2),"") -> 0.37366588 | AD12: -0.077130461 | AE12: 0.066925048 | AF12: =IF(AE12>0,AD12/AE12,"") -> -1.1524902 | AG12: =IF(AE12>0,TDIST(ABS(AF12),MIN(AD27,AD28)-1,2),"") -> 0.26419642 | AH12: -0.058824895 | AI12: 0.052110807 | AJ12: =IF(AI12>0,AH12/AI12,"") -> -1.1288425 | AK12: =IF(AI12>0,TDIST(ABS(AJ12),MIN(AH27,AH28)-1,2),"") -> 0.27378509
A13: Hedge Fund Allocation (%) | B13: -0.11685809 | C13: 0.12599504 | D13: =IF(C13>0,B13/C13,"") -> -0.92748166 | E13: =IF(C13>0,TDIST(ABS(D13),MIN(B27,B28)-1,2),"") -> 0.36594692 | F13: -0.052896705 | G13: 0.060517756 | H13: =IF(G13>0,F13/G13,"") -> -0.87406918 | I13: =IF(G13>0,TDIST(ABS(H13),MIN(F27,F28)-1,2),"") -> 0.39359329 | J13: -0.087180925 | K13: 0.074693646 | L13: =IF(K13>0,J13/K13,"") -> -1.1671799 | M13: =IF(K13>0,TDIST(ABS(L13),MIN(J27,J28)-1,2),"") -> 0.25836779 | N13: -0.14979246 | O13: 0.12604816 | P13: =IF(O13>0,N13/O13,"") -> -1.1883748 | Q13: =IF(O13>0,TDIST(ABS(P13),MIN(N27,N28)-1,2),"") -> 0.25012924 | R13: -0.00065740148 | S13: 0.11754222 | T13: =IF(S13>0,R13/S13,"") -> -0.0055928964 | U13: =IF(S13>0,TDIST(ABS(T13),MIN(R27,R28)-1,2),"") -> 0.99559906 | V13: 0.012725222 | W13: 0.16516393 | X13: =IF(W13>0,V13/W13,"") -> 0.077046009 | Y13: =IF(W13>0,TDIST(ABS(X13),MIN(V27,V28)-1,2),"") -> 0.9394369 | Z13: -0.018767646 | AA13: 0.033827652 | AB13: =IF(AA13>0,Z13/AA13,"") -> -0.5548019 | AC13: =IF(AA13>0,TDIST(ABS(AB13),MIN(Z27,Z28)-1,2),"") -> 0.58585892 | AD13: -0.065956709 | AE13: 0.068223258 | AF13: =IF(AE13>0,AD13/AE13,"") -> -0.96677747 | AG13: =IF(AE13>0,TDIST(ABS(AF13),MIN(AD27,AD28)-1,2),"") -> 0.34646634 | AH13: -0.062892991 | AI13: 0.050976234 | AJ13: =IF(AI13>0,AH13/AI13,"") -> -1.2337708 | AK13: =IF(AI13>0,TDIST(ABS(AJ13),MIN(AH27,AH28)-1,2),"") -> 0.23315609
A14: Misc. Alternatives Allocation (%) | B14: -0.09426531 | C14: 0.13064503 | D14: =IF(C14>0,B14/C14,"") -> -0.72153767 | E14: =IF(C14>0,TDIST(ABS(D14),MIN(B27,B28)-1,2),"") -> 0.47984722 | F14: -0.031628573 | G14: 0.057475411 | H14: =IF(G14>0,F14/G14,"") -> -0.55029747 | I14: =IF(G14>0,TDIST(ABS(H14),MIN(F27,F28)-1,2),"") -> 0.58887997 | J14: -0.081116677 | K14: 0.09014937 | L14: =IF(K14>0,J14/K14,"") -> -0.89980304 | M14: =IF(K14>0,TDIST(ABS(L14),MIN(J27,J28)-1,2),"") -> 0.38010573 | N14: -0.17842445 | O14: 0.12201174 | P14: =IF(O14>0,N14/O14,"") -> -1.4623547 | Q14: =IF(O14>0,TDIST(ABS(P14),MIN(N27,N28)-1,2),"") -> 0.16088509 | R14: -0.017169914 | S14: 0.11359149 | T14: =IF(S14>0,R14/S14,"") -> -0.15115493 | U14: =IF(S14>0,TDIST(ABS(T14),MIN(R27,R28)-1,2),"") -> 0.88153463 | V14: 0.025051024 | W14: 0.17527353 | X14: =IF(W14>0,V14/W14,"") -> 0.14292531 | Y14: =IF(W14>0,TDIST(ABS(X14),MIN(V27,V28)-1,2),"") -> 0.88793695 | Z14: -0.033343615 | AA14: 0.033082445 | AB14: =IF(AA14>0,Z14/AA14,"") -> -1.0078945 | AC14: =IF(AA14>0,TDIST(ABS(AB14),MIN(Z27,Z28)-1,2),"") -> 0.32686281 | AD14: -0.078868699 | AE14: 0.06633256 | AF14: =IF(AE14>0,AD14/AE14,"") -> -1.1889892 | AG14: =IF(AE14>0,TDIST(ABS(AF14),MIN(AD27,AD28)-1,2),"") -> 0.24989342 | AH14: -0.067922735 | AI14: 0.051564721 | AJ14: =IF(AI14>0,AH14/AI14,"") -> -1.3172327 | AK14: =IF(AI14>0,TDIST(ABS(AJ14),MIN(AH27,AH28)-1,2),"") -> 0.20428348
A15: Commodities Allocation (%) | B15: -0.13368998 | C15: 0.13109802 | D15: =IF(C15>0,B15/C15,"") -> -1.0197712 | E15: =IF(C15>0,TDIST(ABS(D15),MIN(B27,B28)-1,2),"") -> 0.3213485 | F15: -0.064838333 | G15: 0.057053744 | H15: =IF(G15>0,F15/G15,"") -> -1.1364431 | I15: =IF(G15>0,TDIST(ABS(H15),MIN(F27,F28)-1,2),"") -> 0.27067543 | J15: -0.13453221 | K15: 0.10041492 | L15: =IF(K15>0,J15/K15,"") -> -1.3397632 | M15: =IF(K15>0,TDIST(ABS(L15),MIN(J27,J28)-1,2),"") -> 0.19699262 | N15: -0.19416671 | O15: 0.13302016 | P15: =IF(O15>0,N15/O15,"") -> -1.4596789 | Q15: =IF(O15>0,TDIST(ABS(P15),MIN(N27,N28)-1,2),"") -> 0.16161122 | R15: -0.029030616 | S15: 0.11638211 | T15: =IF(S15>0,R15/S15,"") -> -0.24944227 | U15: =IF(S15>0,TDIST(ABS(T15),MIN(R27,R28)-1,2),"") -> 0.80584302 | V15: -0.010473506 | W15: 0.16945856 | X15: =IF(W15>0,V15/W15,"") -> -0.061805706 | Y15: =IF(W15>0,TDIST(ABS(X15),MIN(V27,V28)-1,2),"") -> 0.95139868 | Z15: -0.030549048 | AA15: 0.034167464 | AB15: =IF(AA15>0,Z15/AA15,"") -> -0.89409761 | AC15: =IF(AA15>0,TDIST(ABS(AB15),MIN(Z27,Z28)-1,2),"") -> 0.38306918 | AD15: -0.076463512 | AE15: 0.066117157 | AF15: =IF(AE15>0,AD15/AE15,"") -> -1.1564852 | AG15: =IF(AE15>0,TDIST(ABS(AF15),MIN(AD27,AD28)-1,2),"") -> 0.26260161 | AH15: -0.078283467 | AI15: 0.050811578 | AJ15: =IF(AI15>0,AH15/AI15,"") -> -1.540662 | AK15: =IF(AI15>0,TDIST(ABS(AJ15),MIN(AH27,AH28)-1,2),"") -> 0.14079504
A16: Cash Allocation (%) | B16: -0.093603742 | C16: 0.13985951 | D16: =IF(C16>0,B16/C16,"") -> -0.66926979 | E16: =IF(C16>0,TDIST(ABS(D16),MIN(B27,B28)-1,2),"") -> 0.51181724 | F16: -0.038715779 | G16: 0.075060512 | H16: =IF(G16>0,F16/G16,"") -> -0.51579423 | I16: =IF(G16>0,TDIST(ABS(H16),MIN(F27,F28)-1,2),"") -> 0.61227573 | J16: -0.055862086 | K16: 0.1186949 | L16: =IF(K16>0,J16/K16,"") -> -0.47063593 | M16: =IF(K16>0,TDIST(ABS(L16),MIN(J27,J28)-1,2),"") -> 0.64355355 | N16: -0.12483707 | O16: 0.14085678 | P16: =IF(O16>0,N16/O16,"") -> -0.88626953 | Q16: =IF(O16>0,TDIST(ABS(P16),MIN(N27,N28)-1,2),"") -> 0.38716007 | R16: 0.009688208 | S16: 0.12816349 | T16: =IF(S16>0,R16/S16,"") -> 0.075592572 | U16: =IF(S16>0,TDIST(ABS(T16),MIN(R27,R28)-1,2),"") -> 0.94057707 | V16: 0.039724116 | W16: 0.18107431 | X16: =IF(W16>0,V16/W16,"") -> 0.21938019 | Y16: =IF(W16>0,TDIST(ABS(X16),MIN(V27,V28)-1,2),"") -> 0.82882241 | Z16: -0.033562909 | AA16: 0.033301177 | AB16: =IF(AA16>0,Z16/AA16,"") -> -1.0078595 | AC16: =IF(AA16>0,TDIST(ABS(AB16),MIN(Z27,Z28)-1,2),"") -> 0.32687916 | AD16: -0.082337182 | AE16: 0.067632048 | AF16: =IF(AE16>0,AD16/AE16,"") -> -1.2174285 | AG16: =IF(AE16>0,TDIST(ABS(AF16),MIN(AD27,AD28)-1,2),"") -> 0.23916154 | AH16: -0.074190397 | AI16: 0.051862607 | AJ16: =IF(AI16>0,AH16/AI16,"") -> -1.4305181 | AK16: =IF(AI16>0,TDIST(ABS(AJ16),MIN(AH27,AH28)-1,2),"") -> 0.16969947
A17: Financial Center (0/1) | B17: 0.065443389 | C17: 0.14274908 | D17: =IF(C17>0,B17/C17,"") -> 0.45845052 | E17: =IF(C17>0,TDIST(ABS(D17),MIN(B27,B28)-1,2),"") -> 0.65211564 | F17: 0.089048467 | G17: 0.15413335 | H17: =IF(G17>0,F17/G17,"") -> 0.57773653 | I17: =IF(G17>0,TDIST(ABS(H17),MIN(F27,F28)-1,2),"") -> 0.57059926 | N17: -0.17076927 | O17: 0.10487854 | P17: =IF(O17>0,N17/O17,"") -> -1.6282576 | Q17: =IF(O17>0,TDIST(ABS(P17),MIN(N27,N28)-1,2),"") -> 0.12084667 | R17: -0.17927867 | S17: 0.091612195 | T17: =IF(S17>0,R17/S17,"") -> -1.9569302 | U17: =IF(S17>0,TDIST(ABS(T17),MIN(R27,R28)-1,2),"") -> 0.066049471 | Z17: -0.027045896 | AA17: 0.041034756 | AB17: =IF(AA17>0,Z17/AA17,"") -> -0.65909729 | AC17: =IF(AA17>0,TDIST(ABS(AB17),MIN(Z27,Z28)-1,2),"") -> 0.51817703 | AD17: 0.02733371 | AE17: 0.036729092 | AF17: =IF(AE17>0,AD17/AE17,"") -> 0.74419781 | AG17: =IF(AE17>0,TDIST(ABS(AF17),MIN(AD27,AD28)-1,2),"") -> 0.46636185
A18: Log (CIO Age) (t-1) | F18: -0.26965092 | G18: 0.53733653 | H18: =IF(G18>0,F18/G18,"") -> -0.50182875 | I18: =IF(G18>0,TDIST(ABS(H18),MIN(F27,F28)-1,2),"") -> 0.62187078 | J18: 0.79324209 | K18: 0.82936909 | L18: =IF(K18>0,J18/K18,"") -> 0.95644039 | M18: =IF(K18>0,TDIST(ABS(L18),MIN(J27,J28)-1,2),"") -> 0.35152021 | R18: -1.1595688 | S18: 0.50302626 | T18: =IF(S18>0,R18/S18,"") -> -2.3051855 | U18: =IF(S18>0,TDIST(ABS(T18),MIN(R27,R28)-1,2),"") -> 0.033276937 | V18: 0.03566869 | W18: 0.84501561 | X18: =IF(W18>0,V18/W18,"") -> 0.042210688 | Y18: =IF(W18>0,TDIST(ABS(X18),MIN(V27,V28)-1,2),"") -> 0.96679545 | AD18: 0.064348231 | AE18: 0.10092796 | AF18: =IF(AE18>0,AD18/AE18,"") -> 0.63756597 | AG18: =IF(AE18>0,TDIST(ABS(AF18),MIN(AD27,AD28)-1,2),"") -> 0.53178333 | AH18: -0.18807625 | AI18: 0.10539502 | AJ18: =IF(AI18>0,AH18/AI18,"") -> -1.7844889 | AK18: =IF(AI18>0,TDIST(ABS(AJ18),MIN(AH27,AH28)-1,2),"") -> 0.091209393
A19: Log (CIO Tenure) (t-1) | F19: 0.066125451 | G19: 0.084054942 | H19: =IF(G19>0,F19/G19,"") -> 0.7866932 | I19: =IF(G19>0,TDIST(ABS(H19),MIN(F27,F28)-1,2),"") -> 0.44169664 | J19: 0.0077914667 | K19: 0.12292171 | L19: =IF(K19>0,J19/K19,"") -> 0.063385604 | M19: =IF(K19>0,TDIST(ABS(L19),MIN(J27,J28)-1,2),"") -> 0.95015805 | R19: -0.01038015 | S19: 0.11164643 | T19: =IF(S19>0,R19/S19,"") -> -0.092973418 | U19: =IF(S19>0,TDIST(ABS(T19),MIN(R27,R28)-1,2),"") -> 0.92695169 | V19: -0.20265086 | W19: 0.13766967 | X19: =IF(W19>0,V19/W19,"") -> -1.472008 | Y19: =IF(W19>0,TDIST(ABS(X19),MIN(V27,V28)-1,2),"") -> 0.15828775 | AD19: -0.0041791631 | AE19: 0.013158391 | AF19: =IF(AE19>0,AD19/AE19,"") -> -0.31760442 | AG19: =IF(AE19>0,TDIST(ABS(AF19),MIN(AD27,AD28)-1,2),"") -> 0.7544398 | AH19: 0.019034698 | AI19: 0.011458225 | AJ19: =IF(AI19>0,AH19/AI19,"") -> 1.6612257 | AK19: =IF(AI19>0,TDIST(ABS(AJ19),MIN(AH27,AH28)-1,2),"") -> 0.11398586
A20: CIO Prior Private Experience (0/1) | F20: 0.062219782 | G20: 0.11135614 | H20: =IF(G20>0,F20/G20,"") -> 0.55874585 | I20: =IF(G20>0,TDIST(ABS(H20),MIN(F27,F28)-1,2),"") -> 0.5832202 | J20: 0.0085351262 | K20: 0.19794681 | L20: =IF(K20>0,J20/K20,"") -> 0.043118281 | M20: =IF(K20>0,TDIST(ABS(L20),MIN(J27,J28)-1,2),"") -> 0.96608196 | R20: 0.078868469 | S20: 0.14633002 | T20: =IF(S20>0,R20/S20,"") -> 0.53897667 | U20: =IF(S20>0,TDIST(ABS(T20),MIN(R27,R28)-1,2),"") -> 0.5965069 | V20: 0.060515254 | W20: 0.20566566 | X20: =IF(W20>0,V20/W20,"") -> 0.29424093 | Y20: =IF(W20>0,TDIST(ABS(X20),MIN(V27,V28)-1,2),"") -> 0.77194003 | AD20: -0.070205396 | AE20: 0.043175066 | AF20: =IF(AE20>0,AD20/AE20,"") -> -1.6260634 | AG20: =IF(AE20>0,TDIST(ABS(AF20),MIN(AD27,AD28)-1,2),"") -> 0.12131548 | AH20: -0.069146331 | AI20: 0.056591521 | AJ20: =IF(AI20>0,AH20/AI20,"") -> -1.2218497 | AK20: =IF(AI20>0,TDIST(ABS(AJ20),MIN(AH27,AH28)-1,2),"") -> 0.23752529
A21: CIO Attended Elite College (0/1) | F21: -0.18278497 | G21: 0.13966802 | H21: =IF(G21>0,F21/G21,"") -> -1.3087102 | I21: =IF(G21>0,TDIST(ABS(H21),MIN(F27,F28)-1,2),"") -> 0.20709625 | J21: 0.28716978 | K21: 0.25846943 | L21: =IF(K21>0,J21/K21,"") -> 1.1110396 | M21: =IF(K21>0,TDIST(ABS(L21),MIN(J27,J28)-1,2),"") -> 0.2811724 | R21: -0.1760259 | S21: 0.17381881 | T21: =IF(S21>0,R21/S21,"") -> -1.0126976 | U21: =IF(S21>0,TDIST(ABS(T21),MIN(R27,R28)-1,2),"") -> 0.32462475 | V21: 0.022246563 | W21: 0.20174167 | X21: =IF(W21>0,V21/W21,"") -> 0.11027252 | Y21: =IF(W21>0,TDIST(ABS(X21),MIN(V27,V28)-1,2),"") -> 0.91341343 | AD21: 0.026017948 | AE21: 0.039719053 | AF21: =IF(AE21>0,AD21/AE21,"") -> 0.65504955 | AG21: =IF(AE21>0,TDIST(ABS(AF21),MIN(AD27,AD28)-1,2),"") -> 0.52071994 | AH21: -0.068054611 | AI21: 0.035903805 | AJ21: =IF(AI21>0,AH21/AI21,"") -> -1.8954707 | AK21: =IF(AI21>0,TDIST(ABS(AJ21),MIN(AH27,AH28)-1,2),"") -> 0.074204555
A22: Separate Investment Board (0/1) | F22: 0.28107088 | G22: 0.1218627 | H22: =IF(G22>0,F22/G22,"") -> 2.3064554 | I22: =IF(G22>0,TDIST(ABS(H22),MIN(F27,F28)-1,2),"") -> 0.033191448 | J22: 0.25792388 | K22: 0.9224385 | L22: =IF(K22>0,J22/K22,"") -> 0.27961092 | M22: =IF(K22>0,TDIST(ABS(L22),MIN(J27,J28)-1,2),"") -> 0.78296367 | R22: 0.28377704 | S22: 0.17260772 | T22: =IF(S22>0,R22/S22,"") -> 1.6440576 | U22: =IF(S22>0,TDIST(ABS(T22),MIN(R27,R28)-1,2),"") -> 0.117516 | V22: 0.76802804 | W22: 0.58495062 | X22: =IF(W22>0,V22/W22,"") -> 1.3129793 | Y22: =IF(W22>0,TDIST(ABS(X22),MIN(V27,V28)-1,2),"") -> 0.20568349 | AD22: -0.019526376 | AE22: 0.042126547 | AF22: =IF(AE22>0,AD22/AE22,"") -> -0.46351713 | AG22: =IF(AE22>0,TDIST(ABS(AF22),MIN(AD27,AD28)-1,2),"") -> 0.64854945 | AH22: -0.27486009 | AI22: 0.080704726 | AJ22: =IF(AI22>0,AH22/AI22,"") -> -3.4057496 | AK22: =IF(AI22>0,TDIST(ABS(AJ22),MIN(AH27,AH28)-1,2),"") -> 0.0031511241
A23: % Political Appointees on Board | F23: -0.16203177 | G23: 0.28557534 | H23: =IF(G23>0,F23/G23,"") -> -0.56738714 | I23: =IF(G23>0,TDIST(ABS(H23),MIN(F27,F28)-1,2),"") -> 0.57745982 | J23: 0.13980748 | K23: 1.3774518 | L23: =IF(K23>0,J23/K23,"") -> 0.10149719 | M23: =IF(K23>0,TDIST(ABS(L23),MIN(J27,J28)-1,2),"") -> 0.92027787 | R23: -0.063638343 | S23: 0.21785766 | T23: =IF(S23>0,R23/S23,"") -> -0.29210974 | U23: =IF(S23>0,TDIST(ABS(T23),MIN(R27,R28)-1,2),"") -> 0.77354283 | V23: -0.22831474 | W23: 1.3853958 | X23: =IF(W23>0,V23/W23,"") -> -0.1648011 | Y23: =IF(W23>0,TDIST(ABS(X23),MIN(V27,V28)-1,2),"") -> 0.87093716 | AD23: -0.093758022 | AE23: 0.052521673 | AF23: =IF(AE23>0,AD23/AE23,"") -> -1.7851302 | AG23: =IF(AE23>0,TDIST(ABS(AF23),MIN(AD27,AD28)-1,2),"") -> 0.091102077 | AH23: -0.18473717 | AI23: 0.17883026 | AJ23: =IF(AI23>0,AH23/AI23,"") -> -1.0330308 | AK23: =IF(AI23>0,TDIST(ABS(AJ23),MIN(AH27,AH28)-1,2),"") -> 0.31527035
A24: First Half minus Second Half | B24: 0.12143804 | C24: 0.2290746 | D24: =IF(C24>0,B24/C24,"") -> 0.53012441 | E24: =IF(C24>0,TDIST(ABS(D24),MIN(B27,B28)-1,2),"") -> 0.60250458 | F24: 0.039163061 | G24: 0.19943922 | H24: =IF(G24>0,F24/G24,"") -> 0.1963659 | I24: =IF(G24>0,TDIST(ABS(H24),MIN(F27,F28)-1,2),"") -> 0.84652377 | J24: -0.20075324 | K24: 0.23344104 | L24: =IF(K24>0,J24/K24,"") -> -0.85997407 | M24: =IF(K24>0,TDIST(ABS(L24),MIN(J27,J28)-1,2),"") -> 0.40111257 | N24: -0.18759014 | O24: 0.2487984 | P24: =IF(O24>0,N24/O24,"") -> -0.75398452 | Q24: =IF(O24>0,TDIST(ABS(P24),MIN(N27,N28)-1,2),"") -> 0.46060888 | R24: -0.18672118 | S24: 0.21005658 | T24: =IF(S24>0,R24/S24,"") -> -0.88890895 | U24: =IF(S24>0,TDIST(ABS(T24),MIN(R27,R28)-1,2),"") -> 0.38577751 | V24: -0.42687793 | W24: 0.24759763 | X24: =IF(W24>0,V24/W24,"") -> -1.7240792 | Y24: =IF(W24>0,TDIST(ABS(X24),MIN(V27,V28)-1,2),"") -> 0.10182503 | Z24: 0.0036313088 | AA24: 0.04094188 | AB24: =IF(AA24>0,Z24/AA24,"") -> 0.088694237 | AC24: =IF(AA24>0,TDIST(ABS(AB24),MIN(Z27,Z28)-1,2),"") -> 0.93030429 | AD24: 0.015444966 | AE24: 0.042454468 | AF24: =IF(AE24>0,AD24/AE24,"") -> 0.36380073 | AG24: =IF(AE24>0,TDIST(ABS(AF24),MIN(AD27,AD28)-1,2),"") -> 0.72024481 | AH24: 0.0099110183 | AI24: 0.037547382 | AJ24: =IF(AI24>0,AH24/AI24,"") -> 0.26396031 | AK24: =IF(AI24>0,TDIST(ABS(AJ24),MIN(AH27,AH28)-1,2),"") -> 0.79480886
A26: Observations | B26: 1723 | F26: 1478 | J26: 1477 | N26: 1532 | R26: 1313 | V26: 1312 | Z26: 1480 | AD26: 1293 | AH26: 1291
A27: Plan clusters | B27: 19 | F27: 19 | J27: 19 | N27: 19 | R27: 19 | V27: 19 | Z27: 19 | AD27: 19 | AH27: 19
A28: Year clusters | B28: 19 | F28: 19 | J28: 19 | N28: 19 | R28: 19 | V28: 19 | Z28: 19 | AD28: 19 | AH28: 19
A29: Adjusted R-squared | B29: 0.058220713 | F29: 0.069521279 | J29: 0.088644722 | N29: 0.15153953 | R29: 0.16779335 | V29: 0.16301112 | Z29: 0.35213737 | AD29: 0.36348566 | AH29: 0.65835334

Sheet Estimates
A1: Estimates behind the tables (blue = regression output; t and p are formulas). Standard errors double clustered by plan and year; p-values use the t distribution with min(plan clusters, year clusters) - 1 degrees of freedom.
A3: Variable | B3: T1A(1) coef | C3: T1A(1) se | D3: T1A(1) t | E3: T1A(1) p | F3: T1A(2) coef | G3: T1A(2) se | H3: T1A(2) t | I3: T1A(2) p | J3: T1A(3) coef | K3: T1A(3) se | L3: T1A(3) t | M3: T1A(3) p | N3: T1A(4) coef | O3: T1A(4) se | P3: T1A(4) t | Q3: T1A(4) p | R3: T1A(5) coef | S3: T1A(5) se | T3: T1A(5) t | U3: T1A(5) p | V3: T1B(1) coef | W3: T1B(1) se | X3: T1B(1) t | Y3: T1B(1) p | Z3: T1B(2) coef | AA3: T1B(2) se | AB3: T1B(2) t | AC3: T1B(2) p | AD3: T1B(3) coef | AE3: T1B(3) se | AF3: T1B(3) t | AG3: T1B(3) p | AH3: T1B(4) coef | AI3: T1B(4) se | AJ3: T1B(4) t | AK3: T1B(4) p | AL3: T1B(5) coef | AM3: T1B(5) se | AN3: T1B(5) t | AO3: T1B(5) p | AP3: T2A(1) coef | AQ3: T2A(1) se | AR3: T2A(1) t | AS3: T2A(1) p | AT3: T2A(2) coef | AU3: T2A(2) se | AV3: T2A(2) t | AW3: T2A(2) p | AX3: T2A(3) coef | AY3: T2A(3) se | AZ3: T2A(3) t | BA3: T2A(3) p | BB3: T2A(4) coef | BC3: T2A(4) se | BD3: T2A(4) t | BE3: T2A(4) p | BF3: T2A(5) coef | BG3: T2A(5) se | BH3: T2A(5) t | BI3: T2A(5) p
A4: Second Half of Tenure (0/1) | B4: -0.21428579 | C4: 0.18562024 | D4: =IF(C4>0,B4/C4,"") -> -1.1544312 | E4: =IF(C4>0,TDIST(ABS(D4),MIN(B25,B26)-1,2),"") -> 0.2642944 | F4: -0.080963521 | G4: 0.23950378 | H4: =IF(G4>0,F4/G4,"") -> -0.33804694 | I4: =IF(G4>0,TDIST(ABS(H4),MIN(F25,F26)-1,2),"") -> 0.73946653 | J4: -0.088413564 | K4: 0.29567442 | L4: =IF(K4>0,J4/K4,"") -> -0.29902338 | M4: =IF(K4>0,TDIST(ABS(L4),MIN(J25,J26)-1,2),"") -> 0.76854684 | N4: -0.96474051 | O4: 0.51186233 | P4: =IF(O4>0,N4/O4,"") -> -1.8847656 | Q4: =IF(O4>0,TDIST(ABS(P4),MIN(N25,N26)-1,2),"") -> 0.076675568 | R4: -0.26688768 | S4: 1.0021097 | T4: =IF(S4>0,R4/S4,"") -> -0.26632582 | U4: =IF(S4>0,TDIST(ABS(T4),MIN(R25,R26)-1,2),"") -> 0.79319163 | V4: 0.09685311 | W4: 0.24528639 | X4: =IF(W4>0,V4/W4,"") -> 0.39485725 | Y4: =IF(W4>0,TDIST(ABS(X4),MIN(V25,V26)-1,2),"") -> 0.69785838 | Z4: 0.35895318 | AA4: 0.29345092 | AB4: =IF(AA4>0,Z4/AA4,"") -> 1.2232137 | AC4: =IF(AA4>0,TDIST(ABS(AB4),MIN(Z25,Z26)-1,2),"") -> 0.23793498 | AD4: 0.56525798 | AE4: 0.28183252 | AF4: =IF(AE4>0,AD4/AE4,"") -> 2.0056521 | AG4: =IF(AE4>0,TDIST(ABS(AF4),MIN(AD25,AD26)-1,2),"") -> 0.061078325 | AH4: -0.16426162 | AI4: 0.3579633 | AJ4: =IF(AI4>0,AH4/AI4,"") -> -0.45887839 | AK4: =IF(AI4>0,TDIST(ABS(AJ4),MIN(AH25,AH26)-1,2),"") -> 0.6521341 | AL4: 0.0019207815 | AM4: 0.39885434 | AN4: =IF(AM4>0,AL4/AM4,"") -> 0.0048157468 | AO4: =IF(AM4>0,TDIST(ABS(AN4),MIN(AL25,AL26)-1,2),"") -> 0.99621367 | AP4: -0.064627962 | AQ4: 0.039982087 | AR4: =IF(AQ4>0,AP4/AQ4,"") -> -1.6164229 | AS4: =IF(AQ4>0,TDIST(ABS(AR4),MIN(AP25,AP26)-1,2),"") -> 0.12440723 | AT4: -0.082387269 | AU4: 0.058500047 | AV4: =IF(AU4>0,AT4/AU4,"") -> -1.4083283 | AW4: =IF(AU4>0,TDIST(ABS(AV4),MIN(AT25,AT26)-1,2),"") -> 0.17705977 | AX4: -0.058874407 | AY4: 0.042687354 | AZ4: =IF(AY4>0,AX4/AY4,"") -> -1.3792002 | BA4: =IF(AY4>0,TDIST(ABS(AZ4),MIN(AX25,AX26)-1,2),"") -> 0.1857089 | BB4: -0.066275941 | BC4: 0.054780788 | BD4: =IF(BC4>0,BB4/BC4,"") -> -1.2098391 | BE4: =IF(BC4>0,TDIST(ABS(BD4),MIN(BB25,BB26)-1,2),"") -> 0.24289604 | BF4: -0.038273521 | BG4: 0.070378906 | BH4: =IF(BG4>0,BF4/BG4,"") -> -0.54382092 | BI4: =IF(BG4>0,TDIST(ABS(BH4),MIN(BF25,BF26)-1,2),"") -> 0.59362574
A5: Investment Return (t - 1) | B5: 0.16777103 | C5: 0.15216964 | D5: =IF(C5>0,B5/C5,"") -> 1.1025263 | E5: =IF(C5>0,TDIST(ABS(D5),MIN(B25,B26)-1,2),"") -> 0.28559718 | F5: 0.11781578 | G5: 0.16384907 | H5: =IF(G5>0,F5/G5,"") -> 0.71905063 | I5: =IF(G5>0,TDIST(ABS(H5),MIN(F25,F26)-1,2),"") -> 0.48187769 | J5: 0.083578714 | K5: 0.14832191 | L5: =IF(K5>0,J5/K5,"") -> 0.56349541 | M5: =IF(K5>0,TDIST(ABS(L5),MIN(J25,J26)-1,2),"") -> 0.58045518 | N5: 0.099417082 | O5: 0.1318047 | P5: =IF(O5>0,N5/O5,"") -> 0.75427572 | Q5: =IF(O5>0,TDIST(ABS(P5),MIN(N25,N26)-1,2),"") -> 0.46100498 | R5: 0.22346008 | S5: 0.1343483 | T5: =IF(S5>0,R5/S5,"") -> 1.6632892 | U5: =IF(S5>0,TDIST(ABS(T5),MIN(R25,R26)-1,2),"") -> 0.11457884 | V5: 0.13591903 | W5: 0.21719934 | X5: =IF(W5>0,V5/W5,"") -> 0.6257801 | Y5: =IF(W5>0,TDIST(ABS(X5),MIN(V25,V26)-1,2),"") -> 0.53977053 | Z5: 0.050309976 | AA5: 0.20875569 | AB5: =IF(AA5>0,Z5/AA5,"") -> 0.24099931 | AC5: =IF(AA5>0,TDIST(ABS(AB5),MIN(Z25,Z26)-1,2),"") -> 0.81243826 | AD5: 0.015172522 | AE5: 0.18529726 | AF5: =IF(AE5>0,AD5/AE5,"") -> 0.081882059 | AG5: =IF(AE5>0,TDIST(ABS(AF5),MIN(AD25,AD26)-1,2),"") -> 0.93569685 | AH5: -0.13213143 | AI5: 0.10654997 | AJ5: =IF(AI5>0,AH5/AI5,"") -> -1.2400889 | AK5: =IF(AI5>0,TDIST(ABS(AJ5),MIN(AH25,AH26)-1,2),"") -> 0.23178715 | AL5: 0.060283204 | AM5: 0.13174554 | AN5: =IF(AM5>0,AL5/AM5,"") -> 0.45757303 | AO5: =IF(AM5>0,TDIST(ABS(AN5),MIN(AL25,AL26)-1,2),"") -> 0.65305308 | AP5: 0.00016816503 | AQ5: 0.0067141533 | AR5: =IF(AQ5>0,AP5/AQ5,"") -> 0.02504635 | AS5: =IF(AQ5>0,TDIST(ABS(AR5),MIN(AP25,AP26)-1,2),"") -> 0.98030965 | AT5: 0.0036414144 | AU5: 0.0063096623 | AV5: =IF(AU5>0,AT5/AU5,"") -> 0.57711717 | AW5: =IF(AU5>0,TDIST(ABS(AV5),MIN(AT25,AT26)-1,2),"") -> 0.57142465 | AX5: 0.0071016859 | AY5: 0.0055571735 | AZ5: =IF(AY5>0,AX5/AY5,"") -> 1.2779313 | BA5: =IF(AY5>0,TDIST(ABS(AZ5),MIN(AX25,AX26)-1,2),"") -> 0.21844862 | BB5: 0.005031299 | BC5: 0.0042315453 | BD5: =IF(BC5>0,BB5/BC5,"") -> 1.188998 | BE5: =IF(BC5>0,TDIST(ABS(BD5),MIN(BB25,BB26)-1,2),"") -> 0.25078409 | BF5: 0.0069071535 | BG5: 0.0034486285 | BH5: =IF(BG5>0,BF5/BG5,"") -> 2.0028697 | BI5: =IF(BG5>0,TDIST(ABS(BH5),MIN(BF25,BF26)-1,2),"") -> 0.061402563
A6: Log (Plan Size) (t-1) | B6: -0.075392788 | C6: 0.1091471 | D6: =IF(C6>0,B6/C6,"") -> -0.69074478 | E6: =IF(C6>0,TDIST(ABS(D6),MIN(B25,B26)-1,2),"") -> 0.49904971 | F6: -0.081595412 | G6: 0.11730631 | H6: =IF(G6>0,F6/G6,"") -> -0.69557564 | I6: =IF(G6>0,TDIST(ABS(H6),MIN(F25,F26)-1,2),"") -> 0.49609413 | J6: -0.080362927 | K6: 0.91738019 | L6: =IF(K6>0,J6/K6,"") -> -0.087600461 | M6: =IF(K6>0,TDIST(ABS(L6),MIN(J25,J26)-1,2),"") -> 0.93121786 | N6: 1.0854676 | O6: 1.8255053 | P6: =IF(O6>0,N6/O6,"") -> 0.59461216 | Q6: =IF(O6>0,TDIST(ABS(P6),MIN(N25,N26)-1,2),"") -> 0.55993423 | R6: 0.65638948 | S6: 2.0516737 | T6: =IF(S6>0,R6/S6,"") -> 0.31992878 | U6: =IF(S6>0,TDIST(ABS(T6),MIN(R25,R26)-1,2),"") -> 0.75292078 | V6: 0.03529792 | W6: 0.078222989 | X6: =IF(W6>0,V6/W6,"") -> 0.45124739 | Y6: =IF(W6>0,TDIST(ABS(X6),MIN(V25,V26)-1,2),"") -> 0.65751448 | Z6: -0.010469309 | AA6: 0.10585937 | AB6: =IF(AA6>0,Z6/AA6,"") -> -0.098898273 | AC6: =IF(AA6>0,TDIST(ABS(AB6),MIN(Z25,Z26)-1,2),"") -> 0.92237586 | AD6: 0.33588127 | AE6: 0.80569547 | AF6: =IF(AE6>0,AD6/AE6,"") -> 0.41688365 | AG6: =IF(AE6>0,TDIST(ABS(AF6),MIN(AD25,AD26)-1,2),"") -> 0.68198021 | AH6: 0.35623374 | AI6: 0.88815276 | AJ6: =IF(AI6>0,AH6/AI6,"") -> 0.40109513 | AK6: =IF(AI6>0,TDIST(ABS(AJ6),MIN(AH25,AH26)-1,2),"") -> 0.69334663 | AL6: 1.4427172 | AM6: 0.87001283 | AN6: =IF(AM6>0,AL6/AM6,"") -> 1.6582711 | AO6: =IF(AM6>0,TDIST(ABS(AN6),MIN(AL25,AL26)-1,2),"") -> 0.11559839 | AP6: -0.033843327 | AQ6: 0.019315537 | AR6: =IF(AQ6>0,AP6/AQ6,"") -> -1.7521297 | AS6: =IF(AQ6>0,TDIST(ABS(AR6),MIN(AP25,AP26)-1,2),"") -> 0.097768171 | AT6: -0.043727965 | AU6: 0.021641575 | AV6: =IF(AU6>0,AT6/AU6,"") -> -2.0205537 | AW6: =IF(AU6>0,TDIST(ABS(AV6),MIN(AT25,AT26)-1,2),"") -> 0.059367946 | AX6: -0.34781175 | AY6: 0.14803591 | AZ6: =IF(AY6>0,AX6/AY6,"") -> -2.3495093 | BA6: =IF(AY6>0,TDIST(ABS(AZ6),MIN(AX25,AX26)-1,2),"") -> 0.031140608 | BB6: -0.24263783 | BC6: 0.23796666 | BD6: =IF(BC6>0,BB6/BC6,"") -> -1.0196295 | BE6: =IF(BC6>0,TDIST(ABS(BD6),MIN(BB25,BB26)-1,2),"") -> 0.32219639 | BF6: -0.089636722 | BG6: 0.21799042 | BH6: =IF(BG6>0,BF6/BG6,"") -> -0.41119569 | BI6: =IF(BG6>0,TDIST(ABS(BH6),MIN(BF25,BF26)-1,2),"") -> 0.68606619
A7: Funding Ratio (t-1) | B7: -0.016139937 | C7: 0.0098762904 | D7: =IF(C7>0,B7/C7,"") -> -1.6342104 | E7: =IF(C7>0,TDIST(ABS(D7),MIN(B25,B26)-1,2),"") -> 0.12059553 | F7: -0.013544646 | G7: 0.0065847506 | H7: =IF(G7>0,F7/G7,"") -> -2.0569718 | I7: =IF(G7>0,TDIST(ABS(H7),MIN(F25,F26)-1,2),"") -> 0.055368772 | J7: -0.026629232 | K7: 0.027395955 | L7: =IF(K7>0,J7/K7,"") -> -0.97201328 | M7: =IF(K7>0,TDIST(ABS(L7),MIN(J25,J26)-1,2),"") -> 0.34467219 | N7: -0.070591283 | O7: 0.027087017 | P7: =IF(O7>0,N7/O7,"") -> -2.6060929 | Q7: =IF(O7>0,TDIST(ABS(P7),MIN(N25,N26)-1,2),"") -> 0.018446067 | R7: -0.076934747 | S7: 0.034125965 | T7: =IF(S7>0,R7/S7,"") -> -2.2544344 | U7: =IF(S7>0,TDIST(ABS(T7),MIN(R25,R26)-1,2),"") -> 0.037650547 | V7: -0.0075991215 | W7: 0.0089770461 | X7: =IF(W7>0,V7/W7,"") -> -0.84650579 | Y7: =IF(W7>0,TDIST(ABS(X7),MIN(V25,V26)-1,2),"") -> 0.4090292 | Z7: -0.0073243821 | AA7: 0.0068135932 | AB7: =IF(AA7>0,Z7/AA7,"") -> -1.0749662 | AC7: =IF(AA7>0,TDIST(ABS(AB7),MIN(Z25,Z26)-1,2),"") -> 0.29741082 | AD7: -0.010185176 | AE7: 0.0231322 | AF7: =IF(AE7>0,AD7/AE7,"") -> -0.44030295 | AG7: =IF(AE7>0,TDIST(ABS(AF7),MIN(AD25,AD26)-1,2),"") -> 0.6652649 | AH7: -0.0095790278 | AI7: 0.025572242 | AJ7: =IF(AI7>0,AH7/AI7,"") -> -0.37458693 | AK7: =IF(AI7>0,TDIST(ABS(AJ7),MIN(AH25,AH26)-1,2),"") -> 0.71259941 | AL7: -0.041327157 | AM7: 0.032405644 | AN7: =IF(AM7>0,AL7/AM7,"") -> -1.2753074 | AO7: =IF(AM7>0,TDIST(ABS(AN7),MIN(AL25,AL26)-1,2),"") -> 0.21935369 | AP7: -0.0025013779 | AQ7: 0.00082527635 | AR7: =IF(AQ7>0,AP7/AQ7,"") -> -3.0309579 | AS7: =IF(AQ7>0,TDIST(ABS(AR7),MIN(AP25,AP26)-1,2),"") -> 0.0075398149 | AT7: -0.0023657137 | AU7: 0.00074707581 | AV7: =IF(AU7>0,AT7/AU7,"") -> -3.1666314 | AW7: =IF(AU7>0,TDIST(ABS(AV7),MIN(AT25,AT26)-1,2),"") -> 0.0056379202 | AX7: -0.00017538705 | AY7: 0.0025796852 | AZ7: =IF(AY7>0,AX7/AY7,"") -> -0.067987773 | BA7: =IF(AY7>0,TDIST(ABS(AZ7),MIN(AX25,AX26)-1,2),"") -> 0.94658863 | BB7: 0.00010435217 | BC7: 0.0021625572 | BD7: =IF(BC7>0,BB7/BC7,"") -> 0.048254062 | BE7: =IF(BC7>0,TDIST(ABS(BD7),MIN(BB25,BB26)-1,2),"") -> 0.96207614 | BF7: -0.00074591604 | BG7: 0.0020142373 | BH7: =IF(BG7>0,BF7/BG7,"") -> -0.37032183 | BI7: =IF(BG7>0,TDIST(ABS(BH7),MIN(BF25,BF26)-1,2),"") -> 0.71571629
A8: Equity Allocation (%) | B8: 0.024057887 | C8: 0.11481724 | D8: =IF(C8>0,B8/C8,"") -> 0.20953202 | E8: =IF(C8>0,TDIST(ABS(D8),MIN(B25,B26)-1,2),"") -> 0.83652338 | F8: 0.050760969 | G8: 0.11682861 | H8: =IF(G8>0,F8/G8,"") -> 0.43449091 | I8: =IF(G8>0,TDIST(ABS(H8),MIN(F25,F26)-1,2),"") -> 0.66939673 | J8: -0.6053699 | K8: 0.38003783 | L8: =IF(K8>0,J8/K8,"") -> -1.5929201 | M8: =IF(K8>0,TDIST(ABS(L8),MIN(J25,J26)-1,2),"") -> 0.12960027 | N8: -1.64426 | O8: 0.41757374 | P8: =IF(O8>0,N8/O8,"") -> -3.9376518 | Q8: =IF(O8>0,TDIST(ABS(P8),MIN(N25,N26)-1,2),"") -> 0.0010613786 | R8: -2.006329 | S8: 0.47520254 | T8: =IF(S8>0,R8/S8,"") -> -4.2220502 | U8: =IF(S8>0,TDIST(ABS(T8),MIN(R25,R26)-1,2),"") -> 0.00057367199 | V8: -0.34422667 | W8: 0.23286046 | X8: =IF(W8>0,V8/W8,"") -> -1.478253 | Y8: =IF(W8>0,TDIST(ABS(X8),MIN(V25,V26)-1,2),"") -> 0.15762905 | Z8: -0.19844776 | AA8: 0.24790103 | AB8: =IF(AA8>0,Z8/AA8,"") -> -0.80051204 | AC8: =IF(AA8>0,TDIST(ABS(AB8),MIN(Z25,Z26)-1,2),"") -> 0.43445952 | AD8: -0.56026321 | AE8: 0.51272173 | AF8: =IF(AE8>0,AD8/AE8,"") -> -1.0927237 | AG8: =IF(AE8>0,TDIST(ABS(AF8),MIN(AD25,AD26)-1,2),"") -> 0.28975885 | AH8: -0.88739317 | AI8: 0.45123772 | AJ8: =IF(AI8>0,AH8/AI8,"") -> -1.9665758 | AK8: =IF(AI8>0,TDIST(ABS(AJ8),MIN(AH25,AH26)-1,2),"") -> 0.065776389 | AL8: -1.1109946 | AM8: 0.61678162 | AN8: =IF(AM8>0,AL8/AM8,"") -> -1.801277 | AO8: =IF(AM8>0,TDIST(ABS(AN8),MIN(AL25,AL26)-1,2),"") -> 0.089423481 | AP8: -0.089602013 | AQ8: 0.068683987 | AR8: =IF(AQ8>0,AP8/AQ8,"") -> -1.3045546 | AS8: =IF(AQ8>0,TDIST(ABS(AR8),MIN(AP25,AP26)-1,2),"") -> 0.20943012 | AT8: -0.042370849 | AU8: 0.060119241 | AV8: =IF(AU8>0,AT8/AU8,"") -> -0.70478018 | AW8: =IF(AU8>0,TDIST(ABS(AV8),MIN(AT25,AT26)-1,2),"") -> 0.49049095 | AX8: -0.057553575 | AY8: 0.028378306 | AZ8: =IF(AY8>0,AX8/AY8,"") -> -2.0280836 | BA8: =IF(AY8>0,TDIST(ABS(AZ8),MIN(AX25,AX26)-1,2),"") -> 0.058520253 | BB8: -0.057628564 | BC8: 0.047007652 | BD8: =IF(BC8>0,BB8/BC8,"") -> -1.2259401 | BE8: =IF(BC8>0,TDIST(ABS(BD8),MIN(BB25,BB26)-1,2),"") -> 0.23693331 | BF8: 0.011448796 | BG8: 0.066914173 | BH8: =IF(BG8>0,BF8/BG8,"") -> 0.17109673 | BI8: =IF(BG8>0,TDIST(ABS(BH8),MIN(BF25,BF26)-1,2),"") -> 0.86616769
A9: Fixed Income Allocation (%) | B9: -0.0063776662 | C9: 0.11970909 | D9: =IF(C9>0,B9/C9,"") -> -0.053276372 | E9: =IF(C9>0,TDIST(ABS(D9),MIN(B25,B26)-1,2),"") -> 0.95813277 | F9: 0.0074681629 | G9: 0.10953802 | H9: =IF(G9>0,F9/G9,"") -> 0.068178731 | I9: =IF(G9>0,TDIST(ABS(H9),MIN(F25,F26)-1,2),"") -> 0.94643885 | J9: -0.63998702 | K9: 0.37588572 | L9: =IF(K9>0,J9/K9,"") -> -1.7026106 | M9: =IF(K9>0,TDIST(ABS(L9),MIN(J25,J26)-1,2),"") -> 0.1068536 | N9: -1.7093296 | O9: 0.43431214 | P9: =IF(O9>0,N9/O9,"") -> -3.9357169 | Q9: =IF(O9>0,TDIST(ABS(P9),MIN(N25,N26)-1,2),"") -> 0.0010658416 | R9: -2.0904668 | S9: 0.48293275 | T9: =IF(S9>0,R9/S9,"") -> -4.3286914 | U9: =IF(S9>0,TDIST(ABS(T9),MIN(R25,R26)-1,2),"") -> 0.00045594359 | V9: -0.32468944 | W9: 0.22343432 | X9: =IF(W9>0,V9/W9,"") -> -1.4531762 | Y9: =IF(W9>0,TDIST(ABS(X9),MIN(V25,V26)-1,2),"") -> 0.1643853 | Z9: -0.18313464 | AA9: 0.21907758 | AB9: =IF(AA9>0,Z9/AA9,"") -> -0.83593515 | AC9: =IF(AA9>0,TDIST(ABS(AB9),MIN(Z25,Z26)-1,2),"") -> 0.4147869 | AD9: -0.5097532 | AE9: 0.48146439 | AF9: =IF(AE9>0,AD9/AE9,"") -> -1.0587558 | AG9: =IF(AE9>0,TDIST(ABS(AF9),MIN(AD25,AD26)-1,2),"") -> 0.30452371 | AH9: -0.85624636 | AI9: 0.43471437 | AJ9: =IF(AI9>0,AH9/AI9,"") -> -1.9696758 | AK9: =IF(AI9>0,TDIST(ABS(AJ9),MIN(AH25,AH26)-1,2),"") -> 0.065392152 | AL9: -1.0822871 | AM9: 0.61431913 | AN9: =IF(AM9>0,AL9/AM9,"") -> -1.7617668 | AO9: =IF(AM9>0,TDIST(ABS(AN9),MIN(AL25,AL26)-1,2),"") -> 0.096080309 | AP9: -0.098404891 | AQ9: 0.069467028 | AR9: =IF(AQ9>0,AP9/AQ9,"") -> -1.4165698 | AS9: =IF(AQ9>0,TDIST(ABS(AR9),MIN(AP25,AP26)-1,2),"") -> 0.17467279 | AT9: -0.051822532 | AU9: 0.059872923 | AV9: =IF(AU9>0,AT9/AU9,"") -> -0.86554205 | AW9: =IF(AU9>0,TDIST(ABS(AV9),MIN(AT25,AT26)-1,2),"") -> 0.39879186 | AX9: -0.064948705 | AY9: 0.028961247 | AZ9: =IF(AY9>0,AX9/AY9,"") -> -2.2426074 | BA9: =IF(AY9>0,TDIST(ABS(AZ9),MIN(AX25,AX26)-1,2),"") -> 0.038543371 | BB9: -0.066743652 | BC9: 0.048907828 | BD9: =IF(BC9>0,BB9/BC9,"") -> -1.3646824 | BE9: =IF(BC9>0,TDIST(ABS(BD9),MIN(BB25,BB26)-1,2),"") -> 0.19014522 | BF9: 0.0049632832 | BG9: 0.069948214 | BH9: =IF(BG9>0,BF9/BG9,"") -> 0.07095654 | BI9: =IF(BG9>0,TDIST(ABS(BH9),MIN(BF25,BF26)-1,2),"") -> 0.94426041
A10: Real Estate Allocation (%) | B10: 0.074458087 | C10: 0.13243874 | D10: =IF(C10>0,B10/C10,"") -> 0.56220774 | E10: =IF(C10>0,TDIST(ABS(D10),MIN(B25,B26)-1,2),"") -> 0.58131259 | F10: 0.099553941 | G10: 0.11151514 | H10: =IF(G10>0,F10/G10,"") -> 0.89273923 | I10: =IF(G10>0,TDIST(ABS(H10),MIN(F25,F26)-1,2),"") -> 0.38446017 | J10: -0.65956018 | K10: 0.3972446 | L10: =IF(K10>0,J10/K10,"") -> -1.6603377 | M10: =IF(K10>0,TDIST(ABS(L10),MIN(J25,J26)-1,2),"") -> 0.11517758 | N10: -2.0066963 | O10: 0.62563935 | P10: =IF(O10>0,N10/O10,"") -> -3.207433 | Q10: =IF(O10>0,TDIST(ABS(P10),MIN(N25,N26)-1,2),"") -> 0.0051642872 | R10: -2.5389319 | S10: 0.66582649 | T10: =IF(S10>0,R10/S10,"") -> -3.8132034 | U10: =IF(S10>0,TDIST(ABS(T10),MIN(R25,R26)-1,2),"") -> 0.0013904149 | V10: -0.333819 | W10: 0.23796131 | X10: =IF(W10>0,V10/W10,"") -> -1.4028289 | Y10: =IF(W10>0,TDIST(ABS(X10),MIN(V25,V26)-1,2),"") -> 0.17866723 | Z10: -0.17462103 | AA10: 0.23246477 | AB10: =IF(AA10>0,Z10/AA10,"") -> -0.75117204 | AC10: =IF(AA10>0,TDIST(ABS(AB10),MIN(Z25,Z26)-1,2),"") -> 0.46282169 | AD10: -0.47056271 | AE10: 0.46711876 | AF10: =IF(AE10>0,AD10/AE10,"") -> -1.0073728 | AG10: =IF(AE10>0,TDIST(ABS(AF10),MIN(AD25,AD26)-1,2),"") -> 0.32787996 | AH10: -1.0174584 | AI10: 0.4981298 | AJ10: =IF(AI10>0,AH10/AI10,"") -> -2.0425567 | AK10: =IF(AI10>0,TDIST(ABS(AJ10),MIN(AH25,AH26)-1,2),"") -> 0.056921587 | AL10: -1.3517034 | AM10: 0.71560198 | AN10: =IF(AM10>0,AL10/AM10,"") -> -1.888904 | AO10: =IF(AM10>0,TDIST(ABS(AN10),MIN(AL25,AL26)-1,2),"") -> 0.076087814 | AP10: -0.084690174 | AQ10: 0.071848693 | AR10: =IF(AQ10>0,AP10/AQ10,"") -> -1.1787295 | AS10: =IF(AQ10>0,TDIST(ABS(AR10),MIN(AP25,AP26)-1,2),"") -> 0.25474159 | AT10: -0.036364555 | AU10: 0.062348889 | AV10: =IF(AU10>0,AT10/AU10,"") -> -0.58324303 | AW10: =IF(AU10>0,TDIST(ABS(AV10),MIN(AT25,AT26)-1,2),"") -> 0.5673874 | AX10: -0.077139066 | AY10: 0.038927036 | AZ10: =IF(AY10>0,AX10/AY10,"") -> -1.9816322 | BA10: =IF(AY10>0,TDIST(ABS(AZ10),MIN(AX25,AX26)-1,2),"") -> 0.063929011 | BB10: -0.08044283 | BC10: 0.065319188 | BD10: =IF(BC10>0,BB10/BC10,"") -> -1.2315345 | BE10: =IF(BC10>0,TDIST(ABS(BD10),MIN(BB25,BB26)-1,2),"") -> 0.23488811 | BF10: -0.0065707827 | BG10: 0.088212669 | BH10: =IF(BG10>0,BF10/BG10,"") -> -0.074487971 | BI10: =IF(BG10>0,TDIST(ABS(BH10),MIN(BF25,BF26)-1,2),"") -> 0.94149161
A11: Private Equity Allocation (%) | B11: 0.018535699 | C11: 0.13262877 | D11: =IF(C11>0,B11/C11,"") -> 0.13975625 | E11: =IF(C11>0,TDIST(ABS(D11),MIN(B25,B26)-1,2),"") -> 0.89049501 | F11: 0.043085994 | G11: 0.11824223 | H11: =IF(G11>0,F11/G11,"") -> 0.36438752 | I11: =IF(G11>0,TDIST(ABS(H11),MIN(F25,F26)-1,2),"") -> 0.72006161 | J11: -0.54543591 | K11: 0.41126488 | L11: =IF(K11>0,J11/K11,"") -> -1.3262399 | M11: =IF(K11>0,TDIST(ABS(L11),MIN(J25,J26)-1,2),"") -> 0.20230366 | N11: -1.5041458 | O11: 0.39561147 | P11: =IF(O11>0,N11/O11,"") -> -3.8020784 | Q11: =IF(O11>0,TDIST(ABS(P11),MIN(N25,N26)-1,2),"") -> 0.0014244044 | R11: -1.7389897 | S11: 0.45351854 | T11: =IF(S11>0,R11/S11,"") -> -3.8344402 | U11: =IF(S11>0,TDIST(ABS(T11),MIN(R25,R26)-1,2),"") -> 0.0013277724 | V11: -0.34281302 | W11: 0.23766961 | X11: =IF(W11>0,V11/W11,"") -> -1.4423932 | Y11: =IF(W11>0,TDIST(ABS(X11),MIN(V25,V26)-1,2),"") -> 0.16736275 | Z11: -0.19128723 | AA11: 0.23766304 | AB11: =IF(AA11>0,Z11/AA11,"") -> -0.80486739 | AC11: =IF(AA11>0,TDIST(ABS(AB11),MIN(Z25,Z26)-1,2),"") -> 0.43200946 | AD11: -0.48514261 | AE11: 0.47289747 | AF11: =IF(AE11>0,AD11/AE11,"") -> -1.0258939 | AG11: =IF(AE11>0,TDIST(ABS(AF11),MIN(AD25,AD26)-1,2),"") -> 0.31931875 | AH11: -0.85209833 | AI11: 0.39646547 | AJ11: =IF(AI11>0,AH11/AI11,"") -> -2.1492372 | AK11: =IF(AI11>0,TDIST(ABS(AJ11),MIN(AH25,AH26)-1,2),"") -> 0.046309166 | AL11: -0.93066638 | AM11: 0.52868125 | AN11: =IF(AM11>0,AL11/AM11,"") -> -1.7603544 | AO11: =IF(AM11>0,TDIST(ABS(AN11),MIN(AL25,AL26)-1,2),"") -> 0.096326082 | AP11: -0.089946541 | AQ11: 0.069156836 | AR11: =IF(AQ11>0,AP11/AQ11,"") -> -1.3006168 | AS11: =IF(AQ11>0,TDIST(ABS(AR11),MIN(AP25,AP26)-1,2),"") -> 0.21074524 | AT11: -0.043820438 | AU11: 0.059634663 | AV11: =IF(AU11>0,AT11/AU11,"") -> -0.73481488 | AW11: =IF(AU11>0,TDIST(ABS(AV11),MIN(AT25,AT26)-1,2),"") -> 0.47246787 | AX11: -0.030987038 | AY11: 0.028336441 | AZ11: =IF(AY11>0,AX11/AY11,"") -> -1.0935402 | BA11: =IF(AY11>0,TDIST(ABS(AZ11),MIN(AX25,AX26)-1,2),"") -> 0.28941054 | BB11: -0.038892184 | BC11: 0.04416576 | BD11: =IF(BC11>0,BB11/BC11,"") -> -0.88059582 | BE11: =IF(BC11>0,TDIST(ABS(BD11),MIN(BB25,BB26)-1,2),"") -> 0.39081631 | BF11: 0.025229943 | BG11: 0.064433958 | BH11: =IF(BG11>0,BF11/BG11,"") -> 0.39156282 | BI11: =IF(BG11>0,TDIST(ABS(BH11),MIN(BF25,BF26)-1,2),"") -> 0.70024591
A12: Hedge Fund Allocation (%) | B12: -0.0098043776 | C12: 0.10866173 | D12: =IF(C12>0,B12/C12,"") -> -0.090228433 | E12: =IF(C12>0,TDIST(ABS(D12),MIN(B25,B26)-1,2),"") -> 0.92916026 | F12: 0.0026595816 | G12: 0.096157503 | H12: =IF(G12>0,F12/G12,"") -> 0.027658597 | I12: =IF(G12>0,TDIST(ABS(H12),MIN(F25,F26)-1,2),"") -> 0.97825654 | J12: -0.64747997 | K12: 0.31990989 | L12: =IF(K12>0,J12/K12,"") -> -2.0239448 | M12: =IF(K12>0,TDIST(ABS(L12),MIN(J25,J26)-1,2),"") -> 0.058984817 | N12: -1.6988013 | O12: 0.45471742 | P12: =IF(O12>0,N12/O12,"") -> -3.7359495 | Q12: =IF(O12>0,TDIST(ABS(P12),MIN(N25,N26)-1,2),"") -> 0.0016443335 | R12: -2.0554127 | S12: 0.50937161 | T12: =IF(S12>0,R12/S12,"") -> -4.0351929 | U12: =IF(S12>0,TDIST(ABS(T12),MIN(R25,R26)-1,2),"") -> 0.00085915112 | V12: -0.3088314 | W12: 0.23332775 | X12: =IF(W12>0,V12/W12,"") -> -1.3235948 | Y12: =IF(W12>0,TDIST(ABS(X12),MIN(V25,V26)-1,2),"") -> 0.2031625 | Z12: -0.17125809 | AA12: 0.2318897 | AB12: =IF(AA12>0,Z12/AA12,"") -> -0.73853253 | AC12: =IF(AA12>0,TDIST(ABS(AB12),MIN(Z25,Z26)-1,2),"") -> 0.47026494 | AD12: -0.55987261 | AE12: 0.4883007 | AF12: =IF(AE12>0,AD12/AE12,"") -> -1.1465734 | AG12: =IF(AE12>0,TDIST(ABS(AF12),MIN(AD25,AD26)-1,2),"") -> 0.2674406 | AH12: -0.85245305 | AI12: 0.44774407 | AJ12: =IF(AI12>0,AH12/AI12,"") -> -1.9038846 | AK12: =IF(AI12>0,TDIST(ABS(AJ12),MIN(AH25,AH26)-1,2),"") -> 0.073993555 | AL12: -1.1978354 | AM12: 0.61900003 | AN12: =IF(AM12>0,AL12/AM12,"") -> -1.9351137 | AO12: =IF(AM12>0,TDIST(ABS(AN12),MIN(AL25,AL26)-1,2),"") -> 0.069792142 | AP12: -0.092521068 | AQ12: 0.064935551 | AR12: =IF(AQ12>0,AP12/AQ12,"") -> -1.4248138 | AS12: =IF(AQ12>0,TDIST(ABS(AR12),MIN(AP25,AP26)-1,2),"") -> 0.17231134 | AT12: -0.050764984 | AU12: 0.056788339 | AV12: =IF(AU12>0,AT12/AU12,"") -> -0.89393326 | AW12: =IF(AU12>0,TDIST(ABS(AV12),MIN(AT25,AT26)-1,2),"") -> 0.38383893 | AX12: -0.054669498 | AY12: 0.02756944 | AZ12: =IF(AY12>0,AX12/AY12,"") -> -1.9829746 | BA12: =IF(AY12>0,TDIST(ABS(AZ12),MIN(AX25,AX26)-1,2),"") -> 0.063766586 | BB12: -0.059175656 | BC12: 0.04566258 | BD12: =IF(BC12>0,BB12/BC12,"") -> -1.2959332 | BE12: =IF(BC12>0,TDIST(ABS(BD12),MIN(BB25,BB26)-1,2),"") -> 0.21231786 | BF12: -0.0017380119 | BG12: 0.06653406 | BH12: =IF(BG12>0,BF12/BG12,"") -> -0.026122138 | BI12: =IF(BG12>0,TDIST(ABS(BH12),MIN(BF25,BF26)-1,2),"") -> 0.97946411
A13: Misc. Alternatives Allocation (%) | B13: 0.077324917 | C13: 0.13213524 | D13: =IF(C13>0,B13/C13,"") -> 0.58519528 | E13: =IF(C13>0,TDIST(ABS(D13),MIN(B25,B26)-1,2),"") -> 0.56610389 | F13: 0.10539417 | G13: 0.092554421 | H13: =IF(G13>0,F13/G13,"") -> 1.1387265 | I13: =IF(G13>0,TDIST(ABS(H13),MIN(F25,F26)-1,2),"") -> 0.27061039 | J13: -0.25349396 | K13: 1.1378156 | L13: =IF(K13>0,J13/K13,"") -> -0.22279002 | M13: =IF(K13>0,TDIST(ABS(L13),MIN(J25,J26)-1,2),"") -> 0.82635379 | N13: -1.5267025 | O13: 1.1011927 | P13: =IF(O13>0,N13/O13,"") -> -1.3864082 | Q13: =IF(O13>0,TDIST(ABS(P13),MIN(N25,N26)-1,2),"") -> 0.18353747 | R13: -2.0165834 | S13: 1.0867634 | T13: =IF(S13>0,R13/S13,"") -> -1.8555865 | U13: =IF(S13>0,TDIST(ABS(T13),MIN(R25,R26)-1,2),"") -> 0.080935303 | V13: -0.31200415 | W13: 0.23550456 | X13: =IF(W13>0,V13/W13,"") -> -1.3248327 | Y13: =IF(W13>0,TDIST(ABS(X13),MIN(V25,V26)-1,2),"") -> 0.2027602 | Z13: -0.1815023 | AA13: 0.26529121 | AB13: =IF(AA13>0,Z13/AA13,"") -> -0.68416248 | AC13: =IF(AA13>0,TDIST(ABS(AB13),MIN(Z25,Z26)-1,2),"") -> 0.50309322 | AD13: -0.010943391 | AE13: 0.88519876 | AF13: =IF(AE13>0,AD13/AE13,"") -> -0.012362637 | AG13: =IF(AE13>0,TDIST(ABS(AF13),MIN(AD25,AD26)-1,2),"") -> 0.99028022 | AH13: -0.29326092 | AI13: 0.65045144 | AJ13: =IF(AI13>0,AH13/AI13,"") -> -0.45085752 | AK13: =IF(AI13>0,TDIST(ABS(AJ13),MIN(AH25,AH26)-1,2),"") -> 0.65778989 | AL13: -0.38772291 | AM13: 1.0584835 | AN13: =IF(AM13>0,AL13/AM13,"") -> -0.36630038 | AO13: =IF(AM13>0,TDIST(ABS(AN13),MIN(AL25,AL26)-1,2),"") -> 0.71865985 | AP13: -0.097377745 | AQ13: 0.067878451 | AR13: =IF(AQ13>0,AP13/AQ13,"") -> -1.43459 | AS13: =IF(AQ13>0,TDIST(ABS(AR13),MIN(AP25,AP26)-1,2),"") -> 0.1695448 | AT13: -0.065938282 | AU13: 0.061583616 | AV13: =IF(AU13>0,AT13/AU13,"") -> -1.0707114 | AW13: =IF(AU13>0,TDIST(ABS(AV13),MIN(AT25,AT26)-1,2),"") -> 0.29926592 | AX13: -0.092256371 | AY13: 0.050807185 | AZ13: =IF(AY13>0,AX13/AY13,"") -> -1.8158135 | BA13: =IF(AY13>0,TDIST(ABS(AZ13),MIN(AX25,AX26)-1,2),"") -> 0.087078078 | BB13: -0.10915639 | BC13: 0.070223686 | BD13: =IF(BC13>0,BB13/BC13,"") -> -1.5544098 | BE13: =IF(BC13>0,TDIST(ABS(BD13),MIN(BB25,BB26)-1,2),"") -> 0.13850519 | BF13: 0.023158259 | BG13: 0.099025987 | BH13: =IF(BG13>0,BF13/BG13,"") -> 0.23386043 | BI13: =IF(BG13>0,TDIST(ABS(BH13),MIN(BF25,BF26)-1,2),"") -> 0.81788638
A14: Commodities Allocation (%) | B14: -0.027150843 | C14: 0.10498866 | D14: =IF(C14>0,B14/C14,"") -> -0.25860738 | E14: =IF(C14>0,TDIST(ABS(D14),MIN(B25,B26)-1,2),"") -> 0.79904328 | F14: -0.01461712 | G14: 0.10723678 | H14: =IF(G14>0,F14/G14,"") -> -0.13630697 | I14: =IF(G14>0,TDIST(ABS(H14),MIN(F25,F26)-1,2),"") -> 0.89317978 | J14: -0.70213898 | K14: 0.38832341 | L14: =IF(K14>0,J14/K14,"") -> -1.8081294 | M14: =IF(K14>0,TDIST(ABS(L14),MIN(J25,J26)-1,2),"") -> 0.088311051 | N14: -1.5345633 | O14: 0.39514661 | P14: =IF(O14>0,N14/O14,"") -> -3.883529 | Q14: =IF(O14>0,TDIST(ABS(P14),MIN(N25,N26)-1,2),"") -> 0.0011935954 | R14: -1.6702744 | S14: 0.36214459 | T14: =IF(S14>0,R14/S14,"") -> -4.6121755 | U14: =IF(S14>0,TDIST(ABS(T14),MIN(R25,R26)-1,2),"") -> 0.00024852969 | V14: -0.30602066 | W14: 0.22402871 | X14: =IF(W14>0,V14/W14,"") -> -1.3659886 | Y14: =IF(W14>0,TDIST(ABS(X14),MIN(V25,V26)-1,2),"") -> 0.18974262 | Z14: -0.18640309 | AA14: 0.26525258 | AB14: =IF(AA14>0,Z14/AA14,"") -> -0.70273808 | AC14: =IF(AA14>0,TDIST(ABS(AB14),MIN(Z25,Z26)-1,2),"") -> 0.49173084 | AD14: -0.44000349 | AE14: 0.52620132 | AF14: =IF(AE14>0,AD14/AE14,"") -> -0.8361885 | AG14: =IF(AE14>0,TDIST(ABS(AF14),MIN(AD25,AD26)-1,2),"") -> 0.4146483 | AH14: -0.64881699 | AI14: 0.47226439 | AJ14: =IF(AI14>0,AH14/AI14,"") -> -1.3738427 | AK14: =IF(AI14>0,TDIST(ABS(AJ14),MIN(AH25,AH26)-1,2),"") -> 0.18733622 | AL14: -0.85397317 | AM14: 0.60580501 | AN14: =IF(AM14>0,AL14/AM14,"") -> -1.4096502 | AO14: =IF(AM14>0,TDIST(ABS(AN14),MIN(AL25,AL26)-1,2),"") -> 0.17667511 | AP14: -0.10387464 | AQ14: 0.069316332 | AR14: =IF(AQ14>0,AP14/AQ14,"") -> -1.4985594 | AS14: =IF(AQ14>0,TDIST(ABS(AR14),MIN(AP25,AP26)-1,2),"") -> 0.15232747 | AT14: -0.048467765 | AU14: 0.063228463 | AV14: =IF(AU14>0,AT14/AU14,"") -> -0.7665498 | AW14: =IF(AU14>0,TDIST(ABS(AV14),MIN(AT25,AT26)-1,2),"") -> 0.45386315 | AX14: -0.10108497 | AY14: 0.033123539 | AZ14: =IF(AY14>0,AX14/AY14,"") -> -3.0517564 | BA14: =IF(AY14>0,TDIST(ABS(AZ14),MIN(AX25,AX26)-1,2),"") -> 0.0072120821 | BB14: -0.11001264 | BC14: 0.068470844 | BD14: =IF(BC14>0,BB14/BC14,"") -> -1.6067078 | BE14: =IF(BC14>0,TDIST(ABS(BD14),MIN(BB25,BB26)-1,2),"") -> 0.12653201 | BF14: -0.054265746 | BG14: 0.076417927 | BH14: =IF(BG14>0,BF14/BG14,"") -> -0.710118 | BI14: =IF(BG14>0,TDIST(ABS(BH14),MIN(BF25,BF26)-1,2),"") -> 0.48725865
A15: Cash Allocation (%) | B15: 0.033264163 | C15: 0.12032232 | D15: =IF(C15>0,B15/C15,"") -> 0.27645878 | E15: =IF(C15>0,TDIST(ABS(D15),MIN(B25,B26)-1,2),"") -> 0.78552872 | F15: 0.075945722 | G15: 0.1471406 | H15: =IF(G15>0,F15/G15,"") -> 0.51614391 | I15: =IF(G15>0,TDIST(ABS(H15),MIN(F25,F26)-1,2),"") -> 0.61240221 | J15: -0.49925755 | K15: 0.40081685 | L15: =IF(K15>0,J15/K15,"") -> -1.2456002 | M15: =IF(K15>0,TDIST(ABS(L15),MIN(J25,J26)-1,2),"") -> 0.22980617 | N15: -1.5144201 | O15: 0.43751033 | P15: =IF(O15>0,N15/O15,"") -> -3.46145 | Q15: =IF(O15>0,TDIST(ABS(P15),MIN(N25,N26)-1,2),"") -> 0.0029831742 | R15: -2.0311476 | S15: 0.52485066 | T15: =IF(S15>0,R15/S15,"") -> -3.8699534 | U15: =IF(S15>0,TDIST(ABS(T15),MIN(R25,R26)-1,2),"") -> 0.0012292789 | V15: -0.33768263 | W15: 0.23059874 | X15: =IF(W15>0,V15/W15,"") -> -1.4643733 | Y15: =IF(W15>0,TDIST(ABS(X15),MIN(V25,V26)-1,2),"") -> 0.1613397 | Z15: -0.19003236 | AA15: 0.24980792 | AB15: =IF(AA15>0,Z15/AA15,"") -> -0.7607139 | AC15: =IF(AA15>0,TDIST(ABS(AB15),MIN(Z25,Z26)-1,2),"") -> 0.45725033 | AD15: -0.44047436 | AE15: 0.5025298 | AF15: =IF(AE15>0,AD15/AE15,"") -> -0.8765139 | AG15: =IF(AE15>0,TDIST(ABS(AF15),MIN(AD25,AD26)-1,2),"") -> 0.39296843 | AH15: -0.74348143 | AI15: 0.43078927 | AJ15: =IF(AI15>0,AH15/AI15,"") -> -1.7258587 | AK15: =IF(AI15>0,TDIST(ABS(AJ15),MIN(AH25,AH26)-1,2),"") -> 0.10250098 | AL15: -0.91285772 | AM15: 0.6007077 | AN15: =IF(AM15>0,AL15/AM15,"") -> -1.5196371 | AO15: =IF(AM15>0,TDIST(ABS(AN15),MIN(AL25,AL26)-1,2),"") -> 0.14698183 | AP15: -0.075897321 | AQ15: 0.067726317 | AR15: =IF(AQ15>0,AP15/AQ15,"") -> -1.1206474 | AS15: =IF(AQ15>0,TDIST(ABS(AR15),MIN(AP25,AP26)-1,2),"") -> 0.27802016 | AT15: -0.033161825 | AU15: 0.061440916 | AV15: =IF(AU15>0,AT15/AU15,"") -> -0.5397352 | AW15: =IF(AU15>0,TDIST(ABS(AV15),MIN(AT25,AT26)-1,2),"") -> 0.59637943 | AX15: -0.068614803 | AY15: 0.030822951 | AZ15: =IF(AY15>0,AX15/AY15,"") -> -2.2260945 | BA15: =IF(AY15>0,TDIST(ABS(AZ15),MIN(AX25,AX26)-1,2),"") -> 0.039822731 | BB15: -0.064903953 | BC15: 0.04771497 | BD15: =IF(BC15>0,BB15/BC15,"") -> -1.360243 | BE15: =IF(BC15>0,TDIST(ABS(BD15),MIN(BB25,BB26)-1,2),"") -> 0.19151868 | BF15: 0.015326265 | BG15: 0.064455567 | BH15: =IF(BG15>0,BF15/BG15,"") -> 0.23778032 | BI15: =IF(BG15>0,TDIST(ABS(BH15),MIN(BF25,BF26)-1,2),"") -> 0.81489367
A16: Financial Center (0/1) | B16: 0.43451252 | C16: 0.40850874 | D16: =IF(C16>0,B16/C16,"") -> 1.0636554 | E16: =IF(C16>0,TDIST(ABS(D16),MIN(B25,B26)-1,2),"") -> 0.30236096 | F16: 0.41197217 | G16: 0.32311119 | H16: =IF(G16>0,F16/G16,"") -> 1.2750167 | I16: =IF(G16>0,TDIST(ABS(H16),MIN(F25,F26)-1,2),"") -> 0.21945412 | N16: 0.55033932 | O16: 66354.729 | P16: =IF(O16>0,N16/O16,"") -> 8.2938975e-06 | Q16: =IF(O16>0,TDIST(ABS(P16),MIN(N25,N26)-1,2),"") -> 0.99999348 | V16: -0.31247394 | W16: 0.36704404 | X16: =IF(W16>0,V16/W16,"") -> -0.85132547 | Y16: =IF(W16>0,TDIST(ABS(X16),MIN(V25,V26)-1,2),"") -> 0.40642126 | Z16: -0.3812141 | AA16: 0.3124785 | AB16: =IF(AA16>0,Z16/AA16,"") -> -1.2199691 | AC16: =IF(AA16>0,TDIST(ABS(AB16),MIN(Z25,Z26)-1,2),"") -> 0.2391313 | AP16: 0.034057625 | AQ16: 0.046567587 | AR16: =IF(AQ16>0,AP16/AQ16,"") -> 0.73135903 | AS16: =IF(AQ16>0,TDIST(ABS(AR16),MIN(AP25,AP26)-1,2),"") -> 0.47452121 | AT16: 0.022308809 | AU16: 0.055625131 | AV16: =IF(AU16>0,AT16/AU16,"") -> 0.40105628 | AW16: =IF(AU16>0,TDIST(ABS(AV16),MIN(AT25,AT26)-1,2),"") -> 0.69337468
A17: Log (CIO Age) (t-1) | F17: -0.12159607 | G17: 1.0399821 | H17: =IF(G17>0,F17/G17,"") -> -0.11692131 | I17: =IF(G17>0,TDIST(ABS(H17),MIN(F25,F26)-1,2),"") -> 0.90829263 | J17: 0.73333663 | K17: 1.8544639 | L17: =IF(K17>0,J17/K17,"") -> 0.395444 | M17: =IF(K17>0,TDIST(ABS(L17),MIN(J25,J26)-1,2),"") -> 0.6974335 | Z17: 0.809457 | AA17: 0.45532925 | AB17: =IF(AA17>0,Z17/AA17,"") -> 1.77774 | AC17: =IF(AA17>0,TDIST(ABS(AB17),MIN(Z25,Z26)-1,2),"") -> 0.093338681 | AD17: 4.1133361 | AE17: 1.2760976 | AF17: =IF(AE17>0,AD17/AE17,"") -> 3.2233711 | AG17: =IF(AE17>0,TDIST(ABS(AF17),MIN(AD25,AD26)-1,2),"") -> 0.0049900908 | AT17: 0.043630698 | AU17: 0.23451115 | AV17: =IF(AU17>0,AT17/AU17,"") -> 0.18604957 | AW17: =IF(AU17>0,TDIST(ABS(AV17),MIN(AT25,AT26)-1,2),"") -> 0.85460786 | AX17: -0.46106788 | AY17: 0.20477276 | AZ17: =IF(AY17>0,AX17/AY17,"") -> -2.2516074 | BA17: =IF(AY17>0,TDIST(ABS(AZ17),MIN(AX25,AX26)-1,2),"") -> 0.037862193
A18: Log (CIO Tenure) (t-1) | F18: 0.031472968 | G18: 0.188476 | H18: =IF(G18>0,F18/G18,"") -> 0.16698661 | I18: =IF(G18>0,TDIST(ABS(H18),MIN(F25,F26)-1,2),"") -> 0.86935077 | J18: 0.024747019 | K18: 0.36037937 | L18: =IF(K18>0,J18/K18,"") -> 0.068669356 | M18: =IF(K18>0,TDIST(ABS(L18),MIN(J25,J26)-1,2),"") -> 0.94605406 | Z18: -0.25543602 | AA18: 0.22672911 | AB18: =IF(AA18>0,Z18/AA18,"") -> -1.1266133 | AC18: =IF(AA18>0,TDIST(ABS(AB18),MIN(Z25,Z26)-1,2),"") -> 0.27555856 | AD18: -0.8182287 | AE18: 0.37152905 | AF18: =IF(AE18>0,AD18/AE18,"") -> -2.2023277 | AG18: =IF(AE18>0,TDIST(ABS(AF18),MIN(AD25,AD26)-1,2),"") -> 0.041733086 | AT18: -0.0035219536 | AU18: 0.034733018 | AV18: =IF(AU18>0,AT18/AU18,"") -> -0.10140074 | AW18: =IF(AU18>0,TDIST(ABS(AV18),MIN(AT25,AT26)-1,2),"") -> 0.92041873 | AX18: 0.056749151 | AY18: 0.032170797 | AZ18: =IF(AY18>0,AX18/AY18,"") -> 1.7639958 | BA18: =IF(AY18>0,TDIST(ABS(AZ18),MIN(AX25,AX26)-1,2),"") -> 0.095693555
A19: CIO Prior Private Experience (0/1) | F19: -0.033908747 | G19: 0.18370637 | H19: =IF(G19>0,F19/G19,"") -> -0.18458123 | I19: =IF(G19>0,TDIST(ABS(H19),MIN(F25,F26)-1,2),"") -> 0.85574155 | J19: -0.13587625 | K19: 0.85692445 | L19: =IF(K19>0,J19/K19,"") -> -0.1585627 | M19: =IF(K19>0,TDIST(ABS(L19),MIN(J25,J26)-1,2),"") -> 0.87588181 | Z19: -0.25701338 | AA19: 0.46310446 | AB19: =IF(AA19>0,Z19/AA19,"") -> -0.55497928 | AC19: =IF(AA19>0,TDIST(ABS(AB19),MIN(Z25,Z26)-1,2),"") -> 0.58613775 | AD19: -1.3834013 | AE19: 0.78233076 | AF19: =IF(AE19>0,AD19/AE19,"") -> -1.7683074 | AG19: =IF(AE19>0,TDIST(ABS(AF19),MIN(AD25,AD26)-1,2),"") -> 0.094949302 | AT19: -0.20139418 | AU19: 0.068951498 | AV19: =IF(AU19>0,AT19/AU19,"") -> -2.9208093 | AW19: =IF(AU19>0,TDIST(ABS(AV19),MIN(AT25,AT26)-1,2),"") -> 0.0095324863 | AX19: -0.028814909 | AY19: 0.082543779 | AZ19: =IF(AY19>0,AX19/AY19,"") -> -0.34908637 | BA19: =IF(AY19>0,TDIST(ABS(AZ19),MIN(AX25,AX26)-1,2),"") -> 0.73131093
A20: CIO Attended Elite College (0/1) | F20: -0.13407989 | G20: 0.18765742 | H20: =IF(G20>0,F20/G20,"") -> -0.71449287 | I20: =IF(G20>0,TDIST(ABS(H20),MIN(F25,F26)-1,2),"") -> 0.48461885 | J20: 0.15802863 | K20: 0.51037959 | L20: =IF(K20>0,J20/K20,"") -> 0.30962961 | M20: =IF(K20>0,TDIST(ABS(L20),MIN(J25,J26)-1,2),"") -> 0.76060575 | Z20: -0.51963401 | AA20: 0.27524203 | AB20: =IF(AA20>0,Z20/AA20,"") -> -1.8879167 | AC20: =IF(AA20>0,TDIST(ABS(AB20),MIN(Z25,Z26)-1,2),"") -> 0.076227675 | AD20: -0.0058914412 | AE20: 0.44263136 | AF20: =IF(AE20>0,AD20/AE20,"") -> -0.01331004 | AG20: =IF(AE20>0,TDIST(ABS(AF20),MIN(AD25,AD26)-1,2),"") -> 0.9895354 | AT20: -0.067735705 | AU20: 0.057130216 | AV20: =IF(AU20>0,AT20/AU20,"") -> -1.1856371 | AW20: =IF(AU20>0,TDIST(ABS(AV20),MIN(AT25,AT26)-1,2),"") -> 0.25207421 | AX20: -0.10768396 | AY20: 0.051457553 | AZ20: =IF(AY20>0,AX20/AY20,"") -> -2.0926755 | BA20: =IF(AY20>0,TDIST(ABS(AZ20),MIN(AX25,AX26)-1,2),"") -> 0.051687017
A21: Separate Investment Board (0/1) | F21: 0.24014798 | G21: 0.31463003 | H21: =IF(G21>0,F21/G21,"") -> 0.763271 | I21: =IF(G21>0,TDIST(ABS(H21),MIN(F25,F26)-1,2),"") -> 0.45576428 | Z21: 0.1764906 | AA21: 0.3952208 | AB21: =IF(AA21>0,Z21/AA21,"") -> 0.44656203 | AC21: =IF(AA21>0,TDIST(ABS(AB21),MIN(Z25,Z26)-1,2),"") -> 0.66082762 | AT21: 0.072501474 | AU21: 0.060450775 | AV21: =IF(AU21>0,AT21/AU21,"") -> 1.1993473 | AW21: =IF(AU21>0,TDIST(ABS(AV21),MIN(AT25,AT26)-1,2),"") -> 0.24684298
A22: % Political Appointees on Board | F22: 0.033809407 | G22: 0.64876733 | H22: =IF(G22>0,F22/G22,"") -> 0.052113301 | I22: =IF(G22>0,TDIST(ABS(H22),MIN(F25,F26)-1,2),"") -> 0.95904589 | J22: 2.560027 | K22: 4.5630723 | L22: =IF(K22>0,J22/K22,"") -> 0.56103143 | M22: =IF(K22>0,TDIST(ABS(L22),MIN(J25,J26)-1,2),"") -> 0.58209643 | Z22: -0.40770913 | AA22: 0.5184302 | AB22: =IF(AA22>0,Z22/AA22,"") -> -0.78643012 | AC22: =IF(AA22>0,TDIST(ABS(AB22),MIN(Z25,Z26)-1,2),"") -> 0.44244089 | AD22: -4.5311296 | AE22: 2.2083186 | AF22: =IF(AE22>0,AD22/AE22,"") -> -2.0518459 | AG22: =IF(AE22>0,TDIST(ABS(AF22),MIN(AD25,AD26)-1,2),"") -> 0.055916484 | AT22: 0.0032091811 | AU22: 0.087718481 | AV22: =IF(AU22>0,AT22/AU22,"") -> 0.036585006 | AW22: =IF(AU22>0,TDIST(ABS(AV22),MIN(AT25,AT26)-1,2),"") -> 0.97124207 | AX22: 1.1973761 | AY22: 0.64872756 | AZ22: =IF(AY22>0,AX22/AY22,"") -> 1.8457303 | BA22: =IF(AY22>0,TDIST(ABS(AZ22),MIN(AX25,AX26)-1,2),"") -> 0.082420776
A24: Observations | B24: 299 | F24: 274 | J24: 273 | N24: 282 | R24: 190 | V24: 275 | Z24: 254 | AD24: 251 | AH24: 259 | AL24: 175 | AP24: 266 | AT24: 251 | AX24: 250 | BB24: 250 | BF24: 162
A25: Plan clusters | B25: 18 | F25: 18 | J25: 18 | N25: 18 | R25: 18 | V25: 18 | Z25: 18 | AD25: 18 | AH25: 18 | AL25: 18 | AP25: 18 | AT25: 18 | AX25: 18 | BB25: 18 | BF25: 18
A26: Year clusters | B26: 18 | F26: 18 | J26: 18 | N26: 18 | R26: 18 | V26: 18 | Z26: 18 | AD26: 18 | AH26: 18 | AL26: 18 | AP26: 18 | AT26: 18 | AX26: 18 | BB26: 18 | BF26: 18
A27: Adjusted R-squared | B27: 0.080956317 | F27: 0.044884219 | J27: -0.0031475011 | N27: 0.04291211 | R27: 0.11508256 | V27: 0.16117624 | Z27: 0.12811226 | AD27: 0.16156138 | AH27: 0.46213337 | AL27: 0.5191564 | AP27: 0.48282686 | AT27: 0.54630344 | AX27: 0.71872605 | BB27: 0.78206403 | BF27: 0.81172229
A28: Number of CIOs | B28: 43 | F28: 41 | J28: 41 | N28: 43 | R28: 24 | V28: 42 | Z28: 40 | AD28: 40 | AH28: 42 | AL28: 23 | AP28: 40 | AT28: 37 | AX28: 37 | BB28: 40 | BF28: 20
