Workbook

Sheet Table III (updated)
A1: Table III: Conflicted CIO and Plan Performance Regressions (updated policy benchmark, file of Oct 16)
A2: This table reports results of tests that regress the returns of public pension plans on an indicator variable, Conflicted CIO, which is equal to 1 for all years prior to the plan's investment officer (CIO) departure for a position in a private asset management firm and 0 otherwise. The performance measure in Panel A is Peer-Adjusted Return, which is the difference of a plan's return and the average pension plan return each year. The performance measure in Panel B is Benchmark-Adjusted Return, which is calculated as the plan's return minus the return of its policy benchmark, when available. Policy benchmark returns are collected from plans' financial reports; where a report does not state the one-year benchmark return, it is inferred from the plan's reported multi-year benchmark returns or from its policy weights and component index returns (estimates graded A or B only). The other independent variables are as defined in Table I. Columns 5 and 6 redefine Conflicted CIO to equal 1 only in the last 5 or 10 years before departure. The standard errors are double clustered by plan and year. Coefficients marked with ***, **, and * are significant at the 1%, 5%, and 10% level, respectively.
A4: Panel A. Peer-Adjusted Returns
B5: (1) | C5: (2) | D5: (3) | E5: (4) | F5: (5) | G5: (6)
B6: Peer-adj. Ret. (t) | C6: Peer-adj. Ret. (t) | D6: Peer-adj. Ret. (t) | E6: Peer-adj. Ret. (t) | F6: Peer-adj. Ret. (t) | G6: Peer-adj. Ret. (t)
A7: Conflicted CIO (0/1) | B7: =IF(Estimates!H4="","n/a",TEXT(Estimates!D4,"0.000")&IF(Estimates!H4<0.01,"***",IF(Estimates!H4<0.05,"**",IF(Estimates!H4<0.1,"*","")))) -> -0.557*** | C7: =IF(Estimates!H5="","n/a",TEXT(Estimates!D5,"0.000")&IF(Estimates!H5<0.01,"***",IF(Estimates!H5<0.05,"**",IF(Estimates!H5<0.1,"*","")))) -> -0.582*** | D7: =IF(Estimates!H6="","n/a",TEXT(Estimates!D6,"0.000")&IF(Estimates!H6<0.01,"***",IF(Estimates!H6<0.05,"**",IF(Estimates!H6<0.1,"*","")))) -> -0.641** | E7: =IF(Estimates!H7="","n/a",TEXT(Estimates!D7,"0.000")&IF(Estimates!H7<0.01,"***",IF(Estimates!H7<0.05,"**",IF(Estimates!H7<0.1,"*","")))) -> -0.698** | F7: =IF(Estimates!H8="","n/a",TEXT(Estimates!D8,"0.000")&IF(Estimates!H8<0.01,"***",IF(Estimates!H8<0.05,"**",IF(Estimates!H8<0.1,"*","")))) -> -0.475* | G7: =IF(Estimates!H9="","n/a",TEXT(Estimates!D9,"0.000")&IF(Estimates!H9<0.01,"***",IF(Estimates!H9<0.05,"**",IF(Estimates!H9<0.1,"*","")))) -> -0.508**
B8: =IF(Estimates!G4="","","("&TEXT(Estimates!G4,"0.00")&")") -> (-3.68) | C8: =IF(Estimates!G5="","","("&TEXT(Estimates!G5,"0.00")&")") -> (-3.13) | D8: =IF(Estimates!G6="","","("&TEXT(Estimates!G6,"0.00")&")") -> (-2.21) | E8: =IF(Estimates!G7="","","("&TEXT(Estimates!G7,"0.00")&")") -> (-2.38) | F8: =IF(Estimates!G8="","","("&TEXT(Estimates!G8,"0.00")&")") -> (-2.10) | G8: =IF(Estimates!G9="","","("&TEXT(Estimates!G9,"0.00")&")") -> (-2.78)
A9: Investment Return (t - 1) | B9: =IF(Estimates!H10="","n/a",TEXT(Estimates!D10,"0.000")&IF(Estimates!H10<0.01,"***",IF(Estimates!H10<0.05,"**",IF(Estimates!H10<0.1,"*","")))) -> 0.014 | C9: =IF(Estimates!H11="","n/a",TEXT(Estimates!D11,"0.000")&IF(Estimates!H11<0.01,"***",IF(Estimates!H11<0.05,"**",IF(Estimates!H11<0.1,"*","")))) -> 0.004 | D9: =IF(Estimates!H12="","n/a",TEXT(Estimates!D12,"0.000")&IF(Estimates!H12<0.01,"***",IF(Estimates!H12<0.05,"**",IF(Estimates!H12<0.1,"*","")))) -> 0.011 | E9: =IF(Estimates!H13="","n/a",TEXT(Estimates!D13,"0.000")&IF(Estimates!H13<0.01,"***",IF(Estimates!H13<0.05,"**",IF(Estimates!H13<0.1,"*","")))) -> 0.000 | F9: =IF(Estimates!H14="","n/a",TEXT(Estimates!D14,"0.000")&IF(Estimates!H14<0.01,"***",IF(Estimates!H14<0.05,"**",IF(Estimates!H14<0.1,"*","")))) -> 0.004 | G9: =IF(Estimates!H15="","n/a",TEXT(Estimates!D15,"0.000")&IF(Estimates!H15<0.01,"***",IF(Estimates!H15<0.05,"**",IF(Estimates!H15<0.1,"*","")))) -> 0.004
B10: =IF(Estimates!G10="","","("&TEXT(Estimates!G10,"0.00")&")") -> (0.71) | C10: =IF(Estimates!G11="","","("&TEXT(Estimates!G11,"0.00")&")") -> (0.20) | D10: =IF(Estimates!G12="","","("&TEXT(Estimates!G12,"0.00")&")") -> (1.19) | E10: =IF(Estimates!G13="","","("&TEXT(Estimates!G13,"0.00")&")") -> (0.03) | F10: =IF(Estimates!G14="","","("&TEXT(Estimates!G14,"0.00")&")") -> (0.21) | G10: =IF(Estimates!G15="","","("&TEXT(Estimates!G15,"0.00")&")") -> (0.20)
A11: Log (Plan Size) (t-1) | B11: =IF(Estimates!H16="","n/a",TEXT(Estimates!D16,"0.000")&IF(Estimates!H16<0.01,"***",IF(Estimates!H16<0.05,"**",IF(Estimates!H16<0.1,"*","")))) -> 0.008 | C11: =IF(Estimates!H17="","n/a",TEXT(Estimates!D17,"0.000")&IF(Estimates!H17<0.01,"***",IF(Estimates!H17<0.05,"**",IF(Estimates!H17<0.1,"*","")))) -> 0.070 | D11: =IF(Estimates!H18="","n/a",TEXT(Estimates!D18,"0.000")&IF(Estimates!H18<0.01,"***",IF(Estimates!H18<0.05,"**",IF(Estimates!H18<0.1,"*","")))) -> -0.943** | E11: =IF(Estimates!H19="","n/a",TEXT(Estimates!D19,"0.000")&IF(Estimates!H19<0.01,"***",IF(Estimates!H19<0.05,"**",IF(Estimates!H19<0.1,"*","")))) -> -1.430* | F11: =IF(Estimates!H20="","n/a",TEXT(Estimates!D20,"0.000")&IF(Estimates!H20<0.01,"***",IF(Estimates!H20<0.05,"**",IF(Estimates!H20<0.1,"*","")))) -> 0.079 | G11: =IF(Estimates!H21="","n/a",TEXT(Estimates!D21,"0.000")&IF(Estimates!H21<0.01,"***",IF(Estimates!H21<0.05,"**",IF(Estimates!H21<0.1,"*","")))) -> 0.075
B12: =IF(Estimates!G16="","","("&TEXT(Estimates!G16,"0.00")&")") -> (0.15) | C12: =IF(Estimates!G17="","","("&TEXT(Estimates!G17,"0.00")&")") -> (1.14) | D12: =IF(Estimates!G18="","","("&TEXT(Estimates!G18,"0.00")&")") -> (-2.48) | E12: =IF(Estimates!G19="","","("&TEXT(Estimates!G19,"0.00")&")") -> (-1.95) | F12: =IF(Estimates!G20="","","("&TEXT(Estimates!G20,"0.00")&")") -> (1.28) | G12: =IF(Estimates!G21="","","("&TEXT(Estimates!G21,"0.00")&")") -> (1.23)
A13: Funding Ratio (t-1) | B13: =IF(Estimates!H22="","n/a",TEXT(Estimates!D22,"0.000")&IF(Estimates!H22<0.01,"***",IF(Estimates!H22<0.05,"**",IF(Estimates!H22<0.1,"*","")))) -> -0.005 | C13: =IF(Estimates!H23="","n/a",TEXT(Estimates!D23,"0.000")&IF(Estimates!H23<0.01,"***",IF(Estimates!H23<0.05,"**",IF(Estimates!H23<0.1,"*","")))) -> -0.006 | D13: =IF(Estimates!H24="","n/a",TEXT(Estimates!D24,"0.000")&IF(Estimates!H24<0.01,"***",IF(Estimates!H24<0.05,"**",IF(Estimates!H24<0.1,"*","")))) -> -0.027*** | E13: =IF(Estimates!H25="","n/a",TEXT(Estimates!D25,"0.000")&IF(Estimates!H25<0.01,"***",IF(Estimates!H25<0.05,"**",IF(Estimates!H25<0.1,"*","")))) -> -0.030*** | F13: =IF(Estimates!H26="","n/a",TEXT(Estimates!D26,"0.000")&IF(Estimates!H26<0.01,"***",IF(Estimates!H26<0.05,"**",IF(Estimates!H26<0.1,"*","")))) -> -0.005 | G13: =IF(Estimates!H27="","n/a",TEXT(Estimates!D27,"0.000")&IF(Estimates!H27<0.01,"***",IF(Estimates!H27<0.05,"**",IF(Estimates!H27<0.1,"*","")))) -> -0.005
B14: =IF(Estimates!G22="","","("&TEXT(Estimates!G22,"0.00")&")") -> (-1.17) | C14: =IF(Estimates!G23="","","("&TEXT(Estimates!G23,"0.00")&")") -> (-1.13) | D14: =IF(Estimates!G24="","","("&TEXT(Estimates!G24,"0.00")&")") -> (-3.16) | E14: =IF(Estimates!G25="","","("&TEXT(Estimates!G25,"0.00")&")") -> (-3.03) | F14: =IF(Estimates!G26="","","("&TEXT(Estimates!G26,"0.00")&")") -> (-1.01) | G14: =IF(Estimates!G27="","","("&TEXT(Estimates!G27,"0.00")&")") -> (-1.04)
A15: Equity Allocation (%) | B15: =IF(Estimates!H28="","n/a",TEXT(Estimates!D28,"0.000")&IF(Estimates!H28<0.01,"***",IF(Estimates!H28<0.05,"**",IF(Estimates!H28<0.1,"*","")))) -> -0.079 | C15: =IF(Estimates!H29="","n/a",TEXT(Estimates!D29,"0.000")&IF(Estimates!H29<0.01,"***",IF(Estimates!H29<0.05,"**",IF(Estimates!H29<0.1,"*","")))) -> 0.004 | D15: =IF(Estimates!H30="","n/a",TEXT(Estimates!D30,"0.000")&IF(Estimates!H30<0.01,"***",IF(Estimates!H30<0.05,"**",IF(Estimates!H30<0.1,"*","")))) -> -0.059 | E15: =IF(Estimates!H31="","n/a",TEXT(Estimates!D31,"0.000")&IF(Estimates!H31<0.01,"***",IF(Estimates!H31<0.05,"**",IF(Estimates!H31<0.1,"*","")))) -> -0.040 | F15: =IF(Estimates!H32="","n/a",TEXT(Estimates!D32,"0.000")&IF(Estimates!H32<0.01,"***",IF(Estimates!H32<0.05,"**",IF(Estimates!H32<0.1,"*","")))) -> 0.038 | G15: =IF(Estimates!H33="","n/a",TEXT(Estimates!D33,"0.000")&IF(Estimates!H33<0.01,"***",IF(Estimates!H33<0.05,"**",IF(Estimates!H33<0.1,"*","")))) -> 0.040
B16: =IF(Estimates!G28="","","("&TEXT(Estimates!G28,"0.00")&")") -> (-0.58) | C16: =IF(Estimates!G29="","","("&TEXT(Estimates!G29,"0.00")&")") -> (0.06) | D16: =IF(Estimates!G30="","","("&TEXT(Estimates!G30,"0.00")&")") -> (-0.79) | E16: =IF(Estimates!G31="","","("&TEXT(Estimates!G31,"0.00")&")") -> (-0.49) | F16: =IF(Estimates!G32="","","("&TEXT(Estimates!G32,"0.00")&")") -> (0.58) | G16: =IF(Estimates!G33="","","("&TEXT(Estimates!G33,"0.00")&")") -> (0.61)
A17: Fixed Income Allocation (%) | B17: =IF(Estimates!H34="","n/a",TEXT(Estimates!D34,"0.000")&IF(Estimates!H34<0.01,"***",IF(Estimates!H34<0.05,"**",IF(Estimates!H34<0.1,"*","")))) -> -0.088 | C17: =IF(Estimates!H35="","n/a",TEXT(Estimates!D35,"0.000")&IF(Estimates!H35<0.01,"***",IF(Estimates!H35<0.05,"**",IF(Estimates!H35<0.1,"*","")))) -> -0.001 | D17: =IF(Estimates!H36="","n/a",TEXT(Estimates!D36,"0.000")&IF(Estimates!H36<0.01,"***",IF(Estimates!H36<0.05,"**",IF(Estimates!H36<0.1,"*","")))) -> -0.069 | E17: =IF(Estimates!H37="","n/a",TEXT(Estimates!D37,"0.000")&IF(Estimates!H37<0.01,"***",IF(Estimates!H37<0.05,"**",IF(Estimates!H37<0.1,"*","")))) -> -0.047 | F17: =IF(Estimates!H38="","n/a",TEXT(Estimates!D38,"0.000")&IF(Estimates!H38<0.01,"***",IF(Estimates!H38<0.05,"**",IF(Estimates!H38<0.1,"*","")))) -> 0.033 | G17: =IF(Estimates!H39="","n/a",TEXT(Estimates!D39,"0.000")&IF(Estimates!H39<0.01,"***",IF(Estimates!H39<0.05,"**",IF(Estimates!H39<0.1,"*","")))) -> 0.036
B18: =IF(Estimates!G34="","","("&TEXT(Estimates!G34,"0.00")&")") -> (-0.60) | C18: =IF(Estimates!G35="","","("&TEXT(Estimates!G35,"0.00")&")") -> (-0.01) | D18: =IF(Estimates!G36="","","("&TEXT(Estimates!G36,"0.00")&")") -> (-0.80) | E18: =IF(Estimates!G37="","","("&TEXT(Estimates!G37,"0.00")&")") -> (-0.51) | F18: =IF(Estimates!G38="","","("&TEXT(Estimates!G38,"0.00")&")") -> (0.45) | G18: =IF(Estimates!G39="","","("&TEXT(Estimates!G39,"0.00")&")") -> (0.48)
A19: Real Estate Allocation (%) | B19: =IF(Estimates!H40="","n/a",TEXT(Estimates!D40,"0.000")&IF(Estimates!H40<0.01,"***",IF(Estimates!H40<0.05,"**",IF(Estimates!H40<0.1,"*","")))) -> -0.059 | C19: =IF(Estimates!H41="","n/a",TEXT(Estimates!D41,"0.000")&IF(Estimates!H41<0.01,"***",IF(Estimates!H41<0.05,"**",IF(Estimates!H41<0.1,"*","")))) -> 0.026 | D19: =IF(Estimates!H42="","n/a",TEXT(Estimates!D42,"0.000")&IF(Estimates!H42<0.01,"***",IF(Estimates!H42<0.05,"**",IF(Estimates!H42<0.1,"*","")))) -> -0.100 | E19: =IF(Estimates!H43="","n/a",TEXT(Estimates!D43,"0.000")&IF(Estimates!H43<0.01,"***",IF(Estimates!H43<0.05,"**",IF(Estimates!H43<0.1,"*","")))) -> -0.089 | F19: =IF(Estimates!H44="","n/a",TEXT(Estimates!D44,"0.000")&IF(Estimates!H44<0.01,"***",IF(Estimates!H44<0.05,"**",IF(Estimates!H44<0.1,"*","")))) -> 0.062 | G19: =IF(Estimates!H45="","n/a",TEXT(Estimates!D45,"0.000")&IF(Estimates!H45<0.01,"***",IF(Estimates!H45<0.05,"**",IF(Estimates!H45<0.1,"*","")))) -> 0.063
B20: =IF(Estimates!G40="","","("&TEXT(Estimates!G40,"0.00")&")") -> (-0.43) | C20: =IF(Estimates!G41="","","("&TEXT(Estimates!G41,"0.00")&")") -> (0.45) | D20: =IF(Estimates!G42="","","("&TEXT(Estimates!G42,"0.00")&")") -> (-1.41) | E20: =IF(Estimates!G43="","","("&TEXT(Estimates!G43,"0.00")&")") -> (-1.17) | F20: =IF(Estimates!G44="","","("&TEXT(Estimates!G44,"0.00")&")") -> (1.04) | G20: =IF(Estimates!G45="","","("&TEXT(Estimates!G45,"0.00")&")") -> (1.01)
A21: Private Equity Allocation (%) | B21: =IF(Estimates!H46="","n/a",TEXT(Estimates!D46,"0.000")&IF(Estimates!H46<0.01,"***",IF(Estimates!H46<0.05,"**",IF(Estimates!H46<0.1,"*","")))) -> -0.070 | C21: =IF(Estimates!H47="","n/a",TEXT(Estimates!D47,"0.000")&IF(Estimates!H47<0.01,"***",IF(Estimates!H47<0.05,"**",IF(Estimates!H47<0.1,"*","")))) -> 0.024 | D21: =IF(Estimates!H48="","n/a",TEXT(Estimates!D48,"0.000")&IF(Estimates!H48<0.01,"***",IF(Estimates!H48<0.05,"**",IF(Estimates!H48<0.1,"*","")))) -> -0.053 | E21: =IF(Estimates!H49="","n/a",TEXT(Estimates!D49,"0.000")&IF(Estimates!H49<0.01,"***",IF(Estimates!H49<0.05,"**",IF(Estimates!H49<0.1,"*","")))) -> -0.001 | F21: =IF(Estimates!H50="","n/a",TEXT(Estimates!D50,"0.000")&IF(Estimates!H50<0.01,"***",IF(Estimates!H50<0.05,"**",IF(Estimates!H50<0.1,"*","")))) -> 0.056 | G21: =IF(Estimates!H51="","n/a",TEXT(Estimates!D51,"0.000")&IF(Estimates!H51<0.01,"***",IF(Estimates!H51<0.05,"**",IF(Estimates!H51<0.1,"*","")))) -> 0.059
B22: =IF(Estimates!G46="","","("&TEXT(Estimates!G46,"0.00")&")") -> (-0.48) | C22: =IF(Estimates!G47="","","("&TEXT(Estimates!G47,"0.00")&")") -> (0.36) | D22: =IF(Estimates!G48="","","("&TEXT(Estimates!G48,"0.00")&")") -> (-0.64) | E22: =IF(Estimates!G49="","","("&TEXT(Estimates!G49,"0.00")&")") -> (-0.02) | F22: =IF(Estimates!G50="","","("&TEXT(Estimates!G50,"0.00")&")") -> (0.81) | G22: =IF(Estimates!G51="","","("&TEXT(Estimates!G51,"0.00")&")") -> (0.84)
A23: Hedge Fund Allocation (%) | B23: =IF(Estimates!H52="","n/a",TEXT(Estimates!D52,"0.000")&IF(Estimates!H52<0.01,"***",IF(Estimates!H52<0.05,"**",IF(Estimates!H52<0.1,"*","")))) -> -0.126 | C23: =IF(Estimates!H53="","n/a",TEXT(Estimates!D53,"0.000")&IF(Estimates!H53<0.01,"***",IF(Estimates!H53<0.05,"**",IF(Estimates!H53<0.1,"*","")))) -> -0.039 | D23: =IF(Estimates!H54="","n/a",TEXT(Estimates!D54,"0.000")&IF(Estimates!H54<0.01,"***",IF(Estimates!H54<0.05,"**",IF(Estimates!H54<0.1,"*","")))) -> -0.107 | E23: =IF(Estimates!H55="","n/a",TEXT(Estimates!D55,"0.000")&IF(Estimates!H55<0.01,"***",IF(Estimates!H55<0.05,"**",IF(Estimates!H55<0.1,"*","")))) -> -0.094 | F23: =IF(Estimates!H56="","n/a",TEXT(Estimates!D56,"0.000")&IF(Estimates!H56<0.01,"***",IF(Estimates!H56<0.05,"**",IF(Estimates!H56<0.1,"*","")))) -> -0.004 | G23: =IF(Estimates!H57="","n/a",TEXT(Estimates!D57,"0.000")&IF(Estimates!H57<0.01,"***",IF(Estimates!H57<0.05,"**",IF(Estimates!H57<0.1,"*","")))) -> -0.001
B24: =IF(Estimates!G52="","","("&TEXT(Estimates!G52,"0.00")&")") -> (-0.92) | C24: =IF(Estimates!G53="","","("&TEXT(Estimates!G53,"0.00")&")") -> (-0.60) | D24: =IF(Estimates!G54="","","("&TEXT(Estimates!G54,"0.00")&")") -> (-1.61) | E24: =IF(Estimates!G55="","","("&TEXT(Estimates!G55,"0.00")&")") -> (-1.38) | F24: =IF(Estimates!G56="","","("&TEXT(Estimates!G56,"0.00")&")") -> (-0.05) | G24: =IF(Estimates!G57="","","("&TEXT(Estimates!G57,"0.00")&")") -> (-0.02)
A25: Misc. Alternatives Allocation (%) | B25: =IF(Estimates!H58="","n/a",TEXT(Estimates!D58,"0.000")&IF(Estimates!H58<0.01,"***",IF(Estimates!H58<0.05,"**",IF(Estimates!H58<0.1,"*","")))) -> -0.093 | C25: =IF(Estimates!H59="","n/a",TEXT(Estimates!D59,"0.000")&IF(Estimates!H59<0.01,"***",IF(Estimates!H59<0.05,"**",IF(Estimates!H59<0.1,"*","")))) -> -0.011 | D25: =IF(Estimates!H60="","n/a",TEXT(Estimates!D60,"0.000")&IF(Estimates!H60<0.01,"***",IF(Estimates!H60<0.05,"**",IF(Estimates!H60<0.1,"*","")))) -> -0.125 | E25: =IF(Estimates!H61="","n/a",TEXT(Estimates!D61,"0.000")&IF(Estimates!H61<0.01,"***",IF(Estimates!H61<0.05,"**",IF(Estimates!H61<0.1,"*","")))) -> -0.087 | F25: =IF(Estimates!H62="","n/a",TEXT(Estimates!D62,"0.000")&IF(Estimates!H62<0.01,"***",IF(Estimates!H62<0.05,"**",IF(Estimates!H62<0.1,"*","")))) -> 0.024 | G25: =IF(Estimates!H63="","n/a",TEXT(Estimates!D63,"0.000")&IF(Estimates!H63<0.01,"***",IF(Estimates!H63<0.05,"**",IF(Estimates!H63<0.1,"*","")))) -> 0.027
B26: =IF(Estimates!G58="","","("&TEXT(Estimates!G58,"0.00")&")") -> (-0.65) | C26: =IF(Estimates!G59="","","("&TEXT(Estimates!G59,"0.00")&")") -> (-0.17) | D26: =IF(Estimates!G60="","","("&TEXT(Estimates!G60,"0.00")&")") -> (-1.56) | E26: =IF(Estimates!G61="","","("&TEXT(Estimates!G61,"0.00")&")") -> (-1.03) | F26: =IF(Estimates!G62="","","("&TEXT(Estimates!G62,"0.00")&")") -> (0.38) | G26: =IF(Estimates!G63="","","("&TEXT(Estimates!G63,"0.00")&")") -> (0.42)
A27: Commodities Allocation (%) | B27: =IF(Estimates!H64="","n/a",TEXT(Estimates!D64,"0.000")&IF(Estimates!H64<0.01,"***",IF(Estimates!H64<0.05,"**",IF(Estimates!H64<0.1,"*","")))) -> -0.140 | C27: =IF(Estimates!H65="","n/a",TEXT(Estimates!D65,"0.000")&IF(Estimates!H65<0.01,"***",IF(Estimates!H65<0.05,"**",IF(Estimates!H65<0.1,"*","")))) -> -0.048 | D27: =IF(Estimates!H66="","n/a",TEXT(Estimates!D66,"0.000")&IF(Estimates!H66<0.01,"***",IF(Estimates!H66<0.05,"**",IF(Estimates!H66<0.1,"*","")))) -> -0.149 | E27: =IF(Estimates!H67="","n/a",TEXT(Estimates!D67,"0.000")&IF(Estimates!H67<0.01,"***",IF(Estimates!H67<0.05,"**",IF(Estimates!H67<0.1,"*","")))) -> -0.135 | F27: =IF(Estimates!H68="","n/a",TEXT(Estimates!D68,"0.000")&IF(Estimates!H68<0.01,"***",IF(Estimates!H68<0.05,"**",IF(Estimates!H68<0.1,"*","")))) -> -0.014 | G27: =IF(Estimates!H69="","n/a",TEXT(Estimates!D69,"0.000")&IF(Estimates!H69<0.01,"***",IF(Estimates!H69<0.05,"**",IF(Estimates!H69<0.1,"*","")))) -> -0.012
B28: =IF(Estimates!G64="","","("&TEXT(Estimates!G64,"0.00")&")") -> (-0.99) | C28: =IF(Estimates!G65="","","("&TEXT(Estimates!G65,"0.00")&")") -> (-0.78) | D28: =IF(Estimates!G66="","","("&TEXT(Estimates!G66,"0.00")&")") -> (-1.70) | E28: =IF(Estimates!G67="","","("&TEXT(Estimates!G67,"0.00")&")") -> (-1.51) | F28: =IF(Estimates!G68="","","("&TEXT(Estimates!G68,"0.00")&")") -> (-0.22) | G28: =IF(Estimates!G69="","","("&TEXT(Estimates!G69,"0.00")&")") -> (-0.19)
A29: Cash Allocation (%) | B29: =IF(Estimates!H70="","n/a",TEXT(Estimates!D70,"0.000")&IF(Estimates!H70<0.01,"***",IF(Estimates!H70<0.05,"**",IF(Estimates!H70<0.1,"*","")))) -> -0.099 | C29: =IF(Estimates!H71="","n/a",TEXT(Estimates!D71,"0.000")&IF(Estimates!H71<0.01,"***",IF(Estimates!H71<0.05,"**",IF(Estimates!H71<0.1,"*","")))) -> -0.019 | D29: =IF(Estimates!H72="","n/a",TEXT(Estimates!D72,"0.000")&IF(Estimates!H72<0.01,"***",IF(Estimates!H72<0.05,"**",IF(Estimates!H72<0.1,"*","")))) -> -0.078 | E29: =IF(Estimates!H73="","n/a",TEXT(Estimates!D73,"0.000")&IF(Estimates!H73<0.01,"***",IF(Estimates!H73<0.05,"**",IF(Estimates!H73<0.1,"*","")))) -> -0.057 | F29: =IF(Estimates!H74="","n/a",TEXT(Estimates!D74,"0.000")&IF(Estimates!H74<0.01,"***",IF(Estimates!H74<0.05,"**",IF(Estimates!H74<0.1,"*","")))) -> 0.018 | G29: =IF(Estimates!H75="","n/a",TEXT(Estimates!D75,"0.000")&IF(Estimates!H75<0.01,"***",IF(Estimates!H75<0.05,"**",IF(Estimates!H75<0.1,"*","")))) -> 0.020
B30: =IF(Estimates!G70="","","("&TEXT(Estimates!G70,"0.00")&")") -> (-0.66) | C30: =IF(Estimates!G71="","","("&TEXT(Estimates!G71,"0.00")&")") -> (-0.24) | D30: =IF(Estimates!G72="","","("&TEXT(Estimates!G72,"0.00")&")") -> (-0.76) | E30: =IF(Estimates!G73="","","("&TEXT(Estimates!G73,"0.00")&")") -> (-0.54) | F30: =IF(Estimates!G74="","","("&TEXT(Estimates!G74,"0.00")&")") -> (0.24) | G30: =IF(Estimates!G75="","","("&TEXT(Estimates!G75,"0.00")&")") -> (0.26)
A31: Financial Center (0/1) | B31: =IF(Estimates!H76="","n/a",TEXT(Estimates!D76,"0.000")&IF(Estimates!H76<0.01,"***",IF(Estimates!H76<0.05,"**",IF(Estimates!H76<0.1,"*","")))) -> 0.113 | C31: =IF(Estimates!H77="","n/a",TEXT(Estimates!D77,"0.000")&IF(Estimates!H77<0.01,"***",IF(Estimates!H77<0.05,"**",IF(Estimates!H77<0.1,"*","")))) -> 0.142 | F31: =IF(Estimates!H78="","n/a",TEXT(Estimates!D78,"0.000")&IF(Estimates!H78<0.01,"***",IF(Estimates!H78<0.05,"**",IF(Estimates!H78<0.1,"*","")))) -> 0.153 | G31: =IF(Estimates!H79="","n/a",TEXT(Estimates!D79,"0.000")&IF(Estimates!H79<0.01,"***",IF(Estimates!H79<0.05,"**",IF(Estimates!H79<0.1,"*","")))) -> 0.139
B32: =IF(Estimates!G76="","","("&TEXT(Estimates!G76,"0.00")&")") -> (0.76) | C32: =IF(Estimates!G77="","","("&TEXT(Estimates!G77,"0.00")&")") -> (1.00) | F32: =IF(Estimates!G78="","","("&TEXT(Estimates!G78,"0.00")&")") -> (1.11) | G32: =IF(Estimates!G79="","","("&TEXT(Estimates!G79,"0.00")&")") -> (1.02)
A33: Log (CIO Age) (t-1) | C33: =IF(Estimates!H80="","n/a",TEXT(Estimates!D80,"0.000")&IF(Estimates!H80<0.01,"***",IF(Estimates!H80<0.05,"**",IF(Estimates!H80<0.1,"*","")))) -> -0.402 | D33: =IF(Estimates!H81="","n/a",TEXT(Estimates!D81,"0.000")&IF(Estimates!H81<0.01,"***",IF(Estimates!H81<0.05,"**",IF(Estimates!H81<0.1,"*","")))) -> 0.786 | E33: =IF(Estimates!H82="","n/a",TEXT(Estimates!D82,"0.000")&IF(Estimates!H82<0.01,"***",IF(Estimates!H82<0.05,"**",IF(Estimates!H82<0.1,"*","")))) -> 0.855 | F33: =IF(Estimates!H83="","n/a",TEXT(Estimates!D83,"0.000")&IF(Estimates!H83<0.01,"***",IF(Estimates!H83<0.05,"**",IF(Estimates!H83<0.1,"*","")))) -> -0.293 | G33: =IF(Estimates!H84="","n/a",TEXT(Estimates!D84,"0.000")&IF(Estimates!H84<0.01,"***",IF(Estimates!H84<0.05,"**",IF(Estimates!H84<0.1,"*","")))) -> -0.338
C34: =IF(Estimates!G80="","","("&TEXT(Estimates!G80,"0.00")&")") -> (-0.76) | D34: =IF(Estimates!G81="","","("&TEXT(Estimates!G81,"0.00")&")") -> (1.24) | E34: =IF(Estimates!G82="","","("&TEXT(Estimates!G82,"0.00")&")") -> (1.28) | F34: =IF(Estimates!G83="","","("&TEXT(Estimates!G83,"0.00")&")") -> (-0.54) | G34: =IF(Estimates!G84="","","("&TEXT(Estimates!G84,"0.00")&")") -> (-0.62)
A35: Log (CIO Tenure) (t-1) | C35: =IF(Estimates!H85="","n/a",TEXT(Estimates!D85,"0.000")&IF(Estimates!H85<0.01,"***",IF(Estimates!H85<0.05,"**",IF(Estimates!H85<0.1,"*","")))) -> 0.038 | D35: =IF(Estimates!H86="","n/a",TEXT(Estimates!D86,"0.000")&IF(Estimates!H86<0.01,"***",IF(Estimates!H86<0.05,"**",IF(Estimates!H86<0.1,"*","")))) -> 0.007 | E35: =IF(Estimates!H87="","n/a",TEXT(Estimates!D87,"0.000")&IF(Estimates!H87<0.01,"***",IF(Estimates!H87<0.05,"**",IF(Estimates!H87<0.1,"*","")))) -> -0.012 | F35: =IF(Estimates!H88="","n/a",TEXT(Estimates!D88,"0.000")&IF(Estimates!H88<0.01,"***",IF(Estimates!H88<0.05,"**",IF(Estimates!H88<0.1,"*","")))) -> 0.056 | G35: =IF(Estimates!H89="","n/a",TEXT(Estimates!D89,"0.000")&IF(Estimates!H89<0.01,"***",IF(Estimates!H89<0.05,"**",IF(Estimates!H89<0.1,"*","")))) -> 0.057
C36: =IF(Estimates!G85="","","("&TEXT(Estimates!G85,"0.00")&")") -> (0.40) | D36: =IF(Estimates!G86="","","("&TEXT(Estimates!G86,"0.00")&")") -> (0.07) | E36: =IF(Estimates!G87="","","("&TEXT(Estimates!G87,"0.00")&")") -> (-0.10) | F36: =IF(Estimates!G88="","","("&TEXT(Estimates!G88,"0.00")&")") -> (0.61) | G36: =IF(Estimates!G89="","","("&TEXT(Estimates!G89,"0.00")&")") -> (0.62)
A37: CIO Prior Private Experience (0/1) | C37: =IF(Estimates!H90="","n/a",TEXT(Estimates!D90,"0.000")&IF(Estimates!H90<0.01,"***",IF(Estimates!H90<0.05,"**",IF(Estimates!H90<0.1,"*","")))) -> 0.037 | D37: =IF(Estimates!H91="","n/a",TEXT(Estimates!D91,"0.000")&IF(Estimates!H91<0.01,"***",IF(Estimates!H91<0.05,"**",IF(Estimates!H91<0.1,"*","")))) -> -0.043 | E37: =IF(Estimates!H92="","n/a",TEXT(Estimates!D92,"0.000")&IF(Estimates!H92<0.01,"***",IF(Estimates!H92<0.05,"**",IF(Estimates!H92<0.1,"*","")))) -> -0.006 | F37: =IF(Estimates!H93="","n/a",TEXT(Estimates!D93,"0.000")&IF(Estimates!H93<0.01,"***",IF(Estimates!H93<0.05,"**",IF(Estimates!H93<0.1,"*","")))) -> -0.064 | G37: =IF(Estimates!H94="","n/a",TEXT(Estimates!D94,"0.000")&IF(Estimates!H94<0.01,"***",IF(Estimates!H94<0.05,"**",IF(Estimates!H94<0.1,"*","")))) -> -0.036
C38: =IF(Estimates!G90="","","("&TEXT(Estimates!G90,"0.00")&")") -> (0.36) | D38: =IF(Estimates!G91="","","("&TEXT(Estimates!G91,"0.00")&")") -> (-0.26) | E38: =IF(Estimates!G92="","","("&TEXT(Estimates!G92,"0.00")&")") -> (-0.04) | F38: =IF(Estimates!G93="","","("&TEXT(Estimates!G93,"0.00")&")") -> (-0.79) | G38: =IF(Estimates!G94="","","("&TEXT(Estimates!G94,"0.00")&")") -> (-0.48)
A39: CIO Attended Elite College (0/1) | C39: =IF(Estimates!H95="","n/a",TEXT(Estimates!D95,"0.000")&IF(Estimates!H95<0.01,"***",IF(Estimates!H95<0.05,"**",IF(Estimates!H95<0.1,"*","")))) -> -0.116 | D39: =IF(Estimates!H96="","n/a",TEXT(Estimates!D96,"0.000")&IF(Estimates!H96<0.01,"***",IF(Estimates!H96<0.05,"**",IF(Estimates!H96<0.1,"*","")))) -> 0.258 | E39: =IF(Estimates!H97="","n/a",TEXT(Estimates!D97,"0.000")&IF(Estimates!H97<0.01,"***",IF(Estimates!H97<0.05,"**",IF(Estimates!H97<0.1,"*","")))) -> 0.310 | F39: =IF(Estimates!H98="","n/a",TEXT(Estimates!D98,"0.000")&IF(Estimates!H98<0.01,"***",IF(Estimates!H98<0.05,"**",IF(Estimates!H98<0.1,"*","")))) -> -0.074 | G39: =IF(Estimates!H99="","n/a",TEXT(Estimates!D99,"0.000")&IF(Estimates!H99<0.01,"***",IF(Estimates!H99<0.05,"**",IF(Estimates!H99<0.1,"*","")))) -> -0.082
C40: =IF(Estimates!G95="","","("&TEXT(Estimates!G95,"0.00")&")") -> (-0.83) | D40: =IF(Estimates!G96="","","("&TEXT(Estimates!G96,"0.00")&")") -> (1.12) | E40: =IF(Estimates!G97="","","("&TEXT(Estimates!G97,"0.00")&")") -> (1.37) | F40: =IF(Estimates!G98="","","("&TEXT(Estimates!G98,"0.00")&")") -> (-0.58) | G40: =IF(Estimates!G99="","","("&TEXT(Estimates!G99,"0.00")&")") -> (-0.63)
A41: Separate Investment Board (0/1) | C41: =IF(Estimates!H100="","n/a",TEXT(Estimates!D100,"0.000")&IF(Estimates!H100<0.01,"***",IF(Estimates!H100<0.05,"**",IF(Estimates!H100<0.1,"*","")))) -> 0.267* | D41: =IF(Estimates!H101="","n/a",TEXT(Estimates!D101,"0.000")&IF(Estimates!H101<0.01,"***",IF(Estimates!H101<0.05,"**",IF(Estimates!H101<0.1,"*","")))) -> -0.277 | E41: =IF(Estimates!H102="","n/a",TEXT(Estimates!D102,"0.000")&IF(Estimates!H102<0.01,"***",IF(Estimates!H102<0.05,"**",IF(Estimates!H102<0.1,"*","")))) -> -0.199 | F41: =IF(Estimates!H103="","n/a",TEXT(Estimates!D103,"0.000")&IF(Estimates!H103<0.01,"***",IF(Estimates!H103<0.05,"**",IF(Estimates!H103<0.1,"*","")))) -> 0.276** | G41: =IF(Estimates!H104="","n/a",TEXT(Estimates!D104,"0.000")&IF(Estimates!H104<0.01,"***",IF(Estimates!H104<0.05,"**",IF(Estimates!H104<0.1,"*","")))) -> 0.272**
C42: =IF(Estimates!G100="","","("&TEXT(Estimates!G100,"0.00")&")") -> (2.04) | D42: =IF(Estimates!G101="","","("&TEXT(Estimates!G101,"0.00")&")") -> (-0.33) | E42: =IF(Estimates!G102="","","("&TEXT(Estimates!G102,"0.00")&")") -> (-0.20) | F42: =IF(Estimates!G103="","","("&TEXT(Estimates!G103,"0.00")&")") -> (2.20) | G42: =IF(Estimates!G104="","","("&TEXT(Estimates!G104,"0.00")&")") -> (2.16)
A43: % Political Appointees on Board | C43: =IF(Estimates!H105="","n/a",TEXT(Estimates!D105,"0.000")&IF(Estimates!H105<0.01,"***",IF(Estimates!H105<0.05,"**",IF(Estimates!H105<0.1,"*","")))) -> -0.357 | D43: =IF(Estimates!H106="","n/a",TEXT(Estimates!D106,"0.000")&IF(Estimates!H106<0.01,"***",IF(Estimates!H106<0.05,"**",IF(Estimates!H106<0.1,"*","")))) -> -0.065 | E43: =IF(Estimates!H107="","n/a",TEXT(Estimates!D107,"0.000")&IF(Estimates!H107<0.01,"***",IF(Estimates!H107<0.05,"**",IF(Estimates!H107<0.1,"*","")))) -> -0.448 | F43: =IF(Estimates!H108="","n/a",TEXT(Estimates!D108,"0.000")&IF(Estimates!H108<0.01,"***",IF(Estimates!H108<0.05,"**",IF(Estimates!H108<0.1,"*","")))) -> -0.353 | G43: =IF(Estimates!H109="","n/a",TEXT(Estimates!D109,"0.000")&IF(Estimates!H109<0.01,"***",IF(Estimates!H109<0.05,"**",IF(Estimates!H109<0.1,"*","")))) -> -0.355
C44: =IF(Estimates!G105="","","("&TEXT(Estimates!G105,"0.00")&")") -> (-1.50) | D44: =IF(Estimates!G106="","","("&TEXT(Estimates!G106,"0.00")&")") -> (-0.04) | E44: =IF(Estimates!G107="","","("&TEXT(Estimates!G107,"0.00")&")") -> (-0.27) | F44: =IF(Estimates!G108="","","("&TEXT(Estimates!G108,"0.00")&")") -> (-1.48) | G44: =IF(Estimates!G109="","","("&TEXT(Estimates!G109,"0.00")&")") -> (-1.47)
A46: Observations | B46: 1727 | C46: 1483 | D46: 1482 | E46: 1482 | F46: 1483 | G46: 1483
A47: Adjusted R-squared | B47: 0.049684036 | C47: 0.059398101 | D47: 0.081182181 | E47: 0.095642068 | F47: 0.055524906 | G47: 0.056709498
A48: Plan FE | B48: No | C48: No | D48: Yes | E48: Yes | F48: No | G48: No
A49: Year FE | B49: Yes | C49: Yes | D49: No | E49: Yes | F49: Yes | G49: Yes
A50: Last n years | F50: 5 | G50: 10
A53: Panel B. Benchmark-Adjusted Returns (updated benchmark)
B54: (1) | C54: (2) | D54: (3) | E54: (4) | F54: (5) | G54: (6)
B55: Bench-adj. Ret. (t) | C55: Bench-adj. Ret. (t) | D55: Bench-adj. Ret. (t) | E55: Bench-adj. Ret. (t) | F55: Bench-adj. Ret. (t) | G55: Bench-adj. Ret. (t)
A56: Conflicted CIO (0/1) | B56: =IF(Estimates!H110="","n/a",TEXT(Estimates!D110,"0.000")&IF(Estimates!H110<0.01,"***",IF(Estimates!H110<0.05,"**",IF(Estimates!H110<0.1,"*","")))) -> -0.385** | C56: =IF(Estimates!H111="","n/a",TEXT(Estimates!D111,"0.000")&IF(Estimates!H111<0.01,"***",IF(Estimates!H111<0.05,"**",IF(Estimates!H111<0.1,"*","")))) -> -0.491*** | D56: =IF(Estimates!H112="","n/a",TEXT(Estimates!D112,"0.000")&IF(Estimates!H112<0.01,"***",IF(Estimates!H112<0.05,"**",IF(Estimates!H112<0.1,"*","")))) -> -0.373** | E56: =IF(Estimates!H113="","n/a",TEXT(Estimates!D113,"0.000")&IF(Estimates!H113<0.01,"***",IF(Estimates!H113<0.05,"**",IF(Estimates!H113<0.1,"*","")))) -> -0.411** | F56: =IF(Estimates!H114="","n/a",TEXT(Estimates!D114,"0.000")&IF(Estimates!H114<0.01,"***",IF(Estimates!H114<0.05,"**",IF(Estimates!H114<0.1,"*","")))) -> -0.384* | G56: =IF(Estimates!H115="","n/a",TEXT(Estimates!D115,"0.000")&IF(Estimates!H115<0.01,"***",IF(Estimates!H115<0.05,"**",IF(Estimates!H115<0.1,"*","")))) -> -0.441**
B57: =IF(Estimates!G110="","","("&TEXT(Estimates!G110,"0.00")&")") -> (-2.46) | C57: =IF(Estimates!G111="","","("&TEXT(Estimates!G111,"0.00")&")") -> (-4.15) | D57: =IF(Estimates!G112="","","("&TEXT(Estimates!G112,"0.00")&")") -> (-2.23) | E57: =IF(Estimates!G113="","","("&TEXT(Estimates!G113,"0.00")&")") -> (-2.15) | F57: =IF(Estimates!G114="","","("&TEXT(Estimates!G114,"0.00")&")") -> (-1.84) | G57: =IF(Estimates!G115="","","("&TEXT(Estimates!G115,"0.00")&")") -> (-2.36)
A58: Investment Return (t - 1) | B58: =IF(Estimates!H116="","n/a",TEXT(Estimates!D116,"0.000")&IF(Estimates!H116<0.01,"***",IF(Estimates!H116<0.05,"**",IF(Estimates!H116<0.1,"*","")))) -> -0.003 | C58: =IF(Estimates!H117="","n/a",TEXT(Estimates!D117,"0.000")&IF(Estimates!H117<0.01,"***",IF(Estimates!H117<0.05,"**",IF(Estimates!H117<0.1,"*","")))) -> -0.012 | D58: =IF(Estimates!H118="","n/a",TEXT(Estimates!D118,"0.000")&IF(Estimates!H118<0.01,"***",IF(Estimates!H118<0.05,"**",IF(Estimates!H118<0.1,"*","")))) -> 0.006 | E58: =IF(Estimates!H119="","n/a",TEXT(Estimates!D119,"0.000")&IF(Estimates!H119<0.01,"***",IF(Estimates!H119<0.05,"**",IF(Estimates!H119<0.1,"*","")))) -> -0.017 | F58: =IF(Estimates!H120="","n/a",TEXT(Estimates!D120,"0.000")&IF(Estimates!H120<0.01,"***",IF(Estimates!H120<0.05,"**",IF(Estimates!H120<0.1,"*","")))) -> -0.012 | G58: =IF(Estimates!H121="","n/a",TEXT(Estimates!D121,"0.000")&IF(Estimates!H121<0.01,"***",IF(Estimates!H121<0.05,"**",IF(Estimates!H121<0.1,"*","")))) -> -0.012
B59: =IF(Estimates!G116="","","("&TEXT(Estimates!G116,"0.00")&")") -> (-0.20) | C59: =IF(Estimates!G117="","","("&TEXT(Estimates!G117,"0.00")&")") -> (-0.59) | D59: =IF(Estimates!G118="","","("&TEXT(Estimates!G118,"0.00")&")") -> (0.34) | E59: =IF(Estimates!G119="","","("&TEXT(Estimates!G119,"0.00")&")") -> (-1.01) | F59: =IF(Estimates!G120="","","("&TEXT(Estimates!G120,"0.00")&")") -> (-0.64) | G59: =IF(Estimates!G121="","","("&TEXT(Estimates!G121,"0.00")&")") -> (-0.64)
A60: Log (Plan Size) (t-1) | B60: =IF(Estimates!H122="","n/a",TEXT(Estimates!D122,"0.000")&IF(Estimates!H122<0.01,"***",IF(Estimates!H122<0.05,"**",IF(Estimates!H122<0.1,"*","")))) -> -0.045 | C60: =IF(Estimates!H123="","n/a",TEXT(Estimates!D123,"0.000")&IF(Estimates!H123<0.01,"***",IF(Estimates!H123<0.05,"**",IF(Estimates!H123<0.1,"*","")))) -> 0.005 | D60: =IF(Estimates!H124="","n/a",TEXT(Estimates!D124,"0.000")&IF(Estimates!H124<0.01,"***",IF(Estimates!H124<0.05,"**",IF(Estimates!H124<0.1,"*","")))) -> -1.142* | E60: =IF(Estimates!H125="","n/a",TEXT(Estimates!D125,"0.000")&IF(Estimates!H125<0.01,"***",IF(Estimates!H125<0.05,"**",IF(Estimates!H125<0.1,"*","")))) -> -0.288 | F60: =IF(Estimates!H126="","n/a",TEXT(Estimates!D126,"0.000")&IF(Estimates!H126<0.01,"***",IF(Estimates!H126<0.05,"**",IF(Estimates!H126<0.1,"*","")))) -> 0.010 | G60: =IF(Estimates!H127="","n/a",TEXT(Estimates!D127,"0.000")&IF(Estimates!H127<0.01,"***",IF(Estimates!H127<0.05,"**",IF(Estimates!H127<0.1,"*","")))) -> 0.007
B61: =IF(Estimates!G122="","","("&TEXT(Estimates!G122,"0.00")&")") -> (-1.15) | C61: =IF(Estimates!G123="","","("&TEXT(Estimates!G123,"0.00")&")") -> (0.10) | D61: =IF(Estimates!G124="","","("&TEXT(Estimates!G124,"0.00")&")") -> (-1.82) | E61: =IF(Estimates!G125="","","("&TEXT(Estimates!G125,"0.00")&")") -> (-0.40) | F61: =IF(Estimates!G126="","","("&TEXT(Estimates!G126,"0.00")&")") -> (0.20) | G61: =IF(Estimates!G127="","","("&TEXT(Estimates!G127,"0.00")&")") -> (0.15)
A62: Funding Ratio (t-1) | B62: =IF(Estimates!H128="","n/a",TEXT(Estimates!D128,"0.000")&IF(Estimates!H128<0.01,"***",IF(Estimates!H128<0.05,"**",IF(Estimates!H128<0.1,"*","")))) -> 0.003 | C62: =IF(Estimates!H129="","n/a",TEXT(Estimates!D129,"0.000")&IF(Estimates!H129<0.01,"***",IF(Estimates!H129<0.05,"**",IF(Estimates!H129<0.1,"*","")))) -> 0.004 | D62: =IF(Estimates!H130="","n/a",TEXT(Estimates!D130,"0.000")&IF(Estimates!H130<0.01,"***",IF(Estimates!H130<0.05,"**",IF(Estimates!H130<0.1,"*","")))) -> -0.020 | E62: =IF(Estimates!H131="","n/a",TEXT(Estimates!D131,"0.000")&IF(Estimates!H131<0.01,"***",IF(Estimates!H131<0.05,"**",IF(Estimates!H131<0.1,"*","")))) -> -0.017 | F62: =IF(Estimates!H132="","n/a",TEXT(Estimates!D132,"0.000")&IF(Estimates!H132<0.01,"***",IF(Estimates!H132<0.05,"**",IF(Estimates!H132<0.1,"*","")))) -> 0.004 | G62: =IF(Estimates!H133="","n/a",TEXT(Estimates!D133,"0.000")&IF(Estimates!H133<0.01,"***",IF(Estimates!H133<0.05,"**",IF(Estimates!H133<0.1,"*","")))) -> 0.004
B63: =IF(Estimates!G128="","","("&TEXT(Estimates!G128,"0.00")&")") -> (0.78) | C63: =IF(Estimates!G129="","","("&TEXT(Estimates!G129,"0.00")&")") -> (0.81) | D63: =IF(Estimates!G130="","","("&TEXT(Estimates!G130,"0.00")&")") -> (-1.54) | E63: =IF(Estimates!G131="","","("&TEXT(Estimates!G131,"0.00")&")") -> (-1.52) | F63: =IF(Estimates!G132="","","("&TEXT(Estimates!G132,"0.00")&")") -> (0.96) | G63: =IF(Estimates!G133="","","("&TEXT(Estimates!G133,"0.00")&")") -> (0.96)
A64: Equity Allocation (%) | B64: =IF(Estimates!H134="","n/a",TEXT(Estimates!D134,"0.000")&IF(Estimates!H134<0.01,"***",IF(Estimates!H134<0.05,"**",IF(Estimates!H134<0.1,"*","")))) -> -0.174 | C64: =IF(Estimates!H135="","n/a",TEXT(Estimates!D135,"0.000")&IF(Estimates!H135<0.01,"***",IF(Estimates!H135<0.05,"**",IF(Estimates!H135<0.1,"*","")))) -> -0.017 | D64: =IF(Estimates!H136="","n/a",TEXT(Estimates!D136,"0.000")&IF(Estimates!H136<0.01,"***",IF(Estimates!H136<0.05,"**",IF(Estimates!H136<0.1,"*","")))) -> -0.019 | E64: =IF(Estimates!H137="","n/a",TEXT(Estimates!D137,"0.000")&IF(Estimates!H137<0.01,"***",IF(Estimates!H137<0.05,"**",IF(Estimates!H137<0.1,"*","")))) -> 0.004 | F64: =IF(Estimates!H138="","n/a",TEXT(Estimates!D138,"0.000")&IF(Estimates!H138<0.01,"***",IF(Estimates!H138<0.05,"**",IF(Estimates!H138<0.1,"*","")))) -> 0.013 | G64: =IF(Estimates!H139="","n/a",TEXT(Estimates!D139,"0.000")&IF(Estimates!H139<0.01,"***",IF(Estimates!H139<0.05,"**",IF(Estimates!H139<0.1,"*","")))) -> 0.015
B65: =IF(Estimates!G134="","","("&TEXT(Estimates!G134,"0.00")&")") -> (-1.31) | C65: =IF(Estimates!G135="","","("&TEXT(Estimates!G135,"0.00")&")") -> (-0.14) | D65: =IF(Estimates!G136="","","("&TEXT(Estimates!G136,"0.00")&")") -> (-0.11) | E65: =IF(Estimates!G137="","","("&TEXT(Estimates!G137,"0.00")&")") -> (0.02) | F65: =IF(Estimates!G138="","","("&TEXT(Estimates!G138,"0.00")&")") -> (0.12) | G65: =IF(Estimates!G139="","","("&TEXT(Estimates!G139,"0.00")&")") -> (0.13)
A66: Fixed Income Allocation (%) | B66: =IF(Estimates!H140="","n/a",TEXT(Estimates!D140,"0.000")&IF(Estimates!H140<0.01,"***",IF(Estimates!H140<0.05,"**",IF(Estimates!H140<0.1,"*","")))) -> -0.162 | C66: =IF(Estimates!H141="","n/a",TEXT(Estimates!D141,"0.000")&IF(Estimates!H141<0.01,"***",IF(Estimates!H141<0.05,"**",IF(Estimates!H141<0.1,"*","")))) -> -0.013 | D66: =IF(Estimates!H142="","n/a",TEXT(Estimates!D142,"0.000")&IF(Estimates!H142<0.01,"***",IF(Estimates!H142<0.05,"**",IF(Estimates!H142<0.1,"*","")))) -> -0.036 | E66: =IF(Estimates!H143="","n/a",TEXT(Estimates!D143,"0.000")&IF(Estimates!H143<0.01,"***",IF(Estimates!H143<0.05,"**",IF(Estimates!H143<0.1,"*","")))) -> 0.001 | F66: =IF(Estimates!H144="","n/a",TEXT(Estimates!D144,"0.000")&IF(Estimates!H144<0.01,"***",IF(Estimates!H144<0.05,"**",IF(Estimates!H144<0.1,"*","")))) -> 0.017 | G66: =IF(Estimates!H145="","n/a",TEXT(Estimates!D145,"0.000")&IF(Estimates!H145<0.01,"***",IF(Estimates!H145<0.05,"**",IF(Estimates!H145<0.1,"*","")))) -> 0.019
B67: =IF(Estimates!G140="","","("&TEXT(Estimates!G140,"0.00")&")") -> (-1.21) | C67: =IF(Estimates!G141="","","("&TEXT(Estimates!G141,"0.00")&")") -> (-0.11) | D67: =IF(Estimates!G142="","","("&TEXT(Estimates!G142,"0.00")&")") -> (-0.20) | E67: =IF(Estimates!G143="","","("&TEXT(Estimates!G143,"0.00")&")") -> (0.00) | F67: =IF(Estimates!G144="","","("&TEXT(Estimates!G144,"0.00")&")") -> (0.15) | G67: =IF(Estimates!G145="","","("&TEXT(Estimates!G145,"0.00")&")") -> (0.16)
A68: Real Estate Allocation (%) | B68: =IF(Estimates!H146="","n/a",TEXT(Estimates!D146,"0.000")&IF(Estimates!H146<0.01,"***",IF(Estimates!H146<0.05,"**",IF(Estimates!H146<0.1,"*","")))) -> -0.186 | C68: =IF(Estimates!H147="","n/a",TEXT(Estimates!D147,"0.000")&IF(Estimates!H147<0.01,"***",IF(Estimates!H147<0.05,"**",IF(Estimates!H147<0.1,"*","")))) -> -0.018 | D68: =IF(Estimates!H148="","n/a",TEXT(Estimates!D148,"0.000")&IF(Estimates!H148<0.01,"***",IF(Estimates!H148<0.05,"**",IF(Estimates!H148<0.1,"*","")))) -> -0.063 | E68: =IF(Estimates!H149="","n/a",TEXT(Estimates!D149,"0.000")&IF(Estimates!H149<0.01,"***",IF(Estimates!H149<0.05,"**",IF(Estimates!H149<0.1,"*","")))) -> -0.033 | F68: =IF(Estimates!H150="","n/a",TEXT(Estimates!D150,"0.000")&IF(Estimates!H150<0.01,"***",IF(Estimates!H150<0.05,"**",IF(Estimates!H150<0.1,"*","")))) -> 0.014 | G68: =IF(Estimates!H151="","n/a",TEXT(Estimates!D151,"0.000")&IF(Estimates!H151<0.01,"***",IF(Estimates!H151<0.05,"**",IF(Estimates!H151<0.1,"*","")))) -> 0.013
B69: =IF(Estimates!G146="","","("&TEXT(Estimates!G146,"0.00")&")") -> (-1.50) | C69: =IF(Estimates!G147="","","("&TEXT(Estimates!G147,"0.00")&")") -> (-0.17) | D69: =IF(Estimates!G148="","","("&TEXT(Estimates!G148,"0.00")&")") -> (-0.36) | E69: =IF(Estimates!G149="","","("&TEXT(Estimates!G149,"0.00")&")") -> (-0.19) | F69: =IF(Estimates!G150="","","("&TEXT(Estimates!G150,"0.00")&")") -> (0.14) | G69: =IF(Estimates!G151="","","("&TEXT(Estimates!G151,"0.00")&")") -> (0.13)
A70: Private Equity Allocation (%) | B70: =IF(Estimates!H152="","n/a",TEXT(Estimates!D152,"0.000")&IF(Estimates!H152<0.01,"***",IF(Estimates!H152<0.05,"**",IF(Estimates!H152<0.1,"*","")))) -> -0.162 | C70: =IF(Estimates!H153="","n/a",TEXT(Estimates!D153,"0.000")&IF(Estimates!H153<0.01,"***",IF(Estimates!H153<0.05,"**",IF(Estimates!H153<0.1,"*","")))) -> -0.004 | D70: =IF(Estimates!H154="","n/a",TEXT(Estimates!D154,"0.000")&IF(Estimates!H154<0.01,"***",IF(Estimates!H154<0.05,"**",IF(Estimates!H154<0.1,"*","")))) -> -0.040 | E70: =IF(Estimates!H155="","n/a",TEXT(Estimates!D155,"0.000")&IF(Estimates!H155<0.01,"***",IF(Estimates!H155<0.05,"**",IF(Estimates!H155<0.1,"*","")))) -> 0.011 | F70: =IF(Estimates!H156="","n/a",TEXT(Estimates!D156,"0.000")&IF(Estimates!H156<0.01,"***",IF(Estimates!H156<0.05,"**",IF(Estimates!H156<0.1,"*","")))) -> 0.025 | G70: =IF(Estimates!H157="","n/a",TEXT(Estimates!D157,"0.000")&IF(Estimates!H157<0.01,"***",IF(Estimates!H157<0.05,"**",IF(Estimates!H157<0.1,"*","")))) -> 0.026
B71: =IF(Estimates!G152="","","("&TEXT(Estimates!G152,"0.00")&")") -> (-1.23) | C71: =IF(Estimates!G153="","","("&TEXT(Estimates!G153,"0.00")&")") -> (-0.04) | D71: =IF(Estimates!G154="","","("&TEXT(Estimates!G154,"0.00")&")") -> (-0.23) | E71: =IF(Estimates!G155="","","("&TEXT(Estimates!G155,"0.00")&")") -> (0.06) | F71: =IF(Estimates!G156="","","("&TEXT(Estimates!G156,"0.00")&")") -> (0.23) | G71: =IF(Estimates!G157="","","("&TEXT(Estimates!G157,"0.00")&")") -> (0.25)
A72: Hedge Fund Allocation (%) | B72: =IF(Estimates!H158="","n/a",TEXT(Estimates!D158,"0.000")&IF(Estimates!H158<0.01,"***",IF(Estimates!H158<0.05,"**",IF(Estimates!H158<0.1,"*","")))) -> -0.164 | C72: =IF(Estimates!H159="","n/a",TEXT(Estimates!D159,"0.000")&IF(Estimates!H159<0.01,"***",IF(Estimates!H159<0.05,"**",IF(Estimates!H159<0.1,"*","")))) -> -0.009 | D72: =IF(Estimates!H160="","n/a",TEXT(Estimates!D160,"0.000")&IF(Estimates!H160<0.01,"***",IF(Estimates!H160<0.05,"**",IF(Estimates!H160<0.1,"*","")))) -> -0.023 | E72: =IF(Estimates!H161="","n/a",TEXT(Estimates!D161,"0.000")&IF(Estimates!H161<0.01,"***",IF(Estimates!H161<0.05,"**",IF(Estimates!H161<0.1,"*","")))) -> -0.004 | F72: =IF(Estimates!H162="","n/a",TEXT(Estimates!D162,"0.000")&IF(Estimates!H162<0.01,"***",IF(Estimates!H162<0.05,"**",IF(Estimates!H162<0.1,"*","")))) -> 0.022 | G72: =IF(Estimates!H163="","n/a",TEXT(Estimates!D163,"0.000")&IF(Estimates!H163<0.01,"***",IF(Estimates!H163<0.05,"**",IF(Estimates!H163<0.1,"*","")))) -> 0.024
B73: =IF(Estimates!G158="","","("&TEXT(Estimates!G158,"0.00")&")") -> (-1.28) | C73: =IF(Estimates!G159="","","("&TEXT(Estimates!G159,"0.00")&")") -> (-0.08) | D73: =IF(Estimates!G160="","","("&TEXT(Estimates!G160,"0.00")&")") -> (-0.13) | E73: =IF(Estimates!G161="","","("&TEXT(Estimates!G161,"0.00")&")") -> (-0.02) | F73: =IF(Estimates!G162="","","("&TEXT(Estimates!G162,"0.00")&")") -> (0.20) | G73: =IF(Estimates!G163="","","("&TEXT(Estimates!G163,"0.00")&")") -> (0.22)
A74: Misc. Alternatives Allocation (%) | B74: =IF(Estimates!H164="","n/a",TEXT(Estimates!D164,"0.000")&IF(Estimates!H164<0.01,"***",IF(Estimates!H164<0.05,"**",IF(Estimates!H164<0.1,"*","")))) -> -0.182 | C74: =IF(Estimates!H165="","n/a",TEXT(Estimates!D165,"0.000")&IF(Estimates!H165<0.01,"***",IF(Estimates!H165<0.05,"**",IF(Estimates!H165<0.1,"*","")))) -> -0.019 | D74: =IF(Estimates!H166="","n/a",TEXT(Estimates!D166,"0.000")&IF(Estimates!H166<0.01,"***",IF(Estimates!H166<0.05,"**",IF(Estimates!H166<0.1,"*","")))) -> -0.040 | E74: =IF(Estimates!H167="","n/a",TEXT(Estimates!D167,"0.000")&IF(Estimates!H167<0.01,"***",IF(Estimates!H167<0.05,"**",IF(Estimates!H167<0.1,"*","")))) -> 0.017 | F74: =IF(Estimates!H168="","n/a",TEXT(Estimates!D168,"0.000")&IF(Estimates!H168<0.01,"***",IF(Estimates!H168<0.05,"**",IF(Estimates!H168<0.1,"*","")))) -> 0.011 | G74: =IF(Estimates!H169="","n/a",TEXT(Estimates!D169,"0.000")&IF(Estimates!H169<0.01,"***",IF(Estimates!H169<0.05,"**",IF(Estimates!H169<0.1,"*","")))) -> 0.013
B75: =IF(Estimates!G164="","","("&TEXT(Estimates!G164,"0.00")&")") -> (-1.46) | C75: =IF(Estimates!G165="","","("&TEXT(Estimates!G165,"0.00")&")") -> (-0.17) | D75: =IF(Estimates!G166="","","("&TEXT(Estimates!G166,"0.00")&")") -> (-0.22) | E75: =IF(Estimates!G167="","","("&TEXT(Estimates!G167,"0.00")&")") -> (0.09) | F75: =IF(Estimates!G168="","","("&TEXT(Estimates!G168,"0.00")&")") -> (0.10) | G75: =IF(Estimates!G169="","","("&TEXT(Estimates!G169,"0.00")&")") -> (0.12)
A76: Commodities Allocation (%) | B76: =IF(Estimates!H170="","n/a",TEXT(Estimates!D170,"0.000")&IF(Estimates!H170<0.01,"***",IF(Estimates!H170<0.05,"**",IF(Estimates!H170<0.1,"*","")))) -> -0.201 | C76: =IF(Estimates!H171="","n/a",TEXT(Estimates!D171,"0.000")&IF(Estimates!H171<0.01,"***",IF(Estimates!H171<0.05,"**",IF(Estimates!H171<0.1,"*","")))) -> -0.028 | D76: =IF(Estimates!H172="","n/a",TEXT(Estimates!D172,"0.000")&IF(Estimates!H172<0.01,"***",IF(Estimates!H172<0.05,"**",IF(Estimates!H172<0.1,"*","")))) -> -0.048 | E76: =IF(Estimates!H173="","n/a",TEXT(Estimates!D173,"0.000")&IF(Estimates!H173<0.01,"***",IF(Estimates!H173<0.05,"**",IF(Estimates!H173<0.1,"*","")))) -> -0.015 | F76: =IF(Estimates!H174="","n/a",TEXT(Estimates!D174,"0.000")&IF(Estimates!H174<0.01,"***",IF(Estimates!H174<0.05,"**",IF(Estimates!H174<0.1,"*","")))) -> 0.002 | G76: =IF(Estimates!H175="","n/a",TEXT(Estimates!D175,"0.000")&IF(Estimates!H175<0.01,"***",IF(Estimates!H175<0.05,"**",IF(Estimates!H175<0.1,"*","")))) -> 0.002
B77: =IF(Estimates!G170="","","("&TEXT(Estimates!G170,"0.00")&")") -> (-1.47) | C77: =IF(Estimates!G171="","","("&TEXT(Estimates!G171,"0.00")&")") -> (-0.24) | D77: =IF(Estimates!G172="","","("&TEXT(Estimates!G172,"0.00")&")") -> (-0.26) | E77: =IF(Estimates!G173="","","("&TEXT(Estimates!G173,"0.00")&")") -> (-0.08) | F77: =IF(Estimates!G174="","","("&TEXT(Estimates!G174,"0.00")&")") -> (0.02) | G77: =IF(Estimates!G175="","","("&TEXT(Estimates!G175,"0.00")&")") -> (0.02)
A78: Cash Allocation (%) | B78: =IF(Estimates!H176="","n/a",TEXT(Estimates!D176,"0.000")&IF(Estimates!H176<0.01,"***",IF(Estimates!H176<0.05,"**",IF(Estimates!H176<0.1,"*","")))) -> -0.130 | C78: =IF(Estimates!H177="","n/a",TEXT(Estimates!D177,"0.000")&IF(Estimates!H177<0.01,"***",IF(Estimates!H177<0.05,"**",IF(Estimates!H177<0.1,"*","")))) -> 0.014 | D78: =IF(Estimates!H178="","n/a",TEXT(Estimates!D178,"0.000")&IF(Estimates!H178<0.01,"***",IF(Estimates!H178<0.05,"**",IF(Estimates!H178<0.1,"*","")))) -> 0.021 | E78: =IF(Estimates!H179="","n/a",TEXT(Estimates!D179,"0.000")&IF(Estimates!H179<0.01,"***",IF(Estimates!H179<0.05,"**",IF(Estimates!H179<0.1,"*","")))) -> 0.048 | F78: =IF(Estimates!H180="","n/a",TEXT(Estimates!D180,"0.000")&IF(Estimates!H180<0.01,"***",IF(Estimates!H180<0.05,"**",IF(Estimates!H180<0.1,"*","")))) -> 0.048 | G78: =IF(Estimates!H181="","n/a",TEXT(Estimates!D181,"0.000")&IF(Estimates!H181<0.01,"***",IF(Estimates!H181<0.05,"**",IF(Estimates!H181<0.1,"*","")))) -> 0.048
B79: =IF(Estimates!G176="","","("&TEXT(Estimates!G176,"0.00")&")") -> (-0.89) | C79: =IF(Estimates!G177="","","("&TEXT(Estimates!G177,"0.00")&")") -> (0.11) | D79: =IF(Estimates!G178="","","("&TEXT(Estimates!G178,"0.00")&")") -> (0.11) | E79: =IF(Estimates!G179="","","("&TEXT(Estimates!G179,"0.00")&")") -> (0.26) | F79: =IF(Estimates!G180="","","("&TEXT(Estimates!G180,"0.00")&")") -> (0.38) | G79: =IF(Estimates!G181="","","("&TEXT(Estimates!G181,"0.00")&")") -> (0.38)
A80: Financial Center (0/1) | B80: =IF(Estimates!H182="","n/a",TEXT(Estimates!D182,"0.000")&IF(Estimates!H182<0.01,"***",IF(Estimates!H182<0.05,"**",IF(Estimates!H182<0.1,"*","")))) -> -0.129* | C80: =IF(Estimates!H183="","n/a",TEXT(Estimates!D183,"0.000")&IF(Estimates!H183<0.01,"***",IF(Estimates!H183<0.05,"**",IF(Estimates!H183<0.1,"*","")))) -> -0.135* | F80: =IF(Estimates!H184="","n/a",TEXT(Estimates!D184,"0.000")&IF(Estimates!H184<0.01,"***",IF(Estimates!H184<0.05,"**",IF(Estimates!H184<0.1,"*","")))) -> -0.122 | G80: =IF(Estimates!H185="","n/a",TEXT(Estimates!D185,"0.000")&IF(Estimates!H185<0.01,"***",IF(Estimates!H185<0.05,"**",IF(Estimates!H185<0.1,"*","")))) -> -0.136*
B81: =IF(Estimates!G182="","","("&TEXT(Estimates!G182,"0.00")&")") -> (-2.03) | C81: =IF(Estimates!G183="","","("&TEXT(Estimates!G183,"0.00")&")") -> (-1.87) | F81: =IF(Estimates!G184="","","("&TEXT(Estimates!G184,"0.00")&")") -> (-1.72) | G81: =IF(Estimates!G185="","","("&TEXT(Estimates!G185,"0.00")&")") -> (-1.92)
A82: Log (CIO Age) (t-1) | C82: =IF(Estimates!H186="","n/a",TEXT(Estimates!D186,"0.000")&IF(Estimates!H186<0.01,"***",IF(Estimates!H186<0.05,"**",IF(Estimates!H186<0.1,"*","")))) -> -1.220*** | D82: =IF(Estimates!H187="","n/a",TEXT(Estimates!D187,"0.000")&IF(Estimates!H187<0.01,"***",IF(Estimates!H187<0.05,"**",IF(Estimates!H187<0.1,"*","")))) -> -0.221 | E82: =IF(Estimates!H188="","n/a",TEXT(Estimates!D188,"0.000")&IF(Estimates!H188<0.01,"***",IF(Estimates!H188<0.05,"**",IF(Estimates!H188<0.1,"*","")))) -> 0.117 | F82: =IF(Estimates!H189="","n/a",TEXT(Estimates!D189,"0.000")&IF(Estimates!H189<0.01,"***",IF(Estimates!H189<0.05,"**",IF(Estimates!H189<0.1,"*","")))) -> -1.123** | G82: =IF(Estimates!H190="","n/a",TEXT(Estimates!D190,"0.000")&IF(Estimates!H190<0.01,"***",IF(Estimates!H190<0.05,"**",IF(Estimates!H190<0.1,"*","")))) -> -1.164***
C83: =IF(Estimates!G186="","","("&TEXT(Estimates!G186,"0.00")&")") -> (-3.25) | D83: =IF(Estimates!G187="","","("&TEXT(Estimates!G187,"0.00")&")") -> (-0.31) | E83: =IF(Estimates!G188="","","("&TEXT(Estimates!G188,"0.00")&")") -> (0.16) | F83: =IF(Estimates!G189="","","("&TEXT(Estimates!G189,"0.00")&")") -> (-2.79) | G83: =IF(Estimates!G190="","","("&TEXT(Estimates!G190,"0.00")&")") -> (-2.89)
A84: Log (CIO Tenure) (t-1) | C84: =IF(Estimates!H191="","n/a",TEXT(Estimates!D191,"0.000")&IF(Estimates!H191<0.01,"***",IF(Estimates!H191<0.05,"**",IF(Estimates!H191<0.1,"*","")))) -> -0.001 | D84: =IF(Estimates!H192="","n/a",TEXT(Estimates!D192,"0.000")&IF(Estimates!H192<0.01,"***",IF(Estimates!H192<0.05,"**",IF(Estimates!H192<0.1,"*","")))) -> -0.044 | E84: =IF(Estimates!H193="","n/a",TEXT(Estimates!D193,"0.000")&IF(Estimates!H193<0.01,"***",IF(Estimates!H193<0.05,"**",IF(Estimates!H193<0.1,"*","")))) -> -0.149 | F84: =IF(Estimates!H194="","n/a",TEXT(Estimates!D194,"0.000")&IF(Estimates!H194<0.01,"***",IF(Estimates!H194<0.05,"**",IF(Estimates!H194<0.1,"*","")))) -> 0.015 | G84: =IF(Estimates!H195="","n/a",TEXT(Estimates!D195,"0.000")&IF(Estimates!H195<0.01,"***",IF(Estimates!H195<0.05,"**",IF(Estimates!H195<0.1,"*","")))) -> 0.015
C85: =IF(Estimates!G191="","","("&TEXT(Estimates!G191,"0.00")&")") -> (-0.01) | D85: =IF(Estimates!G192="","","("&TEXT(Estimates!G192,"0.00")&")") -> (-0.40) | E85: =IF(Estimates!G193="","","("&TEXT(Estimates!G193,"0.00")&")") -> (-1.26) | F85: =IF(Estimates!G194="","","("&TEXT(Estimates!G194,"0.00")&")") -> (0.16) | G85: =IF(Estimates!G195="","","("&TEXT(Estimates!G195,"0.00")&")") -> (0.15)
A86: CIO Prior Private Experience (0/1) | C86: =IF(Estimates!H196="","n/a",TEXT(Estimates!D196,"0.000")&IF(Estimates!H196<0.01,"***",IF(Estimates!H196<0.05,"**",IF(Estimates!H196<0.1,"*","")))) -> 0.116 | D86: =IF(Estimates!H197="","n/a",TEXT(Estimates!D197,"0.000")&IF(Estimates!H197<0.01,"***",IF(Estimates!H197<0.05,"**",IF(Estimates!H197<0.1,"*","")))) -> 0.127 | E86: =IF(Estimates!H198="","n/a",TEXT(Estimates!D198,"0.000")&IF(Estimates!H198<0.01,"***",IF(Estimates!H198<0.05,"**",IF(Estimates!H198<0.1,"*","")))) -> 0.102 | F86: =IF(Estimates!H199="","n/a",TEXT(Estimates!D199,"0.000")&IF(Estimates!H199<0.01,"***",IF(Estimates!H199<0.05,"**",IF(Estimates!H199<0.1,"*","")))) -> 0.019 | G86: =IF(Estimates!H200="","n/a",TEXT(Estimates!D200,"0.000")&IF(Estimates!H200<0.01,"***",IF(Estimates!H200<0.05,"**",IF(Estimates!H200<0.1,"*","")))) -> 0.050
C87: =IF(Estimates!G196="","","("&TEXT(Estimates!G196,"0.00")&")") -> (1.09) | D87: =IF(Estimates!G197="","","("&TEXT(Estimates!G197,"0.00")&")") -> (0.62) | E87: =IF(Estimates!G198="","","("&TEXT(Estimates!G198,"0.00")&")") -> (0.46) | F87: =IF(Estimates!G199="","","("&TEXT(Estimates!G199,"0.00")&")") -> (0.16) | G87: =IF(Estimates!G200="","","("&TEXT(Estimates!G200,"0.00")&")") -> (0.42)
A88: CIO Attended Elite College (0/1) | C88: =IF(Estimates!H201="","n/a",TEXT(Estimates!D201,"0.000")&IF(Estimates!H201<0.01,"***",IF(Estimates!H201<0.05,"**",IF(Estimates!H201<0.1,"*","")))) -> -0.162 | D88: =IF(Estimates!H202="","n/a",TEXT(Estimates!D202,"0.000")&IF(Estimates!H202<0.01,"***",IF(Estimates!H202<0.05,"**",IF(Estimates!H202<0.1,"*","")))) -> 0.120 | E88: =IF(Estimates!H203="","n/a",TEXT(Estimates!D203,"0.000")&IF(Estimates!H203<0.01,"***",IF(Estimates!H203<0.05,"**",IF(Estimates!H203<0.1,"*","")))) -> -0.008 | F88: =IF(Estimates!H204="","n/a",TEXT(Estimates!D204,"0.000")&IF(Estimates!H204<0.01,"***",IF(Estimates!H204<0.05,"**",IF(Estimates!H204<0.1,"*","")))) -> -0.122 | G88: =IF(Estimates!H205="","n/a",TEXT(Estimates!D205,"0.000")&IF(Estimates!H205<0.01,"***",IF(Estimates!H205<0.05,"**",IF(Estimates!H205<0.1,"*","")))) -> -0.131
C89: =IF(Estimates!G201="","","("&TEXT(Estimates!G201,"0.00")&")") -> (-1.15) | D89: =IF(Estimates!G202="","","("&TEXT(Estimates!G202,"0.00")&")") -> (0.64) | E89: =IF(Estimates!G203="","","("&TEXT(Estimates!G203,"0.00")&")") -> (-0.04) | F89: =IF(Estimates!G204="","","("&TEXT(Estimates!G204,"0.00")&")") -> (-0.89) | G89: =IF(Estimates!G205="","","("&TEXT(Estimates!G205,"0.00")&")") -> (-0.95)
A90: Separate Investment Board (0/1) | C90: =IF(Estimates!H206="","n/a",TEXT(Estimates!D206,"0.000")&IF(Estimates!H206<0.01,"***",IF(Estimates!H206<0.05,"**",IF(Estimates!H206<0.1,"*","")))) -> 0.308* | D90: =IF(Estimates!H207="","n/a",TEXT(Estimates!D207,"0.000")&IF(Estimates!H207<0.01,"***",IF(Estimates!H207<0.05,"**",IF(Estimates!H207<0.1,"*","")))) -> -0.075 | E90: =IF(Estimates!H208="","n/a",TEXT(Estimates!D208,"0.000")&IF(Estimates!H208<0.01,"***",IF(Estimates!H208<0.05,"**",IF(Estimates!H208<0.1,"*","")))) -> 0.494 | F90: =IF(Estimates!H209="","n/a",TEXT(Estimates!D209,"0.000")&IF(Estimates!H209<0.01,"***",IF(Estimates!H209<0.05,"**",IF(Estimates!H209<0.1,"*","")))) -> 0.315* | G90: =IF(Estimates!H210="","n/a",TEXT(Estimates!D210,"0.000")&IF(Estimates!H210<0.01,"***",IF(Estimates!H210<0.05,"**",IF(Estimates!H210<0.1,"*","")))) -> 0.310*
C91: =IF(Estimates!G206="","","("&TEXT(Estimates!G206,"0.00")&")") -> (1.85) | D91: =IF(Estimates!G207="","","("&TEXT(Estimates!G207,"0.00")&")") -> (-0.08) | E91: =IF(Estimates!G208="","","("&TEXT(Estimates!G208,"0.00")&")") -> (0.65) | F91: =IF(Estimates!G209="","","("&TEXT(Estimates!G209,"0.00")&")") -> (1.92) | G91: =IF(Estimates!G210="","","("&TEXT(Estimates!G210,"0.00")&")") -> (1.87)
A92: % Political Appointees on Board | C92: =IF(Estimates!H211="","n/a",TEXT(Estimates!D211,"0.000")&IF(Estimates!H211<0.01,"***",IF(Estimates!H211<0.05,"**",IF(Estimates!H211<0.1,"*","")))) -> 0.008 | D92: =IF(Estimates!H212="","n/a",TEXT(Estimates!D212,"0.000")&IF(Estimates!H212<0.01,"***",IF(Estimates!H212<0.05,"**",IF(Estimates!H212<0.1,"*","")))) -> 0.373 | E92: =IF(Estimates!H213="","n/a",TEXT(Estimates!D213,"0.000")&IF(Estimates!H213<0.01,"***",IF(Estimates!H213<0.05,"**",IF(Estimates!H213<0.1,"*","")))) -> -0.312 | F92: =IF(Estimates!H214="","n/a",TEXT(Estimates!D214,"0.000")&IF(Estimates!H214<0.01,"***",IF(Estimates!H214<0.05,"**",IF(Estimates!H214<0.1,"*","")))) -> -0.007 | G92: =IF(Estimates!H215="","n/a",TEXT(Estimates!D215,"0.000")&IF(Estimates!H215<0.01,"***",IF(Estimates!H215<0.05,"**",IF(Estimates!H215<0.1,"*","")))) -> 0.000
C93: =IF(Estimates!G211="","","("&TEXT(Estimates!G211,"0.00")&")") -> (0.04) | D93: =IF(Estimates!G212="","","("&TEXT(Estimates!G212,"0.00")&")") -> (0.23) | E93: =IF(Estimates!G213="","","("&TEXT(Estimates!G213,"0.00")&")") -> (-0.23) | F93: =IF(Estimates!G214="","","("&TEXT(Estimates!G214,"0.00")&")") -> (-0.03) | G93: =IF(Estimates!G215="","","("&TEXT(Estimates!G215,"0.00")&")") -> (0.00)
A95: Observations | B95: 1538 | C95: 1320 | D95: 1319 | E95: 1319 | F95: 1320 | G95: 1320
A96: Adjusted R-squared | B96: 0.11853027 | C96: 0.12765408 | D96: 0.020739289 | E96: 0.12215393 | F96: 0.12484178 | G96: 0.12619652
A97: Plan FE | B97: No | C97: No | D97: Yes | E97: Yes | F97: No | G97: No
A98: Year FE | B98: Yes | C98: Yes | D98: No | E98: Yes | F98: Yes | G98: Yes
A99: Last n years | F99: 5 | G99: 10

Sheet Benchmark versions
A1: Conflicted CIO coefficient in Table III under alternative benchmark-adjusted returns (same specifications as Table III columns 1-6)
A2: Each row re-estimates the six Table III columns with a different dependent variable; only the Conflicted CIO coefficient is shown, with all controls, fixed effects and clustering as in Table III. 'PPD return' is the plan's investment return in the Public Plans Database (the return used in the paper). 'Document return' is the total-fund return reported on the same page of the plan's financial report as the policy benchmark. 'Reported' benchmarks are stated in the report; 'inferred grade A/B' adds benchmark returns inferred from multi-year benchmark returns or from policy weights and component index returns, using only estimates graded A or B. The row marked 'agree within 0.5 pp' keeps only plan-years in which the PPD and document returns differ by at most 0.5 percentage points, removing fiscal-year misalignments between the two sources.
A4: Dependent variable | B4: (1) | C4: (2) | D4: (3) | E4: (4) | F4: (5) | G4: (6)
A5: Peer-adjusted return (Panel A, unchanged) | B5: =IF(Estimates!H216="","n/a",TEXT(Estimates!D216,"0.000")&IF(Estimates!H216<0.01,"***",IF(Estimates!H216<0.05,"**",IF(Estimates!H216<0.1,"*","")))) -> -0.557*** | C5: =IF(Estimates!H217="","n/a",TEXT(Estimates!D217,"0.000")&IF(Estimates!H217<0.01,"***",IF(Estimates!H217<0.05,"**",IF(Estimates!H217<0.1,"*","")))) -> -0.582*** | D5: =IF(Estimates!H218="","n/a",TEXT(Estimates!D218,"0.000")&IF(Estimates!H218<0.01,"***",IF(Estimates!H218<0.05,"**",IF(Estimates!H218<0.1,"*","")))) -> -0.641** | E5: =IF(Estimates!H219="","n/a",TEXT(Estimates!D219,"0.000")&IF(Estimates!H219<0.01,"***",IF(Estimates!H219<0.05,"**",IF(Estimates!H219<0.1,"*","")))) -> -0.698** | F5: =IF(Estimates!H220="","n/a",TEXT(Estimates!D220,"0.000")&IF(Estimates!H220<0.01,"***",IF(Estimates!H220<0.05,"**",IF(Estimates!H220<0.1,"*","")))) -> -0.475* | G5: =IF(Estimates!H221="","n/a",TEXT(Estimates!D221,"0.000")&IF(Estimates!H221<0.01,"***",IF(Estimates!H221<0.05,"**",IF(Estimates!H221<0.1,"*","")))) -> -0.508**
B6: =IF(Estimates!G216="","","("&TEXT(Estimates!G216,"0.00")&")") -> (-3.68) | C6: =IF(Estimates!G217="","","("&TEXT(Estimates!G217,"0.00")&")") -> (-3.13) | D6: =IF(Estimates!G218="","","("&TEXT(Estimates!G218,"0.00")&")") -> (-2.21) | E6: =IF(Estimates!G219="","","("&TEXT(Estimates!G219,"0.00")&")") -> (-2.38) | F6: =IF(Estimates!G220="","","("&TEXT(Estimates!G220,"0.00")&")") -> (-2.10) | G6: =IF(Estimates!G221="","","("&TEXT(Estimates!G221,"0.00")&")") -> (-2.78)
A7: Observations | B7: 1727 | C7: 1483 | D7: 1482 | E7: 1482 | F7: 1483 | G7: 1483
A8: Original benchmark-adjusted return (paper Panel B) | B8: =IF(Estimates!H222="","n/a",TEXT(Estimates!D222,"0.000")&IF(Estimates!H222<0.01,"***",IF(Estimates!H222<0.05,"**",IF(Estimates!H222<0.1,"*","")))) -> -0.518** | C8: =IF(Estimates!H223="","n/a",TEXT(Estimates!D223,"0.000")&IF(Estimates!H223<0.01,"***",IF(Estimates!H223<0.05,"**",IF(Estimates!H223<0.1,"*","")))) -> -0.598*** | D8: =IF(Estimates!H224="","n/a",TEXT(Estimates!D224,"0.000")&IF(Estimates!H224<0.01,"***",IF(Estimates!H224<0.05,"**",IF(Estimates!H224<0.1,"*","")))) -> -0.959** | E8: =IF(Estimates!H225="","n/a",TEXT(Estimates!D225,"0.000")&IF(Estimates!H225<0.01,"***",IF(Estimates!H225<0.05,"**",IF(Estimates!H225<0.1,"*","")))) -> -0.889* | F8: =IF(Estimates!H226="","n/a",TEXT(Estimates!D226,"0.000")&IF(Estimates!H226<0.01,"***",IF(Estimates!H226<0.05,"**",IF(Estimates!H226<0.1,"*","")))) -> -0.596* | G8: =IF(Estimates!H227="","n/a",TEXT(Estimates!D227,"0.000")&IF(Estimates!H227<0.01,"***",IF(Estimates!H227<0.05,"**",IF(Estimates!H227<0.1,"*","")))) -> -0.611**
B9: =IF(Estimates!G222="","","("&TEXT(Estimates!G222,"0.00")&")") -> (-2.65) | C9: =IF(Estimates!G223="","","("&TEXT(Estimates!G223,"0.00")&")") -> (-3.19) | D9: =IF(Estimates!G224="","","("&TEXT(Estimates!G224,"0.00")&")") -> (-2.23) | E9: =IF(Estimates!G225="","","("&TEXT(Estimates!G225,"0.00")&")") -> (-2.09) | F9: =IF(Estimates!G226="","","("&TEXT(Estimates!G226,"0.00")&")") -> (-1.87) | G9: =IF(Estimates!G227="","","("&TEXT(Estimates!G227,"0.00")&")") -> (-2.24)
A10: Observations | B10: 1240 | C10: 1072 | D10: 1069 | E10: 1069 | F10: 1072 | G10: 1072
A11: PPD return minus updated reported benchmark | B11: =IF(Estimates!H228="","n/a",TEXT(Estimates!D228,"0.000")&IF(Estimates!H228<0.01,"***",IF(Estimates!H228<0.05,"**",IF(Estimates!H228<0.1,"*","")))) -> -0.393** | C11: =IF(Estimates!H229="","n/a",TEXT(Estimates!D229,"0.000")&IF(Estimates!H229<0.01,"***",IF(Estimates!H229<0.05,"**",IF(Estimates!H229<0.1,"*","")))) -> -0.434*** | D11: =IF(Estimates!H230="","n/a",TEXT(Estimates!D230,"0.000")&IF(Estimates!H230<0.01,"***",IF(Estimates!H230<0.05,"**",IF(Estimates!H230<0.1,"*","")))) -> -0.319* | E11: =IF(Estimates!H231="","n/a",TEXT(Estimates!D231,"0.000")&IF(Estimates!H231<0.01,"***",IF(Estimates!H231<0.05,"**",IF(Estimates!H231<0.1,"*","")))) -> -0.333** | F11: =IF(Estimates!H232="","n/a",TEXT(Estimates!D232,"0.000")&IF(Estimates!H232<0.01,"***",IF(Estimates!H232<0.05,"**",IF(Estimates!H232<0.1,"*","")))) -> -0.380* | G11: =IF(Estimates!H233="","n/a",TEXT(Estimates!D233,"0.000")&IF(Estimates!H233<0.01,"***",IF(Estimates!H233<0.05,"**",IF(Estimates!H233<0.1,"*","")))) -> -0.424**
B12: =IF(Estimates!G228="","","("&TEXT(Estimates!G228,"0.00")&")") -> (-2.49) | C12: =IF(Estimates!G229="","","("&TEXT(Estimates!G229,"0.00")&")") -> (-4.12) | D12: =IF(Estimates!G230="","","("&TEXT(Estimates!G230,"0.00")&")") -> (-1.92) | E12: =IF(Estimates!G231="","","("&TEXT(Estimates!G231,"0.00")&")") -> (-2.12) | F12: =IF(Estimates!G232="","","("&TEXT(Estimates!G232,"0.00")&")") -> (-1.92) | G12: =IF(Estimates!G233="","","("&TEXT(Estimates!G233,"0.00")&")") -> (-2.42)
A13: Observations | B13: 1453 | C13: 1249 | D13: 1248 | E13: 1248 | F13: 1249 | G13: 1249
A14: PPD return minus updated benchmark (reported + inferred grade A/B) | B14: =IF(Estimates!H234="","n/a",TEXT(Estimates!D234,"0.000")&IF(Estimates!H234<0.01,"***",IF(Estimates!H234<0.05,"**",IF(Estimates!H234<0.1,"*","")))) -> -0.385** | C14: =IF(Estimates!H235="","n/a",TEXT(Estimates!D235,"0.000")&IF(Estimates!H235<0.01,"***",IF(Estimates!H235<0.05,"**",IF(Estimates!H235<0.1,"*","")))) -> -0.491*** | D14: =IF(Estimates!H236="","n/a",TEXT(Estimates!D236,"0.000")&IF(Estimates!H236<0.01,"***",IF(Estimates!H236<0.05,"**",IF(Estimates!H236<0.1,"*","")))) -> -0.373** | E14: =IF(Estimates!H237="","n/a",TEXT(Estimates!D237,"0.000")&IF(Estimates!H237<0.01,"***",IF(Estimates!H237<0.05,"**",IF(Estimates!H237<0.1,"*","")))) -> -0.411** | F14: =IF(Estimates!H238="","n/a",TEXT(Estimates!D238,"0.000")&IF(Estimates!H238<0.01,"***",IF(Estimates!H238<0.05,"**",IF(Estimates!H238<0.1,"*","")))) -> -0.384* | G14: =IF(Estimates!H239="","n/a",TEXT(Estimates!D239,"0.000")&IF(Estimates!H239<0.01,"***",IF(Estimates!H239<0.05,"**",IF(Estimates!H239<0.1,"*","")))) -> -0.441**
B15: =IF(Estimates!G234="","","("&TEXT(Estimates!G234,"0.00")&")") -> (-2.46) | C15: =IF(Estimates!G235="","","("&TEXT(Estimates!G235,"0.00")&")") -> (-4.15) | D15: =IF(Estimates!G236="","","("&TEXT(Estimates!G236,"0.00")&")") -> (-2.23) | E15: =IF(Estimates!G237="","","("&TEXT(Estimates!G237,"0.00")&")") -> (-2.15) | F15: =IF(Estimates!G238="","","("&TEXT(Estimates!G238,"0.00")&")") -> (-1.84) | G15: =IF(Estimates!G239="","","("&TEXT(Estimates!G239,"0.00")&")") -> (-2.36)
A16: Observations | B16: 1538 | C16: 1320 | D16: 1319 | E16: 1319 | F16: 1320 | G16: 1320
A17: PPD return minus updated benchmark (A/B), rows where PPD and document returns agree within 0.5 pp | B17: =IF(Estimates!H240="","n/a",TEXT(Estimates!D240,"0.000")&IF(Estimates!H240<0.01,"***",IF(Estimates!H240<0.05,"**",IF(Estimates!H240<0.1,"*","")))) -> -0.411** | C17: =IF(Estimates!H241="","n/a",TEXT(Estimates!D241,"0.000")&IF(Estimates!H241<0.01,"***",IF(Estimates!H241<0.05,"**",IF(Estimates!H241<0.1,"*","")))) -> -0.535*** | D17: =IF(Estimates!H242="","n/a",TEXT(Estimates!D242,"0.000")&IF(Estimates!H242<0.01,"***",IF(Estimates!H242<0.05,"**",IF(Estimates!H242<0.1,"*","")))) -> -0.457*** | E17: =IF(Estimates!H243="","n/a",TEXT(Estimates!D243,"0.000")&IF(Estimates!H243<0.01,"***",IF(Estimates!H243<0.05,"**",IF(Estimates!H243<0.1,"*","")))) -> -0.409** | F17: =IF(Estimates!H244="","n/a",TEXT(Estimates!D244,"0.000")&IF(Estimates!H244<0.01,"***",IF(Estimates!H244<0.05,"**",IF(Estimates!H244<0.1,"*","")))) -> -0.403* | G17: =IF(Estimates!H245="","n/a",TEXT(Estimates!D245,"0.000")&IF(Estimates!H245<0.01,"***",IF(Estimates!H245<0.05,"**",IF(Estimates!H245<0.1,"*","")))) -> -0.462**
B18: =IF(Estimates!G240="","","("&TEXT(Estimates!G240,"0.00")&")") -> (-2.70) | C18: =IF(Estimates!G241="","","("&TEXT(Estimates!G241,"0.00")&")") -> (-4.41) | D18: =IF(Estimates!G242="","","("&TEXT(Estimates!G242,"0.00")&")") -> (-3.11) | E18: =IF(Estimates!G243="","","("&TEXT(Estimates!G243,"0.00")&")") -> (-2.36) | F18: =IF(Estimates!G244="","","("&TEXT(Estimates!G244,"0.00")&")") -> (-1.94) | G18: =IF(Estimates!G245="","","("&TEXT(Estimates!G245,"0.00")&")") -> (-2.51)
A19: Observations | B19: 1502 | C19: 1286 | D19: 1284 | E19: 1284 | F19: 1286 | G19: 1286
A20: Document return minus updated benchmark (reported + inferred grade A/B) | B20: =IF(Estimates!H246="","n/a",TEXT(Estimates!D246,"0.000")&IF(Estimates!H246<0.01,"***",IF(Estimates!H246<0.05,"**",IF(Estimates!H246<0.1,"*","")))) -> -0.404** | C20: =IF(Estimates!H247="","n/a",TEXT(Estimates!D247,"0.000")&IF(Estimates!H247<0.01,"***",IF(Estimates!H247<0.05,"**",IF(Estimates!H247<0.1,"*","")))) -> -0.503*** | D20: =IF(Estimates!H248="","n/a",TEXT(Estimates!D248,"0.000")&IF(Estimates!H248<0.01,"***",IF(Estimates!H248<0.05,"**",IF(Estimates!H248<0.1,"*","")))) -> -0.320** | E20: =IF(Estimates!H249="","n/a",TEXT(Estimates!D249,"0.000")&IF(Estimates!H249<0.01,"***",IF(Estimates!H249<0.05,"**",IF(Estimates!H249<0.1,"*","")))) -> -0.357* | F20: =IF(Estimates!H250="","n/a",TEXT(Estimates!D250,"0.000")&IF(Estimates!H250<0.01,"***",IF(Estimates!H250<0.05,"**",IF(Estimates!H250<0.1,"*","")))) -> -0.390* | G20: =IF(Estimates!H251="","n/a",TEXT(Estimates!D251,"0.000")&IF(Estimates!H251<0.01,"***",IF(Estimates!H251<0.05,"**",IF(Estimates!H251<0.1,"*","")))) -> -0.445**
B21: =IF(Estimates!G246="","","("&TEXT(Estimates!G246,"0.00")&")") -> (-2.63) | C21: =IF(Estimates!G247="","","("&TEXT(Estimates!G247,"0.00")&")") -> (-4.21) | D21: =IF(Estimates!G248="","","("&TEXT(Estimates!G248,"0.00")&")") -> (-2.11) | E21: =IF(Estimates!G249="","","("&TEXT(Estimates!G249,"0.00")&")") -> (-2.06) | F21: =IF(Estimates!G250="","","("&TEXT(Estimates!G250,"0.00")&")") -> (-1.90) | G21: =IF(Estimates!G251="","","("&TEXT(Estimates!G251,"0.00")&")") -> (-2.47)
A22: Observations | B22: 1538 | C22: 1320 | D22: 1319 | E22: 1319 | F22: 1320 | G22: 1320
A23: Plan FE | B23: No | C23: No | D23: Yes | E23: Yes | F23: No | G23: No
A24: Year FE | B24: Yes | C24: Yes | D24: No | E24: Yes | F24: Yes | G24: Yes
A25: Last n years | F25: 5 | G25: 10
A27: Note on t-statistics: coefficients and observations match reghdfe exactly. In the year-FE-only columns (1), (2), (5) and (6), these two-way clustered t-statistics run about 4 to 17 percent larger than reghdfe reports for the published Table III (for example, original Panel B column 1: -2.65 here, -2.27 published); plan-FE columns (3) and (4) match to within 0.06. Use the attached Stata code for the exact figures.

Sheet Estimates
A1: Estimates behind the tables. Blue = regression output (coefficient, SE, minimum cluster count). t and p are formulas; p uses the t distribution with (min clusters - 1) df. SE double clustered by plan and fiscal year (Cameron-Gelbach-Miller, with the eigenvalue fix).
A3: Version | B3: Column | C3: Variable | D3: Coefficient | E3: SE | F3: Clusters (min) | G3: t | H3: p
A4: peer | B4: (1) | C4: Conflicted CIO (0/1) | D4: -0.55697013 | E4: 0.15141822 | F4: 19 | G4: =IF(E4>0,D4/E4,"") -> -3.678356 | H4: =IF(G4="","",TDIST(ABS(G4),F4-1,2)) -> 0.0017195765
A5: peer | B5: (2) | C5: Conflicted CIO (0/1) | D5: -0.58232518 | E5: 0.1862998 | F5: 19 | G5: =IF(E5>0,D5/E5,"") -> -3.1257424 | H5: =IF(G5="","",TDIST(ABS(G5),F5-1,2)) -> 0.0058407567
A6: peer | B6: (3) | C6: Conflicted CIO (0/1) | D6: -0.64076312 | E6: 0.29037999 | F6: 19 | G6: =IF(E6>0,D6/E6,"") -> -2.2066366 | H6: =IF(G6="","",TDIST(ABS(G6),F6-1,2)) -> 0.04056821
A7: peer | B7: (4) | C7: Conflicted CIO (0/1) | D7: -0.69792191 | E7: 0.29373848 | F7: 19 | G7: =IF(E7>0,D7/E7,"") -> -2.3759976 | H7: =IF(G7="","",TDIST(ABS(G7),F7-1,2)) -> 0.0288096
A8: peer | B8: (5) | C8: Conflicted CIO (0/1) | D8: -0.47452374 | E8: 0.22639981 | F8: 19 | G8: =IF(E8>0,D8/E8,"") -> -2.0959547 | H8: =IF(G8="","",TDIST(ABS(G8),F8-1,2)) -> 0.050488803
A9: peer | B9: (6) | C9: Conflicted CIO (0/1) | D9: -0.50834616 | E9: 0.1826916 | F9: 19 | G9: =IF(E9>0,D9/E9,"") -> -2.7825371 | H9: =IF(G9="","",TDIST(ABS(G9),F9-1,2)) -> 0.012287709
A10: peer | B10: (1) | C10: Investment Return (t - 1) | D10: 0.013909869 | E10: 0.019513777 | F10: 19 | G10: =IF(E10>0,D10/E10,"") -> 0.712823 | H10: =IF(G10="","",TDIST(ABS(G10),F10-1,2)) -> 0.48509434
A11: peer | B11: (2) | C11: Investment Return (t - 1) | D11: 0.004172387 | E11: 0.020972487 | F11: 19 | G11: =IF(E11>0,D11/E11,"") -> 0.19894574 | H11: =IF(G11="","",TDIST(ABS(G11),F11-1,2)) -> 0.84453511
A12: peer | B12: (3) | C12: Investment Return (t - 1) | D12: 0.010624341 | E12: 0.0089511849 | F12: 19 | G12: =IF(E12>0,D12/E12,"") -> 1.1869201 | H12: =IF(G12="","",TDIST(ABS(G12),F12-1,2)) -> 0.25068825
A13: peer | B13: (4) | C13: Investment Return (t - 1) | D13: 0.00044173875 | E13: 0.016470436 | F13: 19 | G13: =IF(E13>0,D13/E13,"") -> 0.0268201 | H13: =IF(G13="","",TDIST(ABS(G13),F13-1,2)) -> 0.97889833
A14: peer | B14: (5) | C14: Investment Return (t - 1) | D14: 0.004456023 | E14: 0.02131807 | F14: 19 | G14: =IF(E14>0,D14/E14,"") -> 0.20902563 | H14: =IF(G14="","",TDIST(ABS(G14),F14-1,2)) -> 0.83677553
A15: peer | B15: (6) | C15: Investment Return (t - 1) | D15: 0.0042878292 | E15: 0.020925077 | F15: 19 | G15: =IF(E15>0,D15/E15,"") -> 0.20491343 | H15: =IF(G15="","",TDIST(ABS(G15),F15-1,2)) -> 0.8399391
... A251: b_docAB (summary) | B251: (6) | C251: Conflicted CIO | D251: -0.4445863 | E251: 0.17983068 | F251: 19 | G251: =IF(E251>0,D251/E251,"") -> -2.4722494 | H251: =IF(G251="","",TDIST(ABS(G251),F251-1,2)) -> 0.023630368
